Workbook

Sheet CAT Cluster
B1: Central de Serviços de TI
B3: Catálogo de Serviços de TI
M4: elaborado por CHACON Consultoria
M5: 42836
A6: Portal | B6: Produto ou Grupo | C6: Item de Catálogo | D6: Subtítulo | E6: Carac | F6: Tipo de Chamado | G6: Grupo Solucionador | H6: Prioridade | I6: SLA de Resposta | J6: SLA de Resolução | K6: Envio de Feedback | L6: Anexo? | M6: Atributos mínimos para atendimento
A7: Cluster2GO | B7: Backup/Restore | C7: Criação de rotina de backup de Banco de Dados | D7: - | E7: =LEN(D7) -> 1 | F7: Solicitação | G7: Cluster2GO | K7: Sim | L7: Não | M7: Informar o ID da instância e a periodicidade da retenção do backup
A8: Cluster2GO | B8: Backup/Restore | C8: Criação de rotina de backup EC2 | D8: - | E8: =LEN(D8) -> 1 | F8: Solicitação | G8: Cluster2GO | K8: Sim | L8: Não | M8: Informar o ID da instância e a periodicidade da retenção do backup
A9: Cluster2GO | B9: Backup/Restore | C9: Solitação de Restore de Banco de Dados | D9: - | E9: =LEN(D9) -> 1 | F9: Solicitação | G9: Cluster2GO | K9: Sim | L9: Não | M9: Informar o ID da instância e data de referência
A10: Cluster2GO | B10: Backup/Restore | C10: Solitação de Restore EC2 | D10: - | E10: =LEN(D10) -> 1 | F10: Solicitação | G10: Cluster2GO | K10: Sim | L10: Não | M10: Informar o ID da instância e data de referência
A11: Cluster2GO | B11: Banco de Dados | C11: Agendamento de recurso (DBA) | D11: - | E11: =LEN(D11) -> 1 | F11: Solicitação | G11: Cluster2GO | K11: Sim | L11: Não | M11: Informar detalhes da atividade a ser realizada e a respectiva data e horário
A12: Cluster2GO | B12: Banco de Dados | C12: Análise de Performance | D12: - | E12: =LEN(D12) -> 1 | F12: Solicitação | G12: Cluster2GO | K12: Sim | L12: Não | M12: Informar o Banco de Dados e o Ambiente (Produção, Homologação ou Desenvolvimento) que precisa ser analisado
A13: Cluster2GO | B13: Banco de Dados | C13: Criação/Alteração de Monitoração em Banco de Dados | D13: - | E13: =LEN(D13) -> 1 | F13: Solicitação | G13: Cluster2GO | K13: Sim | L13: Não | M13: Informar a monitoração desejada, o Banco de Dados e o Ambiente (Produção, Homologação e Desenvolvimento)
A14: Cluster2GO | B14: Banco de Dados | C14: Dump de Banco de Dados (importação/exportação) | D14: Importação e Exportação de Banco de Dados | E14: =LEN(D14) -> 41 | F14: Solicitação | G14: Cluster2GO | K14: Sim | L14: Não | M14: Informar o Banco de Dados e o Ambiente (Produção, Homologação ou Desenvolvimento) e o destino do Dump
A15: Cluster2GO | B15: Banco de Dados | C15: Execução de script/job | D15: - | E15: =LEN(D15) -> 1 | F15: Solicitação | G15: Cluster2GO | K15: Sim | L15: Não | M15: Informar o Banco de Dados, o Ambiente (Produção, Homologação ou Desenvolvimento) e anexar o script a ser executado
A16: Cluster2GO | B16: Infra/Ambiente | C16: Alteração de acesso a ambiente | D16: - | E16: =LEN(D16) -> 1 | F16: Solicitação | G16: Cluster2GO | K16: Sim | L16: Não | M16: Informar o Nome completo, e-mail e ambiente (Produção, Homologação ou Desenvolvimento)
A17: Cluster2GO | B17: Infra/Ambiente | C17: Alteração de ambiente | D17: - | E17: =LEN(D17) -> 1 | F17: Solicitação | G17: Cluster2GO | K17: Sim | L17: Não | M17: Informar espeficicações necessárias para alteração do ambiente
A18: Cluster2GO | B18: Infra/Ambiente | C18: Criação de ambiente | D18: - | E18: =LEN(D18) -> 1 | F18: Solicitação | G18: Cluster2GO | K18: Sim | L18: Não | M18: Informar espeficicações necessárias para criação do ambiente
... A43: Cluster2GO | B43: VPN AWS | C43: Solicitação de Instalador VPN AWS | D43: - | E43: =LEN(D43) -> 1 | F43: Solicitação | G43: Cluster2GO | K43: Sim | L43: Não | M43: Informar usuário que precisa do instalador

Sheet CAT Cliente Smiles
C2: Central de Serviços de TI
C3: Catálogo de Serviços de TI
L4: elaborado por ABU Consultoria
L5: ='CAT Negócio'!M5 -> 42347
A6: Portal | B6: Produto ou Grupo | C6: Item de Catálogo | D6: Subtítulo | E6: Tipo de Chamado | F6: Grupo Solucionador | G6: Prioridade | H6: SLA de Resposta | I6: SLA de Resolução | J6: Envio de Feedback | K6: Anexo? | L6: Atributos mínimos para atendimento
A7: Cliente Smiles | B7: Erros de Promoção / Bonificação | C7: Erros relacionados à Bonificação de Compra de Milhas | D7: Não entrou a quantidade de milhas esperada na conta do cliente Cliente comprou e a quantindade de milhas cretidata estava errada | E7: Incidente | F7: Operações de TI | G7: MAJOR | H7: 0.33333333 | I7: 1 | J7: Sim | K7: Sim | L7: Anexar a planilha padrão de chamados de promoção.
A8: Cliente Smiles | B8: Erros de Promoção / Bonificação | C8: Erros relacionados à Bonificação de Emissão | D8: Falha na bonificação relacionada a emissões, etc. | E8: Incidente | F8: Operações de TI | G8: MAJOR | H8: 0.33333333 | I8: 1 | J8: Sim | K8: Sim | L8: Anexar a planilha padrão de chamados de promoção.
A9: Cliente Smiles | B9: Erros de Promoção / Bonificação | C9: Erros relacionados à Bonificação de Revalidação de Milhas | D9: Não estão aparecendo as milhas para o cliente revalidar, etc. | E9: Incidente | F9: Operações de TI | G9: MAJOR | H9: 0.33333333 | I9: 1 | J9: Sim | K9: Sim | L9: Anexar a planilha padrão de chamados de promoção.
A10: Cliente Smiles | B10: Erros de Promoção / Bonificação | C10: Erros relacionados à Bonificação de Transferência de Milhas | D10: Falha na bonificação de transferências, etc. | E10: Incidente | F10: Operações de TI | G10: MAJOR | H10: 0.33333333 | I10: 1 | J10: Sim | K10: Sim | L10: Anexar a planilha padrão de chamados de promoção.
A11: Cliente Smiles | B11: Erros de Promoção / Bonificação | C11: Erros relacionados à Bonificação do Clube Smiles | D11: Falha na bonificação do cliente, bonificação a mais ou a menos, etc. | E11: Incidente | F11: Operações de TI | G11: MAJOR | H11: 0.33333333 | I11: 1 | J11: Sim | K11: Sim | L11: Anexar a planilha padrão de chamados de promoção.
A12: Cliente Smiles | B12: Erros de Promoção / Bonificação | C12: Erros relacionados à Bonificação do Crédito Retroativo de Milhas | D12: Falha na bonificação de crédito retroativo, etc. | E12: Incidente | F12: Operações de TI | G12: MAJOR | H12: 0.33333333 | I12: 1 | J12: Sim | K12: Sim | L12: Anexar a planilha padrão de chamados de promoção.
A13: Cliente Smiles | B13: Erros de Promoção / Bonificação | C13: Erros relacionados à Voucher | D13: Voucher com desconto incorreto, Voucher com data de expiração incorreta, etc. | E13: Incidente | F13: Operações de TI | G13: MAJOR | H13: 0.33333333 | I13: 1 | J13: Sim | K13: Sim | L13: Anexar a planilha padrão de chamados de promoção.
A14: Cliente Smiles | B14: Erros de Siebel | C14: Erros no processamento de Transações | D14: Erro no processamento de transações, etc. | E14: Incidente | F14: Operações de TI | G14: MAJOR | H14: 0.33333333 | I14: 1 | J14: Sim | K14: Sim | L14: Informar o Código Smiles, Data do Erro e "Print de Tela" do Erro (caso aplicável).
A15: Cliente Smiles | B15: Erros de Siebel | C15: Erros no processo de Merge | D15: Problema no processo de merge de clientes, etc. | E15: Incidente | F15: Operações de TI | G15: MAJOR | H15: 0.33333333 | I15: 1 | J15: Sim | K15: Sim | L15: Informar o Código Smiles, Data do Erro e "Print de Tela" do Erro (caso aplicável).
A16: Cliente Smiles | B16: Erros de Siebel | C16: Erros relacionados a Cobrança | D16: Cliente cobrado erroneamente, pagamento em duplicidade, etc. | E16: Incidente | F16: Operações de TI | G16: MAJOR | H16: 0.33333333 | I16: 1 | J16: Sim | K16: Sim | L16: Informar o Código Smiles, Data do Erro e "Print de Tela" do Erro (caso aplicável).
A17: Cliente Smiles | B17: Erros de Siebel | C17: Erros relacionados a envio e recebimento de e-mail | D17: Erros relacionados a envio e recebimento de e-mails. | E17: Incidente | F17: Operações de TI | G17: MAJOR | H17: 0.33333333 | I17: 1 | J17: Sim | K17: Sim | L17: Informar o Código Smiles e o tipo de e-mail, exemplo: e-mail de voucher, promocional, emissão, resgate de milhas.
A18: Cliente Smiles | B18: Erros de Siebel | C18: Erros relacionados a Saldo Divergente | D18: Saldo de milhas do cliente apresenta inconsistências, etc. | E18: Incidente | F18: Operações de TI | G18: MAJOR | H18: 0.33333333 | I18: 1 | J18: Sim | K18: Sim | L18: Informar o Código Smiles, Data do Erro e "Print de Tela" do Erro (caso aplicável).
... A54: Cliente Smiles | B54: Outros | C54: Outros | D54: Caso não tenha encontrado a opção adequada a sua necessidade, utilizar esta categoria de abertura de seu chamado | E54: Incidente | F54: Operações de TI | G54: MINOR | H54: 0.33333333 | I54: 1.6666667 | J54: Sim | K54: Sim | L54: Informar detalhadamente sua necessidade ou falha identificada, para que possamos compreendê-la e prover a adequada tratativa. Caso possua algum documento ou "print de tela" que nos ajude no entendimento, favor anexar ao chamado.

Sheet CAT Negócio
C2: Central de Serviços de TI
C3: Catálogo de Serviços de TI
M4: elaborado por ABU Consultoria
M5: 42347
A6: Portal | B6: Produto ou Grupo | C6: Item de Catálogo | D6: Subtítulo | E6: Carac | F6: Tipo de Chamado | G6: Grupo Solucionador | H6: Prioridade | I6: SLA de Resposta | J6: SLA de Resolução | K6: Envio de Feedback | L6: Anexo? | M6: Atributos mínimos para atendimento
A7: Áreas de Negócio | B7: BI | C7: Divergência de informações no BI | D7: Problema com a carga de informações no BI | E7: =LEN(D7) -> 41 | F7: Incidente | G7: Operações de TI | H7: CRITICAL | I7: 0.16666667 | J7: 0.33333333 | K7: Sim | L7: Sim | M7: Informar a tabela com divergência, XML, data e hora da falha e incluir evidências (anexo).
A8: Áreas de Negócio | B8: BI | C8: Performance das consultas | D8: Problemas com performance das consultas, relatórios | E8: =LEN(D8) -> 51 | F8: Incidente | G8: Operações de TI | H8: MAJOR | I8: 0.33333333 | J8: 1 | K8: Sim | L8: Sim | M8: Informar a tabela, data e hora da lentidão e incluir evidências (anexo).
A9: Áreas de Negócio | B9: BI | C9: Outras solicitações (BI) | D9: Caso não tenha encontrado a opção adequada, utilizar esta categoria para abrir seu chamado. | E9: =LEN(D9) -> 91 | F9: Solicitação | G9: Operações de TI | H9: MAJOR | I9: 0.33333333 | J9: 1 | K9: Sim | L9: Sim | M9: Informar detalhadamente sua necessidade ou falha identificada, para que possamos compreendê-la e prover a adequada tratativa. Caso possua algum documento ou "print de tela" que nos ajude no entendimento, favor anexar ao chamado.
A10: Áreas de Negócio | B10: Cadastros | C10: Cadastrar Novo Parceiro (Aéreo) | D10: Criar Novo Parceiro (Aéreo), Mapa de Distância | E10: =LEN(D10) -> 46 | F10: Solicitação | G10: Operações de TI | H10: MAJOR | I10: 0.33333333 | J10: 1 | K10: Sim | L10: Não | M10: Informar o ambiente Siebel onde o parceiro será cadastrado (Produção e/ou Teste), "Alias", Nome do Parceiro e os Produtos do Parceiro.
A11: Áreas de Negócio | B11: Cadastros | C11: Cadastrar Novo Parceiro (Não Aéreo) | D11: Criar Novo Parceiro (Não Aéreo) | E11: =LEN(D11) -> 31 | F11: Solicitação | G11: Operações de TI | H11: MAJOR | I11: 0.33333333 | J11: 1 | K11: Sim | L11: Não | M11: Informar o "Alias", Nome do Parceiro e os Produtos do Parceiro.
A12: Áreas de Negócio | B12: Cadastros | C12: Cadastrar Novo Produto | D12: Criar Produto, Incluir Produto, Novo Produto | E12: =LEN(D12) -> 44 | F12: Solicitação | G12: Operações de TI | H12: MAJOR | I12: 0.33333333 | J12: 1 | K12: Sim | L12: Não | M12: Informar o ambiente Siebel onde o Produto será cadastrado (Produção e/ou Teste) e em qual Parceiro estará vinculado e o número da peça caso aplicável.
A13: Áreas de Negócio | B13: Cadastros | C13: Manutenção de Parceiro | D13: Alteração de Parceiro (Não Aéreo) | E13: =LEN(D13) -> 33 | F13: Solicitação | G13: Operações de TI | H13: MAJOR | I13: 0.33333333 | J13: 1 | K13: Sim | L13: Não | M13: Informar os itens ou parâmetros que necessitam ser alterados, o ambiente Siebel onde o parceiro está cadastrado (Produção e/ou Teste) e também o "Alias" e o Nome do Parceiro.
A14: Áreas de Negócio | B14: Cadastros | C14: Manutenção de Produto | D14: Alteração de Produto | E14: =LEN(D14) -> 20 | F14: Solicitação | G14: Operações de TI | H14: MAJOR | I14: 0.33333333 | J14: 1 | K14: Sim | L14: Não | M14: Informar os itens ou parâmetros que necessitam ser alterados, o ambiente Siebel onde o Produto está cadastrado (Produção e/ou Teste) e também o Nome do Produto.
A15: Áreas de Negócio | B15: EDI | C15: Atraso ou Erro no Arquivo EDI - Outros | D15: Reportar atraso ou erro no envio de arquivos EDI de OUTROS parceiros. | E15: =LEN(D15) -> 69 | F15: Incidente | G15: Operações de TI | H15: MAJOR | I15: 0.33333333 | J15: 1 | K15: Sim | L15: Não | M15: Informar parceiro(s) afetados(s) e a falha que está sendo percebida.
A16: Áreas de Negócio | B16: EDI | C16: Atraso ou Erro no Arquivo EDI - Parceiros Críticos | D16: Itaú (ISP), Bradesco (BBR), HSBC (HSB), Caixa Econômica (CE2), Santander (SAB), Banco do Brasil (BDB). | E16: =LEN(D16) -> 102 | F16: Incidente | G16: Operações de TI | H16: BLOCKER | I16: 0.041666667 | J16: 0.16666667 | K16: Sim | L16: Não | M16: Informar parceiro(s) afetados(s) e a falha que está sendo percebida.
A17: Áreas de Negócio | B17: EDI | C17: Envio, Retenção ou Liberação de arquivos EDI | D17: Enviar, Reter ou Liberar arquivos EDI | E17: =LEN(D17) -> 37 | F17: Solicitação | G17: Operações de TI | H17: MAJOR | I17: 0.33333333 | J17: 1 | K17: Sim | L17: Sim | M17: Informar o Alias do Parceiro e Sequencia do arquivo.
A18: Áreas de Negócio | B18: EDI | C18: Erro no processamento de arquivo de Crédito Retroativo | D18: Erro no processamento de arquivos de Crédito Retroativo. | E18: =LEN(D18) -> 56 | F18: Incidente | G18: Operações de TI | H18: MAJOR | I18: 0.33333333 | J18: 1 | K18: Sim | L18: Não | M18: Informar parceiro(s) afetados(s) e a falha que está sendo percebida.
... A53: Áreas de Negócio | B53: Localiza | C53: Página não abre / não carrega | D53: Localiza não carrega, Erros na página da Localiza | E53: =LEN(D53) -> 49 | F53: Incidente | G53: Operações de TI | H53: BLOCKER | I53: 0.041666667 | J53: 0.16666667 | K53: Sim | L53: Sim | M53: Em caso de mensagem de erro, informar a mensagem e anexar o "print da tela" do erro.

Sheet CAT Escritório
C2: Central de Serviços de TI
C3: Catálogo de Serviços de TI
M4: elaborado por ABU Consultoria
M5: ='CAT Negócio'!M5 -> 42347
A6: Portal | B6: Produto ou Grupo | C6: Item de Catálogo | D6: Subtítulo | E6: Carac | F6: Tipo de Chamado | G6: Grupo Solucionador | H6: Prioridade | I6: SLA de Resposta | J6: SLA de Resolução | K6: Envio de Feedback | L6: Anexo? | M6: Atributos mínimos para atendimento
A7: Escritório / Informática | B7: Telefonia | C7: Solicitação de Ramal | D7: Solicitar ramal para o usuário (funcionário ou terceiro). | E7: =LEN(D7) -> 57 | F7: Solicitação | G7: Operações de TI | H7: MAJOR | I7: 0.33333333 | J7: 1 | K7: Sim | L7: Sim | M7: Informar o login de rede e anexar: a solicitação do RH (em caso de funcionário) ou a solicitação do gestor do projeto (em caso de terceiro).
A8: Escritório / Informática | B8: Telefonia | C8: Configuração e Manutenção de Ramal | D8: Trocar ramal, configurar ramal, alterar nome no ramal, etc. | E8: =LEN(D8) -> 59 | F8: Solicitação | G8: Operações de TI | H8: MAJOR | I8: 0.33333333 | J8: 1 | K8: Sim | L8: Sim | M8: Informar o número do ramal e descrever a necessidade (configuração ou alteração de nome no display, etc.).
A9: Escritório / Informática | B9: Telefonia | C9: Problemas com ramal ou ligações | D9: Ramal não loga, não efetua chamadas internas (ramal para ramal), não efetua chamadas externas. | E9: =LEN(D9) -> 94 | F9: Incidente | G9: Operações de TI | H9: MAJOR | I9: 0.33333333 | J9: 1 | K9: Sim | L9: Sim | M9: Informar o número do ramal e descrever o problema (exemplo: ramal não loga, chamadas internas ou externas não realizadas, etc.)
A10: Escritório / Informática | B10: Impressão | C10: Configuração de Impressora | D10: Configurar impressora para o usuário (funcionário ou terceiros). | E10: =LEN(D10) -> 64 | F10: Solicitação | G10: Operações de TI | H10: MAJOR | I10: 0.33333333 | J10: 1 | K10: Sim | L10: Sim | M10: Configurar impressora para funcionário (preto e branco): informar o nome do usuário, hostname ou número do ativo de seu Laptop. Configurar impressa para terceiros: informar o nome do terceiro e anexar o e-mail de aprovação do gestor do contrato. Configurar impressão colorida: informar o nome do usuário e anexar o e-mail de aprovação do gestor imediato, autorizando impressões coloridas.
A11: Escritório / Informática | B11: Impressão | C11: Erro ou Falha de Impressão | D11: Não consegue imprimir, impressora com erro, falha de Tonner, Tonner baixo, papel preso, etc. | E11: =LEN(D11) -> 92 | F11: Incidente | G11: Operações de TI | H11: MAJOR | I11: 0.33333333 | J11: 1 | K11: Sim | L11: Sim | M11: Informar em qual impressora está tentando imprimir e também descrever o erro ou falha.
A12: Escritório / Informática | B12: Vídeo Conferência | C12: Verificação da Vídeo Conferência para uso | D12: Testar a vídeo conferência antes de uma reunião. | E12: =LEN(D12) -> 48 | F12: Solicitação | G12: Operações de TI | H12: CRITICAL | I12: 0.083333333 | J12: 0.16666667 | K12: Sim | L12: Sim | M12: Infomar a data e hora para realização da verificação (antes da reunião) e também o endereço IP da Vídeo Conferência que será conectada.
A13: Escritório / Informática | B13: Vídeo Conferência | C13: Erro ou Falha da Vídeo Conferência | D13: Vídeo Conferência não funciona. | E13: =LEN(D13) -> 31 | F13: Incidente | G13: Operações de TI | H13: CRITICAL | I13: 0.16666667 | J13: 0.33333333 | K13: Sim | L13: Sim | M13: Informar o erro ou falha apresentada (exemplo: sem sinal, imagem ruim, sem som, etc.).
A14: Escritório / Informática | B14: Salas de Reunião | C14: Erros ou Falhas em equipamentos das Salas de Reunião | D14: Falhas com HDMI, televisões, mouses, projetores ou outros equipamentos das salas de reunião. | E14: =LEN(D14) -> 92 | F14: Incidente | G14: Operações de TI | H14: MAJOR | I14: 0.33333333 | J14: 1 | K14: Sim | L14: Sim | M14: Informar o erro ou falha apresentada (exemplo: projetor desconfigurado, cabo HDMI com problemas, televisão desconfigurada, tomadas com problemas, etc.).
A15: Escritório / Informática | B15: Internet | C15: Lentidão ou Indisponibilidade no acesso à Internet | D15: Internet não funciona. | E15: =LEN(D15) -> 22 | F15: Incidente | G15: Operações de TI | H15: CRITICAL | I15: 0.16666667 | J15: 0.33333333 | K15: Sim | L15: Sim | M15: Informar em qual rede você que está conectado (ex. Wifi Guest, Wifi Corp, etc.).
A16: Escritório / Informática | B16: Internet | C16: Não navega em um site específico | D16: Usuário não consegue navegar em um site específico. | E16: =LEN(D16) -> 51 | F16: Incidente | G16: Operações de TI | H16: MAJOR | I16: 0.33333333 | J16: 1 | K16: Sim | L16: Sim | M16: Informar em qual rede você que está conectado (ex. Wifi Guest, Wifi Corp, etc.) e o site em que não está conseguindo navegar.
A17: Escritório / Informática | B17: VPN | C17: Erro de conexão VPN | D17: VPN não conecta, Erro de VPN. | E17: =LEN(D17) -> 29 | F17: Incidente | G17: Operações de TI | H17: MAJOR | I17: 0.33333333 | J17: 1 | K17: Sim | L17: Sim | M17: Informar o erro ou falha apresentada e anexar evidência (print de tela).
A18: Escritório / Informática | B18: Laptop e Periféricos | C18: Periféricos com mau funcionamento | D18: Usuário com problemas com mouse, teclado, headset, etc. | E18: =LEN(D18) -> 55 | F18: Incidente | G18: Operações de TI | H18: MAJOR | I18: 0.33333333 | J18: 1 | K18: Sim | L18: Sim | M18: Informar o erro ou falha e qual periférico está apresentando problema (mouse, teclado, headset, etc.).
... A31: Escritório / Informática | B31: E-mail | C31: Criação ou Alteração de Conta de E-mail | D31: Criação ou Alteração de Conta de E-mail | E31: =LEN(D31) -> 39 | F31: Solicitação | G31: Operações de TI | H31: MAJOR | I31: 0.33333333 | J31: 1 | K31: Sim | L31: Sim | M31: Informar o usuário de rede, o nome do colaborador e as alterações necessárias (ex. tamanho da caixa de e-mail). Anexar e-mail de aprovação do gestor imediato.

Sheet CAT TIpTI
C2: Central de Serviços de TI
C3: Catálogo de Serviços de TI
M4: elaborado por ABU Consultoria
M5: ='CAT Negócio'!M5 -> 42347
A6: Portal | B6: Produto ou Grupo | C6: Item de Catálogo | D6: Subtítulo | E6: Carac | F6: Tipo de Chamado | G6: Grupo Solucionador | H6: Prioridade | I6: SLA de Resposta | J6: SLA de Resolução | K6: Envio de Feedback | L6: Anexo? | M6: Atributos mínimos para atendimento
A7: TI para TI | B7: Acessos em TI | C7: Alterar Acessos (TI) | D7: Alterar permissionamento ou usuários de Aplicação, Banco de Dados, Console, Servidor, Bucket, Log, etc. | E7: =LEN(D7) -> 103 | F7: Acesso com Aprov. Adicional | G7: SI | H7: Médio | I7: 4 horas úteis | J7: 2 dias úteis | K7: Sim | L7: Sim | M7: Informar o Login de Rede ou E-mail, Componente, Perfil ou permissionamento que deseja alterar o acesso e também uma justificativa da necessidade. Em caso de funcionários Smiles, anexar ao chamado o e-mail de aprovação do Gestor Imediato. Em caso de terceiros, anexar ao chamado o e-mail de aprovação do Gestor do Contrato.
A8: TI para TI | B8: Acessos em TI | C8: Criar Acessos (TI) | D8: Criar usuários de Aplicação, Banco de Dados, Console, Servidor, Bucket, Log, etc. | E8: =LEN(D8) -> 81 | F8: Acesso com Aprov. Adicional | G8: SI | H8: Médio | I8: 4 horas úteis | J8: 2 dias úteis | K8: Sim | L8: Sim | M8: Informar o Login de Rede ou E-mail, Componente que deseja ter acesso, Perfil que deseja ter acesso e também uma justificativa da necessidade. Em caso de funcionários Smiles, anexar ao chamado o e-mail de aprovação do Gestor Imediato. Em caso de terceiros, anexar ao chamado o e-mail de aprovação do Gestor do Contrato.
A9: TI para TI | B9: Acessos em TI | C9: Revogar Acessos (TI) | D9: Excluir usuários de Aplicação, Banco de Dados, Console, Servidor, Bucket, Log, etc. | E9: =LEN(D9) -> 83 | F9: Acesso com Aprov. Adicional | G9: SI | H9: Médio | I9: 4 horas úteis | J9: 2 dias úteis | K9: Sim | L9: Sim | M9: Informar o Login de Rede ou E-mail, Componente que deseja revogar o acesso, Perfil que deseja ter acesso revogado e também uma justificativa. Em caso de funcionários Smiles, anexar ao chamado o e-mail de aprovação do Gestor Imediato. Em caso de terceiros, anexar ao chamado o e-mail de aprovação do Gestor do Contrato.
A10: TI para TI | B10: Deploy | C10: Atualizar Arquivo de Configuração de Aplicação | D10: Soliciações de atualização de arquivos de configuração de aplicações em geral. | E10: =LEN(D10) -> 78 | F10: Solicitação | G10: INFRA | H10: MAJOR | I10: 0.33333333 | J10: 1 | K10: Sim | L10: Sim | M10: Informar o Ambiente, a Aplicação que precisa ser configurada e também anexar o Arquivo de Configuração (mandatório).
A11: TI para TI | B11: Deploy | C11: Erros na execução de Deploys em DEV | D11: Erros na execução de Deploys em DEV | E11: =LEN(D11) -> 35 | F11: Incidente | G11: INFRA | H11: MAJOR | I11: 0.33333333 | J11: 1 | K11: Sim | L11: Sim | M11: Informar o Pacote, Ambiente, Servidor e descrever o erro ou falha apresentado.
A12: TI para TI | B12: Deploy | C12: Executar Deploy de Aplicação | D12: Solicitações de Deploys em geral. | E12: =LEN(D12) -> 33 | F12: Solicitação | G12: INFRA | H12: MAJOR | I12: 0.33333333 | J12: 1 | K12: Sim | L12: Sim | M12: Informar o Ambiente, Lista de URLs (Nexus), informar o Projeto que está sendo trabalhado (caso aplicável).
A13: TI para TI | B13: Deploy | C13: Executar Scritps em Banco de Dados | D13: Criação ou alteração de Tabelas, Inserção ou Deleção de Dados, etc. | E13: =LEN(D13) -> 67 | F13: Solicitação | G13: INFRA | H13: MAJOR | I13: 0.33333333 | J13: 1 | K13: Sim | L13: Sim | M13: Informar o Banco de Dados e anexar o script a ser executado.
A14: TI para TI | B14: Incidentes de Infra | C14: Aplicação lenta ou indisponível | D14: Aplicação lenta ou indisponível | E14: =LEN(D14) -> 31 | F14: Incidente | G14: INFRA | H14: CRITICAL | I14: 0.16666667 | J14: 0.33333333 | K14: Sim | L14: Sim | M14: Informar a Aplicação que esta apresentando lentidão ou Indisponibilidade.
A15: TI para TI | B15: Incidentes de Infra | C15: Aplicação não está enviando e-mail | D15: Aplicação não está enviando e-mail | E15: =LEN(D15) -> 34 | F15: Incidente | G15: INFRA | H15: MAJOR | I15: 0.33333333 | J15: 1 | K15: Sim | L15: Sim | M15: Informar a Aplicação afetada e anexar o Log do Erro (caso aplicável).
A16: TI para TI | B16: Incidentes de Infra | C16: Erro de Conexão com Aplicações | D16: Siebel, Navitaire, Big Data, Integrador de Sites, Gateway Smiles, etc. | E16: =LEN(D16) -> 70 | F16: Incidente | G16: INFRA | H16: CRITICAL | I16: 0.16666667 | J16: 0.33333333 | K16: Sim | L16: Sim | M16: Informar Aplicações afetadas (origem e destino) ou seus componetes que apresentam erro e anexar o Log do Erro (caso aplicável).
A17: TI para TI | B17: Incidentes de Infra | C17: Erro de Conexão na VPN Smiles-AWS | D17: Problemas entre a conexão Smiles - AWS. | E17: =LEN(D17) -> 39 | F17: Incidente | G17: INFRA | H17: CRITICAL | I17: 0.16666667 | J17: 0.33333333 | K17: Sim | L17: Sim | M17: Informar o usuário de VPN com erro e e anexar o Log do Erro (caso aplicável).
A18: TI para TI | B18: Incidentes de Infra | C18: Erro na Integração entre Aplicações | D18: Ex.: Cielo com Barramento, Bancob com API Gateway, etc. | E18: =LEN(D18) -> 55 | F18: Incidente | G18: INFRA | H18: CRITICAL | I18: 0.16666667 | J18: 0.33333333 | K18: Sim | L18: Sim | M18: Informar Aplicações afetadas (origem e destino) ou seus componetes que apresentam erro e anexar o Log do Erro (caso aplicável).
A19: TI para TI | B19: Incidentes de Infra | C19: Erros relacionados a Banco de Dados | D19: Erros relacionados a Banco de Dados | E19: =LEN(D19) -> 35 | F19: Incidente | G19: INFRA | H19: MAJOR | I19: 0.33333333 | J19: 1 | K19: Sim | L19: Sim | M19: Informar o Banco de Dados que apresenta o erro e anexar o Log do Erro (caso aplicável).
A20: TI para TI | B20: Incidentes de Infra | C20: Erros relacionados a Certificados | D20: Certificado Expirado, Incorreto, Inativo | E20: =LEN(D20) -> 40 | F20: Incidente | G20: INFRA | H20: MAJOR | I20: 0.33333333 | J20: 1 | K20: Sim | L20: Sim | M20: Informar o Certificado que está apresentando Erro e anexar o Log do mesmo (caso aplicável).
A21: TI para TI | B21: Solicitações de Infra | C21: Alterar agendamento de start-stop de Ambiente | D21: Alterar agendamento de start-stop de Ambiente | E21: =LEN(D21) -> 45 | F21: Solicitação | G21: INFRA | H21: MAJOR | I21: 0.33333333 | J21: 1 | K21: Sim | L21: Sim | M21: Informar qual ambiente e qual período.
... A40: TI para TI | B40: Solicitações de Infra | C40: Sincronizar Bucket | D40: Sincronizar Bucket PROD com HOM, etc. | E40: =LEN(D40) -> 37 | F40: Solicitação | G40: INFRA | H40: MAJOR | I40: 0.33333333 | J40: 1 | K40: Sim | L40: Sim | M40: Informar origem e destino e data prevista para execução da sincronização.

Sheet CAT GA
C2: Central de Serviços de TI
C3: Catálogo de Serviços de TI
M4: elaborado por ABU Consultoria
M5: ='CAT Negócio'!M5 -> 42347
A6: Portal | B6: Produto ou Grupo | C6: Item de Catálogo | D6: Subtítulo | E6: Carac | F6: Tipo de Chamado | G6: Grupo Solucionador | H6: Prioridade | I6: SLA de Resposta | J6: SLA de Resolução | K6: Envio de Feedback | L6: Anexo? | M6: Atributos mínimos para atendimento
A7: Gestão de Acessos | B7: 1. Concessão de Acessos | C7: Conceder Login de Rede (AD) | D7: Solicitação de novo acesso ao AD. | E7: =LEN(D7) -> 33 | F7: Acesso com Aprov. de SI | G7: SI | H7: Alta | I7: 4 horas úteis | J7: 2 dias úteis | K7: Sim | L7: Sim | M7: Informar o Nome do Usuário, CPF, RG, Data de Nascimento, E-mail, Telefone. Em caso de terceiros, anexar ao chamado o e-mail de aprovação do Gestor do Contrato.
A8: Gestão de Acessos | B8: 1. Concessão de Acessos | C8: Conceder Acesso VPN | D8: Solicitação de novo acesso à VPN. | E8: =LEN(D8) -> 33 | F8: Acesso com Aprov. Adicional | G8: SI | H8: Médio | I8: 4 horas úteis | J8: 3 dias úteis | K8: Sim | L8: Sim | M8: Informar o Nome do Usuário, Login de Rede, Período de Início e Fim para uso da VPN e também uma justificativa da necessidade. Em caso de funcionários Smiles, anexar ao chamado o e-mail de aprovação do Gestor Imediato. Em caso de terceiros, anexar ao chamado o e-mail de aprovação do Gestor do Contrato.
A9: Gestão de Acessos | B9: 1. Concessão de Acessos | C9: Conceder Acesso ao Siebel ou Outras Ferramentas | D9: Solicitação de novo acesso ao Siebel ou outras Ferramentas. | E9: =LEN(D9) -> 59 | F9: Acesso com Aprov. Adicional | G9: SI | H9: Médio | I9: 4 horas úteis | J9: 2 dias úteis | K9: Sim | L9: Sim | M9: Informar o Nome do Usuário, Login de Rede, Nome da Ferramenta, Perfil que deseja ter acesso e também uma justificativa da necessidade. Em caso de funcionários Smiles, anexar ao chamado o e-mail de aprovação do Gestor Imediato. Em caso de terceiros, anexar ao chamado o e-mail de aprovação do Gestor do Contrato.
A10: Gestão de Acessos | B10: 1. Concessão de Acessos | C10: Conceder Acesso à Pasta ou Diretório de Rede | D10: Solicitação de novo acesso a alguma pasta ou diretório de rede. | E10: =LEN(D10) -> 63 | F10: Acesso com Aprov. Adicional | G10: SI | H10: Médio | I10: 4 horas úteis | J10: 2 dias úteis | K10: Sim | L10: Sim | M10: Informar o Nome do Usuário, Login de Rede, Pasta ou Diretório que deseja ter acesso e também uma justificativa da necessidade. Em caso de funcionários Smiles, anexar ao chamado o e-mail de aprovação do Gestor Imediato. Em caso de terceiros, anexar ao chamado o e-mail de aprovação do Gestor do Contrato.
A11: Gestão de Acessos | B11: 2. Revogação de Acessos | C11: Revogar Login de Rede (AD) | D11: Exclusão de acesso ao AD. | E11: =LEN(D11) -> 25 | F11: Acesso com Aprov. de SI | G11: SI | H11: Alta | I11: 4 horas úteis | J11: 2 dias úteis | K11: Sim | L11: Sim | M11: Informar o Nome do Usuário e o Login de Rede que precisa ser revogado. Em caso de terceiros, incluir o e-mail de aprovação do Gestor do Contrato.
A12: Gestão de Acessos | B12: 2. Revogação de Acessos | C12: Revogar Acesso VPN | D12: Revogação de acesso à VPN. | E12: =LEN(D12) -> 26 | F12: Acesso com Aprov. de SI | G12: SI | H12: Médio | I12: 4 horas úteis | J12: 3 dias úteis | K12: Sim | L12: Sim | M12: Informar o Nome do Usuário e o Login de Rede que precisa ter o acesso VPN revogado. Em caso de terceiros, incluir o e-mail de aprovação do Gestor do Contrato.
A13: Gestão de Acessos | B13: 2. Revogação de Acessos | C13: Revogar Acesso ao Siebel ou Outras Ferramentas | D13: Revogação de acesso ao ao Siebel ou outras Ferramentas. | E13: =LEN(D13) -> 55 | F13: Acesso com Aprov. de SI | G13: SI | H13: Médio | I13: 4 horas úteis | J13: 2 dias úteis | K13: Sim | L13: Sim | M13: Informar o Nome da Ferramenta, Nome do Usuário e Login de Rede que precisa ter o acesso revogado. Em caso de terceiros, incluir o e-mail de aprovação do Gestor do Contrato.
A14: Gestão de Acessos | B14: 3. Alteração de Perfil | C14: Alterar Perfil de Acesso ao Siebel ou Outras Ferramentas | D14: Alteração de perfil de acesso ao Siebel ou outras Ferramentas. | E14: =LEN(D14) -> 62 | F14: Acesso com Aprov. Adicional | G14: SI | H14: Médio | I14: 4 horas úteis | J14: 2 dias úteis | K14: Sim | L14: Sim | M14: Informar o Nome da Ferramenta, Nome do Usuário, Login de Rede e perfil de acesso que precisa ser alterado. Em caso de funcionários Smiles, anexar ao chamado o e-mail de aprovação do Gestor Imediato. Em caso de terceiros, anexar ao chamado o e-mail de aprovação do Gestor do Contrato.
A15: Gestão de Acessos | B15: 3. Alteração de Perfil | C15: Alterar Permissionamentos Específicos | D15: Alteração de permissionamentos específicos em Ferramentas ou Pastas/Diretórios. | E15: =LEN(D15) -> 79 | F15: Acesso com Aprov. Adicional | G15: SI | H15: Médio | I15: 4 horas úteis | J15: 2 dias úteis | K15: Sim | L15: Sim | M15: Informar o Nome da Ferramenta, Nome do Usuário, Login de Rede e permissionamentos que precisam ser alterados. Em caso de funcionários Smiles, anexar ao chamado o e-mail de aprovação do Gestor Imediato. Em caso de terceiros, anexar ao chamado o e-mail de aprovação do Gestor do Contrato.

Sheet Protótipo de Navegação
B2: Central de Serviços de TI
B3: Protótipo de Navegação no Catálogo de Serviços
G4: elaborado por ABU Consultoria
G5: ='CAT Negócio'!M5 -> 42347
A7: CSTI - Negócio / Produtos | C7: Rótulos de Linha
A8: Compra de Milhas | C8: Central de Atendimento
A9: Promoções | C9: Erros de Promoção / Bonificação
A10: Transferência de Milhas | C10: Erros de Siebel
A11: EDI | C11: Erros no Amadeus
A12: Relatórios / Arquivos | C12: Erros de Site
A13: Shopping Smiles | C13: Total Geral
A14: Crédito de Vôo
A15: Emissão
A16: Fraude/Perda Financeira | C16: Rótulos de Linha
A17: Portal Parceiros | C17: TI pra TI (Infra)
A18: Reativação de Milhas | C18: Acessos em TI
A19: Siebel Loyalty | C19: AD - Active Directory
A20: Site Smiles | C20: Amazon
A21: Smiles Pay | C21: DHCP
A22: URA | C22: DNS
A23: Clube Smiles | C23: File Server
A24: Total Geral | C24: Firewall
C25: Middleware
C26: Network / Link
C27: Proxy
C28: (vazio)
C29: Total Geral

Sheet Escopo
A1: Assunto | B1: Área
A2: Cadastros | B2: Negócio
A3: Clube Smiles | B3: BackOffice (Central de Atendimento)
A4: Compra de Milhas | B4: BackOffice (Central de Atendimento)
A5: Crédito de Vôo | B5: BackOffice (Central de Atendimento)
A6: EDI | B6: Negócio
A7: Emissão | B7: BackOffice (Central de Atendimento)
A8: Fraude/Perda Financeira | B8: Negócio
A9: Incidente Siebel | B9: BackOffice (Central de Atendimento)
A10: Portal Parceiros | B10: Negócio
A11: Promoções | B11: Negócio
A12: Reativação de Milhas | B12: BackOffice (Central de Atendimento)
... A19: URA | B19: BackOffice (Central de Atendimento)

Sheet CAT Monitoração
C2: Central de Serviços de TI
C3: Catálogo de Serviços de TI
L4: elaborado por ABU Consultoria
L5: ='CAT Negócio'!M5 -> 42347
A6: Portal | B6: Produto ou Grupo | C6: Item de Catálogo | D6: Subtítulo | E6: Tipo de Chamado | F6: Grupo Solucionador | G6: Prioridade | H6: SLA de Resposta | I6: SLA de Resolução | J6: Envio de Feedback | K6: Anexo? | L6: Atributos mínimos para atendimento
B7: Gateway de Pagamento - ADYEN | C7: Processo de checkout assíncrono | D7: Ero sistêmico ou de código | E7: Incidente | F7: Operações de TI | G7: MAJOR | H7: 0.33333333 | I7: 1 | J7: Não | K7: Não | L7: Mensagem de erro/log
B8: Emissão sem Milhas | E8: Incidente | F8: Operações de TI | G8: MAJOR | H8: 0.33333333 | I8: 1 | J8: Não | K8: Não | L8: Mensagem de erro/log
