Workbook
Name Slicer_KPI: #N/A

Sheet Dashboard
H27: =IF(Calculate!AE7=1,Calculate!AB7,"") -> Varinace with Base [31/12/2014] | L27: =IF(Calculate!AE8=1,Calculate!AB8,"") | P27: =IF(Calculate!AE9=1,Calculate!AB9,"") -> Varinace with Target [Dec 2015]
H29: =IF(Calculate!AE7=1,Calculate!AD7,"") -> 0.33405899 | J29: =IF(Calculate!AE7=1,Calculate!AC7,"") -> 2093.379 | L29: =IF(Calculate!AE8=1,Calculate!AD8,"") | N29: =IF(Calculate!AE8=1,Calculate!AC8,"") | P29: =IF(Calculate!AE9=1,Calculate!AD9,"") -> 0.2000577 | R29: =IF(Calculate!AE9=1,Calculate!AC9,"") -> 1393.6473

Sheet Raw
B2: KPI | C2: Base | D2: Corresp: | E2: Current | F2: Proportionate | G2: Proportionate | H2: Variance | J2: Variance | L2: Variance | N2: Target
D3: Month | E3: Month | F3: Target | G3: Target | H3: with Base | J3: Corresp: Month | L3: with Target | N3: December
C4: 31.12.2014 | D4: 31.08.2014 | E4: 31.08.2015 | F4: 31.08.2015 | G4: 30.09.2015 | H4: Amount | I4: % | J4: Amount | K4: % | L4: Amount | M4: % | N4: 2015
B5: Absolute Deposit | C5: 6266.495 | D5: 0 | E5: 8359.874 | F5: 6389.1091 | G5: 6526.8667 | H5: 2093.379 | I5: 0.33405899 | J5: 8359.874 | K5: 0 | L5: 1970.7649 | M5: 0.30845691 | N5: 6966.2267
B6: CASA Deposit | C6: 5407.551 | D6: 3934.188 | E6: 4160.844 | F6: 5387.4561 | G6: 5507.3751 | H6: -1246.707 | I6: -0.23054928 | J6: 226.656 | K6: 0.057611888 | L6: -1226.6121 | M6: -0.22767927 | N6: 5893.2191
B7: Average Deposit | C7: 5433.8268 | D7: 5482.2397 | E7: 5791.8329 | F7: 5862.5332 | G7: 5930.5292 | H7: 358.00615 | I7: 0.065884719 | J7: 309.59325 | K7: 0.056472039 | L7: -70.700242 | M7: -0.012059675 | N7: 6206.5697
B8: Weekly Deposit 10-09-2015 | C8: 6266.495 | D8: 4908.91 | E8: 8776.695 | F8: 6389.1091 | G8: 6526.8667 | H8: 2510.2 | I8: 0.4005748 | J8: 3867.785 | K8: 0.78791117 | L8: 2387.5859 | M8: 0.37369621 | N8: 6966.2267
B9: No of Current A/Cs Opened during Month | C9: 2280 | D9: 20 | E9: 41 | F9: 190 | G9: 190 | H9: -2239 | I9: -0.98201754 | J9: 21 | K9: 1.05 | L9: -149 | M9: -0.78421053 | N9: 2280
B10: No of Current A/cs Opened Progressive | C10: 157 | D10: 340 | E10: 263 | F10: 2280 | G10: 2280 | H10: 106 | I10: 0.67515924 | J10: -77 | K10: -0.22647059 | L10: -2017 | M10: -0.88464912 | N10: 2280
B11: Number of Depositors Accounts (CASA) | C11: 0 | D11: 0 | E11: 0 | F11: 0 | G11: 0 | H11: 0 | I11: 0 | J11: 0 | K11: 0 | L11: 0 | M11: 0 | N11: 0
B12: Profit/Loss | C12: -26.512 | D12: -13.202 | E12: 32.369539 | F12: 25.347089 | G12: 28.869012 | H12: 58.881539 | I12: -2.2209392 | J12: 45.571539 | K12: -3.4518663 | L12: 7.0224499 | M12: 0.27705153 | N12: 39.416258
B13: Advances | C13: 1220.997 | D13: 1135.671 | E13: 1224.341 | F13: 1281.4567 | G13: 1280.0202 | H13: 3.344 | I13: 0.0027387455 | J13: 88.67 | K13: 0.07807719 | L13: -57.115667 | M13: -0.044570892 | N13: 1311.686
B14: Performing Adances | C14: 0 | D14: 0 | E14: 0 | F14: 0 | G14: 0 | H14: 0 | I14: 0 | J14: 0 | K14: 0 | L14: 0 | M14: 0 | N14: 0
B15: Classified Advances | C15: 361.963 | D15: 365.632 | E15: 352.939 | F15: 280.12167 | G15: 260.89775 | H15: -9.024 | I15: -0.024930725 | J15: -12.693 | K15: -0.034715233 | L15: 72.817333 | M15: 0.25994895 | N15: 239.201
B16: Non Fund Base Advances | C16: 4252.1737 | D16: 389.194 | E16: 337.64074 | F16: 4677.3911 | G16: 4730.5433 | H16: -3914.533 | I16: -0.92059573 | J16: -51.553262 | K16: -0.13246161 | L16: -4339.7504 | M16: -0.9278143 | N16: 4889.9998
... B33: Other Expenses | C33: 81.796 | D33: 44.84 | E33: 40.643 | F33: 52.5346 | G33: 59.101425 | H33: -41.153 | I33: -0.50311751 | J33: -4.197 | K33: -0.093599465 | L33: -11.8916 | M33: -0.22635749 | N33: 78.8019

Sheet Calculate
B2: 0 | C2: 1 | D2: 2 | E2: 3 | F2: 4 | G2: 5 | H2: 6 | I2: 7 | J2: 8 | K2: 9 | L2: 10 | M2: 11 | N2: 12 | O2: 13 | Q2: 1 | R2: KPI | T2: 1 | U2: Base [31/12/2014] | V2: 2 | X2: Base [31/12/2014] | Z2: Slicer | AA2: =MATCH($AJ$3,AG3:$AG$25,0) -> 1 | AB2: =INDEX($C$4:$O$26,MATCH($AJ$3,AG3:$AG$25,0),1) -> Absolute Deposit | AC2: Amount | AD2: Max | AE2: Min | AG2: KPI | AH2: Row | AJ2: KPI | AK2: Sum of Row
B3: # | C3: KPI | D3: Base [31/12/2014] | E3: Corresp Month [31/08/2014] | F3: Current Month [31/08/2015] | G3: Proportionate target [31/08/2015] | H3: Porportionate target [30/09/2015] | I3: Variance with Base | J3: Variance with Base [%] | K3: Variance with Corresp : Month | L3: Variance with Corresp : Month [%] | M3: Variance with Target | N3: Variance with Target [%] | O3: Target [Dec 2015] | Q3: 2 | R3: Base [31/12/2014] | T3: 2 | U3: Corresp Month [31/08/2014] | V3: 3 | X3: Corresp Month [31/08/2014] | Z3: Combo Box 1 | AA3: 1 | AB3: =VLOOKUP(AA3,$T$2:$V$8,2,0) -> Base [31/12/2014] | AC3: =INDEX($C$4:$O$26,$AA$2,MATCH(AB3,$R$2:$R$14,0)) -> 6266.495 | AD3: =IF(AC3=MAX($AC$3:$AC$5),AC3,NA()) -> #N/A | AE3: =IF(AC3=MIN($AC$3:$AC$5),AC3,NA()) -> 6266.495 | AG3: Absolute Deposit | AH3: 1 | AJ3: Absolute Deposit | AK3: 1
B4: 1 | C4: Absolute Deposit | D4: 6266.495 | E4: 0 | F4: 8359.874 | G4: 6389.1091 | H4: 6526.8667 | I4: 2093.379 | J4: 0.33405899 | K4: 8359.874 | L4: 0 | M4: 1970.7649 | N4: 0.30845691 | O4: 6966.2267 | Q4: 3 | R4: Corresp Month [31/08/2014] | T4: 3 | U4: Current Month [31/08/2015] | V4: 4 | X4: Target [Dec 2015] | Z4: Combo Box 2 | AA4: 3 | AB4: =VLOOKUP(AA4,$T$2:$V$8,2,0) -> Current Month [31/08/2015] | AC4: =INDEX($C$4:$O$26,$AA$2,MATCH(AB4,$R$2:$R$14,0)) -> 8359.874 | AD4: =IF(AC4=MAX($AC$3:$AC$5),AC4,NA()) -> 8359.874 | AE4: =IF(AC4=MIN($AC$3:$AC$5),AC4,NA()) -> #N/A | AG4: Advances | AH4: 2
B5: 8 | C5: Advances | D5: 1220.997 | E5: 1135.671 | F5: 1224.341 | G5: 1281.4567 | H5: 1280.0202 | I5: 3.344 | J5: 0.0027387455 | K5: 88.67 | L5: 0.07807719 | M5: -57.115667 | N5: -0.044570892 | O5: 1311.686 | Q5: 4 | R5: Current Month [31/08/2015] | T5: 4 | U5: Proportionate target [31/08/2015] | V5: 5 | Z5: Combo Box 3 | AA5: 6 | AB5: =VLOOKUP(AA5,$T$2:$V$8,2,0) -> Target [Dec 2015] | AC5: =INDEX($C$4:$O$26,$AA$2,MATCH(AB5,$R$2:$R$14,0)) -> 6966.2267 | AD5: =IF(AC5=MAX($AC$3:$AC$5),AC5,NA()) -> #N/A | AE5: =IF(AC5=MIN($AC$3:$AC$5),AC5,NA()) -> #N/A | AG5: Agr: Finance O/S | AH5: 3
B6: 19 | C6: Agr: Finance O/S | D6: 5.06 | E6: 5.138 | F6: 4.75 | G6: 11.629333 | H6: 12.4505 | I6: -0.31 | J6: -0.061264822 | K6: -0.388 | L6: -0.075515765 | M6: -6.8793333 | N6: -0.5915501 | O6: 14.914 | Q6: 5 | R6: Proportionate target [31/08/2015] | T6: 5 | U6: Porportionate target [30/09/2015] | V6: 6 | X6: Current Month [31/08/2015] | AG6: Average Deposit | AH6: 4
B7: 3 | C7: Average Deposit | D7: 5433.8268 | E7: 5482.2397 | F7: 5791.8329 | G7: 5862.5332 | H7: 5930.5292 | I7: 358.00615 | J7: 0.065884719 | K7: 309.59325 | L7: 0.056472039 | M7: -70.700242 | N7: -0.012059675 | O7: 6206.5697 | Q7: 6 | R7: Porportionate target [30/09/2015] | T7: 6 | U7: Target [Dec 2015] | V7: 13 | AB7: =IF(AND(SUMPRODUCT(COUNTIF(AB3,$X$2:$X$4))>0,OR(AB4=$X$6,AB5=$X$6)),"Varinace with"&CHAR(10)&AB3,"") -> Varinace with Base [31/12/2014] | AC7: =IF(AND(SUMPRODUCT(COUNTIF(AB3,$X$2:$X$4))>0,OR(AB4=$X$6,AB5=$X$6)),IF(AB4=$X$6,AC4-AC3,AC5-AC3),"") -> 2093.379 | AD7: =IFERROR(IF(AC7<0,-ABS(IF(AND(SUMPRODUCT(COUNTIF(AB3,$X$2:$X$4))>0,OR(AB4=$X$6,AB5=$X$6)),IF(AB4=$X$6,(AC4-AC3)/AC3,(AC5-AC3)/AC3),"")),ABS(IF(AND(SUMPRODUCT(COUNTIF(AB3,$X$2:$X$4))>0,OR(AB4=$X$6,AB5=$X$6)),IF(AB4=$X$6,(AC4-AC3)/AC3,(AC5-AC3)/AC3),""))),"") -> 0.33405899 | AE7: =IF(AND(SUMPRODUCT(COUNTIF(AB3,$X$2:$X$4))>0,OR(AB4=$X$6,AB5=$X$6)),1,0) -> 1 | AG7: CASA Deposit | AH7: 5
B8: 2 | C8: CASA Deposit | D8: 5407.551 | E8: 3934.188 | F8: 4160.844 | G8: 5387.4561 | H8: 5507.3751 | I8: -1246.707 | J8: -0.23054928 | K8: 226.656 | L8: 0.057611888 | M8: -1226.6121 | N8: -0.22767927 | O8: 5893.2191 | Q8: 7 | R8: Variance with Base | AB8: =IF(AND(SUMPRODUCT(COUNTIF(AB4,$X$2:$X$4))>0,OR(AB3=$X$6,AB5=$X$6)),"Varinace with "&CHAR(10)&AB4,"") | AC8: =IF(AND(SUMPRODUCT(COUNTIF(AB4,$X$2:$X$4))>0,OR(AB3=$X$6,AB5=$X$6)),IF(AB5=$X$6,AC5-AC4,AC3-AC4),"") | AD8: =IFERROR(IF(AC8<0,-ABS(IF(AND(SUMPRODUCT(COUNTIF(AB4,$X$2:$X$4))>0,OR(AB3=$X$6,AB5=$X$6)),IF(AB3=$X$6,(AC3-AC4)/AC4,(AC5-AC4)/AC4),"")),ABS(IF(AND(SUMPRODUCT(COUNTIF(AB4,$X$2:$X$4))>0,OR(AB3=$X$6,AB5=$X$6)),IF(AB3=$X$6,(AC3-AC4)/AC4,(AC5-AC4)/AC4),""))),"") | AE8: =IF(AND(SUMPRODUCT(COUNTIF(AB4,$X$2:$X$4))>0,OR(AB3=$X$6,AB5=$X$6)),1,0) -> 0 | AG8: Classified Advances | AH8: 6
B9: 9 | C9: Classified Advances | D9: 361.963 | E9: 365.632 | F9: 352.939 | G9: 280.12167 | H9: 260.89775 | I9: -9.024 | J9: -0.024930725 | K9: -12.693 | L9: -0.034715233 | M9: 72.817333 | N9: 0.25994895 | O9: 239.201 | Q9: 8 | R9: Variance with Base [%] | AB9: =IF(AND(SUMPRODUCT(COUNTIF(AB5,$X$2:$X$4))>0,OR(AB3=$X$6,AB4=$X$6)),"Varinace with"&CHAR(10)&AB5,"") -> Varinace with Target [Dec 2015] | AC9: =IF(AND(SUMPRODUCT(COUNTIF(AB5,$X$2:$X$4))>0,OR(AB4=$X$6,AB3=$X$6)),IF(AB3=$X$6,AC3-AC5,AC4-AC5),"") -> 1393.6473 | AD9: =IFERROR(IF(AC9<0,-ABS(IF(AND(SUMPRODUCT(COUNTIF(AB5,$X$2:$X$4))>0,OR(AB4=$X$6,AB3=$X$6)),IF(AB3=$X$6,(AC3-AC5)/AC5,(AC4-AC5)/AC5),"")),ABS(IF(AND(SUMPRODUCT(COUNTIF(AB5,$X$2:$X$4))>0,OR(AB4=$X$6,AB3=$X$6)),IF(AB3=$X$6,(AC3-AC5)/AC5,(AC4-AC5)/AC5),""))),"") -> 0.2000577 | AE9: =IF(AND(SUMPRODUCT(COUNTIF(AB5,$X$2:$X$4))>0,OR(AB3=$X$6,AB4=$X$6)),1,0) -> 1 | AG9: Cost of Fund | AH9: 7
B10: 13 | C10: Cost of Fund | D10: 0.4676595 | E10: 0.4501924 | F10: 0.30679659 | G10: 0.37312555 | H10: 0.37277152 | I10: -0.16086291 | J10: -0.34397443 | K10: -0.14339581 | L10: -0.31852116 | M10: -0.066328951 | N10: -0.17776577 | O10: 0.36997217 | Q10: 9 | R10: Variance with Corresp : Month | AG10: Expenditure Excluding Administrative Exp. | AH10: 8
B11: 21 | C11: Expenditure Excluding Administrative Exp. | D11: 346.73 | E11: 271.056 | F11: 177.085 | G11: 222.14427 | H11: 252.16047 | I11: -169.645 | J11: -0.48927119 | K11: -93.971 | L11: -0.34668482 | M11: -45.059267 | N11: -0.20283786 | O11: 345.20666 | Q11: 10 | R11: Variance with Corresp : Month [%] | AG11: Exports | AH11: 9
B12: 16 | C12: Exports | D12: 78.792 | E12: 76.044 | F12: 2.252 | G12: 63.0336 | H12: 70.9128 | I12: -76.54 | J12: -0.97141842 | K12: -73.792 | L12: -0.97038557 | M12: -60.7816 | N12: -0.96427302 | O12: 94.5504 | Q12: 11 | R12: Variance with Target | AG12: Home Remittance | AH12: 10
B13: 12 | C13: Home Remittance | D13: 25.082 | E13: 6.832 | F13: 33.172 | G13: 18.393467 | H13: 20.69265 | I13: 8.09 | J13: 0.32254206 | K13: 26.34 | L13: 3.8553864 | M13: 14.778533 | N13: 0.80346645 | O13: 27.5902 | Q13: 12 | R13: Variance with Target [%] | AG13: Imports | AH13: 11
B14: 15 | C14: Imports | D14: 1473.237 | E14: 1473.237 | F14: 0 | G14: 1080.3738 | H14: 1215.4205 | I14: -1473.237 | J14: -1 | K14: -1473.237 | L14: -1 | M14: -1080.3738 | N14: -1 | O14: 1620.5607 | Q14: 13 | R14: Target [Dec 2015] | AG14: Income | AH14: 12
B15: 20 | C15: Income | D15: 560.924 | E15: 409.789 | F15: 345.675 | G15: 415.29262 | H15: 469.80591 | I15: -215.249 | J15: -0.38374004 | K15: -64.114 | L15: -0.15645613 | M15: -69.617623 | N15: -0.16763511 | O15: 636.32482 | AG15: Intermediation Cost | AH15: 13
B16: 14 | C16: Intermediation Cost | D16: 0.3602926 | E16: 0.30327106 | F16: 0.26046598 | G16: 0.29487225 | H16: 0.29182776 | I16: -0.099826624 | J16: -0.27707098 | K16: -0.042805079 | L16: -0.14114462 | M16: -0.034406271 | N16: -0.11668196 | O16: 0.28158883 | AG16: NBP Adv: Sal: O/S | AH16: 14
B17: 17 | C17: NBP Adv: Sal: O/S | D17: 128.208 | E17: 116.773 | F17: 137.208 | G17: 143.01933 | H17: 146.4015 | I17: 9 | J17: 0.070198428 | K17: 20.435 | L17: 0.17499765 | M17: -5.8113333 | N17: -0.040633201 | O17: 156.548 | AG17: No of Current A/Cs Opened during Month | AH17: 15
B18: 5 | C18: No of Current A/Cs Opened during Month | D18: 2280 | E18: 20 | F18: 41 | G18: 190 | H18: 190 | I18: -2239 | J18: -0.98201754 | K18: 21 | L18: 1.05 | M18: -149 | N18: -0.78421053 | O18: 2280 | AG18: No of Current A/cs Opened Progressive | AH18: 16
B19: 6 | C19: No of Current A/cs Opened Progressive | D19: 157 | E19: 340 | F19: 263 | G19: 2280 | H19: 2280 | I19: 106 | J19: 0.67515924 | K19: -77 | L19: -0.22647059 | M19: -2017 | N19: -0.88464912 | O19: 2280 | AG19: Non Fund Base Advances | AH19: 17
B20: 10 | C20: Non Fund Base Advances | D20: 4252.1737 | E20: 389.194 | F20: 337.64074 | G20: 4677.3911 | H20: 4730.5433 | I20: -3914.533 | J20: -0.92059573 | K20: -51.553262 | L20: -0.13246161 | M20: -4339.7504 | N20: -0.9278143 | O20: 4889.9998 | AG20: Non Fund Base Income | AH20: 18
B21: 11 | C21: Non Fund Base Income | D21: 103.716 | E21: 68.133 | F21: 75.644 | G21: 88.603333 | H21: 99.67875 | I21: -28.072 | J21: -0.27066219 | K21: 7.511 | L21: 0.11024027 | M21: -12.959333 | N21: -0.14626237 | O21: 132.905 | AG21: Other Expenses | AH21: 19
B22: 23 | C22: Other Expenses | D22: 81.796 | E22: 44.84 | F22: 40.643 | G22: 52.5346 | H22: 59.101425 | I22: -41.153 | J22: -0.50311751 | K22: -4.197 | L22: -0.093599465 | M22: -11.8916 | N22: -0.22635749 | O22: 78.8019 | AG22: Overdue Adv: Sal: over 90 Days | AH22: 20
B23: 18 | C23: Overdue Adv: Sal: over 90 Days | D23: 12.246 | E23: 11.138 | F23: 12.362 | G23: 10.612667 | H23: 10.4085 | I23: 0.116 | J23: 0.0094724808 | K23: 1.224 | L23: 0.10989406 | M23: 1.7493333 | N23: 0.16483447 | O23: 9.796 | AG23: Personal Expenses | AH23: 21
B24: 22 | C24: Personal Expenses | D24: 158.91 | E24: 107.095 | F24: 95.576 | G24: 115.26667 | H24: 129.675 | I24: -63.334 | J24: -0.39855264 | K24: -11.519 | L24: -0.10755871 | M24: -19.690667 | N24: -0.17082707 | O24: 172.9 | AG24: Profit/Loss | AH24: 22
B25: 7 | C25: Profit/Loss | D25: -26.512 | E25: -13.202 | F25: 32.369539 | G25: 25.347089 | H25: 28.869012 | I25: 58.881539 | J25: -2.2209392 | K25: 45.571539 | L25: -3.4518663 | M25: 7.0224499 | N25: 0.27705153 | O25: 39.416258 | AG25: Weekly Deposit 10-09-2015 | AH25: 23
B26: 4 | C26: Weekly Deposit 10-09-2015 | D26: 6266.495 | E26: 4908.91 | F26: 8776.695 | G26: 6389.1091 | H26: 6526.8667 | I26: 2510.2 | J26: 0.4005748 | K26: 3867.785 | L26: 0.78791117 | M26: 2387.5859 | N26: 0.37369621 | O26: 6966.2267
