Workbook

Sheet Menu Principal (2)

Sheet Framework COBIT

Sheet Instruções
N1: Instruções
B2: Olá!
B4: Ficamos felizes e parabenizamos pelo seu interesse em avaliar o Nível de Maturidade da sua TI!
B6: Este material foi elaborado seguindo os princípios da metodologia COBIT e tem como objetivo ajudar os profissionais de TI avaliarem e assim proporem uma transformação para sua TI.
B7: Seguem Instruções para que você consiga fazer a avaliação no menor tempo possível e com muita assetividade:
B9: 1) No menu Principal você encontrará links (botões) para abrir cada um dos 4 Domínios da metodologia
B10: 2) Cada domínio é composto de perguntas, para cada pergunta você deverá atribuir uma nota entre 0-5 para situação ATUAL e META desejada
B11: 3) Nas celulas de atribuição das notas você encontrará explicações para a avaliação e atribuição dos pontos
B12: 4) Caso você não tenha resposta para todas as perguntas, faça entrevistas com os respectivos responsáveis para que lhe ajudem na atribuição das notas, você também poderá incluir comentários
B13: 5) Consulte o framework do COBIT clicando na imagem do COBIT no menu principal
B14: 6) Tempo estimado para cada Domínio:
B15: Planejar e Organizar = 20 Min
B16: Adquirir e Implementar = 15 Min
... B25: Contatos:
B26: email: | C26: sidnei.goncalves@up2place.com.br
B27: Fone: | C27: (11) 3198-3696
B28: Chat: | C28: www.up2place.com.br
B30: Boa Avaliação!
B32: Sidnei Gonçalves
B33: Co-Fundador UP2Place

Sheet Quadro Geral
A1: ACME
A2: Levantamento do Nível de Maturidade de TI
C4: Abrangência | S4: Total Objetos Ctrl
A5: Domínio | B5: ID/ Processo | C5: 1 | D5: 2 | E5: 3 | F5: 4 | G5: 5 | H5: 6 | I5: 7 | J5: 8 | K5: 9 | L5: 10 | M5: 11 | N5: 12 | O5: 13 | P5: 14 | Q5: 15 | R5: Maturidade Avaliada | S5: Total Objetivos Ctrl | T5: 0 - Inexistente | U5: 1- Inicial | V5: 2- Repetitivo/Intuitivo | W5: 3- Definidos | X5: 4- Gerenciados | Y5: 5- Otimizados | Z5: META ESTABELECIDA
A6: PO | B6: Planejar e Organizar
B7: PO1 - Definir um Plano Estratégico de TI | C7: =+'PO - Questionário'!D5 -> 0 | D7: =+'PO - Questionário'!D6 -> 0 | E7: =+'PO - Questionário'!D7 -> 0 | F7: =+'PO - Questionário'!D8 -> 0 | G7: =+'PO - Questionário'!D9 -> 0 | H7: =+'PO - Questionário'!D10 -> 0 | R7: =+SUM(C7:Q7)/S7 -> 0 | S7: =COUNTA(C7:Q7) -> 6 | T7: =IF($R7<1,"X","") -> X | U7: =IF( AND($R7>=1,$R7<2),"X","") | V7: =IF( AND($R7>=2,$R7<3),"X","") | W7: =IF( AND($R7>=3,$R7<4),"X","") | X7: =IF( AND($R7>=4,$R7<5),"X","") | Y7: =IF( $R7>=5,"X","") | Z7: ='PO - Questionário'!E11 -> 0
B8: PO2 - Definir a Arquitetura da Informação | C8: =+'PO - Questionário'!D15 -> 0 | D8: =+'PO - Questionário'!D16 -> 0 | E8: =+'PO - Questionário'!D17 -> 0 | F8: =+'PO - Questionário'!D18 -> 0 | R8: =+SUM(C8:Q8)/S8 -> 0 | S8: =COUNTA(C8:Q8) -> 4 | T8: =IF($R8<1,"X","") -> X | U8: =IF( AND($R8>=1,$R8<2),"X","") | V8: =IF( AND($R8>=2,$R8<3),"X","") | W8: =IF( AND($R8>=3,$R8<4),"X","") | X8: =IF( AND($R8>=4,$R8<5),"X","") | Y8: =IF( $R8>=5,"X","") | Z8: ='PO - Questionário'!E19 -> 0
B9: PO3 - Determinar o Direcionamento Tecnológico | C9: =+'PO - Questionário'!D23 -> 0 | D9: =+'PO - Questionário'!D24 -> 0 | E9: =+'PO - Questionário'!D25 -> 0 | F9: =+'PO - Questionário'!D26 -> 0 | G9: =+'PO - Questionário'!D27 -> 0 | R9: =+SUM(C9:Q9)/S9 -> 0 | S9: =COUNTA(C9:Q9) -> 5 | T9: =IF($R9<1,"X","") -> X | U9: =IF( AND($R9>=1,$R9<2),"X","") | V9: =IF( AND($R9>=2,$R9<3),"X","") | W9: =IF( AND($R9>=3,$R9<4),"X","") | X9: =IF( AND($R9>=4,$R9<5),"X","") | Y9: =IF( $R9>=5,"X","") | Z9: ='PO - Questionário'!E28 -> 0
B10: PO4 - Definir os Processos, Organização e os Relacionamentos de TI | C10: =+'PO - Questionário'!D32 -> 0 | D10: =+'PO - Questionário'!D33 -> 0 | E10: =+'PO - Questionário'!D34 -> 0 | F10: =+'PO - Questionário'!D35 -> 0 | G10: =+'PO - Questionário'!D36 -> 0 | H10: =+'PO - Questionário'!D37 -> 0 | I10: =+'PO - Questionário'!D38 -> 0 | J10: =+'PO - Questionário'!D39 -> 0 | K10: =+'PO - Questionário'!D40 -> 0 | L10: =+'PO - Questionário'!D41 -> 0 | M10: =+'PO - Questionário'!D42 -> 0 | N10: =+'PO - Questionário'!D43 -> 0 | O10: =+'PO - Questionário'!D44 -> 0 | P10: =+'PO - Questionário'!D45 -> 0 | Q10: =+'PO - Questionário'!D46 -> 0 | R10: =+SUM(C10:Q10)/S10 -> 0 | S10: =COUNTA(C10:Q10) -> 15 | T10: =IF($R10<1,"X","") -> X | U10: =IF( AND($R10>=1,$R10<2),"X","") | V10: =IF( AND($R10>=2,$R10<3),"X","") | W10: =IF( AND($R10>=3,$R10<4),"X","") | X10: =IF( AND($R10>=4,$R10<5),"X","") | Y10: =IF( $R10>=5,"X","") | Z10: ='PO - Questionário'!E47 -> 0
B11: PO5 - Gerenciar o Investimento de TI | C11: =+'PO - Questionário'!D51 -> 0 | D11: =+'PO - Questionário'!D52 -> 0 | E11: =+'PO - Questionário'!D53 -> 0 | F11: =+'PO - Questionário'!D54 -> 0 | G11: =+'PO - Questionário'!D55 -> 0 | R11: =+SUM(C11:Q11)/S11 -> 0 | S11: =COUNTA(C11:Q11) -> 5 | T11: =IF($R11<1,"X","") -> X | U11: =IF( AND($R11>=1,$R11<2),"X","") | V11: =IF( AND($R11>=2,$R11<3),"X","") | W11: =IF( AND($R11>=3,$R11<4),"X","") | X11: =IF( AND($R11>=4,$R11<5),"X","") | Y11: =IF( $R11>=5,"X","") | Z11: ='PO - Questionário'!E56 -> 0
B12: PO6 - Comunicar as Diretrizes e Expectativas da Diretoria | C12: =+'PO - Questionário'!D60 -> 0 | D12: =+'PO - Questionário'!D61 -> 0 | E12: =+'PO - Questionário'!D62 -> 0 | F12: =+'PO - Questionário'!D63 -> 0 | G12: =+'PO - Questionário'!D64 -> 0 | R12: =+SUM(C12:Q12)/S12 -> 0 | S12: =COUNTA(C12:Q12) -> 5 | T12: =IF($R12<1,"X","") -> X | U12: =IF( AND($R12>=1,$R12<2),"X","") | V12: =IF( AND($R12>=2,$R12<3),"X","") | W12: =IF( AND($R12>=3,$R12<4),"X","") | X12: =IF( AND($R12>=4,$R12<5),"X","") | Y12: =IF( $R12>=5,"X","") | Z12: ='PO - Questionário'!E65 -> 0
B13: PO7 - Gerenciar os Recursos Humanos de TI | C13: =+'PO - Questionário'!D69 -> 0 | D13: =+'PO - Questionário'!D70 -> 0 | E13: =+'PO - Questionário'!D71 -> 0 | F13: =+'PO - Questionário'!D72 -> 0 | G13: =+'PO - Questionário'!D73 -> 0 | H13: =+'PO - Questionário'!D74 -> 0 | I13: =+'PO - Questionário'!D75 -> 0 | J13: =+'PO - Questionário'!D76 -> 0 | R13: =+SUM(C13:Q13)/S13 -> 0 | S13: =COUNTA(C13:Q13) -> 8 | T13: =IF($R13<1,"X","") -> X | U13: =IF( AND($R13>=1,$R13<2),"X","") | V13: =IF( AND($R13>=2,$R13<3),"X","") | W13: =IF( AND($R13>=3,$R13<4),"X","") | X13: =IF( AND($R13>=4,$R13<5),"X","") | Y13: =IF( $R13>=5,"X","") | Z13: ='PO - Questionário'!E77 -> 0
B14: PO8 - Gerenciar a Qualidade | C14: =+'PO - Questionário'!D81 -> 0 | D14: =+'PO - Questionário'!D82 -> 0 | E14: =+'PO - Questionário'!D83 -> 0 | F14: =+'PO - Questionário'!D84 -> 0 | G14: =+'PO - Questionário'!D85 -> 0 | H14: =+'PO - Questionário'!D86 -> 0 | R14: =+SUM(C14:Q14)/S14 -> 0 | S14: =COUNTA(C14:Q14) -> 6 | T14: =IF($R14<1,"X","") -> X | U14: =IF( AND($R14>=1,$R14<2),"X","") | V14: =IF( AND($R14>=2,$R14<3),"X","") | W14: =IF( AND($R14>=3,$R14<4),"X","") | X14: =IF( AND($R14>=4,$R14<5),"X","") | Y14: =IF( $R14>=5,"X","") | Z14: ='PO - Questionário'!E87 -> 0
B15: PO9 - Avaliar e Gerenciar os Riscos de TI | C15: =+'PO - Questionário'!D91 -> 0 | D15: =+'PO - Questionário'!D92 -> 0 | E15: =+'PO - Questionário'!D93 -> 0 | F15: =+'PO - Questionário'!D94 -> 0 | G15: =+'PO - Questionário'!D95 -> 0 | H15: =+'PO - Questionário'!D96 -> 0 | R15: =+SUM(C15:Q15)/S15 -> 0 | S15: =COUNTA(C15:Q15) -> 6 | T15: =IF($R15<1,"X","") -> X | U15: =IF( AND($R15>=1,$R15<2),"X","") | V15: =IF( AND($R15>=2,$R15<3),"X","") | W15: =IF( AND($R15>=3,$R15<4),"X","") | X15: =IF( AND($R15>=4,$R15<5),"X","") | Y15: =IF( $R15>=5,"X","") | Z15: ='PO - Questionário'!E97 -> 0
B16: PO10 - Gerenciar Projetos | C16: =+'PO - Questionário'!D101 -> 0 | D16: =+'PO - Questionário'!D102 -> 0 | E16: =+'PO - Questionário'!D103 -> 0 | F16: =+'PO - Questionário'!D104 -> 0 | G16: =+'PO - Questionário'!D105 -> 0 | H16: =+'PO - Questionário'!D106 -> 0 | I16: =+'PO - Questionário'!D107 -> 0 | J16: =+'PO - Questionário'!D108 -> 0 | K16: =+'PO - Questionário'!D109 -> 0 | L16: =+'PO - Questionário'!D110 -> 0 | M16: =+'PO - Questionário'!D111 -> 0 | N16: =+'PO - Questionário'!D112 -> 0 | O16: =+'PO - Questionário'!D113 -> 0 | P16: =+'PO - Questionário'!D114 -> 0 | R16: =+SUM(C16:Q16)/S16 -> 0 | S16: =COUNTA(C16:Q16) -> 14 | T16: =IF($R16<1,"X","") -> X | U16: =IF( AND($R16>=1,$R16<2),"X","") | V16: =IF( AND($R16>=2,$R16<3),"X","") | W16: =IF( AND($R16>=3,$R16<4),"X","") | X16: =IF( AND($R16>=4,$R16<5),"X","") | Y16: =IF( $R16>=5,"X","") | Z16: ='PO - Questionário'!E115 -> 0
A17: AI | B17: Adquirir e Implementar
B18: AI1 - Identificar Solução Automatizadas | C18: =+'AI - Questionário'!$D6 -> 0 | D18: =+'AI - Questionário'!D7 -> 0 | E18: =+'AI - Questionário'!D8 -> 0 | F18: =+'AI - Questionário'!D9 -> 0 | R18: =+SUM(C18:Q18)/S18 -> 0 | S18: =COUNTA(C18:Q18) -> 4 | T18: =IF($R18<1,"X","") -> X | U18: =IF( AND($R18>=1,$R18<2),"X","") | V18: =IF( AND($R18>=2,$R18<3),"X","") | W18: =IF( AND($R18>=3,$R18<4),"X","") | X18: =IF( AND($R18>=4,$R18<5),"X","") | Y18: =IF( $R18>=5,"X","") | Z18: ='AI - Questionário'!E10 -> 0
B19: AI2 - Adquirir e Manter Software Aplicativo | C19: =+'AI - Questionário'!D14 -> 0 | D19: =+'AI - Questionário'!D15 -> 0 | E19: =+'AI - Questionário'!D16 -> 0 | F19: =+'AI - Questionário'!D17 -> 0 | G19: =+'AI - Questionário'!D18 -> 0 | H19: =+'AI - Questionário'!D19 -> 0 | I19: =+'AI - Questionário'!D20 -> 0 | J19: =+'AI - Questionário'!D21 -> 0 | K19: =+'AI - Questionário'!D22 -> 0 | L19: =+'AI - Questionário'!D23 -> 0 | R19: =+SUM(C19:Q19)/S19 -> 0 | S19: =COUNTA(C19:Q19) -> 10 | T19: =IF($R19<1,"X","") -> X | U19: =IF( AND($R19>=1,$R19<2),"X","") | V19: =IF( AND($R19>=2,$R19<3),"X","") | W19: =IF( AND($R19>=3,$R19<4),"X","") | X19: =IF( AND($R19>=4,$R19<5),"X","") | Y19: =IF( $R19>=5,"X","") | Z19: ='AI - Questionário'!E24 -> 0
B20: AI3 - Adquirir e Manter Infraestrutura de Tecnologia | C20: =+'AI - Questionário'!D28 -> 0 | D20: =+'AI - Questionário'!D29 -> 0 | E20: =+'AI - Questionário'!D30 -> 0 | F20: =+'AI - Questionário'!D31 -> 0 | R20: =+SUM(C20:Q20)/S20 -> 0 | S20: =COUNTA(C20:Q20) -> 4 | T20: =IF($R20<1,"X","") -> X | U20: =IF( AND($R20>=1,$R20<2),"X","") | V20: =IF( AND($R20>=2,$R20<3),"X","") | W20: =IF( AND($R20>=3,$R20<4),"X","") | X20: =IF( AND($R20>=4,$R20<5),"X","") | Y20: =IF( $R20>=5,"X","") | Z20: ='AI - Questionário'!E32 -> 0
B21: AI4 - Habilitar Operação e Uso | C21: =+'AI - Questionário'!D36 -> 0 | D21: =+'AI - Questionário'!D37 -> 0 | E21: =+'AI - Questionário'!D38 -> 0 | F21: =+'AI - Questionário'!D39 -> 0 | R21: =+SUM(C21:Q21)/S21 -> 0 | S21: =COUNTA(C21:Q21) -> 4 | T21: =IF($R21<1,"X","") -> X | U21: =IF( AND($R21>=1,$R21<2),"X","") | V21: =IF( AND($R21>=2,$R21<3),"X","") | W21: =IF( AND($R21>=3,$R21<4),"X","") | X21: =IF( AND($R21>=4,$R21<5),"X","") | Y21: =IF( $R21>=5,"X","") | Z21: ='AI - Questionário'!E40 -> 0
B22: AI5 - Adquirir Recursos de TI | C22: =+'AI - Questionário'!D44 -> 0 | D22: =+'AI - Questionário'!D45 -> 0 | E22: =+'AI - Questionário'!D46 -> 0 | F22: =+'AI - Questionário'!D47 -> 0 | R22: =+SUM(C22:Q22)/S22 -> 0 | S22: =COUNTA(C22:Q22) -> 4 | T22: =IF($R22<1,"X","") -> X | U22: =IF( AND($R22>=1,$R22<2),"X","") | V22: =IF( AND($R22>=2,$R22<3),"X","") | W22: =IF( AND($R22>=3,$R22<4),"X","") | X22: =IF( AND($R22>=4,$R22<5),"X","") | Y22: =IF( $R22>=5,"X","") | Z22: ='AI - Questionário'!E48 -> 0
B23: AI6 - Gerenciar Mudanças | C23: =+'AI - Questionário'!D52 -> 0 | D23: =+'AI - Questionário'!D53 -> 0 | E23: =+'AI - Questionário'!D54 -> 0 | F23: =+'AI - Questionário'!D55 -> 0 | G23: =+'AI - Questionário'!D56 -> 0 | R23: =+SUM(C23:Q23)/S23 -> 0 | S23: =COUNTA(C23:Q23) -> 5 | T23: =IF($R23<1,"X","") -> X | U23: =IF( AND($R23>=1,$R23<2),"X","") | V23: =IF( AND($R23>=2,$R23<3),"X","") | W23: =IF( AND($R23>=3,$R23<4),"X","") | X23: =IF( AND($R23>=4,$R23<5),"X","") | Y23: =IF( $R23>=5,"X","") | Z23: ='AI - Questionário'!E57 -> 0
B24: AI7 - Instalar e Homologar Soluções e Mudanças | C24: =+'AI - Questionário'!D61 -> 0 | D24: =+'AI - Questionário'!D62 -> 0 | E24: =+'AI - Questionário'!D63 -> 0 | F24: =+'AI - Questionário'!D64 -> 0 | G24: =+'AI - Questionário'!D65 -> 0 | H24: =+'AI - Questionário'!D66 -> 0 | I24: =+'AI - Questionário'!D67 -> 0 | J24: =+'AI - Questionário'!D68 -> 0 | K24: =+'AI - Questionário'!D69 -> 0 | R24: =+SUM(C24:Q24)/S24 -> 0 | S24: =COUNTA(C24:Q24) -> 9 | T24: =IF($R24<1,"X","") -> X | U24: =IF( AND($R24>=1,$R24<2),"X","") | V24: =IF( AND($R24>=2,$R24<3),"X","") | W24: =IF( AND($R24>=3,$R24<4),"X","") | X24: =IF( AND($R24>=4,$R24<5),"X","") | Y24: =IF( $R24>=5,"X","") | Z24: ='AI - Questionário'!E70 -> 0
A25: DS | B25: Entregar Suportar
B26: DS1 - Definir e Gerenciar Níveis de Serviços | C26: =+'DS - Questionário'!D6 -> 0 | D26: =+'DS - Questionário'!D7 -> 0 | E26: =+'DS - Questionário'!D8 -> 0 | F26: =+'DS - Questionário'!D9 -> 0 | G26: =+'DS - Questionário'!D10 -> 0 | H26: =+'DS - Questionário'!D11 -> 0 | R26: =+SUM(C26:Q26)/S26 -> 0 | S26: =COUNTA(C26:Q26) -> 6 | T26: =IF($R26<1,"X","") -> X | U26: =IF( AND($R26>=1,$R26<2),"X","") | V26: =IF( AND($R26>=2,$R26<3),"X","") | W26: =IF( AND($R26>=3,$R26<4),"X","") | X26: =IF( AND($R26>=4,$R26<5),"X","") | Y26: =IF( $R26>=5,"X","") | Z26: ='DS - Questionário'!E12 -> 0
B27: DS2 - Gerenciar Serviços de Terceiros | C27: =+'DS - Questionário'!D16 -> 0 | D27: =+'DS - Questionário'!D17 -> 0 | E27: =+'DS - Questionário'!D18 -> 0 | F27: =+'DS - Questionário'!D19 -> 0 | R27: =+SUM(C27:Q27)/S27 -> 0 | S27: =COUNTA(C27:Q27) -> 4 | T27: =IF($R27<1,"X","") -> X | U27: =IF( AND($R27>=1,$R27<2),"X","") | V27: =IF( AND($R27>=2,$R27<3),"X","") | W27: =IF( AND($R27>=3,$R27<4),"X","") | X27: =IF( AND($R27>=4,$R27<5),"X","") | Y27: =IF( $R27>=5,"X","") | Z27: ='DS - Questionário'!E20 -> 0
B28: DS3 - Gerenciar Capacidade e Desempenho | C28: =+'DS - Questionário'!D24 -> 0 | D28: =+'DS - Questionário'!D25 -> 0 | E28: =+'DS - Questionário'!D26 -> 0 | F28: =+'DS - Questionário'!D27 -> 0 | G28: =+'DS - Questionário'!D28 -> 0 | R28: =+SUM(C28:Q28)/S28 -> 0 | S28: =COUNTA(C28:Q28) -> 5 | T28: =IF($R28<1,"X","") -> X | U28: =IF( AND($R28>=1,$R28<2),"X","") | V28: =IF( AND($R28>=2,$R28<3),"X","") | W28: =IF( AND($R28>=3,$R28<4),"X","") | X28: =IF( AND($R28>=4,$R28<5),"X","") | Y28: =IF( $R28>=5,"X","") | Z28: ='DS - Questionário'!E29 -> 0
B29: DS4 - Assegurar Continuidade de Serviços: | C29: =+'DS - Questionário'!D33 -> 0 | D29: =+'DS - Questionário'!D34 -> 0 | E29: =+'DS - Questionário'!D35 -> 0 | F29: =+'DS - Questionário'!D36 -> 0 | G29: =+'DS - Questionário'!D37 -> 0 | H29: =+'DS - Questionário'!D38 -> 0 | I29: =+'DS - Questionário'!D39 -> 0 | J29: =+'DS - Questionário'!D41 -> 0 | K29: =+'DS - Questionário'!D42 -> 0 | R29: =+SUM(C29:Q29)/S29 -> 0 | S29: =COUNTA(C29:Q29) -> 9 | T29: =IF($R29<1,"X","") -> X | U29: =IF( AND($R29>=1,$R29<2),"X","") | V29: =IF( AND($R29>=2,$R29<3),"X","") | W29: =IF( AND($R29>=3,$R29<4),"X","") | X29: =IF( AND($R29>=4,$R29<5),"X","") | Y29: =IF( $R29>=5,"X","") | Z29: ='DS - Questionário'!E43 -> 0
B30: DS5 - Assegurar a Segurança dos Serviços | C30: =+'DS - Questionário'!D47 -> 0 | D30: =+'DS - Questionário'!D48 -> 0 | E30: =+'DS - Questionário'!D49 -> 0 | F30: =+'DS - Questionário'!D50 -> 0 | G30: =+'DS - Questionário'!D51 -> 0 | H30: =+'DS - Questionário'!D52 -> 0 | I30: =+'DS - Questionário'!D53 -> 0 | J30: =+'DS - Questionário'!D54 -> 0 | K30: =+'DS - Questionário'!D55 -> 0 | L30: =+'DS - Questionário'!D56 -> 0 | M30: =+'DS - Questionário'!D57 -> 0 | R30: =+SUM(C30:Q30)/S30 -> 0 | S30: =COUNTA(C30:Q30) -> 11 | T30: =IF($R30<1,"X","") -> X | U30: =IF( AND($R30>=1,$R30<2),"X","") | V30: =IF( AND($R30>=2,$R30<3),"X","") | W30: =IF( AND($R30>=3,$R30<4),"X","") | X30: =IF( AND($R30>=4,$R30<5),"X","") | Y30: =IF( $R30>=5,"X","") | Z30: ='DS - Questionário'!E58 -> 0
B31: DS6 - Identificar e Alocar Custos | C31: =+'DS - Questionário'!D62 -> 0 | D31: =+'DS - Questionário'!D63 -> 0 | E31: =+'DS - Questionário'!D64 -> 0 | F31: =+'DS - Questionário'!D65 -> 0 | R31: =+SUM(C31:Q31)/S31 -> 0 | S31: =COUNTA(C31:Q31) -> 4 | T31: =IF($R31<1,"X","") -> X | U31: =IF( AND($R31>=1,$R31<2),"X","") | V31: =IF( AND($R31>=2,$R31<3),"X","") | W31: =IF( AND($R31>=3,$R31<4),"X","") | X31: =IF( AND($R31>=4,$R31<5),"X","") | Y31: =IF( $R31>=5,"X","") | Z31: ='DS - Questionário'!E66 -> 0
B32: DS7 - Educar e Treinar os Usuários | C32: =+'DS - Questionário'!D70 -> 0 | D32: =+'DS - Questionário'!D71 -> 0 | E32: =+'DS - Questionário'!D72 -> 0 | R32: =+SUM(C32:Q32)/S32 -> 0 | S32: =COUNTA(C32:Q32) -> 3 | T32: =IF($R32<1,"X","") -> X | U32: =IF( AND($R32>=1,$R32<2),"X","") | V32: =IF( AND($R32>=2,$R32<3),"X","") | W32: =IF( AND($R32>=3,$R32<4),"X","") | X32: =IF( AND($R32>=4,$R32<5),"X","") | Y32: =IF( $R32>=5,"X","") | Z32: ='DS - Questionário'!E73 -> 0
B33: DS8 - Gerenciar a Central de Serviço e os Incidentes | C33: =+'DS - Questionário'!D77 -> 0 | D33: =+'DS - Questionário'!D78 -> 0 | E33: =+'DS - Questionário'!D79 -> 0 | F33: =+'DS - Questionário'!D80 -> 0 | G33: =+'DS - Questionário'!D81 -> 0 | R33: =+SUM(C33:Q33)/S33 -> 0 | S33: =COUNTA(C33:Q33) -> 5 | T33: =IF($R33<1,"X","") -> X | U33: =IF( AND($R33>=1,$R33<2),"X","") | V33: =IF( AND($R33>=2,$R33<3),"X","") | W33: =IF( AND($R33>=3,$R33<4),"X","") | X33: =IF( AND($R33>=4,$R33<5),"X","") | Y33: =IF( $R33>=5,"X","") | Z33: ='DS - Questionário'!E82 -> 0
B34: DS9 - Gerenciar a Configuração | C34: =+'DS - Questionário'!D86 -> 0 | D34: =+'DS - Questionário'!D87 -> 0 | E34: =+'DS - Questionário'!D88 -> 0 | R34: =+SUM(C34:Q34)/S34 -> 0 | S34: =COUNTA(C34:Q34) -> 3 | T34: =IF($R34<1,"X","") -> X | U34: =IF( AND($R34>=1,$R34<2),"X","") | V34: =IF( AND($R34>=2,$R34<3),"X","") | W34: =IF( AND($R34>=3,$R34<4),"X","") | X34: =IF( AND($R34>=4,$R34<5),"X","") | Y34: =IF( $R34>=5,"X","") | Z34: ='DS - Questionário'!E89 -> 0
B35: DS10 - Gerenciar os Problemas | C35: =+'DS - Questionário'!D93 -> 0 | D35: =+'DS - Questionário'!D94 -> 0 | R35: =+SUM(C35:Q35)/S35 -> 0 | S35: =COUNTA(C35:Q35) -> 2 | T35: =IF($R35<1,"X","") -> X | U35: =IF( AND($R35>=1,$R35<2),"X","") | V35: =IF( AND($R35>=2,$R35<3),"X","") | W35: =IF( AND($R35>=3,$R35<4),"X","") | X35: =IF( AND($R35>=4,$R35<5),"X","") | Y35: =IF( $R35>=5,"X","") | Z35: ='DS - Questionário'!E95 -> 0
B36: DS11 - Gerenciar Dados | C36: =+'DS - Questionário'!D99 -> 0 | D36: =+'DS - Questionário'!D100 -> 0 | E36: =+'DS - Questionário'!D101 -> 0 | F36: =+'DS - Questionário'!D102 -> 0 | G36: =+'DS - Questionário'!D103 -> 0 | H36: =+'DS - Questionário'!D104 -> 0 | R36: =+SUM(C36:Q36)/S36 -> 0 | S36: =COUNTA(C36:Q36) -> 6 | T36: =IF($R36<1,"X","") -> X | U36: =IF( AND($R36>=1,$R36<2),"X","") | V36: =IF( AND($R36>=2,$R36<3),"X","") | W36: =IF( AND($R36>=3,$R36<4),"X","") | X36: =IF( AND($R36>=4,$R36<5),"X","") | Y36: =IF( $R36>=5,"X","") | Z36: ='DS - Questionário'!E105 -> 0
B37: DS12- Gerenciar Ambiente Físico | C37: =+'DS - Questionário'!D109 -> 0 | D37: =+'DS - Questionário'!D110 -> 0 | E37: =+'DS - Questionário'!D111 -> 0 | F37: =+'DS - Questionário'!D112 -> 0 | G37: =+'DS - Questionário'!D113 -> 0 | R37: =+SUM(C37:Q37)/S37 -> 0 | S37: =COUNTA(C37:Q37) -> 5 | T37: =IF($R37<1,"X","") -> X | U37: =IF( AND($R37>=1,$R37<2),"X","") | V37: =IF( AND($R37>=2,$R37<3),"X","") | W37: =IF( AND($R37>=3,$R37<4),"X","") | X37: =IF( AND($R37>=4,$R37<5),"X","") | Y37: =IF( $R37>=5,"X","") | Z37: ='DS - Questionário'!E114 -> 0
B38: DS13 - Gerenciar operações | C38: =+'DS - Questionário'!D118 -> 0 | D38: =+'DS - Questionário'!D119 -> 0 | E38: =+'DS - Questionário'!D120 -> 0 | F38: =+'DS - Questionário'!D121 -> 0 | G38: =+'DS - Questionário'!D122 -> 0 | R38: =+SUM(C38:Q38)/S38 -> 0 | S38: =COUNTA(C38:Q38) -> 5 | T38: =IF($R38<1,"X","") -> X | U38: =IF( AND($R38>=1,$R38<2),"X","") | V38: =IF( AND($R38>=2,$R38<3),"X","") | W38: =IF( AND($R38>=3,$R38<4),"X","") | X38: =IF( AND($R38>=4,$R38<5),"X","") | Y38: =IF( $R38>=5,"X","") | Z38: ='DS - Questionário'!E123 -> 0
A39: MA | B39: Monitorar e Avaliar
B40: MA1 - Monitorar e Avaliar o Desempenho | C40: =+'MA - Questionário'!D7 -> 0 | D40: =+'MA - Questionário'!D8 -> 0 | E40: =+'MA - Questionário'!D9 -> 0 | F40: =+'MA - Questionário'!D10 -> 0 | G40: =+'MA - Questionário'!D11 -> 0 | H40: =+'MA - Questionário'!D12 -> 0 | R40: =+SUM(C40:Q40)/S40 -> 0 | S40: =COUNTA(C40:Q40) -> 6 | T40: =IF($R40<1,"X","") -> X | U40: =IF( AND($R40>=1,$R40<2),"X","") | V40: =IF( AND($R40>=2,$R40<3),"X","") | W40: =IF( AND($R40>=3,$R40<4),"X","") | X40: =IF( AND($R40>=4,$R40<5),"X","") | Y40: =IF( $R40>=5,"X","") | Z40: ='MA - Questionário'!E13 -> 0
B41: MA2 - Monitorar e Avaliar os Controles Internos | C41: =+'MA - Questionário'!D17 -> 0 | D41: =+'MA - Questionário'!D18 -> 0 | E41: =+'MA - Questionário'!D19 -> 0 | F41: =+'MA - Questionário'!D20 -> 0 | G41: =+'MA - Questionário'!D21 -> 0 | H41: =+'MA - Questionário'!D22 -> 0 | I41: =+'MA - Questionário'!D23 -> 0 | R41: =+SUM(C41:Q41)/S41 -> 0 | S41: =COUNTA(C41:Q41) -> 7 | T41: =IF($R41<1,"X","") -> X | U41: =IF( AND($R41>=1,$R41<2),"X","") | V41: =IF( AND($R41>=2,$R41<3),"X","") | W41: =IF( AND($R41>=3,$R41<4),"X","") | X41: =IF( AND($R41>=4,$R41<5),"X","") | Y41: =IF( $R41>=5,"X","") | Z41: ='MA - Questionário'!E24 -> 0
B42: MA3 - Assegurar a Conformidade com Requisitos Externos | C42: =+'MA - Questionário'!D28 -> 0 | D42: =+'MA - Questionário'!D29 -> 0 | E42: =+'MA - Questionário'!D30 -> 0 | F42: =+'MA - Questionário'!D31 -> 0 | G42: =+'MA - Questionário'!D32 -> 0 | R42: =+SUM(C42:Q42)/S42 -> 0 | S42: =COUNTA(C42:Q42) -> 5 | T42: =IF($R42<1,"X","") -> X | U42: =IF( AND($R42>=1,$R42<2),"X","") | V42: =IF( AND($R42>=2,$R42<3),"X","") | W42: =IF( AND($R42>=3,$R42<4),"X","") | X42: =IF( AND($R42>=4,$R42<5),"X","") | Y42: =IF( $R42>=5,"X","") | Z42: ='MA - Questionário'!E33 -> 0
B43: MA4 - Prover a Governança de TI | C43: =+'MA - Questionário'!D37 -> 0 | D43: =+'MA - Questionário'!D38 -> 0 | E43: =+'MA - Questionário'!D39 -> 0 | F43: =+'MA - Questionário'!D40 -> 0 | G43: =+'MA - Questionário'!D41 -> 0 | H43: =+'MA - Questionário'!D42 -> 0 | I43: =+'MA - Questionário'!D43 -> 0 | R43: =+SUM(C43:Q43)/S43 -> 0 | S43: =COUNTA(C43:Q43) -> 7 | T43: =IF($R43<1,"X","") -> X | U43: =IF( AND($R43>=1,$R43<2),"X","") | V43: =IF( AND($R43>=2,$R43<3),"X","") | W43: =IF( AND($R43>=3,$R43<4),"X","") | X43: =IF( AND($R43>=4,$R43<5),"X","") | Y43: =IF( $R43>=5,"X","") | Z43: ='MA - Questionário'!E44 -> 0
A44: Maturidade Geral da Diretoria de TI | R44: =(MEDIAN(R40:R43)+MEDIAN(R26:R38)+MEDIAN(R18:R24)+MEDIAN(R7:R16))/4 -> 0 | T44: =IF($R44<1,"X","") -> X | U44: =IF( AND($R44>=1,$R44<2),"X","") | V44: =IF( AND($R44>=2,$R44<3),"X","") | W44: =IF( AND($R44>=3,$R44<4),"X","") | X44: =IF( AND($R44>=4,$R44<5),"X","") | Y44: =IF( $R44>=5,"X","") | Z44: =(MEDIAN(Z40:Z43)+MEDIAN(Z26:Z38)+MEDIAN(Z18:Z24)+MEDIAN(Z7:Z16))/4 -> 0

Sheet PO - Questionário
A3: PO1 | B3: Definir um plano estratégico de TI | D3: Atual | E3: Meta
A4: Objetivos Controle | C4: Pergunta | D4: (0-5) | E4: (0-5) | F4: Comentários
A5: 1 | B5: Gerenciamento do valor de TI | C5: Há um alinhamento da estratégia de TI com a estratégia da empresa? Se sim esta estratégia é avaliada periodicamente? | D5: 0 | E5: 0
A6: 2 | B6: Alinhamento entre TI e Negócio | C6: As prioridades de negócio estão alinhadas com as prioridades de TI? | D6: 0 | E6: 0
A7: 3 | B7: Avaliação da Capacidade e Desempenho Correntes | C7: De acordo com o plano de negócios atual TI consegue entregar os produtos esperados e possui capacidade de planejamento para demandas futuras fruto do crescimento do negócio? | D7: 0 | E7: 0
A8: 4 | B8: Plano Estratégico de TI | C8: Existe um plano estratégico de TI de forma que TI contribua com os objetivos de negócio da empresa? | D8: 0 | E8: 0
A9: 5 | B9: Planos Táticos de TI | C9: Há um plano tático que direcionem os projetos e por consequencia as iniciativas e recursos necessários para implantação dos mesmos? | D9: 0 | E9: 0
A10: 6 | B10: Gerenciamento do Portfólio de TI | C10: Há uma gestão do portfólio de projetos de TI alinhada com os objetivos de negócio e priorizados conforme a sua relevância para este objetivos? | D10: 0 | E10: 0
A11: Maturidade do Processo | D11: =+SUM(D5:D10)/COUNTA(D5:D10) -> 0 | E11: =+SUM(E5:E10)/COUNTA(E5:E10) -> 0
A13: PO2 | B13: Definir a arquitetura da informação
A14: Objetivos Controle | C14: Pergunta | D14: (0-5) | E14: (0-5) | F14: Comentários
A15: 1 | B15: Modelo de Arquitetura da Informação da XP | C15: Existe uma aqruitetura definida que permita o desenvolvimento de aplicações que suportem a tomada de decisão de negócios provendo suporte a segurança da informação? | D15: 0 | E15: 0
A16: 2 | B16: Dicionário de Dados corporativo e regras de sintaxe de dados | C16: Há um dicionário de dados e regras de sintaxe definidas que permita o compartilhamento por toda a organização previnindo a duplicidade de dados? | D16: 0 | E16: 0
A17: 3 | B17: Esquema de Classificação de Dados | C17: Os dados são classificados quanto ao acesso (público, confidencial e restrito) e há a definição do proprietário da informação e das permissãoes de acesso? | D17: 0 | E17: 0
A18: 4 | B18: Gerenciamento de Integridade | C18: Existem procedimentos que garantam a integridade e a concistência dos dados de forma eletrônica independente do método utilizado? | D18: 0 | E18: 0
A19: Maturidade do Processo | D19: =+SUM(D15:D18)/COUNTA(D15:D18) -> 0 | E19: =+SUM(E15:E18)/COUNTA(E15:E18) -> 0
A21: PO3 | B21: Determinar Direção Tecnológica
A22: Objetivos Controle | C22: Pergunta | D22: (0-5) | E22: (0-5) | F22: Comentários
A23: 1 | B23: Planejamento da Diretriz Tecnológica | C23: Há um processo de análise das tecnologias existentes e emergentes no sentido de direcionar o planejamento da área de tecnologia para suportar o negócio? | D23: 0 | E23: 0
A24: 2 | B24: Plano de Infraestrutura Tecnológica | C24: Há um processo que considera mudanças no ambiente competitivo, economia de escala em investimento em pessoal e sistemas, bem como melhorias na interoperabilidade entre plataformas e aplicações? Elas objetivam proporcionar contingência e um plano de aquisições? | D24: 0 | E24: 0
A25: 3 | B25: Monitoramento, Regulamentos e Tendências Futuras | C25: Há um processo para monitorar as tendências das áreas de negócio, tecnologia, infraestrutura, legal e regulatória visando antecipar impactos em TI? As consequências dessas tendências são incorporadas ao desenvolvimento do plano de infraestrutura de tecnologia de TI? | D25: 0 | E25: 0
A26: 4 | B26: Padrões tecnológicos | C26: Existe processo para prover soluções tecnológicas seguras, eficazes e consistentes, em toda a organização? Há um fórum de tecnologia para prover diretrizes tecnológicas, aconselhamento sobre a infraestrutura de produtos, orientação na seleção da tecnologia e avaliar a conformidade com estes padrões e diretrizes? | D26: 0 | E26: 0
A27: 5 | B27: Conselho de Arquitetura de TI | C27: Foi estabelecido um conselho de arquitetura de TI para prover diretrizes de arquitetura, orientar as aplicações e verificar a conformidade? | D27: 0 | E27: 0
A28: Maturidade do Processo | D28: =+SUM(D23:D27)/COUNTA(D23:D27) -> 0 | E28: =+SUM(E23:E27)/COUNTA(E23:E27) -> 0
D29: 0
A30: PO4 | B30: Definir os Processos, Organização e Relacionamentos de TI | D30: 0
A31: Objetivos Controle | C31: Pergunta | D31: (0-5) | E31: (0-5) | F31: Comentários
A32: 1 | B32: Estrutura de Processos de TI | C32: Há uma estrutura de processos e relacionamentos de TI (por exemplo, gerenciar falhas ou interposições de processos), definição de um proprietário, maturidade, medição de desempenho, melhorias, conformidade, metas de qualidade e planos para atingi-las? | D32: 0 | E32: 0
A33: 2 | B33: Comitê Estratégico de TI | C33: Foi estabelecido um comitê estratégico de TI em nível de Diretoria que assegure que a governança de TI seja devidamente considerada como parte da governança corporativa, aconselha sobre o direcionamento estratégico e analisa os principais investimentos em nome de toda a Direção? | D33: 0 | E33: 0
A34: 3 | B34: Comitê Executivo de TI | C34: Já foi estabelecido um comitê executivo (ou equivalente) composto pelas Diretorias Executiva, Negócios e TI para Determinar prioridades dos programas de investimentos em TI em linha com as estratégias e prioridades do negócio? Monitorar o estado atual dos projetos e resolver conflitos de recursos? | D34: 0 | E34: 0
A35: 4 | B35: Posicionamento Organizacional da área de TI | C35: Já foi realizado um posicionamento da área de TI na estrutura geral organizacional através de um modelo que efetivamente considere sua importância e as necessidades de contingência, considerando a importância da TI para a estratégia de negócio e o nível de dependência operacional? | D35: 0 | E35: 0
A36: 5 | B36: Estrutura Organizacional de TI | C36: Há uma estrutura organizacional interna e externa de TI que reflita as necessidades do negócio? Há um processo para revisar periodicamente a estrutura organizacional de TI e ajustar os requisitos de pessoal e estratégias de fornecimento para atender aos objetivos de negócio esperados e a possíveis situações de mudança? | D36: 0 | E36: 0
A37: 6 | B37: Definição de Papéis e Responsabilidades | C37: Estão claros,para o pessoal de TI e usuários finais, seus respectivos papéis e responsabilidades, que especifiquem a autoridade, responsabilidade e responsabilização, com o objetivo de atender às necessidades da organização? | D37: 0 | E37: 0
A38: 7 | B38: Responsabilidade pela Garantia de Qualidade | C38: É atribuida a pelo menos um colaborador a responsabilidade pelo desempenho da função de garantia de qualidade (QA, quality assurance)? | D38: 0 | E38: 0
A39: 8 | B39: Responsabilidade por Riscos, Segurança e Conformidade | C39: Há um papel definido para realizar o gerenciamento dos riscos de TI, incluindo a responsabilidade específica pela segurança da informação, segurança física e conformidade? | D39: 0 | E39: 0
A40: 9 | B40: Proprietários de Dados e Sistemas | C40: Foram estabelecidos os procedimentos e disponibilizadas as ferramentas que possibilitem tratar as responsabilidades dos proprietários dos dados e sistemas de informação? Os proprietários tomam decisões sobre a classificação da informação, dos sistemas e os protegem determinando direitos de acesso em conformidade com essa classificação? | D40: 0 | E40: 0
A41: 10 | B41: Supervisão | C41: Foram implementadas técnicas de supervisão adequadas na área de TI para assegurar que os papéis e as responsabilidades sejam adequadamente exercidos? Também é possível avaliar se todo o pessoal tem autoridade e recursos suficientes para exercer seus papéis e responsabilidades e revisar de forma geral os indicadores-chave de desempenho? | D41: 0 | E41: 0
A42: 11 | B42: Segregação de Funções | C42: Foi implementada uma separação de papéis e responsabilidades que reduza a possibilidade de um único indivíduo comprometer um processo crítico ou comprometer a segurança operacional? A gerência tem como garantir que o pessoal esteja executando apenas tarefas autorizadas relevantes aos seus respectivos cargos e posições? | D42: 0 | E42: 0
A43: 12 | B43: Recrutamento de pessoal de TI | C43: Existe um processo para avaliar os requisitos de recrutamento regularmente ou com base em grandes mudanças nos ambientes de TI, operacional ou de negócio para garantir que a área de TI tenha quantidade suficiente de pessoal para suportar de forma adequada os objetivos e metas de negócios? | D43: 0 | E43: 0
... A46: 15 | B46: Relacionamentos | C46: Já foi estabelecida uma estrutura otimizada de coordenação, comunicação e conexão entre a função de TI e diversos outros interesses dentro ou fora da área de TI; por exemplo, Diretoria, unidades de negócios, usuários individuais, fornecedores, profissionais de segurança, gerentes de risco, gerenciamento de pessoal terceirizado e externo e o grupo de conformidade corporativa (compliance)? | D46: 0 | E46: 0
A47: Maturidade do Processo | D47: =+SUM(D32:D46)/COUNTA(D32:D46) -> 0 | E47: =+SUM(E32:E46)/COUNTA(E32:E46) -> 0
A49: PO5 | B49: Gerenciar os Investimentos de TI
A50: Objetivos Controle | C50: Pergunta | D50: (0-5) | E50: (0-5) | F50: Comentários
A51: 1 | B51: Estrutura da Administração Financeira | C51: Já foi criada uma estrutura financeira para gerenciar investimentos e custos de bens e serviços de TI através de portfólios de investimentos, estudos de caso e orçamentos de TI? | D51: 0 | E51: 0
A52: 2 | B52: Priorização dentro do Orçamento de TI | C52: Há um processo de tomada de decisão para priorizar a alocação dos recursos de TI em operações, projetos e manutenção visando maximizar a contribuição da TI nos retornos dos investimentos realizados em TI e outros serviços e recursos da TI? | D52: 0 | E52: 0
A53: 3 | B53: Processo de Orçamento de TI | C53: Há um processo para preparar e controlar um orçamento que reflita as prioridades estabelecidas pelo portfólio de projetos e/ou de investimentos de TI da organização, incluindo os custos contínuos de operação e manutenção da infraestrutura atual (Opex)? | D53: 0 | E53: 0
A54: 4 | B54: Gerenciamento de Custo | C54: Há um processo de gerenciamento de custo comparando os custos e benefícios reais x planejados? | D54: 0 | E54: 0
A55: 5 | B55: Gerenciamento de Benefícios | C55: Há um processoque monitore a capacidades de TI verificando as condições de prestação de serviços pactuadas, realize monitoramento e report das contribuições esperadas de TI para com os resultados de negócio, tanto como um componente de programas de investimento em TI quanto como parte da operação de suporte regular? | D55: 0 | E55: 0
A56: Maturidade do Processo | D56: =+SUM(D51:D55)/COUNTA(D51:D55) -> 0 | E56: =+SUM(E51:E55)/COUNTA(E51:E55) -> 0
A58: PO6 | B58: Comunicar Metas e Diretrizes Gerenciais
A59: Objetivos Controle | C59: Pergunta | D59: (0-5) | E59: (0-5) | F59: Comentários
A60: 1 | B60: Política de TI e Ambiente de Controle | C60: Já foram definidos os elementos de um ambiente de controle de TI alinhados com o os processo operacional e a filosofia de gerenciamento da empresa? Entre esses elementos estão as expectativas e os requisitos de entrega de valor dos investimentos de TI, o grau de aceitação de risco, a integridade, os valores éticos, a competência do pessoal e a responsabilização.? | D60: 0 | E60: 0
A61: 2 | B61: Risco de TI Corporativo e Estrutura Interna de Controle | C61: Há uma estrutura que estabeleça uma abordagem dos riscos e controles de TI e buscando o alinhamento com as políticas e o ambiente e a estrutura de riscos e controles da organização? | D61: 0 | E61: 0
A62: 3 | B62: Gerenciamento de Políticas de TI | C62: Foi desenvolvido um conjunto de políticas para apoiar a estratégia de TI? Essas políticas incluem os objetivos das políticas, papéis e responsabilidades, processos de exceções, abordagem de conformidade, referências a procedimentos, padrões e diretrizes? | D62: 0 | E62: 0
A63: 4 | B63: Distribuição da Política | C63: Há um processo que assegure que as políticas de TI sejam exercidas e distribuídas para todo o pessoal relevante, sendo parte integrante das operações corporativas? | D63: 0 | E63: 0
A64: 5 | B64: Comunicação dos Objetivos e Diretrizes de TI | C64: É realizada comunicação no sentido de proporcionar a conscientização e entendimento dos objetivos e direcionamentos de TI de todas as partes interessadas? | D64: 0 | E64: 0
A65: Maturidade do Processo | D65: =+SUM(D60:D64)/COUNTA(D60:D64) -> 0 | E65: =+SUM(E60:E64)/COUNTA(E60:E64) -> 0
A67: PO7 | B67: Gerenciar os Recursos Humanos de TI
A68: Objetivos Controle | C68: Pergunta | D68: (0-5) | E68: (0-5) | F68: Comentários
A69: 1 | B69: Recrutamento e Retenção de Pessoal | C69: Há processos de recrutamento de pessoal estejam alinhados com as políticas e os procedimentos de pessoal da organização (por exemplo, nível de escolaridade, comportamental, etc.) que assegurem que a organização tenha uma força de trabalho de TI apropriada e com as habilidades necessárias para atingir os objetivos da organização? | D69: 0 | E69: 0
A70: 2 | B70: Competências Pessoais | C70: Há um processo formal e regular de avaliação se o pessoal tem as competências necessárias para exercer suas funções com base na formação, no treinamento ou na experiência apresentada na prática? Há um programa de qualificação e certificação apropriado para minimizar discrepâncias? | D70: 0 | E70: 0
A71: 3 | B71: Preenchimento de Vagas | C71: Há um processo claro para o preenchimento de vagas por posição ou alterações estruturais de TI? Se sim como é feita esta avaliação, formal ou informal? | D71: 0 | E71: 0
A72: 4 | B72: Treinamento do Pessoal | C72: É fornecido ao pessoal de TI treinamento apropriado para manter conhecimento, especializações, habilidades, conscientização sobre controles internos e segurança no nível exigido para atingir os objetivos organizacionais? | D72: 0 | E72: 0
A73: 5 | B73: Dependência de Indivíduos | C73: O que é feito para minimizar a exposição à dependência crítica de pessoas-chave através de captação do conhecimento (documentação), compartilhamento de conhecimento, planejamento da sucessão e desenvolvimento de possíveis substitutos para o papel e a função determinados? | D73: 0 | E73: 0
A74: 6 | B74: Procedimentos de Liberação de Pessoal | C74: Há uma análise de antecedentes (antigas ocupações) no processo de recrutamento de TI variando conforme a confidencialidade e/ou da importância da função e aplicadas aos funcionários, prestadores de serviço e fornecedores? | D74: 0 | E74: 0
A75: 7 | B75: Avaliação de Desempenho Profissional | C75: Há periodicamente a realização de avaliação dos objetivos individuais derivados dos objetivos da organização, padrões estabelecidos e responsabilidades específicas do cargo? Há feedback formal para os colaboradores? | D75: 0 | E75: 0
A76: 8 | B76: Mudança e Desligamento de Cargo | C76: Há um processo que endereçe as mudanças de cargo, especialmente no caso de desligamentos? A transferência de conhecimento é providenciada, as responsabilidades redistribuídas e os direitos de acesso eliminados, para que os riscos sejam minimizados e seja assegurada a continuidade da função? | D76: 0 | E76: 0
A77: Maturidade do Processo | D77: =+SUM(D69:D76)/COUNTA(D69:D76) -> 0 | E77: =+SUM(E69:E76)/COUNTA(E69:E76) -> 0
A79: PO8 | B79: Gerenciar a Qualidade
A80: Objetivos Controle | C80: Pergunta | D80: (0-5) | E80: (0-5) | F80: Comentários
A81: 1 | B81: Sistema de Gerenciamento de Qualidade (SGQ) | C81: Há um SGQ que forneça uma abordagem padronizada, formal e contínua de gerenciamento da qualidade e alinhada com os requisitos de negócios? | D81: 0 | E81: 0
A82: 2 | B82: Padrões e Práticas de Qualidade de TI | C82: Existem procedimentos e padrões para os processos-chave de TI de forma a orientar a organização para alcançar as intenções do SGQ? | D82: 0 | E82: 0
A83: 3 | B83: Padrões de Desenvolvimento e Aquisição | C83: Existem padrões de codificação, convenção de nomes, formato de arquivos, padrões de projeto de arquitetura e dicionário de dados, padrões de interface de usuário, interoperabilidade, eficiência no desempenho de sistemas, escalabilidade, padrões de desenvolvimento e testes, validações comparadas com requisitos, planos de teste, testes unitários, testes de regressão e testes integrados? | D83: 0 | E83: 0
A84: 4 | B84: Foco no Cliente | C84: A gestão de qualidade tem como foco o cliente determinando seus requisitos e os mantendo alinhados com os padrões e práticas de TI? Existem Papéis e responsabilidades definidos para a resolução de conflitos entre usuário/cliente e a organização de TI? | D84: 0 | E84: 0
A85: 5 | B85: Melhoria Contínua | C85: Há um plano geral de qualidade que promove a melhoria continua que é mantido e comunicado regularmente? | D85: 0 | E85: 0
A86: 6 | B86: Medição, Monitoramento e Revisão da Qualidade | C86: Existem métricas implantadas para monitorar continuamente o atendimento ao SGQ, bem como o valor que o SGQ fornece? | D86: 0 | E86: 0
A87: Maturidade do Processo | D87: =+SUM(D81:D86)/COUNTA(D81:D86) -> 0 | E87: =+SUM(E81:E86)/COUNTA(E81:E86) -> 0
A89: PO9 | B89: Avaliar e Gerenciar os Riscos de TI
A90: Objetivos Controle | C90: Pergunta | D90: (0-5) | E90: (0-5) | F90: Comentários
A91: 1 | B91: Alinhamento da gestão de riscos de TI e de Negócios | C91: Há estrutura de gestão de riscos de TI alinhada com a estrutura de gestão de riscos da organização (corporação)? | D91: 0 | E91: 0
A92: 2 | B92: Estabelecimento do Contexto de Risco | C92: Quando é que a estrutura de avaliação de risco é aplicada para assegurar resultados esperados? (Isso inclui a definição dos contextos interno e externo de cada avaliação de risco, o objetivo da avaliação e os critérios pelos quais os riscos são avaliados.) | D92: 0 | E92: 0
A93: 3 | B93: Identificação de Eventos | C93: São identificados os eventos (importante ameaça real que explora significativas vulnerabilidades) com potencial impacto negativo nos objetivos ou nas operações da organização, incluindo aspectos de negócios, regulamentação, aspectos jurídicos, tecnologia, parcerias de negócio, recursos humanos e operacionais? | D93: 0 | E93: 0
A94: 4 | B94: Avaliação de Risco | C94: Há avaliação regular da probabilidade e o impacto de todos os riscos identificados, utilizando métodos qualitativos e quantitativos? | D94: 0 | E94: 0
A95: 5 | B95: Resposta ao Risco | C95: Existe um processo de respostas a riscos para assegurar que controles mitiguem a exposição aos riscos de forma contínua? Esse processo se existir identifica as estratégias de risco, tais como evitar, reduzir, compartilhar ou aceitar o risco, determinar responsabilidades, e considerar os níveis de tolerância definidos? | D95: 0 | E95: 0
A96: 6 | B96: Manutenção e Monitoramento do Plano de Ação de Risco | C96: São priorizadas e planejadas as atividades de controle em todos os níveis da organização para implementar as respostas aos riscos identificadas como necessárias, incluindo a identificação de custos, benefícios e responsabilidade pela execução? | D96: 0 | E96: 0
A97: Maturidade do Processo | D97: =+SUM(D91:D96)/COUNTA(D91:D96) -> 0 | E97: =+SUM(E91:E96)/COUNTA(E91:E96) -> 0
A99: PO10 | B99: Gerenciar Projetos
A100: Objetivos Controle | C100: Pergunta | D100: (0-5) | E100: (0-5) | F100: Comentários
A101: 1 | B101: Estrutura de Gestão de Programas | C101: São mantidos o programa de projetos (relacionados ao portfólio de programas de investimentos em TI) identificando, definindo, avaliando, priorizando, selecionando, iniciando, gerenciando e controlando projetos? | D101: 0 | E101: 0
A102: 2 | B102: Estrutura de Gestão de Projetos | C102: Há uma estrutura de gestão de projetos que defina o escopo e a abrangência dos projetos gerenciados, bem como os métodos a serem adotados e aplicados a cada projeto iniciado? A estrutura e as metodologias de suporte são integradas aos processos de gerenciamento de projetos? | D102: 0 | E102: 0
A103: 3 | B103: Abordagem da Gestão de Projetos | C103: Existe uma abordagem de gestão de projetos adequada ao tamanho, à complexidade e aos requisitos regulatórios de cada projeto? | D103: 0 | E103: 0
A104: 4 | B104: Comprometimento das Partes Interessadas | C104: É obtido o comprometimento e participação das partes interessadas afetadas na definição e na execução do projeto dentro do contexto do programa de investimento geral de TI? | D104: 0 | E104: 0
A105: 5 | B105: Declaração do Escopo do Projeto | C105: É comum documentar a natureza e o escopo do projeto, visando confirmar e desenvolver um entendimento comum do escopo do projeto com as partes interessadas e quanto ao relacionamento com outros projetos de um programa de investimento em TI? | D105: 0 | E105: 0
A106: 6 | B106: Fase de Início do Projeto | C106: É assegurado que a fase de início do projeto seja formalmente aprovada e comunicada a todas as partes interessadas? A aprovação da fase de início é baseada nas decisões da governança do PMO? | D106: 0 | E106: 0
A107: 7 | B107: Plano Integrado de Projeto | C107: Há um plano integrado de projeto formalizado e aprovado (que abranja recursos de negócio e de sistemas de informação) para orientar a execução e o controle em todas as etapas do projeto? As atividades e interdependências de múltiplos projetos dentro de um programa são entendidas e documentadas? | D107: 0 | E107: 0
A108: 8 | B108: Recursos do Projeto | C108: Estão definidas as responsabilidades, relacionamentos, autoridades e critérios de desempenho para os membros da equipe de projeto? Há especificação da base de aquisição e atribuição de funcionários e/ou prestadores de serviço competentes para o projeto? | D108: 0 | E108: 0
A109: 9 | B109: Gestão de Risco do Projeto | C109: São eliminados ou minimizados os riscos específicos associados a cada projeto através de um processo sistemático de planejamento, identificação, análise, resposta, monitoramento e controle de áreas ou eventos com potencial para causar mudanças indesejadas? | D109: 0 | E109: 0
A110: 10 | B110: Plano de Qualidade de Projeto | C110: Há um plano de gestão de qualidade que descreva os critérios de qualidade do projeto e como será implementado? O plano é formalmente revisado e aceito por todas as partes envolvidas e então incorporado ao plano integrado de projeto? | D110: 0 | E110: 0
A111: 11 | B111: Controle de Mudança de Projeto | C111: Há um preocesso de controle de mudança para cada projeto, de forma que todas as mudanças feitas no escopo original do projeto (como custo, cronograma, escopo e qualidade) sejam devidamente revisadas, aprovadas e incorporadas ao plano de projeto integrado em alinhamento com a estrutura de governança de programa e projeto? | D111: 0 | E111: 0
A112: 12 | B112: Planejamento de métodos de validação | C112: São realizadas as atividades necessárias para suportar a validação de novos sistemas (ou suas modificações) durante o planejamento do projeto e incluí-las no plano integrado do projeto? | D112: 0 | E112: 0
...

Sheet AI - Questionário
A4: AI1 | B4: Identificar Soluções Automatizadas | D4: Atual | E4: Meta
A5: Objetivos Controle | C5: Pergunta | D5: (0-5) | E5: (0-5) | F5: Comentários
A6: 1 | B6: Definição e Manutenção de Requisitos Técnicos e Funcionais de Negócio | C6: Como são Identificados, priorizados, especificados e pactuados os requisitos técnicos e funcionais do negócio ? | D6: 0 | E6: 0
A7: 2 | B7: Relatório de Análise de Risco | C7: Como são Identificados, documentados e analisados os riscos associados aos requisitos de negócio e desenho de soluções como parte do processo de desenvolvimento dos requisitos da organização? | D7: 0 | E7: 0
A8: 3 | B8: Estudo de Viabilidade e Formulação de Ações Alternativas | C8: É realizado um estudo de viabilidade que examine a possibilidade de implementar os requisitos? O gerenciamento de negócios, suportado pela área de TI, avalia a viabilidade e as ações alternativas e faz recomendações ao patrocinador do negócio? | D8: 0 | E8: 0
A9: 4 | B9: Decisão e Aprovação de Requisitos e Estudo de Viabilidade | C9: O patrocinador do negócio analisa e aprova os requisitos técnicos e funcionais do negócio, bem como os relatórios de estudo de viabilidade em estágios-chave predeterminados? | D9: 0 | E9: 0
A10: Maturidade do Processo | D10: =+SUM(D6:D9)/COUNTA(D6:D9) -> 0 | E10: =+SUM(E6:E9)/COUNTA(E6:E9) -> 0
A12: AI2 | B12: Adquirir e Manter Software Aplicativo
A13: Objetivos Controle | C13: Pergunta | D13: (0-5) | E13: (0-5) | F13: Comentários
A14: 1 | B14: Projeto em Nível Macro | C14: Os requisitos de negócio são traduzidos em especificações de projeto em nível macro para o desenvolvimento de software, levando em consideração o direcionamento tecnológico e a arquitetura de informação da organização? O gerenciamento aprova asespecificações de projeto para assegurar que o projeto de alto nível atenda aos requisitos? | D14: 0 | E14: 0
A15: 2 | B15: Projeto Detalhado | C15: São detalhados os requisitos técnicos e de projeto dos softwares aplicativos a serem desenvolvidos? São definidos os critérios de aceitação dos requisitos? Como? São aprovados os requisitos para assegurar que eles correspondam ao projeto em nível macro? | D15: 0 | E15: 0
A16: 3 | B16: Controle e Auditabilidade do Aplicativo | C16: São criados dispositivos do tipo log, trilhas de auditoria dos sistemas quanto as suas funcionalidades, acessos concedidos e conteúdo acessado? Há ferramentas para recuperação e análise destas informações e as mesmas podem ser recuperadas de forma rápida em casos de emergência? | D16: 0 | E16: 0
A17: 4 | B17: Segurança e Disponibilidade do Aplicativo | C17: Como são considerados os requisitos de segurança e disponibilidade em resposta aos riscos identificados? Estão em linha com a classificação de sensibilidade dos dados, com a arquitetura de segurança da informação e o perfil de tolerância a riscos da organização? | D17: 0 | E17: 0
A18: 5 | B18: Configuração e Implementação de Software Aplicativo Adquirido | C18: São Customizadas e implementadas as funcionalidades automatizadas adquiridas para alcançar os objetivos de negócios? | D18: 0 | E18: 0
A19: 6 | B19: Principais Atualizações dos Sistemas Existentes | C19: É seguido um processo de desenvolvimento similar ao de desenvolvimento de novos sistemas quando ocorrer grandes mudanças nos sistemas existentes que possam resultar em mudanças significativas nos projetos e/ou funcionalidades atuais? | D19: 0 | E19: 0
A20: 7 | B20: Desenvolvimento de Software Aplicativo | C20: É garantido que as funcionalidades automatizadas sejam desenvolvidas em conformidade com as especificações de projeto, padrões de desenvolvimento e documentação e requisitos de qualidade e de autorização? Além disso é assegurado que todos os aspectos contratuais e legais sejam identificados e considerados nos softwares aplicativos desenvolvidos por terceiros? | D20: 0 | E20: 0
A21: 8 | B21: Garantia de Qualidade de Software | C21: Desenvolver e executar o plano de garantia de qualidade de software para obter a qualidade especificada na definição dos requisitos de projeto e nos procedimentos e políticas de qualidade da organização? | D21: 0 | E21: 0
A22: 9 | B22: Gestão dos Requisitos das Aplicações | C22: É acompanhada a situação individual dos requisitos (incluindo rejeição de requisitos) durante o desenho, o desenvolvimento e a implementação e garantir que as mudanças nos requisitos sejam aprovadas através de um processo de gerenciamento de mudanças? | D22: 0 | E22: 0
A23: 10 | B23: Manutenção de Software Aplicativo | C23: Foi desenvolvida uma estratégia e um plano de manutenção de software aplicativo? | D23: 0 | E23: 0
A24: Maturidade do Processo | D24: =+SUM(D14:D23)/COUNTA(D14:D23) -> 0 | E24: =+SUM(E14:E23)/COUNTA(E14:E23) -> 0
A26: AI3 | B26: Adquirir e Manter Infraestrutura de Tecnologia
A27: Objetivos Controle | C27: Pergunta | D27: (0-5) | E27: (0-5) | F27: Comentários
A28: 1 | B28: Plano de Aquisição de Infraestrutura Tecnológica | C28: É preparado um plano para aquisição, implementação e manutenção da infraestrutura tecnológica que satisfaça aos requisitos técnicos e funcionais estabelecidos do negócio e esteja de acordo com a direção tecnológica da organização? | D28: 0 | E28: 0
A29: 2 | B29: Infraestrutura de Recursos, Proteção e Disponibilidade | C29: Foram ou estão sendo implementados controles internos, medidas de segurança e auditabilidade durante a configuração, integração e manutenção de hardware e software da infraestrutura para proteger os recursos e assegurar disponibilidade e integridade? | D29: 0 | E29: 0
A30: 3 | B30: Manutenção da Infraestrutura | C30: Foi ou está sendo implementada uma estratégia e um plano para manutenção da infraestrutura e para assegurar que as mudanças sejam controladas em alinhamento com os procedimentos de gerenciamento de mudança da organização? | D30: 0 | E30: 0
A31: 4 | B31: Viabilidade do Ambiente de Teste | C31: Há um ambiente de desenvolvimento e de teste para proporcionar eficiência e eficácia nos testes de viabilidade e integração dos componentes da infraestrutura? | D31: 0 | E31: 0
A32: Maturidade do Processo | D32: =+SUM(D28:D31)/COUNTA(D28:D31) -> 0 | E32: =+SUM(E28:E31)/COUNTA(E28:E31) -> 0
D33: 5 | E33: 5
A34: AI4 | B34: Habilitar Operação e Uso | D34: 5 | E34: 5
A35: Objetivos Controle | C35: Pergunta | D35: (0-5) | E35: (0-5) | F35: Comentários
A36: 1 | B36: Planejamento para Soluções Operacionais | C36: Háum plano para identificar e documentar todos os aspectos técnicos, a capacidade operacional e os níveis de serviços necessários para que todos que irão operar, utilizar e manter as soluções automatizadas possam exercer suas responsabilidades? | D36: 0 | E36: 0
A37: 2 | B37: Transferência de Conhecimento ao Gerenciamento do Negócio | C37: É transferido o conhecimento ao gerenciamento do negócio para permitir que este assuma a propriedade do sistema e dados, bem como exerça suas responsabilidades nos processos de entrega, qualidade de serviço, controles internos e administração da aplicação? | D37: 0 | E37: 0
A38: 3 | B38: Transferência de Conhecimento aos Usuários Finais | C38: É transferido o conhecimento e habilidades para permitir aos usuários o uso efetivo e eficiente dos sistemas aplicativos que sustentam processos de negócio? | D38: 0 | E38: 0
A39: 4 | B39: Transferência de Conhecimento às Equipes de Operações e Suporte | C39: Há transferência de conhecimento e habilidades para permitir que as equipes de operações e suporte técnico entreguem, suportem e mantenham os sistemas e a infraestrutura associada de forma eficaz e eficiente? | D39: 0 | E39: 0
A40: Maturidade do Processo | D40: =+SUM(D36:D39)/COUNTA(D36:D39) -> 0 | E40: =+SUM(E36:E39)/COUNTA(E36:E39) -> 0
A42: AI5 | B42: Adquirir Recursos de TI
A43: Objetivos Controle | C43: Pergunta | D43: (0-5) | E43: (0-5) | F43: Comentários
A44: 1 | B44: Controle de Aquisição | C44: Existe um conjunto de procedimentos e padrões consistentes com o processo e a estratégia corporativa de aquisição para assegurar que a aquisição de infraestrutura, instalações, hardware, software e serviços satisfaça aos requisitos de negócio? | D44: 0 | E44: 0
A45: 2 | B45: Gerenciamento de Contratos de Fornecedores | C45: Há um procedimento para estabelecer, modificar e rescindir contratos com todos os fornecedores? Se sim, o procedimento contempla as formalidades legais, financeiras, organizacionais, documentais, de desempenho, de segurança e de propriedade intelectual e as responsabilidades e obrigações legais em casos de cancelamento (incluindo cláusulas de penalidades)? | D45: 0 | E45: 0
A46: 3 | B46: Seleção de Fornecedores | C46: Ao selecionar fornecedores de acordo há uma prática formal e justa que assegure a melhor opção viável com base nos requisitos definidos a partir de informações dadas por fornecedores em potencial e acordadas entre fornecedores internos e clientes? | D46: 0 | E46: 0
A47: 4 | B47: Aquisição de Recursos de TI | C47: Há algum tipo de garantia que os interesses da organização sejam protegidos em todos os contratos de aquisição, incluíndo o exercício dos direitos e as obrigações de todas as partes nos termos contratuais de aquisição de software, desenvolvimento de recursos, infraestrutura e serviços? | D47: 0 | E47: 0
A48: Maturidade do Processo | D48: =+SUM(D44:D47)/COUNTA(D44:D47) -> 0 | E48: =+SUM(E44:E47)/COUNTA(E44:E47) -> 0
A50: AI6 | B50: Gerenciar Mudanças
A51: Objetivos Controle | C51: Pergunta | D51: (0-5) | E51: (0-5) | F51: Comentários
A52: 1 | B52: Padrões e Procedimentos de Mudança | C52: Foi estabelecido procedimentos formais de gerenciamento de mudanças para lidar de modo padronizado com todas as solicitações de mudança em aplicações, procedimentos, processos, parâmetros de sistema, parâmetros de serviço e plataformas subjacentes (inclusive solicitações de manutenção e reparo)? | D52: 0 | E52: 0
A53: 2 | B53: Avaliação de Impacto, Priorização e Autorização | C53: São avaliadas todas as solicitações de mudança de modo estruturado com relação a impactos no sistema operacional e na respectiva funcionalidade, assegurando que todas as mudanças sejam categorizadas, priorizadas e autorizadas? | D53: 0 | E53: 0
A54: 3 | B54: Mudanças de Emergência | C54: Foi estebelecido um processo para definição, solicitação, testes, documentação, avaliação e autorização de mudanças de emergência que não sigam o processo de mudança estabelecido? | D54: 0 | E54: 0
A55: 4 | B55: Acompanhamento de Status e Relatórios de Mudanças | C55: Foi estabelecido um sistema de acompanhamento e relatórios de mudanças para documentar mudanças rejeitadas, comunicar o status de mudanças aprovadas e em andamento e executar mudanças além de garantir que as mudanças autorizadas sejam implementadas conforme planejado? | D55: 0 | E55: 0
A56: 5 | B56: Finalização da Mudança e Documentação | C56: A documentação os procedimentos do sistema e de usuários são atualizados sempre que forem implementadas mudanças no sistema? | D56: 0 | E56: 0
A57: Maturidade do Processo | D57: =+SUM(D52:D56)/COUNTA(D52:D56) -> 0 | E57: =+SUM(E52:E56)/COUNTA(E52:E56) -> 0
A59: AI7 | B59: Gerenciar Mudanças
A60: Objetivos Controle | C60: Pergunta | D60: (0-5) | E60: (0-5) | F60: Comentários
A61: 1 | B61: Treinamento | C61: É comum Treinar a equipe dos departamentos usuários envolvidos e as equipes de operações de TI de acordo com o plano de implementação e treinamento definido e os materiais associados, como parte de todos os projetos de desenvolvimento, implementação ou modificação de sistemas de informação? | D61: 0 | E61: 0
A62: 2 | B62: Plano de Teste | C62: Podemos afirmar que foi estabelecido um plano de teste baseado nos padrões organizacionais que definem papéis, responsabilidades e critérios de sucesso de entrada e saída e que o plano seja aprovado pelas partes relevantes? | D62: 0 | E62: 0
A63: 3 | B63: Plano de Implementação | C63: Há um plano de implementação e de retorno à configuração anterior? É obtida a aprovação de todas as partes relevantes? | D63: 0 | E63: 0
A64: 4 | B64: Ambiente de Testes | C64: Há um ambiente de testes seguro que reflita o ambiente de operações planejado no que diz respeito a segurança, controles internos, práticas operacionais, exigências de qualidade e confidencialidade e cargas de trabalho? | D64: 0 | E64: 0
A65: 5 | B65: Conversão de Dados e Sistemas | C65: Há um planejamento da conversão de dados e da migração da infraestrutura como parte dos métodos de desenvolvimento da organização, incluindo trilhas de auditoria, procedimentos de retorno à situação anterior e de recuperação de falhas. | D65: 0 | E65: 0
A66: 6 | B66: Teste de Mudanças | C66: É garantido que as mudanças sejam testadas de maneira independente e de acordo com o plano de testes definido antes da migração para o ambiente de produção? | D66: 0 | E66: 0
A67: 7 | B67: Teste de Aceitação Final | C67: É assegurado que o gerenciamento do departamento usuário e da área de TI avalie o resultado do processo de testes como determinado no plano de testes, corrigindo erros significativos identificados no processo de testes, executando todos os testes listados no plano de testes, bem como qualquer teste de regressão necessário? | D67: 0 | E67: 0
A68: 8 | B68: Promoção para a Produção | C68: Após a conclusão dos testes, é fato controlar a transferência dos sistemas alterados para operação, de acordo com o plano de implementação e obter a aprovação das partes interessadas, como usuários, proprietário do sistema e gerência operacional? | D68: 0 | E68: 0
A69: 9 | B69: Revisão pós-implementação | C69: São estabelecidos procedimentos em linha com o gerenciamento de mudanças organizacionais para garantir a realização da revisão pósimplementação, conforme definido no plano de implementação? | D69: 0 | E69: 0
A70: Maturidade do Processo | D70: =+SUM(D61:D69)/COUNTA(D61:D69) -> 0 | E70: =+SUM(E61:E69)/COUNTA(E61:E69) -> 0

Sheet DS - Questionário
A4: DS1 | B4: Definir e Gerenciar Níveis de Serviço | D4: Atual | E4: Meta | G4: 1
A5: Objetivos Controle | C5: Pergunta | D5: (0-5) | E5: (0-5) | F5: Comentários | G5: 2
A6: 1 | B6: Estrutura de Gestão de Níveis de Serviço | C6: Existe um modelo que fornece um processo formalizado de gerenciamento de níveis de serviço entre o cliente e o provedor de serviço? Se sim, esse modelo mantém um contínuo alinhamento com os requisitos de negócio e suas prioridades e facilita um entendimento comum entre o cliente e o(s) provedor(es)? | D6: 0 | E6: 0 | G6: 3
A7: 2 | B7: Definição de Serviços | C7: Os serviços de TI são baseados nas características de serviços e requisitos do negócio, organizados e armazenados centralmente por meio da implementação de uma abordagem de catálogo/portfólio de serviços? | D7: 0 | E7: 0 | G7: 4
A8: 3 | B8: Acordos de Nível de Serviço | C8: São definidos os acordos de nível de serviço para todos os serviços críticos de TI com base nos requisitos do cliente e na capacidade de entrega por parte da TI? | D8: 0 | E8: 0 | G8: 5
A9: 4 | B9: Acordos de Nível Operacional | C9: É garantido que os acordos de nível operacional (OLAs) expliquem como os serviços serão realizados tecnicamente de modo a apoiar o(s) SLA(s) adequadamente? | D9: 0 | E9: 0
A10: 5 | B10: Monitoramento e Relatório de Realizações de Nível de Serviço | C10: É comum monitorar continuamente os critérios de desempenho dos níveis de serviço especificados.? Os relatórios são disponibilizados em um formato compreensível às partes interessadas em termos de realização de níveis de serviço? | D10: 0 | E10: 0
A11: 6 | B11: Revisão dos Acordos de Nível de Serviço e dos Contratos | C11: É feita regularmente a análise crítica dos acordos de nível de serviço e dos contratos com provedores de serviço internos e externos para assegurar que sejam eficazes e atualizados e que as mudanças em requisitos tenham sido consideradas? | D11: 0 | E11: 0
A12: Maturidade do Processo | D12: =+SUM(D6:D11)/COUNTA(D6:D11) -> 0 | E12: =+SUM(E6:E11)/COUNTA(E6:E11) -> 0
A14: DS2 | B14: Gerenciar Serviços Terceirizados
A15: Objetivos Controle | C15: Pergunta | D15: (0-5) | E15: (0-5) | F15: Comentários
A16: 1 | B16: Identificação do Relacionamento com Todos os Fornecedores | C16: Todos os serviços terceirizados estão identificados e categorizados de acordo com o tipo, a importância e a criticidade? É usual manter documentação formal dos relacionamentos técnicos e organizacionais contemplando papéis e responsabilidades, metas, produtos esperados e as credenciais dos representantes desses fornecedores? | D16: 0 | E16: 0
A17: 2 | B17: Gestão do Relacionamento com Fornecedores | C17: É norma formalizar o processo de gestão do relacionamento com cada fornecedor estabelecendo a ligação entre os clientes e os negócios dos fornecedores e garantindo a qualidade do relacionamento com base na confiança e na transparência (por exemplo, através dos acordos de nível de serviço)? | D17: 0 | E17: 0
A18: 3 | B18: Gerenciamento de Riscos do Fornecedor | C18: É usual identificar e minimizar os riscos relacionados à capacidade dos fornecedores de prestação efetiva de serviços de maneira contínua, segura e eficiente, garantindo que os contratos estejam em conformidade com os padrões universais de negócios e de acordo com as exigências legais e regulamentares, acordos de confidencialidade (NDA)? | D18: 0 | E18: 0
A19: 4 | B19: Monitoramento de Desempenho do Fornecedor | C19: Já foi estabelecido um processo para monitorar a prestação do serviço de modo a assegurar que o fornecedor atenda aos requisitos atuais do negócio, obedecendo os contratos e acordos de nível de serviço firmados, e que seu desempenho seja competitivo com outros prestadores e condições do mercado? | D19: 0 | E19: 0
A20: Maturidade do Processo | D20: =+SUM(D16:D19)/COUNTA(D16:D19) -> 0 | E20: =+SUM(E16:E19)/COUNTA(E16:E19) -> 0
A22: DS3 | B22: Gerenciar o Desempenho e a Capacidade
A23: Objetivos Controle | C23: Pergunta | D23: (0-5) | E23: (0-5) | F23: Comentários
A24: 1 | B24: Desempenho e Planejamento de Capacidade | C24: Foi estabelecido um processo de planejamento para a realização de análise crítica do desempenho e da capacidade dos recursos de TI, de forma a assegurar que com custos justificáveis o desempenho e a capacidade estejam disponíveis para processar a carga de serviço acordada conforme determinam os acordos de nível de serviço? | D24: 0 | E24: 0
A25: 2 | B25: Capacidade e Desempenho Atuais | C25: Foi estebelecido um processo para realizar a análise crítica do desempenho e a capacidade atual dos recursos de TI de forma a determinar se existe capacidade e desempenho suficientes para atendimento conforme os níveis de serviço acordados? | D25: 0 | E25: 0
A26: 3 | B26: Capacidade e Desempenho Futuros | C26: É conduzida regularmente a previsão de desempenho e capacidade dos recursos de TI para minimizar o risco de interrupção de serviços devido a capacidade insuficiente ou degradação do desempenho? São identificados também o excesso de capacidade para possível remanejamento? | D26: 0 | E26: 0
A27: 4 | B27: Disponibilidade de Recursos de TI | C27: Fornece a capacidade e o desempenho necessários, levando em consideração aspectos como cargas normais de trabalho, contingências, requisitos de armazenamento e ciclos de vida de recurso de TI? | D27: 0 | E27: 0
A28: 5 | B28: Monitoramento e Relatórios | C28: Ha monitoramento constante do desempenho e da capacidade dos recursos de TI? Os dados acumulados permitem manter e sintonizar o desempenho atual no ambiente de TI e tratar questões como capacidade de recuperação, contingência, cargas de trabalho atuais e previstas, planejamento de armazenamento e aquisição de recursos? | D28: 0 | E28: 0
A29: Maturidade do Processo | D29: =+SUM(D24:D28)/COUNTA(D24:D28) -> 0 | E29: =+SUM(E24:E28)/COUNTA(E24:E28) -> 0
A31: DS4 | B31: Assegurar a Continuidade dos Serviços
A32: Objetivos Controle | C32: Pergunta | D32: (0-5) | E32: (0-5) | F32: Comentários
A33: 1 | B33: Estrutura de Continuidade | C33: Foi desenvolvido um modelo para continuidade de TI a fim de apoiar o gerenciamento da continuidade do negócio de toda a empresa através de um processo consistente? Este modelo apoia a determinação das necessidades de capacitação em recuperação da infraestrutura e conduzir o desenvolvimento dos planos de contingência de TI e recuperação de desastres? | D33: 0 | E33: 0
A34: 2 | B34: Planos de Continuidade de TI | C34: Foram desenvolvidos planos de continuidade de TI com base na estrutura e projetados para reduzir o impacto de uma grande interrupção de funções e processos de negócio fundamentais? | D34: 0 | E34: 0
A35: 3 | B35: Recursos Críticos de TI | C35: É dada uma atenção especial aos itens mais críticos no plano de continuidade de TI para assegurar a capacidade de restabelecimento e definir prioridades em situações de recuperação? | D35: 0 | E35: 0
A36: 4 | B36: Manutenção do Plano de Continuidade de TI | C36: A gerência de TI é encorajada a definir e executar procedimentos de controle de mudança para assegurar que o plano de continuidade de TI seja mantido atualizado e reflita sempre os requisitos de negócios atuais? | D36: 0 | E36: 0
A37: 5 | B37: Teste do Plano de Continuidade de TI | C37: O plano de continuidade de TI é testado regularmente para assegurar que os sistemas de TI possam ser efetivamente recuperados, que desvios sejam tratados e que o plano se mantenha relevante? | D37: 0 | E37: 0
A38: 6 | B38: Treinamento do Plano de Continuidade de TI | C38: Há um processo para assegurar que todas as partes envolvidas recebam treinamento regular sobre os procedimentos, papéis e respectivas responsabilidades no caso de um incidente ou desastre. Com qual intensidade e frequencia? | D38: 0 | E38: 0
A39: 7 | B39: Distribuição do Plano de Continuidade | C39: Está definida uma estratégia de distribuição para assegurar que os planos sejam seguramente distribuídos e que estejam apropriadamente disponíveis às partes interessadas e autorizados quando e onde necessário? | D39: 0 | E39: 0
A40: 8 | B40: Recuperação e Retomada dos Serviços de TI | C40: São planejadas as ações a serem executadas nos momentos de recuperação e retomada dos serviços de TI. Isto pode incluir ativação de backup sites, iniciação de processamento alternativo, comunicação para as partes interessadas e os clientes, procedimentos de retorno à produção, etc? | D40: 0 | E40: 0
A41: 9 | B41: Armazenamento de Cópias de Segurança em Locais Remotos | C41: São armazenadas remotamente todas as mídias de cópias de segurança críticas, documentação e outros recursos de TI necessários para a recuperação da TI e os planos de continuidade de negócio? | D41: 0 | E41: 0
A42: 10 | B42: Revisão Pós-Retomada dos Serviços | C42: Após a retomada bem-sucedida da função de TI depois de um desastre, é são aplicados procedimentos para avaliar a adequação do plano atual e realizar sua atualização, se necessário? | D42: 0 | E42: 0
A43: Maturidade do Processo | D43: =+SUM(D33:D42)/COUNTA(D33:D42) -> 0 | E43: =+SUM(E33:E42)/COUNTA(E33:E42) -> 0
A45: DS5 | B45: Garantir a Segurança dos Sistemas
A46: Objetivos Controle | C46: Pergunta | D46: (0-5) | E46: (0-5) | F46: Comentários
A47: 1 | B47: Gestão da Segurança de TI | C47: A segurança de TI é gerenciada no mais alto nível organizacional da empresa de modo que a gestão das ações de segurança esteja em alinhamento com os requisitos do negócio? | D47: 0 | E47: 0
A48: 2 | B48: Plano de Segurança de TI | C48: Os requisitos de negócio, de risco e conformidade, em um plano abrangente de segurança de TI, que leve em consideração a infraestrutura de TI e a cultura de segurança estão implementados? | D48: 0 | E48: 0
A49: 3 | B49: Gestão de Identidade | C49: Todos os usuários (internos, externos e temporários) e suas atividades nos sistemas de TI (aplicação de negócio, desenvolvimento, operação e manutenção de sistemas) são identificáveis de modo exclusivo? Os direitos de acesso dos usuários aos sistemas e dados estão em conformidade com as necessidades dos negócios e com os requisitos da função definidos e documentados? | D49: 0 | E49: 0
A50: 4 | B50: Gestão de Contas de Usuário | C50: A solicitação, a emissão, a suspensão, a modificação e o bloqueio de contas de usuário e dos respectivos privilégios são tratados por procedimentos de gestão de contas de usuário, existindo um processo de inclusão e exclusão claro? | D50: 0 | E50: 0
A51: 5 | B51: Teste de Segurança, Vigilância e Monitoramento | C51: As implementações de segurança de TI são testada e monitoradas proativamente e também revalidadas que o nível de segurança aprovado seja mantido? A função de monitoramento e registro de eventos (logging) possibilita a prevenção e/ou detecção prematura de atividades anormais e incomuns que precisem ser tratadas, bem como a subsequente geração de relatórios no tempo apropriado? | D51: 0 | E51: 0
A52: 6 | B52: Definição de Incidente de Segurança | C52: São definidos e comunicados claramente as características de incidentes de segurança em potencial para que possam ser tratados adequadamente pelos processos de gestão de incidentes ou gestão de problemas? | D52: 0 | E52: 0
A53: 7 | B53: Proteção da Tecnologia de Segurança | C53: Há processos que garantam que as tecnologias de segurança importantes sejam invioláveis e que as documentações de segurança não sejam reveladas desnecessariamente? | D53: 0 | E53: 0
A54: 8 | B54: Gestão de Chave Criptográfica | C54: São estabelecidas políticas e procedimentos de geração, mudança, revogação, destruição, distribuição, certificação, armazenamento, inserção, uso e arquivamento das chaves criptográficas visando proteger contra sua modificação ou revelação pública não autorizada? | D54: 0 | E54: 0
A55: 9 | B55: Prevenção, Detecção e Correção de Software Malicioso | C55: É possível assegurar que medidas preventivas, de detecção e corretivas foram estabelecidas corporativamente, em especial correções de segurança (patches) e controles de vírus, para proteger os sistemas de informação e tecnologias contra malwares (vírus, worms, spyware, spam.)? | D55: 0 | E55: 0
A56: 10 | B56: Segurança de Rede | C56: Há processos que garamtam que técnicas de segurança e procedimentos de gestão relacionados (como firewalls, aplicativos de segurança, segmentação de rede e detecção de intrusão sejam utilizados para autorizar o acesso e controlar os fluxos de informação entre redes? | D56: 0 | E56: 0
A57: 11 | B57: Comunicação de Dados Confidenciais | C57: É possível assegurar que as transações de comunicação de dados confidenciais ocorram somente por um caminho confiável ou controlado de modo a fornecer autenticação de conteúdo, comprovante de envio, comprovante de recebimento e transações em ambiente seguro? | D57: 0 | E57: 0
A58: Maturidade do Processo | D58: =+SUM(D47:D57)/COUNTA(D47:D57) -> 0 | E58: =+SUM(E47:E57)/COUNTA(E47:E57) -> 0
A60: DS6 | B60: Identificar e Alocar Custos
A61: Objetivos Controle | C61: Pergunta | D61: (0-5) | E61: (0-5) | F61: Comentários
A62: 1 | B62: Definição de Serviços | C62: Há um processo para Identificar todos os custos de TI e associá-los aos serviços de TI, sustentando um modelo transparente de custeio? Os serviços de TI são associados aos processos de negócio de forma que permita identificar os níveis de faturamento de serviço correspondentes? | D62: 0 | E62: 0
A63: 2 | B63: Contabilidade de TI | C63: Há um processo para coletar e alocar os custos vigentes de acordo com o modelo de centros de custo definidos? Variações entre as previsões e os custos reais são analisadas e relatadas em conformidade com os sistemas de medição financeira corporativos? | D63: 0 | E63: 0
A64: 3 | B64: Modelagem de Custo e Cobrança | C64: Com base na definição de serviço, foi definido um modelo de custo que considere os custos diretos, indiretos e gerais dos serviços e suporte o cálculo das taxas de cobrança por serviço? | D64: 0 | E64: 0
A65: 4 | B65: Manutenção do Modelo de Custo | C65: É realizada periodicamente análise crítica e comparação com referências do mercado (benchmarking) da adequação do modelo de custo/cobrança visando manter a relevância e a adequação aos negócios e às atividades de TI envolvidas? | D65: 0 | E65: 0
A66: Maturidade do Processo | D66: =+SUM(D62:D65)/COUNTA(D62:D65) -> 0 | E66: =+SUM(E62:E65)/COUNTA(E62:E65) -> 0
A68: DS7 | B68: Educar e Treinar os Usuários
A69: Objetivos Controle | C69: Pergunta | D69: (0-5) | E69: (0-5) | F69: Comentários
A70: 1 | B70: Identificação das Necessidades de Ensino e Treinamento | C70: É estabelecida e atualizada regularmente um currículo para cada grupo-alvo de empregados? considerando: · As estratégias e necessidades atuais e futuras do negócio · Valor da informação como um bem · Os valores corporativos (valores éticos, cultura de segurança e controle etc.) · A implementação de nova infraestrutura de TI e softwares (pacotes e aplicações) · As habilidades, competências, certificação e atualizações necessárias | D70: 0 | E70: 0
A71: 2 | B71: Entrega de Treinamento e Ensino | C71: Com base nas necessidades de ensino e treinamento identificadas, foram definidos os grupos-alvo e seus membros, mecanismos adequados de ministrar os treinamentos, professores, instrutores e monitores? | D71: 0 | E71: 0
A72: 3 | B72: Avaliação do Treinamento Recebido | C72: Há avaliação do conteúdo do ensino e do treinamento recebidos no que diz respeito a relevância, qualidade, efetividade, absorção e retenção do conhecimento, custo e valor? (Os resultados dessa avaliação servem de base para a definição dos futuros currículos e sessões de treinamento.) | D72: 0 | E72: 0
A73: Maturidade do Processo | D73: =+SUM(D70:D72)/COUNTA(D70:D72) -> 0 | E73: =+SUM(E70:E72)/COUNTA(E70:E72) -> 0
A75: DS8 | B75: Gerenciar a Central de Serviço e os Incidentes
A76: Objetivos Controle | C76: Pergunta | D76: (0-5) | E76: (0-5) | F76: Comentários
A77: 1 | B77: Central de Serviço | C77: Foi estebelecida uma central de serviço, que é a interface entre o usuário e a TI, para registrar, comunicar, despachar e analisar todos os chamados, incidentes reportados, solicitações de serviços e demanda de informações? | D77: 0 | E77: 0
A78: 2 | B78: Registro dos Chamados dos Clientes | C78: Foi estabelecida uma função e um sistema que permitam o registro e o rastreamento de ligações, incidentes, solicitações de serviços e necessidade de informações? Os incidentes são classificados de acordo com as prioridades de negócio e serviço e direcionados à equipe adequada de gerenciamento de problemas? | D78: 0 | E78: 0
A79: 3 | B79: Escalonamento de Incidentes | C79: Foram estabelecidos os procedimentos da central de serviço para que os incidentes que não podem ser resolvidos imediatamente sejam adequadamente encaminhados, conforme os limites definidos no SLA, e soluções temporárias sejam implementadas, se aplicável? | D79: 0 | E79: 0
A80: 4 | B80: Encerramento de Incidente | C80: Foram estabelecidos procedimentos para o monitoramento periódico do encerramento de chamados de cliente assegurando que a central de serviço registre os passos adotados para sua resolução e confirmar se as ações adotadas foram aceitas pelo cliente.? | D80: 0 | E80: 0
A81: 5 | B81: Relatórios e Análises de Tendências | C81: São gerados relatórios de atividades da central de serviço, permitindo aos gestores medir o desempenho e o tempo de resposta dos serviços e identificar tendências ou problemas recorrentes, para que o serviço possa ser melhorado? | D81: 0 | E81: 0
A82: Maturidade do Processo | D82: =+SUM(D77:D81)/COUNTA(D77:D81) -> 0 | E82: =+SUM(E77:E81)/COUNTA(E77:E81) -> 0
A84: DS9 | B84: Gerenciar a Configuração
A85: Objetivos Controle | C85: Pergunta | D85: (0-5) | E85: (0-5) | F85: Comentários
A86: 1 | B86: Repositório de Configuração e Perfis Básicos | C86: Foi estabelecida uma ferramenta de suporte e um repositório central para conter todas as informações relevantes sobre os itens de configuração? Existem meios de monitorar e registrar todos os bens e as mudanças ocorridas neles e manter um perfil básico de itens de configuração de todo sistema e serviço como um ponto de verificação seguro para eventual retorno após as mudanças? | D86: 0 | E86: 0
A87: 2 | B87: Identificação e Manutenção dos Itens de Configuração | C87: Foi implantado procedimentos de configuração para suportar a Direção e registrar todas as alterações no repositório de configurações e integrar esses procedimentos com gerenciamento de mudanças, gerenciamento de incidentes e gerenciamento de problemas? | D87: 0 | E87: 0
A88: 3 | B88: Revisão da Integridade de Configuração | C88: Periodicamente são revisados os dados de configuração para verificar e confirmar a integridade da configuração atual e histórica? É realizada uma análise crítica periódica da política de uso de software, verificando a eventual existência de software pessoal, não autorizado ou excedente ao contrato de licenças vigente? | D88: 0 | E88: 0
A89: Maturidade do Processo | D89: =+SUM(D86:D88)/COUNTA(D86:D88) -> 0 | E89: =+SUM(E86:E88)/COUNTA(E86:E88) -> 0
A91: DS10 | B91: Gerenciar os Problemas
A92: Objetivos Controle | C92: Pergunta | D92: (0-5) | E92: (0-5) | F92: Comentários
A93: 1 | B93: Identificar e Classificar os Problemas | C93: Implementar processos para reportar e classificar os problemas identificados como parte do gerenciamento de incidentes? Os passos envolvidos na classificação de problemas são similares aos passos da classificação de incidentes? Eles determinam a categoria, o impacto, a urgência e a prioridade? | D93: 0 | E93: 0
A94: 2 | B94: Rastreamento e Resolução de Problemas | C94: O sistema de gerenciamento de problemas fornece recursos de trilha de auditoria adequados que permitam o rastreamento, a análise e a identificação da causa-raiz de todos os problemas reportados? considerando: · Todos os itens de configuração associados · Os problemas e incidentes pendentes · Os erros conhecidos e suspeitos · Rastreamento de tendências de problemas | D94: 0 | E94: 0
A95: Maturidade do Processo | D95: =+SUM(D93:D94)/COUNTA(D93:D94) -> 0 | E95: =+SUM(E93:E94)/COUNTA(E93:E94) -> 0
A97: DS11 | B97: Gerenciar os Dados
A98: Objetivos Controle | C98: Pergunta | D98: (0-5) | E98: (0-5) | F98: Comentários
A99: 1 | B99: Requisitos de Negócio para o Gerenciamento de Dados | C99: Foram estabelecidos processo para assegurar que todos os dados esperados sejam recebidos, processados de maneira completa, precisa e no tempo apropriado e que toda saída seja entregue de acordo com os requisitos de negócio? | D99: 0 | E99: 0
A100: 2 | B100: Arranjos de Armazenamento e Retenção | C100: Foram definidos e implantados procedimentos para um efetivo e eficiente armazenamento de dados, retenção e arquivamento para atender aos objetivos de negócio, à política de segurança da organização e às exigências regulatórias? | D100: 0 | E100: 0
A101: 3 | B101: Sistema de Gerenciamento de Biblioteca de Mídia | C101: Foram definidos e implantados procedimentos para manter um inventário de mídia local, assegurando sua usabilidade e integridade? | D101: 0 | E101: 0
A102: 4 | B102: Descarte de Dados e Equipamentos | C102: Foram definidos e implantados os procedimentos para assegurar que os requisitos de negócios sejam atendidos no que diz respeito à proteção de dados confidenciais e softwares quando dados e equipamentos são descartados ou transferidos? | D102: 0 | E102: 0
A103: 5 | B103: Backup e Restauração | C103: Foram definidos e implantados os procedimentos de cópia de segurança (backup) e restauração de sistemas, aplicativos, dados e documentação em alinhamento com os requisitos de negócio e o plano de continuidade? | D103: 0 | E103: 0
A104: 6 | B104: Requisitos de Segurança para o Gerenciamento de Dados | C104: Foram definidas e implantadas políticas e procedimentos para identificar e aplicar requisitos de segurança aplicáveis ao recebimento, processamento, armazenamento físico e saída de dados para atender aos objetivos de negócio, à política de segurança da organização e a exigências regulatórias? | D104: 0 | E104: 0
A105: Maturidade do Processo | D105: =+SUM(D99:D104)/COUNTA(D99:D104) -> 0 | E105: =+SUM(E99:E104)/COUNTA(E99:E104) -> 0
A107: DS12 | B107: Gerenciar o Ambiente Físico
A108: Objetivos Controle | C108: Pergunta | D108: (0-5) | E108: (0-5) | F108: Comentários
A109: 1 | B109: Seleção do Local e Layout | C109: Foi definido e selecionado um local para os equipamentos de TI, considerando o alinhamento da estratégia de tecnológica com a estratégia de negócio? A seleção e o planejamento do layout da instalação física devem levaram em consideração os riscos associados a possíveis desastres naturais e não naturais, bem como as leis e regulamentações relevantes, tais como regulamentações de saúde ocupacional e segurança do trabalho? | D109: 0 | E109: 0
A110: 2 | B110: Medidas de Segurança Física | C110: Foram definidos e implantados as medidas de segurança física alinhadas com os requisitos de negócio para proteger o local e os ativos físicos? As medidas de segurança física são capazes de efetivamente prevenir, detectar e mitigar riscos relacionados a roubo, temperatura, fogo, fumaça, água, vibração, terrorismo, vandalismo, quedas de energia, produtos químicos ou explosivos? | D110: 0 | E110: 0
A111: 3 | B111: Acesso Físico | C111: Foram definidos e implantados os procedimentos para conceder, limitar e revogar o acesso a instalações, prédios e áreas de acordo com as necessidades do negócio, inclusive em situações de emergências? | D111: 0 | E111: 0
A112: 4 | B112: Proteção contra Fatores Ambientais | C112: Foram projetados e implementadas medidas de proteção contra fatores ambientais com equipamentos e dispositivos especializados para monitorar e controlar o ambiente devidamente instalados? | D112: 0 | E112: 0
A113: 5 | B113: Gerenciamento de Instalações Físicas | C113: As instalações físicas são gerenciadas, incluindo equipamentos de energia e comunicação, em alinhamento com leis e regulamentações, requisitos técnicos e de negócio, especificações dos fabricantes e distribuidores de equipamentos e diretrizes de segurança e saúde ocupacional? | D113: 0 | E113: 0
A114: Maturidade do Processo | D114: =+SUM(D109:D113)/COUNTA(D109:D113) -> 0 | E114: =+SUM(E109:E113)/COUNTA(E109:E113) -> 0
...

Sheet MA - Questionário
F2: Gerente de Sistemas | G2: 0
A5: MA1 | B5: Monitorar e Avaliar o Desempenho de TI | D5: Atual | E5: Meta | G5: 1
A6: Objetivos Controle | C6: Pergunta | D6: (0-5) | E6: (0-5) | F6: Comentários | G6: 2
A7: 1 | B7: Abordagem de Monitoramento | C7: Existe uma abordagem e uma estrutura de monitoramento geral que definam o escopo, a metodologia e o processo a serem seguidos para avaliar a entrega de soluções e serviços de TI e monitorar a contribuição da TI para os resultados do negócio? A estrutura deve está integrada com o sistema de gestão de desempenho corporativo? | D7: 0 | E7: 0 | G7: 3
A8: 2 | B8: Definição e Coleta dos Dados de Monitoramento | C8: Há integração com a área de negócios na definição de um conjunto equilibrado de metas de performance que sejam aprovadas pelas áreas de negócio e demais partes interessadas relevantes? | D8: 0 | E8: 0 | G8: 4
A9: 3 | B9: Método de Monitoramento | C9: Há um método de monitoramento de performance (por exemplo, balanced scorecard) que registre as metas, capture as medições, apresente uma visão ampla e sucinta do desempenho da TI e se ajuste ao sistema de monitoramento corporativo (PL)? | D9: 0 | E9: 0 | G9: 5
A10: 4 | B10: Avaliação de Desempenho | C10: É analisado periodicamente o desempenho com base nas metas, executando a análise de causa-raiz dos problemas e iniciando ação corretiva para tratar as causas ocultas ou pouco claras? | D10: 0 | E10: 0
A11: 5 | B11: Relatórios para a Alta Direção | C11: São disponibilizados informes para a Alta Direção sobre a contribuição de TI para o negócio, especialmente em termos de desempenho do portfólio da organização, programas de investimentos em TI e soluções e serviços de cada programa? | D11: 0 | E11: 0
A12: 6 | B12: Ações Corretivas | C12: São implementadas ações corretivas com base no monitoramento, na avaliação e nos relatórios de desempenho? Isso inclui acompanhamento de todo o processo de monitoramento, relatórios e avaliações com: · Análise crítica, negociação e estabelecimento de respostas da gerência · Atribuição de responsabilidade pelas correções · Verificação dos resultados das ações acordadas | D12: 0 | E12: 0
A13: Maturidade do Processo | D13: =+SUM(D7:D12)/COUNTA(D7:D12) -> 0 | E13: =+SUM(E7:E12)/COUNTA(E7:E12) -> 0
A15: MA2 | B15: Monitorar e Avaliar os Controles Internos
A16: Objetivos Controle | C16: Pergunta | D16: (0-5) | E16: (0-5) | F16: Comentários
A17: 1 | B17: Monitoramento da Estrutura de Controles Internos | C17: A gerencia e diretoria monitoram os controles internos dos seus colaboradores? De que forma? | D17: 0 | E17: 0
A18: 2 | B18: Revisão Gerencial | C18: Há um processo de revisão e melhoria dos controles internos por parte dos níveis gerenciais? | D18: 0 | E18: 0
A19: 3 | B19: Exceções aos Controles | C19: São identificadas todas as exceções aos controles,assegurando que seja feita uma análise crítica das causas-raiz? São encaminhardas e reportadas adequadamente as exceções às partes interessadas.? | D19: 0 | E19: 0
A20: 4 | B20: Autoavaliação dos Controles | C20: Qual o grau de abrangência e a efetividade dos controles internos sobre os processos, as políticas e os contratos de TI através de um programa contínuo de autoavaliação? | D20: 0 | E20: 0
A21: 5 | B21: Garantia dos Controles Internos | C21: É possível obter maior garantia da abrangência e da eficácia dos controles internos através de avaliações de das áreas usuárias? | D21: 0 | E21: 0
A22: 6 | B22: Controles Internos Aplicados a Terceiros | C22: É possível avaliar o status dos controles internos aplicados a cada fornecedor de serviço, certificando-se de que fornecedores externos de serviço atendem às exigências legais e regulatórias e às obrigações contratuais? | D22: 0 | E22: 0
A23: 7 | B23: Ações Corretivas | C23: É possível identificar, iniciar, monitorar e implementar ações corretivas com base nas avaliações e nos relatórios de controle? | D23: 0 | E23: 0
A24: Maturidade do Processo | D24: =+SUM(D17:D23)/COUNTA(D17:D23) -> 0 | E24: =+SUM(E17:E23)/COUNTA(E17:E23) -> 0
A26: MA3 | B26: Assegurar a Conformidade com Requisitos Externos
A27: Objetivos Controle | C27: Pergunta | D27: (0-5) | E27: (0-5) | F27: Comentários
A28: 1 | B28: Identificação dos Requisitos de Conformidade com Leis, Regulamentações e Contratos Externos | C28: Há um processo que permita continuamente identificar as exigências de leis, regulamentos e contratos locais e internacionais que precisam ser atendidos para a inclusão em políticas, padrões, procedimentos e metodologias de TI? | D28: 0 | E28: 0
A29: 2 | B29: Otimização da Resposta aos Requisitos Externos | C29: É usual revisar e ajustar políticas, padrões, procedimentos e metodologias de TI para assegurar que os requisitos legais, regulatórios e contratuais sejam atendidos e comunicados? | D29: 0 | E29: 0
A30: 3 | B30: Avaliação da Conformidade com Requisitos Externos | C30: Há um processo para confirmar a conformidade de políticas, padrões, procedimentos e metodologias de TI com os requisitos legais e regulatórios? | D30: 0 | E30: 0
A31: 4 | B31: Assegurar a Conformidade | C31: Ha um processo para obter e assegurar a conformidade e adesão a todas as políticas internas derivadas de diretrizes legais internas ou externas e requisitos regulatórios ou contratuais externos, confirmando que ações corretivas foram tomadas oportunamente para resolver quaisquer desvios de conformidade pelos proprietário do processo? | D31: 0 | E31: 0
A32: 5 | B32: Informes Integrados | C32: Estão integrados os informes de TI sobre requisitos legais, regulatórios e contratuais aos informes similares de outras funções do negócio? | D32: 0 | E32: 0
A33: Maturidade do Processo | D33: =+SUM(D28:D32)/COUNTA(D28:D32) -> 0 | E33: =+SUM(E28:E32)/COUNTA(E28:E32) -> 0
D34: 3 | E34: 3
A35: MA4 | B35: Prover Governança de TI
A36: Objetivos Controle | C36: Pergunta | D36: (0-5) | E36: (0-5) | F36: Comentários
A37: 1 | B37: Estabelecimento de uma Estrutura de Governança de TI | C37: Define, estabelece e alinha a estrutura de governança de TI com a governança organizacional e o ambiente de controle? Basear a estrutura em processos e modelos de controle de TI adequados e implementar práticas e responsabilidades claras para evitar falhas de controle interno e supervisão. | D37: 0 | E37: 0
A38: 2 | B38: Alinhamento Estratégico | C38: A Alta Direção está habilitada no entendimento das questões estratégicas de TI, tais como os papéis de TI, as capacidades e os conhecimentos tecnológicos? Certificar-se de que há um entendimento compartilhado entre o negócio e a TI quanto ao potencial de contribuição de TI com a estratégia de negócio. | D38: 0 | E38: 0
A39: 3 | B39: Entrega de Valor | C39: Gerenciar os programas de investimentos e demais recursos e serviços de TI para assegurar que eles forneçam o maior valor possível no suporte aos objetivos e estratégia do negócio. Assegurar que sejam alcançados os resultados esperados pelo negócio quanto aos investimentos de TI, que o escopo completo de esforços necessários para o alcance desses resultados seja entendido, que estudos de caso abrangentes e consistentes sejam criados e aprovados pelas partes interessadas | D39: 0 | E39: 0
A40: 4 | B40: Gerenciamento de Recursos | C40: É supervisionar o investimento, o uso e a alocação dos recursos de TI por meio de avaliações periódicas das iniciativas e operações de TI, visando assegurar a existência recursos suficientes e o alinhamento com objetivos estratégicos e necessidades de negócios atuais e futuras? | D40: 0 | E40: 0
A41: 5 | B41: Gestão de Riscos | C41: Trabalhar com o conselho diretor para definir o apetite corporativo por riscos de TI e obter uma razoável segurança de que as práticas de gerenciamento de riscos de TI são adequadas para assegurar que os riscos atuais de TI não excedem o apetite de risco da Alta Direção. | D41: 0 | E41: 0
A42: 6 | B42: Medição de Desempenho | C42: Confirmar se os objetivos acordados de TI foram atingidos ou excedidos ou se o progresso na direção dos objetivos de TI atende as expectativas. | D42: 0 | E42: 0
A43: 7 | B43: Avaliação Independente | C43: É Obtido avaliação independente (interna ou externa) sobre a conformidade de TI com leis e regulamentos relevantes, com políticas padrões e procedimentos organizacionais, com práticas geralmente aceitas e a efetiva e eficiente performance de TI? | D43: 0 | E43: 0
A44: Maturidade do Processo | D44: =+SUM(D37:D43)/COUNTA(D37:D43) -> 0 | E44: =+SUM(E37:E43)/COUNTA(E37:E43) -> 0

Sheet Gráficos Maturidade
A1: Banchmark de Maturidade : Brazil Infrastructure Maturity X-Ray 2011 (Accenture e IDC)
R2: Processos | S2: Maturidade Apurada | T2: META Estabelecida
A3: Processos | B3: Maturidade Apurada | C3: META Estabelecida | R3: DS1 | S3: =+'DS - Questionário'!D12 -> 0 | T3: =+'DS - Questionário'!E12 -> 0
A4: PO1 | B4: =+'PO - Questionário'!D11 -> 0 | C4: =+'PO - Questionário'!E11 -> 0 | R4: DS2 | S4: =+'DS - Questionário'!D20 -> 0 | T4: =+'DS - Questionário'!E20 -> 0
A5: PO2 | B5: =+'PO - Questionário'!D19 -> 0 | C5: =+'PO - Questionário'!E19 -> 0 | R5: DS3 | S5: =+'DS - Questionário'!D29 -> 0 | T5: =+'DS - Questionário'!E29 -> 0
A6: PO3 | B6: =+'PO - Questionário'!D28 -> 0 | C6: =+'PO - Questionário'!E28 -> 0 | R6: DS4 | S6: =+'DS - Questionário'!D43 -> 0 | T6: =+'DS - Questionário'!E43 -> 0
A8: PO4 | B8: =+'PO - Questionário'!D47 -> 0 | C8: =+'PO - Questionário'!E47 -> 0 | R8: DS5 | S8: =+'DS - Questionário'!D58 -> 0 | T8: =+'DS - Questionário'!E58 -> 0
A9: PO5 | B9: =+'PO - Questionário'!D56 -> 0 | C9: =+'PO - Questionário'!E56 -> 0 | R9: DS6 | S9: =+'DS - Questionário'!D66 -> 0 | T9: =+'DS - Questionário'!E66 -> 0
A10: PO6 | B10: =+'PO - Questionário'!D65 -> 0 | C10: =+'PO - Questionário'!E65 -> 0 | R10: DS7 | S10: =+'DS - Questionário'!D73 -> 0 | T10: =+'DS - Questionário'!E73 -> 0
A11: PO7 | B11: =+'PO - Questionário'!D77 -> 0 | C11: =+'PO - Questionário'!E77 -> 0 | R11: DS8 | S11: =+'DS - Questionário'!D82 -> 0 | T11: =+'DS - Questionário'!E82 -> 0
A12: PO8 | B12: =+'PO - Questionário'!D87 -> 0 | C12: =+'PO - Questionário'!E87 -> 0 | R12: DS9 | S12: =+'DS - Questionário'!D89 -> 0 | T12: =+'DS - Questionário'!E89 -> 0
A13: PO9 | B13: =+'PO - Questionário'!D97 -> 0 | C13: =+'PO - Questionário'!E97 -> 0 | R13: DS10 | S13: =+'DS - Questionário'!D95 -> 0 | T13: =+'DS - Questionário'!E95 -> 0
A14: PO10 | B14: =+'PO - Questionário'!D115 -> 0 | C14: =+'PO - Questionário'!E115 -> 0 | R14: DS11 | S14: =+'DS - Questionário'!D105 -> 0 | T14: =+'DS - Questionário'!E105 -> 0
A15: Média | B15: =MEDIAN(B4:B14) -> 0 | C15: =MEDIAN(C4:C14) -> 0 | R15: DS12 | S15: =+'DS - Questionário'!D114 -> 0 | T15: =+'DS - Questionário'!E114 -> 0
R16: DS13 | S16: =+'DS - Questionário'!D123 -> 0 | T16: =+'DS - Questionário'!E123 -> 0
A26: Processos | B26: Maturidade Apurada | C26: META Estabelecida
A27: AI1 | B27: =+'AI - Questionário'!D10 -> 0 | C27: =+'AI - Questionário'!E10 -> 0
A28: AI2 | B28: =+'AI - Questionário'!D24 -> 0 | C28: =+'AI - Questionário'!E24 -> 0
A29: AI3 | B29: =+'AI - Questionário'!D32 -> 0 | C29: =+'AI - Questionário'!E32 -> 0
A30: AI4 | B30: =+'AI - Questionário'!D40 -> 0 | C30: =+'AI - Questionário'!E40 -> 0
A31: AI5 | B31: =+'AI - Questionário'!D48 -> 0 | C31: =+'AI - Questionário'!E48 -> 0
A32: AI6 | B32: =+'AI - Questionário'!D57 -> 0 | C32: =+'AI - Questionário'!E57 -> 0
A33: AI7 | B33: =+'AI - Questionário'!D70 -> 0 | C33: =+'AI - Questionário'!E70 -> 0
R46: Processos | S46: Maturidade Apurada | T46: META Estabelecida
R47: PO1 | S47: =+B4 -> 0 | T47: =+C4 -> 0
R48: PO2 | S48: =+B5 -> 0 | T48: =+C5 -> 0
R49: PO3 | S49: =+B6 -> 0 | T49: =+C6 -> 0
R50: PO4 | S50: =+B8 -> 0 | T50: =+C8 -> 0
A51: Processos | B51: Maturidade Apurada | C51: META Estabelecida | R51: PO5 | S51: =+B9 -> 0 | T51: =+C9 -> 0
A52: MA1 | B52: =+'MA - Questionário'!D13 -> 0 | C52: =+'MA - Questionário'!E13 -> 0 | R52: PO6 | S52: =+B10 -> 0 | T52: =+C10 -> 0
A53: MA2 | B53: =+'MA - Questionário'!D24 -> 0 | C53: =+'MA - Questionário'!E24 -> 0 | R53: PO7 | S53: =+B11 -> 0 | T53: =+C11 -> 0
A54: MA3 | B54: =+'MA - Questionário'!D33 -> 0 | C54: =+'MA - Questionário'!E33 -> 0 | R54: PO8 | S54: =+B12 -> 0 | T54: =+C12 -> 0
A55: MA4 | B55: =+'MA - Questionário'!D44 -> 0 | C55: =+'MA - Questionário'!E44 -> 0 | R55: PO9 | S55: =+B13 -> 0 | T55: =+C13 -> 0
R56: PO10 | S56: =+B14 -> 0 | T56: =+C14 -> 0
R57: AI1 | S57: =+B27 -> 0 | T57: =+C27 -> 0
R58: AI2 | S58: =+B28 -> 0 | T58: =+C28 -> 0
R59: AI3 | S59: =+B29 -> 0 | T59: =+C29 -> 0
R60: AI4 | S60: =+B30 -> 0 | T60: =+C30 -> 0
R61: AI5 | S61: =+B31 -> 0 | T61: =+C31 -> 0
R62: AI6 | S62: =+B32 -> 0 | T62: =+C32 -> 0
R63: AI7 | S63: =+B33 -> 0 | T63: =+C33 -> 0
R64: DS1 | S64: =+S3 -> 0 | T64: =+T3 -> 0
R65: DS2 | S65: =+S4 -> 0 | T65: =+T4 -> 0
R66: DS3 | S66: =+S5 -> 0 | T66: =+T5 -> 0
R67: DS4 | S67: =+S6 -> 0 | T67: =+T6 -> 0
R68: DS5 | S68: =+S8 -> 0 | T68: =+T8 -> 0
R69: DS6 | S69: =+S9 -> 0 | T69: =+T9 -> 0
R70: DS7 | S70: =+S10 -> 0 | T70: =+T10 -> 0
R71: DS8 | S71: =+S11 -> 0 | T71: =+T11 -> 0
R72: DS9 | S72: =+S12 -> 0 | T72: =+T12 -> 0
R73: DS10 | S73: =+S13 -> 0 | T73: =+T13 -> 0
R74: DS11 | S74: =+S14 -> 0 | T74: =+T14 -> 0
R75: DS12 | S75: =+S15 -> 0 | T75: =+T15 -> 0
R76: DS13 | S76: =+S16 -> 0 | T76: =+T16 -> 0
R77: MA1 | S77: =+B52 -> 0 | T77: =+C52 -> 0
R78: MA2 | S78: =+B53 -> 0 | T78: =+C53 -> 0
R79: MA3 | S79: =+B54 -> 0 | T79: =+C54 -> 0
R80: MA4 | S80: =+B55 -> 0 | T80: =+C55 -> 0
C102: Nível Maturidade
B103: META Estabelecida | C103: =+'Quadro Geral'!Z44 -> 0
B104: Maturidade Apurada | C104: =+'Quadro Geral'!R44 -> 0

Sheet Gráficos Conformidade
A1: Domínio PO
A2: Processo | B2: Nível 0 | C2: Nível 1 | D2: Nível 2 | E2: Nível 3 | F2: Nível 4 | G2: Nível 5 | H2: Total Objetivos
A3: PO1 - Definir o plano estratégico de TI | B3: =COUNTIFS('PO - Questionário'!$D$5:$D$10,0) -> 6 | C3: =COUNTIFS('PO - Questionário'!$D$5:$D$10,1) -> 0 | D3: =COUNTIFS('PO - Questionário'!$D$5:$D$10,2) -> 0 | E3: =COUNTIFS('PO - Questionário'!$D$5:$D$10,3) -> 0 | F3: =COUNTIFS('PO - Questionário'!$D$5:$D$10,4) -> 0 | G3: =COUNTIFS('PO - Questionário'!$D$5:$D$10,5) -> 0 | H3: =SUM(B3:G3) -> 6
A4: PO2 - Definir a arquitetura da informação | B4: =COUNTIFS('PO - Questionário'!$D$15:$D$18,0) -> 4 | C4: =COUNTIFS('PO - Questionário'!$D$15:$D$18,1) -> 0 | D4: =COUNTIFS('PO - Questionário'!$D$15:$D$18,2) -> 0 | E4: =COUNTIFS('PO - Questionário'!$D$15:$D$18,3) -> 0 | F4: =COUNTIFS('PO - Questionário'!$D$15:$D$18,4) -> 0 | G4: =COUNTIFS('PO - Questionário'!$D$15:$D$18,5) -> 0 | H4: =SUM(B4:G4) -> 4
A5: PO3 - Determinar a direção tecnológica | B5: =COUNTIFS('PO - Questionário'!$D$23:$D$27,0) -> 5 | C5: =COUNTIFS('PO - Questionário'!$D$23:$D$27,1) -> 0 | D5: =COUNTIFS('PO - Questionário'!$D$23:$D$27,2) -> 0 | E5: =COUNTIFS('PO - Questionário'!$D$23:$D$27,3) -> 0 | F5: =COUNTIFS('PO - Questionário'!$D$23:$D$27,4) -> 0 | G5: =COUNTIFS('PO - Questionário'!$D$23:$D$27,5) -> 0 | H5: =SUM(B5:G5) -> 5
A6: PO4 - Definir processos, organização e relacionamentos da TI | B6: =+COUNTIFS('PO - Questionário'!$D$32:$D$46,0) -> 15 | C6: =+COUNTIFS('PO - Questionário'!$D$32:$D$46,1) -> 0 | D6: =+COUNTIFS('PO - Questionário'!$D$32:$D$46,2) -> 0 | E6: =+COUNTIFS('PO - Questionário'!$D$32:$D$46,3) -> 0 | F6: =+COUNTIFS('PO - Questionário'!$D$32:$D$46,4) -> 0 | G6: =+COUNTIFS('PO - Questionário'!$D$32:$D$46,5) -> 0 | H6: =SUM(B6:G6) -> 15
A7: PO5 - Gerenciar os investimentos de TI | B7: =COUNTIFS('PO - Questionário'!$D$51:$D$55,0) -> 5 | C7: =COUNTIFS('PO - Questionário'!$D$51:$D$55,1) -> 0 | D7: =COUNTIFS('PO - Questionário'!$D$51:$D$55,2) -> 0 | E7: =COUNTIFS('PO - Questionário'!$D$51:$D$55,3) -> 0 | F7: =COUNTIFS('PO - Questionário'!$D$51:$D$55,4) -> 0 | G7: =COUNTIFS('PO - Questionário'!$D$51:$D$55,5) -> 0 | H7: =SUM(B7:G7) -> 5
A8: PO6 - Comunicar os objetivos e direção da administração | B8: =+COUNTIFS('PO - Questionário'!$D$60:$D$64,0) -> 5 | C8: =+COUNTIFS('PO - Questionário'!$D$60:$D$64,1) -> 0 | D8: =+COUNTIFS('PO - Questionário'!$D$60:$D$64,2) -> 0 | E8: =+COUNTIFS('PO - Questionário'!$D$60:$D$64,3) -> 0 | F8: =+COUNTIFS('PO - Questionário'!$D$60:$D$64,4) -> 0 | G8: =+COUNTIFS('PO - Questionário'!$D$60:$D$64,5) -> 0 | H8: =SUM(B8:G8) -> 5
A9: PO7 - Gerenciar os recursos humanos | B9: =+COUNTIFS('PO - Questionário'!$D$69:$D$76,0) -> 8 | C9: =+COUNTIFS('PO - Questionário'!$D$69:$D$76,1) -> 0 | D9: =+COUNTIFS('PO - Questionário'!$D$69:$D$76,2) -> 0 | E9: =+COUNTIFS('PO - Questionário'!$D$69:$D$76,3) -> 0 | F9: =+COUNTIFS('PO - Questionário'!$D$69:$D$76,4) -> 0 | G9: =+COUNTIFS('PO - Questionário'!$D$69:$D$76,5) -> 0 | H9: =SUM(B9:G9) -> 8
A10: PO8 - Gerenciar a qualidade | B10: =+COUNTIFS('PO - Questionário'!$D$81:$D$86,0) -> 6 | C10: =+COUNTIFS('PO - Questionário'!$D$81:$D$86,1) -> 0 | D10: =+COUNTIFS('PO - Questionário'!$D$81:$D$86,2) -> 0 | E10: =+COUNTIFS('PO - Questionário'!$D$81:$D$86,3) -> 0 | F10: =+COUNTIFS('PO - Questionário'!$D$81:$D$86,4) -> 0 | G10: =+COUNTIFS('PO - Questionário'!$D$81:$D$86,5) -> 0 | H10: =SUM(B10:G10) -> 6
A11: PO9 - Avaliar e gerenciar os riscos de TI | B11: =+COUNTIFS('PO - Questionário'!$D$91:$D$96,0) -> 6 | C11: =+COUNTIFS('PO - Questionário'!$D$91:$D$96,1) -> 0 | D11: =+COUNTIFS('PO - Questionário'!$D$91:$D$96,2) -> 0 | E11: =+COUNTIFS('PO - Questionário'!$D$91:$D$96,3) -> 0 | F11: =+COUNTIFS('PO - Questionário'!$D$91:$D$96,4) -> 0 | G11: =+COUNTIFS('PO - Questionário'!$D$91:$D$96,5) -> 0 | H11: =SUM(B11:G11) -> 6
A12: PO10 - Gerenciar projetos | B12: =+COUNTIFS('PO - Questionário'!$D$101:$D$114,0) -> 14 | C12: =+COUNTIFS('PO - Questionário'!$D$101:$D$114,1) -> 0 | D12: =+COUNTIFS('PO - Questionário'!$D$101:$D$114,2) -> 0 | E12: =+COUNTIFS('PO - Questionário'!$D$101:$D$114,3) -> 0 | F12: =+COUNTIFS('PO - Questionário'!$D$101:$D$114,4) -> 0 | G12: =+COUNTIFS('PO - Questionário'!$D$101:$D$114,5) -> 0 | H12: =SUM(B12:G12) -> 14
A67: Domínio AI
A68: Processo | B68: Nível 0 | C68: Nível 1 | D68: Nível 2 | E68: Nível 3 | F68: Nível 4 | G68: Nível 5
A69: AI1 - Identificar as soluções de automação | B69: =+COUNTIFS('AI - Questionário'!$D$6:$D$9,0) -> 4 | C69: =+COUNTIFS('AI - Questionário'!$D$6:$D$9,1) -> 0 | D69: =+COUNTIFS('AI - Questionário'!$D$6:$D$9,2) -> 0 | E69: =+COUNTIFS('AI - Questionário'!$D$6:$D$9,3) -> 0 | F69: =+COUNTIFS('AI - Questionário'!$D$6:$D$9,4) -> 0 | G69: =+COUNTIFS('AI - Questionário'!$D$6:$D$9,5) -> 0
A70: AI2 - Adquirir e manter os Softwares Aplicativos | B70: =COUNTIFS('AI - Questionário'!$D$14:$D$23,0) -> 10 | C70: =COUNTIFS('AI - Questionário'!$D$14:$D$23,1) -> 0 | D70: =COUNTIFS('AI - Questionário'!$D$14:$D$23,2) -> 0 | E70: =COUNTIFS('AI - Questionário'!$D$14:$D$23,3) -> 0 | F70: =COUNTIFS('AI - Questionário'!$D$14:$D$23,4) -> 0 | G70: =COUNTIFS('AI - Questionário'!$D$14:$D$23,5) -> 0
A71: AI3 - Adquirir e manter a infra-estrutura tecnológica | B71: =+COUNTIFS('AI - Questionário'!$D$28:$D$31,0) -> 4 | C71: =+COUNTIFS('AI - Questionário'!$D$28:$D$31,1) -> 0 | D71: =+COUNTIFS('AI - Questionário'!$D$28:$D$31,2) -> 0 | E71: =+COUNTIFS('AI - Questionário'!$D$28:$D$31,3) -> 0 | F71: =+COUNTIFS('AI - Questionário'!$D$28:$D$31,4) -> 0 | G71: =+COUNTIFS('AI - Questionário'!$D$28:$D$31,5) -> 0
A72: AI4 - Habilitar a operação e o uso | B72: =+COUNTIFS('AI - Questionário'!$D$36:$D$39,0) -> 4 | C72: =+COUNTIFS('AI - Questionário'!$D$36:$D$39,1) -> 0 | D72: =+COUNTIFS('AI - Questionário'!$D$36:$D$39,2) -> 0 | E72: =+COUNTIFS('AI - Questionário'!$D$36:$D$39,3) -> 0 | F72: =+COUNTIFS('AI - Questionário'!$D$36:$D$39,4) -> 0 | G72: =+COUNTIFS('AI - Questionário'!$D$36:$D$39,5) -> 0
A73: AI5 - Obter recursos de TI | B73: =COUNTIFS('AI - Questionário'!$D$44:$D$47,0) -> 4 | C73: =COUNTIFS('AI - Questionário'!$D$44:$D$47,1) -> 0 | D73: =COUNTIFS('AI - Questionário'!$D$44:$D$47,2) -> 0 | E73: =COUNTIFS('AI - Questionário'!$D$44:$D$47,3) -> 0 | F73: =COUNTIFS('AI - Questionário'!$D$44:$D$47,4) -> 0 | G73: =COUNTIFS('AI - Questionário'!$D$44:$D$47,5) -> 0
A74: AI6 - Gerenciar as mudanças | B74: =COUNTIFS('AI - Questionário'!$D$52:$D$56,0) -> 5 | C74: =COUNTIFS('AI - Questionário'!$D$52:$D$56,1) -> 0 | D74: =COUNTIFS('AI - Questionário'!$D$52:$D$56,2) -> 0 | E74: =COUNTIFS('AI - Questionário'!$D$52:$D$56,3) -> 0 | F74: =COUNTIFS('AI - Questionário'!$D$52:$D$56,4) -> 0 | G74: =COUNTIFS('AI - Questionário'!$D$52:$D$56,5) -> 0
A75: AI7 - Instalar e validar as soluções e as mudanças | B75: =+COUNTIFS('AI - Questionário'!$D$61:$F$69,0) -> 18 | C75: =+COUNTIFS('AI - Questionário'!$D$61:$F$69,1) -> 0 | D75: =+COUNTIFS('AI - Questionário'!$D$61:$F$69,2) -> 0 | E75: =+COUNTIFS('AI - Questionário'!$D$61:$F$69,3) -> 0 | F75: =+COUNTIFS('AI - Questionário'!$D$61:$F$69,4) -> 0 | G75: =+COUNTIFS('AI - Questionário'!$D$61:$F$69,5) -> 0
A116: Domínio MA
A117: Processo | B117: Nível 0 | C117: Nível 1 | D117: Nível 2 | E117: Nível 3 | F117: Nível 4 | G117: Nível 5 | I117: 0 | J117: 1 | K117: 2 | L117: 3 | M117: 4 | N117: 5
A118: MA1 - Monitorar e Avaliar o Desempenho | B118: =COUNTIF('MA - Questionário'!$D$7:$D$12,I117) -> 6 | C118: =COUNTIF('MA - Questionário'!$D$7:$D$12,J117) -> 0 | D118: =COUNTIF('MA - Questionário'!$D$7:$D$12,K117) -> 0 | E118: =COUNTIF('MA - Questionário'!$D$7:$D$12,L117) -> 0 | F118: =COUNTIF('MA - Questionário'!$D$7:$D$12,M117) -> 0 | G118: =COUNTIF('MA - Questionário'!$D$7:$D$12,N117) -> 0
A119: MA2 - Monitorar e Avaliar os Controles Internos | B119: =COUNTIF('MA - Questionário'!$D$17:$D$23,I117) -> 7 | C119: =COUNTIF('MA - Questionário'!$D$17:$D$23,J117) -> 0 | D119: =COUNTIF('MA - Questionário'!$D$17:$D$23,K117) -> 0 | E119: =COUNTIF('MA - Questionário'!$D$17:$D$23,L117) -> 0 | F119: =COUNTIF('MA - Questionário'!$D$17:$D$23,M117) -> 0 | G119: =COUNTIF('MA - Questionário'!$D$17:$D$23,N117) -> 0
A120: MA3 - Assegurar a Conformidade com Requisitos Externos | B120: =COUNTIF('MA - Questionário'!$D$28:$D$32,I117) -> 5 | C120: =COUNTIF('MA - Questionário'!$D$28:$D$32,J117) -> 0 | D120: =COUNTIF('MA - Questionário'!$D$28:$D$32,K117) -> 0 | E120: =COUNTIF('MA - Questionário'!$D$28:$D$32,L117) -> 0 | F120: =COUNTIF('MA - Questionário'!$D$28:$D$32,M117) -> 0 | G120: =COUNTIF('MA - Questionário'!$D$28:$D$32,N117) -> 0
A121: MA4 - Prover a Governança de TI | B121: =COUNTIF('MA - Questionário'!$D$37:$D$43,I117) -> 7 | C121: =COUNTIF('MA - Questionário'!$D$37:$D$43,J117) -> 0 | D121: =COUNTIF('MA - Questionário'!$D$37:$D$43,K117) -> 0 | E121: =COUNTIF('MA - Questionário'!$D$37:$D$43,L117) -> 0 | F121: =COUNTIF('MA - Questionário'!$D$37:$D$43,M117) -> 0 | G121: =COUNTIF('MA - Questionário'!$D$37:$D$43,N117) -> 0
A148: Domínio DS
A149: Processo | B149: Nível 0 | C149: Nível 1 | D149: Nível 2 | E149: Nível 3 | F149: Nível 4 | G149: Nível 5 | I149: 0 | J149: 1 | K149: 2 | L149: 3 | M149: 4 | N149: 5
A150: DS1 - Definir e Gerenciar Níveis de Serviços | B150: =COUNTIF('DS - Questionário'!$D$6:$D$11,'Gráficos Conformidade'!I149) -> 6 | C150: =COUNTIF('DS - Questionário'!$D$6:$D$11,'Gráficos Conformidade'!J149) -> 0 | D150: =COUNTIF('DS - Questionário'!$D$6:$D$11,'Gráficos Conformidade'!K149) -> 0 | E150: =COUNTIF('DS - Questionário'!$D$6:$D$11,'Gráficos Conformidade'!L149) -> 0 | F150: =COUNTIF('DS - Questionário'!$D$6:$D$11,'Gráficos Conformidade'!M149) -> 0 | G150: =COUNTIF('DS - Questionário'!$D$6:$D$11,'Gráficos Conformidade'!N149) -> 0
A151: DS2 - Gerenciar Serviços de Terceiros | B151: =COUNTIF('DS - Questionário'!$D$16:$D$19,'Gráficos Conformidade'!I149) -> 4 | C151: =COUNTIF('DS - Questionário'!$D$16:$D$19,'Gráficos Conformidade'!J149) -> 0 | D151: =COUNTIF('DS - Questionário'!$D$16:$D$19,'Gráficos Conformidade'!K149) -> 0 | E151: =COUNTIF('DS - Questionário'!$D$16:$D$19,'Gráficos Conformidade'!L149) -> 0 | F151: =COUNTIF('DS - Questionário'!$D$16:$D$19,'Gráficos Conformidade'!M149) -> 0 | G151: =COUNTIF('DS - Questionário'!$D$16:$D$19,'Gráficos Conformidade'!N149) -> 0
A152: DS3 - Gerenciar Capacidade e Desempenho | B152: =COUNTIF('DS - Questionário'!$D$24:$D$28,'Gráficos Conformidade'!I149) -> 5 | C152: =COUNTIF('DS - Questionário'!$D$24:$D$28,'Gráficos Conformidade'!J149) -> 0 | D152: =COUNTIF('DS - Questionário'!$D$24:$D$28,'Gráficos Conformidade'!K149) -> 0 | E152: =COUNTIF('DS - Questionário'!$D$24:$D$28,'Gráficos Conformidade'!L149) -> 0 | F152: =COUNTIF('DS - Questionário'!$D$24:$D$28,'Gráficos Conformidade'!M149) -> 0 | G152: =COUNTIF('DS - Questionário'!$D$24:$D$28,'Gráficos Conformidade'!N149) -> 0
A153: DS4 - Assegurar Continuidade de Serviços: | B153: =COUNTIF('DS - Questionário'!$D$33:$D$42,'Gráficos Conformidade'!I149) -> 10 | C153: =COUNTIF('DS - Questionário'!$D$33:$D$42,'Gráficos Conformidade'!J149) -> 0 | D153: =COUNTIF('DS - Questionário'!$D$33:$D$42,'Gráficos Conformidade'!K149) -> 0 | E153: =COUNTIF('DS - Questionário'!$D$33:$D$42,'Gráficos Conformidade'!L149) -> 0 | F153: =COUNTIF('DS - Questionário'!$D$33:$D$42,'Gráficos Conformidade'!M149) -> 0 | G153: =COUNTIF('DS - Questionário'!$D$33:$D$42,'Gráficos Conformidade'!N149) -> 0
A154: DS5 - Assegurar a Segurança dos Serviços | B154: =COUNTIF('DS - Questionário'!$D$47:$D$57,'Gráficos Conformidade'!I149) -> 11 | C154: =COUNTIF('DS - Questionário'!$D$47:$D$57,'Gráficos Conformidade'!J149) -> 0 | D154: =COUNTIF('DS - Questionário'!$D$47:$D$57,'Gráficos Conformidade'!K149) -> 0 | E154: =COUNTIF('DS - Questionário'!$D$47:$D$57,'Gráficos Conformidade'!L149) -> 0 | F154: =COUNTIF('DS - Questionário'!$D$47:$D$57,'Gráficos Conformidade'!M149) -> 0 | G154: =COUNTIF('DS - Questionário'!$D$47:$D$57,'Gráficos Conformidade'!N149) -> 0
A155: DS6 - Identificar e Alocar Custos | B155: =COUNTIF('DS - Questionário'!$D$62:$D$65,'Gráficos Conformidade'!I149) -> 4 | C155: =COUNTIF('DS - Questionário'!$D$62:$D$65,'Gráficos Conformidade'!J149) -> 0 | D155: =COUNTIF('DS - Questionário'!$D$62:$D$65,'Gráficos Conformidade'!K149) -> 0 | E155: =COUNTIF('DS - Questionário'!$D$62:$D$65,'Gráficos Conformidade'!L149) -> 0 | F155: =COUNTIF('DS - Questionário'!$D$62:$D$65,'Gráficos Conformidade'!M149) -> 0 | G155: =COUNTIF('DS - Questionário'!$D$62:$D$65,'Gráficos Conformidade'!N149) -> 0
A156: DS7 - Educar e Treinar os Usuários | B156: =COUNTIF('DS - Questionário'!$D$70:$D$72,'Gráficos Conformidade'!I149) -> 3 | C156: =COUNTIF('DS - Questionário'!$D$70:$D$72,'Gráficos Conformidade'!J149) -> 0 | D156: =COUNTIF('DS - Questionário'!$D$70:$D$72,'Gráficos Conformidade'!K149) -> 0 | E156: =COUNTIF('DS - Questionário'!$D$70:$D$72,'Gráficos Conformidade'!L149) -> 0 | F156: =COUNTIF('DS - Questionário'!$D$70:$D$72,'Gráficos Conformidade'!M149) -> 0 | G156: =COUNTIF('DS - Questionário'!$D$70:$D$72,'Gráficos Conformidade'!N149) -> 0
A157: DS8 - Gerenciar a Central de Serviço e os Incidentes | B157: =COUNTIF('DS - Questionário'!$D$77:$D$81,'Gráficos Conformidade'!I149) -> 5 | C157: =COUNTIF('DS - Questionário'!$D$77:$D$81,'Gráficos Conformidade'!J149) -> 0 | D157: =COUNTIF('DS - Questionário'!$D$77:$D$81,'Gráficos Conformidade'!K149) -> 0 | E157: =COUNTIF('DS - Questionário'!$D$77:$D$81,'Gráficos Conformidade'!L149) -> 0 | F157: =COUNTIF('DS - Questionário'!$D$77:$D$81,'Gráficos Conformidade'!M149) -> 0 | G157: =COUNTIF('DS - Questionário'!$D$77:$D$81,'Gráficos Conformidade'!N149) -> 0
A158: DS9 - Gerenciar a Configuração | B158: =COUNTIF('DS - Questionário'!$D$86:$D$88,'Gráficos Conformidade'!I149) -> 3 | C158: =COUNTIF('DS - Questionário'!$D$86:$D$88,'Gráficos Conformidade'!J149) -> 0 | D158: =COUNTIF('DS - Questionário'!$D$86:$D$88,'Gráficos Conformidade'!K149) -> 0 | E158: =COUNTIF('DS - Questionário'!$D$86:$D$88,'Gráficos Conformidade'!L149) -> 0 | F158: =COUNTIF('DS - Questionário'!$D$86:$D$88,'Gráficos Conformidade'!M149) -> 0 | G158: =COUNTIF('DS - Questionário'!$D$86:$D$88,'Gráficos Conformidade'!N149) -> 0
A159: DS10 - Gerenciar os Problemas | B159: =COUNTIF('DS - Questionário'!$D$93:$D$94,'Gráficos Conformidade'!I149) -> 2 | C159: =COUNTIF('DS - Questionário'!$D$93:$D$94,'Gráficos Conformidade'!J149) -> 0 | D159: =COUNTIF('DS - Questionário'!$D$93:$D$94,'Gráficos Conformidade'!K149) -> 0 | E159: =COUNTIF('DS - Questionário'!$D$93:$D$94,'Gráficos Conformidade'!L149) -> 0 | F159: =COUNTIF('DS - Questionário'!$D$93:$D$94,'Gráficos Conformidade'!M149) -> 0 | G159: =COUNTIF('DS - Questionário'!$D$93:$D$94,'Gráficos Conformidade'!N149) -> 0
A160: DS11 - Gerenciar Dados | B160: =COUNTIF('DS - Questionário'!$D$99:$D$104,'Gráficos Conformidade'!I149) -> 6 | C160: =COUNTIF('DS - Questionário'!$D$99:$D$104,'Gráficos Conformidade'!J149) -> 0 | D160: =COUNTIF('DS - Questionário'!$D$99:$D$104,'Gráficos Conformidade'!K149) -> 0 | E160: =COUNTIF('DS - Questionário'!$D$99:$D$104,'Gráficos Conformidade'!L149) -> 0 | F160: =COUNTIF('DS - Questionário'!$D$99:$D$104,'Gráficos Conformidade'!M149) -> 0 | G160: =COUNTIF('DS - Questionário'!$D$99:$D$104,'Gráficos Conformidade'!N149) -> 0
A161: DS12- Gerenciar Ambiente Físico | B161: =COUNTIF('DS - Questionário'!$D$109:$D$113,'Gráficos Conformidade'!I149) -> 5 | C161: =COUNTIF('DS - Questionário'!$D$109:$D$113,'Gráficos Conformidade'!J149) -> 0 | D161: =COUNTIF('DS - Questionário'!$D$109:$D$113,'Gráficos Conformidade'!K149) -> 0 | E161: =COUNTIF('DS - Questionário'!$D$109:$D$113,'Gráficos Conformidade'!L149) -> 0 | F161: =COUNTIF('DS - Questionário'!$D$109:$D$113,'Gráficos Conformidade'!M149) -> 0 | G161: =COUNTIF('DS - Questionário'!$D$109:$D$113,'Gráficos Conformidade'!N149) -> 0
A162: DS13 - Gerenciar operações | B162: =COUNTIF('DS - Questionário'!$D$118:$D$122,'Gráficos Conformidade'!I149) -> 5 | C162: =COUNTIF('DS - Questionário'!$D$118:$D$122,'Gráficos Conformidade'!J149) -> 0 | D162: =COUNTIF('DS - Questionário'!$D$118:$D$122,'Gráficos Conformidade'!K149) -> 0 | E162: =COUNTIF('DS - Questionário'!$D$118:$D$122,'Gráficos Conformidade'!L149) -> 0 | F162: =COUNTIF('DS - Questionário'!$D$118:$D$122,'Gráficos Conformidade'!M149) -> 0 | G162: =COUNTIF('DS - Questionário'!$D$118:$D$122,'Gráficos Conformidade'!N149) -> 0

Sheet Quadro de Domínios e Processos
A18: Criação: | B18: Ronaldo Martins (Cobit,Itil ePmBok)
A19: Contato : | B19: ronaldogmartins@hotmail.com
A21: Esta planilha foi disponibilizada para uso púbico e os dados aqui apresentados são fictícios, use a vontade entretanto seria ético e correto citar o autor.
A23: O Autor não se responsabiliza por eventuais erros de funcionamento não detectados
