Workbook

Sheet Campaign Name
B1: Mandatory Fields | I1: Optional | M1: CAMPAIGN NAME
A2: ID | B2: Country (List) | C2: Campaign Name Description (FF) | D2: Merchant Code (List) | E2: Date (List) | F2: PO# (FF) | G2: Sponsorship | H2: Activity | I2: Campaign Objective (List) | J2: U1 | K2: U2 | L2: U3
B3: Brazil | C3: DOTZ | D3: None | E3: 20Q1 | F3: 5020004460 | G3: N/A | H3: Client Marketing | I3: Consideration | M3: =CONCATENATE("MK|",(VLOOKUP(B3,Dictionary!$A:$B,2,FALSE)),"_CN|",SUBSTITUTE(SUBSTITUTE(IF(C3="","NONE",C3),"_","-"),"|","-"),"_MN|",(VLOOKUP(D3,Dictionary!$D:$E,2,0)),"_YQ|",(VLOOKUP(E3,Dictionary!$AR:$AR,1,0)),"_CP|",SUBSTITUTE(SUBSTITUTE(IF(F3="","NONE",F3),"_","-"),"|","-"),"_SP|",(VLOOKUP(G3,Dictionary!$AY:$AZ,2,0)),"_AC|",(VLOOKUP(H3,Dictionary!$BA:$BB,2,0)),IF(I3="","",CONCATENATE("_OB|",(VLOOKUP(I3,Dictionary!$AS:$AT,2,0)))),IF(J3="","",CONCATENATE("_U1|",SUBSTITUTE(SUBSTITUTE(J3,"_","-"),"|","-"))),IF(K3="","",CONCATENATE("_U2|",SUBSTITUTE(SUBSTITUTE(K3,"_","-"),"|","-"))),IF(L3="","",CONCATENATE("_U3|",SUBSTITUTE(SUBSTITUTE(L3,"_","-"),"|","-")))) -> MK|BR_CN|DOTZ_MN|NONE_YQ|20Q1_CP|5020004460_SP|NA_AC|CMKT_OB|CON
B4: Brazil | C4: DOTZ | D4: None | E4: 20Q1Q4 | F4: 5020004460 | G4: N/A | H4: Client Marketing | M4: =CONCATENATE("MK|",(VLOOKUP(B4,Dictionary!$A:$B,2,FALSE)),"_CN|",SUBSTITUTE(SUBSTITUTE(IF(C4="","NONE",C4),"_","-"),"|","-"),"_MN|",(VLOOKUP(D4,Dictionary!$D:$E,2,0)),"_YQ|",(VLOOKUP(E4,Dictionary!$AR:$AR,1,0)),"_CP|",SUBSTITUTE(SUBSTITUTE(IF(F4="","NONE",F4),"_","-"),"|","-"),"_SP|",(VLOOKUP(G4,Dictionary!$AY:$AZ,2,0)),"_AC|",(VLOOKUP(H4,Dictionary!$BA:$BB,2,0)),IF(I4="","",CONCATENATE("_OB|",(VLOOKUP(I4,Dictionary!$AS:$AT,2,0)))),IF(J4="","",CONCATENATE("_U1|",SUBSTITUTE(SUBSTITUTE(J4,"_","-"),"|","-"))),IF(K4="","",CONCATENATE("_U2|",SUBSTITUTE(SUBSTITUTE(K4,"_","-"),"|","-"))),IF(L4="","",CONCATENATE("_U3|",SUBSTITUTE(SUBSTITUTE(L4,"_","-"),"|","-")))) -> MK|BR_CN|DOTZ_MN|NONE_YQ|20Q1Q4_CP|5020004460_SP|NA_AC|CMKT
B5: Brazil | C5: DOTZ | D5: None | E5: 20Q2Q4 | F5: 5020004460 | G5: N/A | H5: Client Marketing | I5: Acquisition | M5: =CONCATENATE("MK|",(VLOOKUP(B5,Dictionary!$A:$B,2,FALSE)),"_CN|",SUBSTITUTE(SUBSTITUTE(IF(C5="","NONE",C5),"_","-"),"|","-"),"_MN|",(VLOOKUP(D5,Dictionary!$D:$E,2,0)),"_YQ|",(VLOOKUP(E5,Dictionary!$AR:$AR,1,0)),"_CP|",SUBSTITUTE(SUBSTITUTE(IF(F5="","NONE",F5),"_","-"),"|","-"),"_SP|",(VLOOKUP(G5,Dictionary!$AY:$AZ,2,0)),"_AC|",(VLOOKUP(H5,Dictionary!$BA:$BB,2,0)),IF(I5="","",CONCATENATE("_OB|",(VLOOKUP(I5,Dictionary!$AS:$AT,2,0)))),IF(J5="","",CONCATENATE("_U1|",SUBSTITUTE(SUBSTITUTE(J5,"_","-"),"|","-"))),IF(K5="","",CONCATENATE("_U2|",SUBSTITUTE(SUBSTITUTE(K5,"_","-"),"|","-"))),IF(L5="","",CONCATENATE("_U3|",SUBSTITUTE(SUBSTITUTE(L5,"_","-"),"|","-")))) -> MK|BR_CN|DOTZ_MN|NONE_YQ|20Q2Q4_CP|5020004460_SP|NA_AC|CMKT_OB|ACQ
B6: Brazil | C6: FWWC | D6: None | E6: 19Q1Q4 | F6: NONE | G6: N/A | H6: Cash Conversion | I6: Acquisition | M6: =CONCATENATE("MK|",(VLOOKUP(B6,Dictionary!$A:$B,2,FALSE)),"_CN|",SUBSTITUTE(SUBSTITUTE(IF(C6="","NONE",C6),"_","-"),"|","-"),"_MN|",(VLOOKUP(D6,Dictionary!$D:$E,2,0)),"_YQ|",(VLOOKUP(E6,Dictionary!$AR:$AR,1,0)),"_CP|",SUBSTITUTE(SUBSTITUTE(IF(F6="","NONE",F6),"_","-"),"|","-"),"_SP|",(VLOOKUP(G6,Dictionary!$AY:$AZ,2,0)),"_AC|",(VLOOKUP(H6,Dictionary!$BA:$BB,2,0)),IF(I6="","",CONCATENATE("_OB|",(VLOOKUP(I6,Dictionary!$AS:$AT,2,0)))),IF(J6="","",CONCATENATE("_U1|",SUBSTITUTE(SUBSTITUTE(J6,"_","-"),"|","-"))),IF(K6="","",CONCATENATE("_U2|",SUBSTITUTE(SUBSTITUTE(K6,"_","-"),"|","-"))),IF(L6="","",CONCATENATE("_U3|",SUBSTITUTE(SUBSTITUTE(L6,"_","-"),"|","-")))) -> MK|BR_CN|FWWC_MN|NONE_YQ|19Q1Q4_CP|NONE_SP|NA_AC|CC_OB|ACQ
M17: =CONCATENATE("MK|",(VLOOKUP(B17,Dictionary!$A:$B,2,FALSE)),"_CN|",SUBSTITUTE(SUBSTITUTE(IF(C17="","NONE",C17),"_","-"),"|","-"),"_MN|",(VLOOKUP(D17,Dictionary!$D:$E,2,0)),"_YQ|",(VLOOKUP(E17,Dictionary!$AR:$AR,1,0)),"_CP|",SUBSTITUTE(SUBSTITUTE(IF(F17="","NONE",F17),"_","-"),"|","-"),"_SP|",(VLOOKUP(G17,Dictionary!$AY:$AZ,2,0)),"_AC|",(VLOOKUP(H17,Dictionary!$BA:$BB,2,0)),IF(I17="","",CONCATENATE("_OB|",(VLOOKUP(I17,Dictionary!$AS:$AT,2,0)))),IF(J17="","",CONCATENATE("_U1|",SUBSTITUTE(SUBSTITUTE(J17,"_","-"),"|","-"))),IF(K17="","",CONCATENATE("_U2|",SUBSTITUTE(SUBSTITUTE(K17,"_","-"),"|","-"))),IF(L17="","",CONCATENATE("_U3|",SUBSTITUTE(SUBSTITUTE(L17,"_","-"),"|","-")))) -> #N/A
M18: =CONCATENATE("MK|",(VLOOKUP(B18,Dictionary!$A:$B,2,FALSE)),"_CN|",SUBSTITUTE(SUBSTITUTE(IF(C18="","NONE",C18),"_","-"),"|","-"),"_MN|",(VLOOKUP(D18,Dictionary!$D:$E,2,0)),"_YQ|",(VLOOKUP(E18,Dictionary!$AR:$AR,1,0)),"_CP|",SUBSTITUTE(SUBSTITUTE(IF(F18="","NONE",F18),"_","-"),"|","-"),"_SP|",(VLOOKUP(G18,Dictionary!$AY:$AZ,2,0)),"_AC|",(VLOOKUP(H18,Dictionary!$BA:$BB,2,0)),IF(I18="","",CONCATENATE("_OB|",(VLOOKUP(I18,Dictionary!$AS:$AT,2,0)))),IF(J18="","",CONCATENATE("_U1|",SUBSTITUTE(SUBSTITUTE(J18,"_","-"),"|","-"))),IF(K18="","",CONCATENATE("_U2|",SUBSTITUTE(SUBSTITUTE(K18,"_","-"),"|","-"))),IF(L18="","",CONCATENATE("_U3|",SUBSTITUTE(SUBSTITUTE(L18,"_","-"),"|","-")))) -> #N/A
M19: =CONCATENATE("MK|",(VLOOKUP(B19,Dictionary!$A:$B,2,FALSE)),"_CN|",SUBSTITUTE(SUBSTITUTE(IF(C19="","NONE",C19),"_","-"),"|","-"),"_MN|",(VLOOKUP(D19,Dictionary!$D:$E,2,0)),"_YQ|",(VLOOKUP(E19,Dictionary!$AR:$AR,1,0)),"_CP|",SUBSTITUTE(SUBSTITUTE(IF(F19="","NONE",F19),"_","-"),"|","-"),"_SP|",(VLOOKUP(G19,Dictionary!$AY:$AZ,2,0)),"_AC|",(VLOOKUP(H19,Dictionary!$BA:$BB,2,0)),IF(I19="","",CONCATENATE("_OB|",(VLOOKUP(I19,Dictionary!$AS:$AT,2,0)))),IF(J19="","",CONCATENATE("_U1|",SUBSTITUTE(SUBSTITUTE(J19,"_","-"),"|","-"))),IF(K19="","",CONCATENATE("_U2|",SUBSTITUTE(SUBSTITUTE(K19,"_","-"),"|","-"))),IF(L19="","",CONCATENATE("_U3|",SUBSTITUTE(SUBSTITUTE(L19,"_","-"),"|","-")))) -> #N/A
M20: =CONCATENATE("MK|",(VLOOKUP(B20,Dictionary!$A:$B,2,FALSE)),"_CN|",SUBSTITUTE(SUBSTITUTE(IF(C20="","NONE",C20),"_","-"),"|","-"),"_MN|",(VLOOKUP(D20,Dictionary!$D:$E,2,0)),"_YQ|",(VLOOKUP(E20,Dictionary!$AR:$AR,1,0)),"_CP|",SUBSTITUTE(SUBSTITUTE(IF(F20="","NONE",F20),"_","-"),"|","-"),"_SP|",(VLOOKUP(G20,Dictionary!$AY:$AZ,2,0)),"_AC|",(VLOOKUP(H20,Dictionary!$BA:$BB,2,0)),IF(I20="","",CONCATENATE("_OB|",(VLOOKUP(I20,Dictionary!$AS:$AT,2,0)))),IF(J20="","",CONCATENATE("_U1|",SUBSTITUTE(SUBSTITUTE(J20,"_","-"),"|","-"))),IF(K20="","",CONCATENATE("_U2|",SUBSTITUTE(SUBSTITUTE(K20,"_","-"),"|","-"))),IF(L20="","",CONCATENATE("_U3|",SUBSTITUTE(SUBSTITUTE(L20,"_","-"),"|","-")))) -> #N/A
M21: =CONCATENATE("MK|",(VLOOKUP(B21,Dictionary!$A:$B,2,FALSE)),"_CN|",SUBSTITUTE(SUBSTITUTE(IF(C21="","NONE",C21),"_","-"),"|","-"),"_MN|",(VLOOKUP(D21,Dictionary!$D:$E,2,0)),"_YQ|",(VLOOKUP(E21,Dictionary!$AR:$AR,1,0)),"_CP|",SUBSTITUTE(SUBSTITUTE(IF(F21="","NONE",F21),"_","-"),"|","-"),"_SP|",(VLOOKUP(G21,Dictionary!$AY:$AZ,2,0)),"_AC|",(VLOOKUP(H21,Dictionary!$BA:$BB,2,0)),IF(I21="","",CONCATENATE("_OB|",(VLOOKUP(I21,Dictionary!$AS:$AT,2,0)))),IF(J21="","",CONCATENATE("_U1|",SUBSTITUTE(SUBSTITUTE(J21,"_","-"),"|","-"))),IF(K21="","",CONCATENATE("_U2|",SUBSTITUTE(SUBSTITUTE(K21,"_","-"),"|","-"))),IF(L21="","",CONCATENATE("_U3|",SUBSTITUTE(SUBSTITUTE(L21,"_","-"),"|","-")))) -> #N/A
M22: =CONCATENATE("MK|",(VLOOKUP(B22,Dictionary!$A:$B,2,FALSE)),"_CN|",SUBSTITUTE(SUBSTITUTE(IF(C22="","NONE",C22),"_","-"),"|","-"),"_MN|",(VLOOKUP(D22,Dictionary!$D:$E,2,0)),"_YQ|",(VLOOKUP(E22,Dictionary!$AR:$AR,1,0)),"_CP|",SUBSTITUTE(SUBSTITUTE(IF(F22="","NONE",F22),"_","-"),"|","-"),"_SP|",(VLOOKUP(G22,Dictionary!$AY:$AZ,2,0)),"_AC|",(VLOOKUP(H22,Dictionary!$BA:$BB,2,0)),IF(I22="","",CONCATENATE("_OB|",(VLOOKUP(I22,Dictionary!$AS:$AT,2,0)))),IF(J22="","",CONCATENATE("_U1|",SUBSTITUTE(SUBSTITUTE(J22,"_","-"),"|","-"))),IF(K22="","",CONCATENATE("_U2|",SUBSTITUTE(SUBSTITUTE(K22,"_","-"),"|","-"))),IF(L22="","",CONCATENATE("_U3|",SUBSTITUTE(SUBSTITUTE(L22,"_","-"),"|","-")))) -> #N/A
M23: =CONCATENATE("MK|",(VLOOKUP(B23,Dictionary!$A:$B,2,FALSE)),"_CN|",SUBSTITUTE(SUBSTITUTE(IF(C23="","NONE",C23),"_","-"),"|","-"),"_MN|",(VLOOKUP(D23,Dictionary!$D:$E,2,0)),"_YQ|",(VLOOKUP(E23,Dictionary!$AR:$AR,1,0)),"_CP|",SUBSTITUTE(SUBSTITUTE(IF(F23="","NONE",F23),"_","-"),"|","-"),"_SP|",(VLOOKUP(G23,Dictionary!$AY:$AZ,2,0)),"_AC|",(VLOOKUP(H23,Dictionary!$BA:$BB,2,0)),IF(I23="","",CONCATENATE("_OB|",(VLOOKUP(I23,Dictionary!$AS:$AT,2,0)))),IF(J23="","",CONCATENATE("_U1|",SUBSTITUTE(SUBSTITUTE(J23,"_","-"),"|","-"))),IF(K23="","",CONCATENATE("_U2|",SUBSTITUTE(SUBSTITUTE(K23,"_","-"),"|","-"))),IF(L23="","",CONCATENATE("_U3|",SUBSTITUTE(SUBSTITUTE(L23,"_","-"),"|","-")))) -> #N/A
M24: =CONCATENATE("MK|",(VLOOKUP(B24,Dictionary!$A:$B,2,FALSE)),"_CN|",SUBSTITUTE(SUBSTITUTE(IF(C24="","NONE",C24),"_","-"),"|","-"),"_MN|",(VLOOKUP(D24,Dictionary!$D:$E,2,0)),"_YQ|",(VLOOKUP(E24,Dictionary!$AR:$AR,1,0)),"_CP|",SUBSTITUTE(SUBSTITUTE(IF(F24="","NONE",F24),"_","-"),"|","-"),"_SP|",(VLOOKUP(G24,Dictionary!$AY:$AZ,2,0)),"_AC|",(VLOOKUP(H24,Dictionary!$BA:$BB,2,0)),IF(I24="","",CONCATENATE("_OB|",(VLOOKUP(I24,Dictionary!$AS:$AT,2,0)))),IF(J24="","",CONCATENATE("_U1|",SUBSTITUTE(SUBSTITUTE(J24,"_","-"),"|","-"))),IF(K24="","",CONCATENATE("_U2|",SUBSTITUTE(SUBSTITUTE(K24,"_","-"),"|","-"))),IF(L24="","",CONCATENATE("_U3|",SUBSTITUTE(SUBSTITUTE(L24,"_","-"),"|","-")))) -> #N/A
M25: =CONCATENATE("MK|",(VLOOKUP(B25,Dictionary!$A:$B,2,FALSE)),"_CN|",SUBSTITUTE(SUBSTITUTE(IF(C25="","NONE",C25),"_","-"),"|","-"),"_MN|",(VLOOKUP(D25,Dictionary!$D:$E,2,0)),"_YQ|",(VLOOKUP(E25,Dictionary!$AR:$AR,1,0)),"_CP|",SUBSTITUTE(SUBSTITUTE(IF(F25="","NONE",F25),"_","-"),"|","-"),"_SP|",(VLOOKUP(G25,Dictionary!$AY:$AZ,2,0)),"_AC|",(VLOOKUP(H25,Dictionary!$BA:$BB,2,0)),IF(I25="","",CONCATENATE("_OB|",(VLOOKUP(I25,Dictionary!$AS:$AT,2,0)))),IF(J25="","",CONCATENATE("_U1|",SUBSTITUTE(SUBSTITUTE(J25,"_","-"),"|","-"))),IF(K25="","",CONCATENATE("_U2|",SUBSTITUTE(SUBSTITUTE(K25,"_","-"),"|","-"))),IF(L25="","",CONCATENATE("_U3|",SUBSTITUTE(SUBSTITUTE(L25,"_","-"),"|","-")))) -> #N/A
M26: =CONCATENATE("MK|",(VLOOKUP(B26,Dictionary!$A:$B,2,FALSE)),"_CN|",SUBSTITUTE(SUBSTITUTE(IF(C26="","NONE",C26),"_","-"),"|","-"),"_MN|",(VLOOKUP(D26,Dictionary!$D:$E,2,0)),"_YQ|",(VLOOKUP(E26,Dictionary!$AR:$AR,1,0)),"_CP|",SUBSTITUTE(SUBSTITUTE(IF(F26="","NONE",F26),"_","-"),"|","-"),"_SP|",(VLOOKUP(G26,Dictionary!$AY:$AZ,2,0)),"_AC|",(VLOOKUP(H26,Dictionary!$BA:$BB,2,0)),IF(I26="","",CONCATENATE("_OB|",(VLOOKUP(I26,Dictionary!$AS:$AT,2,0)))),IF(J26="","",CONCATENATE("_U1|",SUBSTITUTE(SUBSTITUTE(J26,"_","-"),"|","-"))),IF(K26="","",CONCATENATE("_U2|",SUBSTITUTE(SUBSTITUTE(K26,"_","-"),"|","-"))),IF(L26="","",CONCATENATE("_U3|",SUBSTITUTE(SUBSTITUTE(L26,"_","-"),"|","-")))) -> #N/A
M27: =CONCATENATE("MK|",(VLOOKUP(B27,Dictionary!$A:$B,2,FALSE)),"_CN|",SUBSTITUTE(SUBSTITUTE(IF(C27="","NONE",C27),"_","-"),"|","-"),"_MN|",(VLOOKUP(D27,Dictionary!$D:$E,2,0)),"_YQ|",(VLOOKUP(E27,Dictionary!$AR:$AR,1,0)),"_CP|",SUBSTITUTE(SUBSTITUTE(IF(F27="","NONE",F27),"_","-"),"|","-"),"_SP|",(VLOOKUP(G27,Dictionary!$AY:$AZ,2,0)),"_AC|",(VLOOKUP(H27,Dictionary!$BA:$BB,2,0)),IF(I27="","",CONCATENATE("_OB|",(VLOOKUP(I27,Dictionary!$AS:$AT,2,0)))),IF(J27="","",CONCATENATE("_U1|",SUBSTITUTE(SUBSTITUTE(J27,"_","-"),"|","-"))),IF(K27="","",CONCATENATE("_U2|",SUBSTITUTE(SUBSTITUTE(K27,"_","-"),"|","-"))),IF(L27="","",CONCATENATE("_U3|",SUBSTITUTE(SUBSTITUTE(L27,"_","-"),"|","-")))) -> #N/A
M28: =CONCATENATE("MK|",(VLOOKUP(B28,Dictionary!$A:$B,2,FALSE)),"_CN|",SUBSTITUTE(SUBSTITUTE(IF(C28="","NONE",C28),"_","-"),"|","-"),"_MN|",(VLOOKUP(D28,Dictionary!$D:$E,2,0)),"_YQ|",(VLOOKUP(E28,Dictionary!$AR:$AR,1,0)),"_CP|",SUBSTITUTE(SUBSTITUTE(IF(F28="","NONE",F28),"_","-"),"|","-"),"_SP|",(VLOOKUP(G28,Dictionary!$AY:$AZ,2,0)),"_AC|",(VLOOKUP(H28,Dictionary!$BA:$BB,2,0)),IF(I28="","",CONCATENATE("_OB|",(VLOOKUP(I28,Dictionary!$AS:$AT,2,0)))),IF(J28="","",CONCATENATE("_U1|",SUBSTITUTE(SUBSTITUTE(J28,"_","-"),"|","-"))),IF(K28="","",CONCATENATE("_U2|",SUBSTITUTE(SUBSTITUTE(K28,"_","-"),"|","-"))),IF(L28="","",CONCATENATE("_U3|",SUBSTITUTE(SUBSTITUTE(L28,"_","-"),"|","-")))) -> #N/A
... M337: =CONCATENATE("MK|",(VLOOKUP(B337,Dictionary!$A:$B,2,FALSE)),"_CN|",SUBSTITUTE(SUBSTITUTE(IF(C337="","NONE",C337),"_","-"),"|","-"),"_MN|",(VLOOKUP(D337,Dictionary!$D:$E,2,0)),"_YQ|",(VLOOKUP(E337,Dictionary!$AR:$AR,1,0)),"_CP|",SUBSTITUTE(SUBSTITUTE(IF(F337="","NONE",F337),"_","-"),"|","-"),"_SP|",(VLOOKUP(G337,Dictionary!$AY:$AZ,2,0)),"_AC|",(VLOOKUP(H337,Dictionary!$BA:$BB,2,0)),IF(I337="","",CONCATENATE("_OB|",(VLOOKUP(I337,Dictionary!$AS:$AT,2,0)))),IF(J337="","",CONCATENATE("_U1|",SUBSTITUTE(SUBSTITUTE(J337,"_","-"),"|","-"))),IF(K337="","",CONCATENATE("_U2|",SUBSTITUTE(SUBSTITUTE(K337,"_","-"),"|","-"))),IF(L337="","",CONCATENATE("_U3|",SUBSTITUTE(SUBSTITUTE(L337,"_","-"),"|","-")))) -> #N/A

Sheet ADSET Name
B1: Mandatory Fields | O1: Optional Fields
A2: ID | B2: Country (List) | C2: Media Channel | D2: Device(List) | E2: Publisher(List) | F2: Placement Type(List) | G2: Placement Rate Type(List) | H2: Placement Description(FF) | I2: Primary Target (List) | J2: Secondary Target (List) | K2: Target Description (FF) | L2: Placement Execution Size(List) | M2: Serving Method (List) | N2: Inventory Type (List) | O2: U1 | P2: U2 | Q2: U3
B3: Brazil | C3: SEM | D3: Cross Device/ Screen | E3: Google Adwords Search | F3: TEXT UNIT | G3: Cost per Click | H3: DOTZ-BENEFICIOS | I3: None | J3: None | L3: Text | M3: Adwords | N3: Search | R3: =IF(K3="----","#N/A",CONCATENATE("MK|",(VLOOKUP(B3,Dictionary!$A:$B,2,0)),"_CH|",(VLOOKUP(C3,Dictionary!$AV:$AW,2,0)),"_DT|",(VLOOKUP(D3,Dictionary!$P:$Q,2,0)),"_PB|",(VLOOKUP(E3,Dictionary!$G:$H,2,0)),"_FM|",(VLOOKUP(F3,Dictionary!$S:$T,2,0)),"_RT|",(VLOOKUP(G3,Dictionary!$V:$W,2,0)),"_PD|",SUBSTITUTE(SUBSTITUTE(IF(H3="","NONE",H3),"_","-"),"|","-"),"_TG|",(VLOOKUP(I3,Dictionary!$J:$K,2,0)),"_ST|",(VLOOKUP(J3,Dictionary!$M:$N,2,0)),"_TS|",SUBSTITUTE(SUBSTITUTE(IF(K3="","NONE",K3),"_","-"),"|","-"),"_SZ|",(VLOOKUP(L3,Dictionary!$Y:$Z,1,0)),"_AD|",(VLOOKUP(M3,Dictionary!$AB:$AC,2,0)),"_IT|",(VLOOKUP(N3,Dictionary!$BC:$BD,2,0)),IF(O3="","",CONCATENATE("_U1|",SUBSTITUTE(SUBSTITUTE(O3,"_","-"),"|","-"))),IF(P3="","",CONCATENATE("_U2|",SUBSTITUTE(SUBSTITUTE(P3,"_","-"),"|","-"))),IF(Q3="","",CONCATENATE("_U3|",SUBSTITUTE(SUBSTITUTE(Q3,"_","-"),"|","-"))))) -> MK|BR_CH|SEM_DT|CROSS_PB|GADS_FM|TXT_RT|CPC_PD|DOTZ-BENEFICIOS_TG|NON_ST|NON_TS|NONE_SZ|Text_AD|ADW_IT|SEM
B4: Brazil | C4: Paid Social Display | D4: Cross Device/ Screen | E4: Facebook | F4: SOCIAL POSTS | G4: Cost per Acquisition | H4: DOTZ-BENEFICIOS | I4: Contextual | J4: Behavioral | K4: VIAGENS | L4: 1X1 | M4: Site-Served w/ DCM Tracking | N4: Social | R4: =IF(K4="----","#N/A",CONCATENATE("MK|",(VLOOKUP(B4,Dictionary!$A:$B,2,0)),"_CH|",(VLOOKUP(C4,Dictionary!$AV:$AW,2,0)),"_DT|",(VLOOKUP(D4,Dictionary!$P:$Q,2,0)),"_PB|",(VLOOKUP(E4,Dictionary!$G:$H,2,0)),"_FM|",(VLOOKUP(F4,Dictionary!$S:$T,2,0)),"_RT|",(VLOOKUP(G4,Dictionary!$V:$W,2,0)),"_PD|",SUBSTITUTE(SUBSTITUTE(IF(H4="","NONE",H4),"_","-"),"|","-"),"_TG|",(VLOOKUP(I4,Dictionary!$J:$K,2,0)),"_ST|",(VLOOKUP(J4,Dictionary!$M:$N,2,0)),"_TS|",SUBSTITUTE(SUBSTITUTE(IF(K4="","NONE",K4),"_","-"),"|","-"),"_SZ|",(VLOOKUP(L4,Dictionary!$Y:$Z,1,0)),"_AD|",(VLOOKUP(M4,Dictionary!$AB:$AC,2,0)),"_IT|",(VLOOKUP(N4,Dictionary!$BC:$BD,2,0)),IF(O4="","",CONCATENATE("_U1|",SUBSTITUTE(SUBSTITUTE(O4,"_","-"),"|","-"))),IF(P4="","",CONCATENATE("_U2|",SUBSTITUTE(SUBSTITUTE(P4,"_","-"),"|","-"))),IF(Q4="","",CONCATENATE("_U3|",SUBSTITUTE(SUBSTITUTE(Q4,"_","-"),"|","-"))))) -> MK|BR_CH|PSD_DT|CROSS_PB|FCBK_FM|SPOST_RT|CPA_PD|DOTZ-BENEFICIOS_TG|CON_ST|BHV_TS|VIAGENS_SZ|1X1_AD|CM1_IT|SOC
B5: Brazil | C5: Programmatic Display | D5: Cross Device/ Screen | E5: Google DV360 | F5: Banner | G5: Cost per Acquisition | H5: DOTZ-BENEFICIOS | I5: Contextual | J5: None | K5: VIAGENS | L5: None | M5: DCM Ad Served | N5: Programmatic Open Exchange | R5: =IF(K5="----","#N/A",CONCATENATE("MK|",(VLOOKUP(B5,Dictionary!$A:$B,2,0)),"_CH|",(VLOOKUP(C5,Dictionary!$AV:$AW,2,0)),"_DT|",(VLOOKUP(D5,Dictionary!$P:$Q,2,0)),"_PB|",(VLOOKUP(E5,Dictionary!$G:$H,2,0)),"_FM|",(VLOOKUP(F5,Dictionary!$S:$T,2,0)),"_RT|",(VLOOKUP(G5,Dictionary!$V:$W,2,0)),"_PD|",SUBSTITUTE(SUBSTITUTE(IF(H5="","NONE",H5),"_","-"),"|","-"),"_TG|",(VLOOKUP(I5,Dictionary!$J:$K,2,0)),"_ST|",(VLOOKUP(J5,Dictionary!$M:$N,2,0)),"_TS|",SUBSTITUTE(SUBSTITUTE(IF(K5="","NONE",K5),"_","-"),"|","-"),"_SZ|",(VLOOKUP(L5,Dictionary!$Y:$Z,1,0)),"_AD|",(VLOOKUP(M5,Dictionary!$AB:$AC,2,0)),"_IT|",(VLOOKUP(N5,Dictionary!$BC:$BD,2,0)),IF(O5="","",CONCATENATE("_U1|",SUBSTITUTE(SUBSTITUTE(O5,"_","-"),"|","-"))),IF(P5="","",CONCATENATE("_U2|",SUBSTITUTE(SUBSTITUTE(P5,"_","-"),"|","-"))),IF(Q5="","",CONCATENATE("_U3|",SUBSTITUTE(SUBSTITUTE(Q5,"_","-"),"|","-"))))) -> MK|BR_CH|PD_DT|CROSS_PB|DV36_FM|BAN_RT|CPA_PD|DOTZ-BENEFICIOS_TG|CON_ST|NON_TS|VIAGENS_SZ|None_AD|CM_IT|POE
B6: Brazil | C6: Programmatic Display | D6: Cross Device/ Screen | E6: Google DV360 | F6: Banner | G6: Cost per Acquisition | H6: DOTZ-BENEFICIOS | I6: Contextual | J6: None | K6: FINANCE | L6: None | M6: DCM Ad Served | N6: Programmatic Open Exchange | R6: =IF(K6="----","#N/A",CONCATENATE("MK|",(VLOOKUP(B6,Dictionary!$A:$B,2,0)),"_CH|",(VLOOKUP(C6,Dictionary!$AV:$AW,2,0)),"_DT|",(VLOOKUP(D6,Dictionary!$P:$Q,2,0)),"_PB|",(VLOOKUP(E6,Dictionary!$G:$H,2,0)),"_FM|",(VLOOKUP(F6,Dictionary!$S:$T,2,0)),"_RT|",(VLOOKUP(G6,Dictionary!$V:$W,2,0)),"_PD|",SUBSTITUTE(SUBSTITUTE(IF(H6="","NONE",H6),"_","-"),"|","-"),"_TG|",(VLOOKUP(I6,Dictionary!$J:$K,2,0)),"_ST|",(VLOOKUP(J6,Dictionary!$M:$N,2,0)),"_TS|",SUBSTITUTE(SUBSTITUTE(IF(K6="","NONE",K6),"_","-"),"|","-"),"_SZ|",(VLOOKUP(L6,Dictionary!$Y:$Z,1,0)),"_AD|",(VLOOKUP(M6,Dictionary!$AB:$AC,2,0)),"_IT|",(VLOOKUP(N6,Dictionary!$BC:$BD,2,0)),IF(O6="","",CONCATENATE("_U1|",SUBSTITUTE(SUBSTITUTE(O6,"_","-"),"|","-"))),IF(P6="","",CONCATENATE("_U2|",SUBSTITUTE(SUBSTITUTE(P6,"_","-"),"|","-"))),IF(Q6="","",CONCATENATE("_U3|",SUBSTITUTE(SUBSTITUTE(Q6,"_","-"),"|","-"))))) -> MK|BR_CH|PD_DT|CROSS_PB|DV36_FM|BAN_RT|CPA_PD|DOTZ-BENEFICIOS_TG|CON_ST|NON_TS|FINANCE_SZ|None_AD|CM_IT|POE
B7: Brazil | C7: Programmatic Display | D7: Cross Device/ Screen | E7: Google DV360 | F7: Banner | G7: Cost per Acquisition | H7: DOTZ-BENEFICIOS | I7: Contextual | J7: None | K7: SHOPPERS | L7: None | M7: DCM Ad Served | N7: Programmatic Open Exchange | R7: =IF(K7="----","#N/A",CONCATENATE("MK|",(VLOOKUP(B7,Dictionary!$A:$B,2,0)),"_CH|",(VLOOKUP(C7,Dictionary!$AV:$AW,2,0)),"_DT|",(VLOOKUP(D7,Dictionary!$P:$Q,2,0)),"_PB|",(VLOOKUP(E7,Dictionary!$G:$H,2,0)),"_FM|",(VLOOKUP(F7,Dictionary!$S:$T,2,0)),"_RT|",(VLOOKUP(G7,Dictionary!$V:$W,2,0)),"_PD|",SUBSTITUTE(SUBSTITUTE(IF(H7="","NONE",H7),"_","-"),"|","-"),"_TG|",(VLOOKUP(I7,Dictionary!$J:$K,2,0)),"_ST|",(VLOOKUP(J7,Dictionary!$M:$N,2,0)),"_TS|",SUBSTITUTE(SUBSTITUTE(IF(K7="","NONE",K7),"_","-"),"|","-"),"_SZ|",(VLOOKUP(L7,Dictionary!$Y:$Z,1,0)),"_AD|",(VLOOKUP(M7,Dictionary!$AB:$AC,2,0)),"_IT|",(VLOOKUP(N7,Dictionary!$BC:$BD,2,0)),IF(O7="","",CONCATENATE("_U1|",SUBSTITUTE(SUBSTITUTE(O7,"_","-"),"|","-"))),IF(P7="","",CONCATENATE("_U2|",SUBSTITUTE(SUBSTITUTE(P7,"_","-"),"|","-"))),IF(Q7="","",CONCATENATE("_U3|",SUBSTITUTE(SUBSTITUTE(Q7,"_","-"),"|","-"))))) -> MK|BR_CH|PD_DT|CROSS_PB|DV36_FM|BAN_RT|CPA_PD|DOTZ-BENEFICIOS_TG|CON_ST|NON_TS|SHOPPERS_SZ|None_AD|CM_IT|POE
R88: =IF(K88="----","#N/A",CONCATENATE("MK|",(VLOOKUP(B88,Dictionary!$A:$B,2,0)),"_CH|",(VLOOKUP(C88,Dictionary!$AV:$AW,2,0)),"_DT|",(VLOOKUP(D88,Dictionary!$P:$Q,2,0)),"_PB|",(VLOOKUP(E88,Dictionary!$G:$H,2,0)),"_FM|",(VLOOKUP(F88,Dictionary!$S:$T,2,0)),"_RT|",(VLOOKUP(G88,Dictionary!$V:$W,2,0)),"_PD|",SUBSTITUTE(SUBSTITUTE(IF(H88="","NONE",H88),"_","-"),"|","-"),"_TG|",(VLOOKUP(I88,Dictionary!$J:$K,2,0)),"_ST|",(VLOOKUP(J88,Dictionary!$M:$N,2,0)),"_TS|",SUBSTITUTE(SUBSTITUTE(IF(K88="","NONE",K88),"_","-"),"|","-"),"_SZ|",(VLOOKUP(L88,Dictionary!$Y:$Z,1,0)),"_AD|",(VLOOKUP(M88,Dictionary!$AB:$AC,2,0)),"_IT|",(VLOOKUP(N88,Dictionary!$BC:$BD,2,0)),IF(O88="","",CONCATENATE("_U1|",SUBSTITUTE(SUBSTITUTE(O88,"_","-"),"|","-"))),IF(P88="","",CONCATENATE("_U2|",SUBSTITUTE(SUBSTITUTE(P88,"_","-"),"|","-"))),IF(Q88="","",CONCATENATE("_U3|",SUBSTITUTE(SUBSTITUTE(Q88,"_","-"),"|","-"))))) -> #N/A
R89: =IF(K89="----","#N/A",CONCATENATE("MK|",(VLOOKUP(B89,Dictionary!$A:$B,2,0)),"_CH|",(VLOOKUP(C89,Dictionary!$AV:$AW,2,0)),"_DT|",(VLOOKUP(D89,Dictionary!$P:$Q,2,0)),"_PB|",(VLOOKUP(E89,Dictionary!$G:$H,2,0)),"_FM|",(VLOOKUP(F89,Dictionary!$S:$T,2,0)),"_RT|",(VLOOKUP(G89,Dictionary!$V:$W,2,0)),"_PD|",SUBSTITUTE(SUBSTITUTE(IF(H89="","NONE",H89),"_","-"),"|","-"),"_TG|",(VLOOKUP(I89,Dictionary!$J:$K,2,0)),"_ST|",(VLOOKUP(J89,Dictionary!$M:$N,2,0)),"_TS|",SUBSTITUTE(SUBSTITUTE(IF(K89="","NONE",K89),"_","-"),"|","-"),"_SZ|",(VLOOKUP(L89,Dictionary!$Y:$Z,1,0)),"_AD|",(VLOOKUP(M89,Dictionary!$AB:$AC,2,0)),"_IT|",(VLOOKUP(N89,Dictionary!$BC:$BD,2,0)),IF(O89="","",CONCATENATE("_U1|",SUBSTITUTE(SUBSTITUTE(O89,"_","-"),"|","-"))),IF(P89="","",CONCATENATE("_U2|",SUBSTITUTE(SUBSTITUTE(P89,"_","-"),"|","-"))),IF(Q89="","",CONCATENATE("_U3|",SUBSTITUTE(SUBSTITUTE(Q89,"_","-"),"|","-"))))) -> #N/A
R90: =IF(K90="----","#N/A",CONCATENATE("MK|",(VLOOKUP(B90,Dictionary!$A:$B,2,0)),"_CH|",(VLOOKUP(C90,Dictionary!$AV:$AW,2,0)),"_DT|",(VLOOKUP(D90,Dictionary!$P:$Q,2,0)),"_PB|",(VLOOKUP(E90,Dictionary!$G:$H,2,0)),"_FM|",(VLOOKUP(F90,Dictionary!$S:$T,2,0)),"_RT|",(VLOOKUP(G90,Dictionary!$V:$W,2,0)),"_PD|",SUBSTITUTE(SUBSTITUTE(IF(H90="","NONE",H90),"_","-"),"|","-"),"_TG|",(VLOOKUP(I90,Dictionary!$J:$K,2,0)),"_ST|",(VLOOKUP(J90,Dictionary!$M:$N,2,0)),"_TS|",SUBSTITUTE(SUBSTITUTE(IF(K90="","NONE",K90),"_","-"),"|","-"),"_SZ|",(VLOOKUP(L90,Dictionary!$Y:$Z,1,0)),"_AD|",(VLOOKUP(M90,Dictionary!$AB:$AC,2,0)),"_IT|",(VLOOKUP(N90,Dictionary!$BC:$BD,2,0)),IF(O90="","",CONCATENATE("_U1|",SUBSTITUTE(SUBSTITUTE(O90,"_","-"),"|","-"))),IF(P90="","",CONCATENATE("_U2|",SUBSTITUTE(SUBSTITUTE(P90,"_","-"),"|","-"))),IF(Q90="","",CONCATENATE("_U3|",SUBSTITUTE(SUBSTITUTE(Q90,"_","-"),"|","-"))))) -> #N/A
R91: =IF(K91="----","#N/A",CONCATENATE("MK|",(VLOOKUP(B91,Dictionary!$A:$B,2,0)),"_CH|",(VLOOKUP(C91,Dictionary!$AV:$AW,2,0)),"_DT|",(VLOOKUP(D91,Dictionary!$P:$Q,2,0)),"_PB|",(VLOOKUP(E91,Dictionary!$G:$H,2,0)),"_FM|",(VLOOKUP(F91,Dictionary!$S:$T,2,0)),"_RT|",(VLOOKUP(G91,Dictionary!$V:$W,2,0)),"_PD|",SUBSTITUTE(SUBSTITUTE(IF(H91="","NONE",H91),"_","-"),"|","-"),"_TG|",(VLOOKUP(I91,Dictionary!$J:$K,2,0)),"_ST|",(VLOOKUP(J91,Dictionary!$M:$N,2,0)),"_TS|",SUBSTITUTE(SUBSTITUTE(IF(K91="","NONE",K91),"_","-"),"|","-"),"_SZ|",(VLOOKUP(L91,Dictionary!$Y:$Z,1,0)),"_AD|",(VLOOKUP(M91,Dictionary!$AB:$AC,2,0)),"_IT|",(VLOOKUP(N91,Dictionary!$BC:$BD,2,0)),IF(O91="","",CONCATENATE("_U1|",SUBSTITUTE(SUBSTITUTE(O91,"_","-"),"|","-"))),IF(P91="","",CONCATENATE("_U2|",SUBSTITUTE(SUBSTITUTE(P91,"_","-"),"|","-"))),IF(Q91="","",CONCATENATE("_U3|",SUBSTITUTE(SUBSTITUTE(Q91,"_","-"),"|","-"))))) -> #N/A
R92: =IF(K92="----","#N/A",CONCATENATE("MK|",(VLOOKUP(B92,Dictionary!$A:$B,2,0)),"_CH|",(VLOOKUP(C92,Dictionary!$AV:$AW,2,0)),"_DT|",(VLOOKUP(D92,Dictionary!$P:$Q,2,0)),"_PB|",(VLOOKUP(E92,Dictionary!$G:$H,2,0)),"_FM|",(VLOOKUP(F92,Dictionary!$S:$T,2,0)),"_RT|",(VLOOKUP(G92,Dictionary!$V:$W,2,0)),"_PD|",SUBSTITUTE(SUBSTITUTE(IF(H92="","NONE",H92),"_","-"),"|","-"),"_TG|",(VLOOKUP(I92,Dictionary!$J:$K,2,0)),"_ST|",(VLOOKUP(J92,Dictionary!$M:$N,2,0)),"_TS|",SUBSTITUTE(SUBSTITUTE(IF(K92="","NONE",K92),"_","-"),"|","-"),"_SZ|",(VLOOKUP(L92,Dictionary!$Y:$Z,1,0)),"_AD|",(VLOOKUP(M92,Dictionary!$AB:$AC,2,0)),"_IT|",(VLOOKUP(N92,Dictionary!$BC:$BD,2,0)),IF(O92="","",CONCATENATE("_U1|",SUBSTITUTE(SUBSTITUTE(O92,"_","-"),"|","-"))),IF(P92="","",CONCATENATE("_U2|",SUBSTITUTE(SUBSTITUTE(P92,"_","-"),"|","-"))),IF(Q92="","",CONCATENATE("_U3|",SUBSTITUTE(SUBSTITUTE(Q92,"_","-"),"|","-"))))) -> #N/A
R93: =IF(K93="----","#N/A",CONCATENATE("MK|",(VLOOKUP(B93,Dictionary!$A:$B,2,0)),"_CH|",(VLOOKUP(C93,Dictionary!$AV:$AW,2,0)),"_DT|",(VLOOKUP(D93,Dictionary!$P:$Q,2,0)),"_PB|",(VLOOKUP(E93,Dictionary!$G:$H,2,0)),"_FM|",(VLOOKUP(F93,Dictionary!$S:$T,2,0)),"_RT|",(VLOOKUP(G93,Dictionary!$V:$W,2,0)),"_PD|",SUBSTITUTE(SUBSTITUTE(IF(H93="","NONE",H93),"_","-"),"|","-"),"_TG|",(VLOOKUP(I93,Dictionary!$J:$K,2,0)),"_ST|",(VLOOKUP(J93,Dictionary!$M:$N,2,0)),"_TS|",SUBSTITUTE(SUBSTITUTE(IF(K93="","NONE",K93),"_","-"),"|","-"),"_SZ|",(VLOOKUP(L93,Dictionary!$Y:$Z,1,0)),"_AD|",(VLOOKUP(M93,Dictionary!$AB:$AC,2,0)),"_IT|",(VLOOKUP(N93,Dictionary!$BC:$BD,2,0)),IF(O93="","",CONCATENATE("_U1|",SUBSTITUTE(SUBSTITUTE(O93,"_","-"),"|","-"))),IF(P93="","",CONCATENATE("_U2|",SUBSTITUTE(SUBSTITUTE(P93,"_","-"),"|","-"))),IF(Q93="","",CONCATENATE("_U3|",SUBSTITUTE(SUBSTITUTE(Q93,"_","-"),"|","-"))))) -> #N/A
R94: =IF(K94="----","#N/A",CONCATENATE("MK|",(VLOOKUP(B94,Dictionary!$A:$B,2,0)),"_CH|",(VLOOKUP(C94,Dictionary!$AV:$AW,2,0)),"_DT|",(VLOOKUP(D94,Dictionary!$P:$Q,2,0)),"_PB|",(VLOOKUP(E94,Dictionary!$G:$H,2,0)),"_FM|",(VLOOKUP(F94,Dictionary!$S:$T,2,0)),"_RT|",(VLOOKUP(G94,Dictionary!$V:$W,2,0)),"_PD|",SUBSTITUTE(SUBSTITUTE(IF(H94="","NONE",H94),"_","-"),"|","-"),"_TG|",(VLOOKUP(I94,Dictionary!$J:$K,2,0)),"_ST|",(VLOOKUP(J94,Dictionary!$M:$N,2,0)),"_TS|",SUBSTITUTE(SUBSTITUTE(IF(K94="","NONE",K94),"_","-"),"|","-"),"_SZ|",(VLOOKUP(L94,Dictionary!$Y:$Z,1,0)),"_AD|",(VLOOKUP(M94,Dictionary!$AB:$AC,2,0)),"_IT|",(VLOOKUP(N94,Dictionary!$BC:$BD,2,0)),IF(O94="","",CONCATENATE("_U1|",SUBSTITUTE(SUBSTITUTE(O94,"_","-"),"|","-"))),IF(P94="","",CONCATENATE("_U2|",SUBSTITUTE(SUBSTITUTE(P94,"_","-"),"|","-"))),IF(Q94="","",CONCATENATE("_U3|",SUBSTITUTE(SUBSTITUTE(Q94,"_","-"),"|","-"))))) -> #N/A
R95: =IF(K95="----","#N/A",CONCATENATE("MK|",(VLOOKUP(B95,Dictionary!$A:$B,2,0)),"_CH|",(VLOOKUP(C95,Dictionary!$AV:$AW,2,0)),"_DT|",(VLOOKUP(D95,Dictionary!$P:$Q,2,0)),"_PB|",(VLOOKUP(E95,Dictionary!$G:$H,2,0)),"_FM|",(VLOOKUP(F95,Dictionary!$S:$T,2,0)),"_RT|",(VLOOKUP(G95,Dictionary!$V:$W,2,0)),"_PD|",SUBSTITUTE(SUBSTITUTE(IF(H95="","NONE",H95),"_","-"),"|","-"),"_TG|",(VLOOKUP(I95,Dictionary!$J:$K,2,0)),"_ST|",(VLOOKUP(J95,Dictionary!$M:$N,2,0)),"_TS|",SUBSTITUTE(SUBSTITUTE(IF(K95="","NONE",K95),"_","-"),"|","-"),"_SZ|",(VLOOKUP(L95,Dictionary!$Y:$Z,1,0)),"_AD|",(VLOOKUP(M95,Dictionary!$AB:$AC,2,0)),"_IT|",(VLOOKUP(N95,Dictionary!$BC:$BD,2,0)),IF(O95="","",CONCATENATE("_U1|",SUBSTITUTE(SUBSTITUTE(O95,"_","-"),"|","-"))),IF(P95="","",CONCATENATE("_U2|",SUBSTITUTE(SUBSTITUTE(P95,"_","-"),"|","-"))),IF(Q95="","",CONCATENATE("_U3|",SUBSTITUTE(SUBSTITUTE(Q95,"_","-"),"|","-"))))) -> #N/A
R96: =IF(K96="----","#N/A",CONCATENATE("MK|",(VLOOKUP(B96,Dictionary!$A:$B,2,0)),"_CH|",(VLOOKUP(C96,Dictionary!$AV:$AW,2,0)),"_DT|",(VLOOKUP(D96,Dictionary!$P:$Q,2,0)),"_PB|",(VLOOKUP(E96,Dictionary!$G:$H,2,0)),"_FM|",(VLOOKUP(F96,Dictionary!$S:$T,2,0)),"_RT|",(VLOOKUP(G96,Dictionary!$V:$W,2,0)),"_PD|",SUBSTITUTE(SUBSTITUTE(IF(H96="","NONE",H96),"_","-"),"|","-"),"_TG|",(VLOOKUP(I96,Dictionary!$J:$K,2,0)),"_ST|",(VLOOKUP(J96,Dictionary!$M:$N,2,0)),"_TS|",SUBSTITUTE(SUBSTITUTE(IF(K96="","NONE",K96),"_","-"),"|","-"),"_SZ|",(VLOOKUP(L96,Dictionary!$Y:$Z,1,0)),"_AD|",(VLOOKUP(M96,Dictionary!$AB:$AC,2,0)),"_IT|",(VLOOKUP(N96,Dictionary!$BC:$BD,2,0)),IF(O96="","",CONCATENATE("_U1|",SUBSTITUTE(SUBSTITUTE(O96,"_","-"),"|","-"))),IF(P96="","",CONCATENATE("_U2|",SUBSTITUTE(SUBSTITUTE(P96,"_","-"),"|","-"))),IF(Q96="","",CONCATENATE("_U3|",SUBSTITUTE(SUBSTITUTE(Q96,"_","-"),"|","-"))))) -> #N/A
R97: =IF(K97="----","#N/A",CONCATENATE("MK|",(VLOOKUP(B97,Dictionary!$A:$B,2,0)),"_CH|",(VLOOKUP(C97,Dictionary!$AV:$AW,2,0)),"_DT|",(VLOOKUP(D97,Dictionary!$P:$Q,2,0)),"_PB|",(VLOOKUP(E97,Dictionary!$G:$H,2,0)),"_FM|",(VLOOKUP(F97,Dictionary!$S:$T,2,0)),"_RT|",(VLOOKUP(G97,Dictionary!$V:$W,2,0)),"_PD|",SUBSTITUTE(SUBSTITUTE(IF(H97="","NONE",H97),"_","-"),"|","-"),"_TG|",(VLOOKUP(I97,Dictionary!$J:$K,2,0)),"_ST|",(VLOOKUP(J97,Dictionary!$M:$N,2,0)),"_TS|",SUBSTITUTE(SUBSTITUTE(IF(K97="","NONE",K97),"_","-"),"|","-"),"_SZ|",(VLOOKUP(L97,Dictionary!$Y:$Z,1,0)),"_AD|",(VLOOKUP(M97,Dictionary!$AB:$AC,2,0)),"_IT|",(VLOOKUP(N97,Dictionary!$BC:$BD,2,0)),IF(O97="","",CONCATENATE("_U1|",SUBSTITUTE(SUBSTITUTE(O97,"_","-"),"|","-"))),IF(P97="","",CONCATENATE("_U2|",SUBSTITUTE(SUBSTITUTE(P97,"_","-"),"|","-"))),IF(Q97="","",CONCATENATE("_U3|",SUBSTITUTE(SUBSTITUTE(Q97,"_","-"),"|","-"))))) -> #N/A
R98: =IF(K98="----","#N/A",CONCATENATE("MK|",(VLOOKUP(B98,Dictionary!$A:$B,2,0)),"_CH|",(VLOOKUP(C98,Dictionary!$AV:$AW,2,0)),"_DT|",(VLOOKUP(D98,Dictionary!$P:$Q,2,0)),"_PB|",(VLOOKUP(E98,Dictionary!$G:$H,2,0)),"_FM|",(VLOOKUP(F98,Dictionary!$S:$T,2,0)),"_RT|",(VLOOKUP(G98,Dictionary!$V:$W,2,0)),"_PD|",SUBSTITUTE(SUBSTITUTE(IF(H98="","NONE",H98),"_","-"),"|","-"),"_TG|",(VLOOKUP(I98,Dictionary!$J:$K,2,0)),"_ST|",(VLOOKUP(J98,Dictionary!$M:$N,2,0)),"_TS|",SUBSTITUTE(SUBSTITUTE(IF(K98="","NONE",K98),"_","-"),"|","-"),"_SZ|",(VLOOKUP(L98,Dictionary!$Y:$Z,1,0)),"_AD|",(VLOOKUP(M98,Dictionary!$AB:$AC,2,0)),"_IT|",(VLOOKUP(N98,Dictionary!$BC:$BD,2,0)),IF(O98="","",CONCATENATE("_U1|",SUBSTITUTE(SUBSTITUTE(O98,"_","-"),"|","-"))),IF(P98="","",CONCATENATE("_U2|",SUBSTITUTE(SUBSTITUTE(P98,"_","-"),"|","-"))),IF(Q98="","",CONCATENATE("_U3|",SUBSTITUTE(SUBSTITUTE(Q98,"_","-"),"|","-"))))) -> #N/A
R99: =IF(K99="----","#N/A",CONCATENATE("MK|",(VLOOKUP(B99,Dictionary!$A:$B,2,0)),"_CH|",(VLOOKUP(C99,Dictionary!$AV:$AW,2,0)),"_DT|",(VLOOKUP(D99,Dictionary!$P:$Q,2,0)),"_PB|",(VLOOKUP(E99,Dictionary!$G:$H,2,0)),"_FM|",(VLOOKUP(F99,Dictionary!$S:$T,2,0)),"_RT|",(VLOOKUP(G99,Dictionary!$V:$W,2,0)),"_PD|",SUBSTITUTE(SUBSTITUTE(IF(H99="","NONE",H99),"_","-"),"|","-"),"_TG|",(VLOOKUP(I99,Dictionary!$J:$K,2,0)),"_ST|",(VLOOKUP(J99,Dictionary!$M:$N,2,0)),"_TS|",SUBSTITUTE(SUBSTITUTE(IF(K99="","NONE",K99),"_","-"),"|","-"),"_SZ|",(VLOOKUP(L99,Dictionary!$Y:$Z,1,0)),"_AD|",(VLOOKUP(M99,Dictionary!$AB:$AC,2,0)),"_IT|",(VLOOKUP(N99,Dictionary!$BC:$BD,2,0)),IF(O99="","",CONCATENATE("_U1|",SUBSTITUTE(SUBSTITUTE(O99,"_","-"),"|","-"))),IF(P99="","",CONCATENATE("_U2|",SUBSTITUTE(SUBSTITUTE(P99,"_","-"),"|","-"))),IF(Q99="","",CONCATENATE("_U3|",SUBSTITUTE(SUBSTITUTE(Q99,"_","-"),"|","-"))))) -> #N/A
... R347: =IF(K347="----","#N/A",CONCATENATE("MK|",(VLOOKUP(B347,Dictionary!$A:$B,2,0)),"_CH|",(VLOOKUP(C347,Dictionary!$AV:$AW,2,0)),"_DT|",(VLOOKUP(D347,Dictionary!$P:$Q,2,0)),"_PB|",(VLOOKUP(E347,Dictionary!$G:$H,2,0)),"_FM|",(VLOOKUP(F347,Dictionary!$S:$T,2,0)),"_RT|",(VLOOKUP(G347,Dictionary!$V:$W,2,0)),"_PD|",SUBSTITUTE(SUBSTITUTE(IF(H347="","NONE",H347),"_","-"),"|","-"),"_TG|",(VLOOKUP(I347,Dictionary!$J:$K,2,0)),"_ST|",(VLOOKUP(J347,Dictionary!$M:$N,2,0)),"_TS|",SUBSTITUTE(SUBSTITUTE(IF(K347="","NONE",K347),"_","-"),"|","-"),"_SZ|",(VLOOKUP(L347,Dictionary!$Y:$Z,1,0)),"_AD|",(VLOOKUP(M347,Dictionary!$AB:$AC,2,0)),"_IT|",(VLOOKUP(N347,Dictionary!$BC:$BD,2,0)),IF(O347="","",CONCATENATE("_U1|",SUBSTITUTE(SUBSTITUTE(O347,"_","-"),"|","-"))),IF(P347="","",CONCATENATE("_U2|",SUBSTITUTE(SUBSTITUTE(P347,"_","-"),"|","-"))),IF(Q347="","",CONCATENATE("_U3|",SUBSTITUTE(SUBSTITUTE(Q347,"_","-"),"|","-"))))) -> #N/A

Sheet Placement (DCM)
B1: Mandatory Fields | O1: Optional Fields
A2: ID | B2: Country (List) | C2: Media Channel | D2: Device(List) | E2: Publisher(List) | F2: Placement Type(List) | G2: Placement Rate Type(List) | H2: Placement Description(FF) | I2: Primary Target (List) | J2: Secondary Target (List) | K2: Target Description (FF) | L2: Placement Execution Size(List) | M2: Serving Method (List) | N2: Inventory Type (List) | O2: U1 | P2: U2 | Q2: U3
B3: Brazil | C3: Programmatic Display | D3: Mobile Web + In-App | E3: Verizon | F3: Native Display | G3: Cost per Thousand | H3: DOTZ-10MIL | I3: None | J3: None | L3: 627x627 | M3: Site-Served w/ DCM Tracking | N3: Owned & Operated | R3: =IF(K3="----","#N/A",CONCATENATE("MK|",(VLOOKUP(B3,Dictionary!$A:$B,2,0)),"_CH|",(VLOOKUP(C3,Dictionary!$AV:$AW,2,0)),"_DT|",(VLOOKUP(D3,Dictionary!$P:$Q,2,0)),"_PB|",(VLOOKUP(E3,Dictionary!$G:$H,2,0)),"_FM|",(VLOOKUP(F3,Dictionary!$S:$T,2,0)),"_RT|",(VLOOKUP(G3,Dictionary!$V:$W,2,0)),"_PD|",SUBSTITUTE(SUBSTITUTE(IF(H3="","NONE",H3),"_","-"),"|","-"),"_TG|",(VLOOKUP(I3,Dictionary!$J:$K,2,0)),"_ST|",(VLOOKUP(J3,Dictionary!$M:$N,2,0)),"_TS|",SUBSTITUTE(SUBSTITUTE(IF(K3="","NONE",K3),"_","-"),"|","-"),"_SZ|",(VLOOKUP(L3,Dictionary!$Y:$Z,1,0)),"_AD|",(VLOOKUP(M3,Dictionary!$AB:$AC,2,0)),"_IT|",(VLOOKUP(N3,Dictionary!$BC:$BD,2,0)),IF(O3="","",CONCATENATE("_U1|",SUBSTITUTE(SUBSTITUTE(O3,"_","-"),"|","-"))),IF(P3="","",CONCATENATE("_U2|",SUBSTITUTE(SUBSTITUTE(P3,"_","-"),"|","-"))),IF(Q3="","",CONCATENATE("_U3|",SUBSTITUTE(SUBSTITUTE(Q3,"_","-"),"|","-"))))) -> MK|BR_CH|PD_DT|MWIA_PB|VER_FM|NAT_RT|CPM_PD|DOTZ-10MIL_TG|NON_ST|NON_TS|NONE_SZ|627x627_AD|CM1_IT|OO
B4: Brazil | C4: Programmatic Display | D4: Cross Device/ Screen | E4: Verizon | F4: Native Display | G4: Cost per Thousand | H4: DOTZ-TAXA-ZERO | I4: None | J4: None | L4: 627x627 | M4: Site-Served w/ DCM Tracking | N4: Owned & Operated | R4: =IF(K4="----","#N/A",CONCATENATE("MK|",(VLOOKUP(B4,Dictionary!$A:$B,2,0)),"_CH|",(VLOOKUP(C4,Dictionary!$AV:$AW,2,0)),"_DT|",(VLOOKUP(D4,Dictionary!$P:$Q,2,0)),"_PB|",(VLOOKUP(E4,Dictionary!$G:$H,2,0)),"_FM|",(VLOOKUP(F4,Dictionary!$S:$T,2,0)),"_RT|",(VLOOKUP(G4,Dictionary!$V:$W,2,0)),"_PD|",SUBSTITUTE(SUBSTITUTE(IF(H4="","NONE",H4),"_","-"),"|","-"),"_TG|",(VLOOKUP(I4,Dictionary!$J:$K,2,0)),"_ST|",(VLOOKUP(J4,Dictionary!$M:$N,2,0)),"_TS|",SUBSTITUTE(SUBSTITUTE(IF(K4="","NONE",K4),"_","-"),"|","-"),"_SZ|",(VLOOKUP(L4,Dictionary!$Y:$Z,1,0)),"_AD|",(VLOOKUP(M4,Dictionary!$AB:$AC,2,0)),"_IT|",(VLOOKUP(N4,Dictionary!$BC:$BD,2,0)),IF(O4="","",CONCATENATE("_U1|",SUBSTITUTE(SUBSTITUTE(O4,"_","-"),"|","-"))),IF(P4="","",CONCATENATE("_U2|",SUBSTITUTE(SUBSTITUTE(P4,"_","-"),"|","-"))),IF(Q4="","",CONCATENATE("_U3|",SUBSTITUTE(SUBSTITUTE(Q4,"_","-"),"|","-"))))) -> MK|BR_CH|PD_DT|CROSS_PB|VER_FM|NAT_RT|CPM_PD|DOTZ-TAXA-ZERO_TG|NON_ST|NON_TS|NONE_SZ|627x627_AD|CM1_IT|OO
B5: Brazil | C5: Paid Social Display | D5: Cross Device/ Screen | E5: Facebook | F5: Link Ad | G5: Cost per Thousand | H5: DOTZ-10MIL-AZUL | I5: None | J5: None | L5: 1X1 | M5: Site-Served w/ DCM Tracking | N5: Social | R5: =IF(K5="----","#N/A",CONCATENATE("MK|",(VLOOKUP(B5,Dictionary!$A:$B,2,0)),"_CH|",(VLOOKUP(C5,Dictionary!$AV:$AW,2,0)),"_DT|",(VLOOKUP(D5,Dictionary!$P:$Q,2,0)),"_PB|",(VLOOKUP(E5,Dictionary!$G:$H,2,0)),"_FM|",(VLOOKUP(F5,Dictionary!$S:$T,2,0)),"_RT|",(VLOOKUP(G5,Dictionary!$V:$W,2,0)),"_PD|",SUBSTITUTE(SUBSTITUTE(IF(H5="","NONE",H5),"_","-"),"|","-"),"_TG|",(VLOOKUP(I5,Dictionary!$J:$K,2,0)),"_ST|",(VLOOKUP(J5,Dictionary!$M:$N,2,0)),"_TS|",SUBSTITUTE(SUBSTITUTE(IF(K5="","NONE",K5),"_","-"),"|","-"),"_SZ|",(VLOOKUP(L5,Dictionary!$Y:$Z,1,0)),"_AD|",(VLOOKUP(M5,Dictionary!$AB:$AC,2,0)),"_IT|",(VLOOKUP(N5,Dictionary!$BC:$BD,2,0)),IF(O5="","",CONCATENATE("_U1|",SUBSTITUTE(SUBSTITUTE(O5,"_","-"),"|","-"))),IF(P5="","",CONCATENATE("_U2|",SUBSTITUTE(SUBSTITUTE(P5,"_","-"),"|","-"))),IF(Q5="","",CONCATENATE("_U3|",SUBSTITUTE(SUBSTITUTE(Q5,"_","-"),"|","-"))))) -> MK|BR_CH|PSD_DT|CROSS_PB|FCBK_FM|LNK_RT|CPM_PD|DOTZ-10MIL-AZUL_TG|NON_ST|NON_TS|NONE_SZ|1X1_AD|CM1_IT|SOC
B6: Brazil | C6: Paid Social Display | D6: Cross Device/ Screen | E6: Facebook | F6: Link Ad | G6: Cost per Thousand | H6: DOTZ-10MIL-AZUL-QUAD | I6: None | J6: None | L6: 1X1 | M6: Site-Served w/ DCM Tracking | N6: Social | R6: =IF(K6="----","#N/A",CONCATENATE("MK|",(VLOOKUP(B6,Dictionary!$A:$B,2,0)),"_CH|",(VLOOKUP(C6,Dictionary!$AV:$AW,2,0)),"_DT|",(VLOOKUP(D6,Dictionary!$P:$Q,2,0)),"_PB|",(VLOOKUP(E6,Dictionary!$G:$H,2,0)),"_FM|",(VLOOKUP(F6,Dictionary!$S:$T,2,0)),"_RT|",(VLOOKUP(G6,Dictionary!$V:$W,2,0)),"_PD|",SUBSTITUTE(SUBSTITUTE(IF(H6="","NONE",H6),"_","-"),"|","-"),"_TG|",(VLOOKUP(I6,Dictionary!$J:$K,2,0)),"_ST|",(VLOOKUP(J6,Dictionary!$M:$N,2,0)),"_TS|",SUBSTITUTE(SUBSTITUTE(IF(K6="","NONE",K6),"_","-"),"|","-"),"_SZ|",(VLOOKUP(L6,Dictionary!$Y:$Z,1,0)),"_AD|",(VLOOKUP(M6,Dictionary!$AB:$AC,2,0)),"_IT|",(VLOOKUP(N6,Dictionary!$BC:$BD,2,0)),IF(O6="","",CONCATENATE("_U1|",SUBSTITUTE(SUBSTITUTE(O6,"_","-"),"|","-"))),IF(P6="","",CONCATENATE("_U2|",SUBSTITUTE(SUBSTITUTE(P6,"_","-"),"|","-"))),IF(Q6="","",CONCATENATE("_U3|",SUBSTITUTE(SUBSTITUTE(Q6,"_","-"),"|","-"))))) -> MK|BR_CH|PSD_DT|CROSS_PB|FCBK_FM|LNK_RT|CPM_PD|DOTZ-10MIL-AZUL-QUAD_TG|NON_ST|NON_TS|NONE_SZ|1X1_AD|CM1_IT|SOC
B7: Brazil | C7: Paid Social Display | D7: Cross Device/ Screen | E7: Facebook | F7: GIF | G7: Cost per Thousand | H7: DOTZ-10MIL-AZUL | I7: None | J7: None | L7: 1X1 | M7: Site-Served w/ DCM Tracking | N7: Social | R7: =IF(K7="----","#N/A",CONCATENATE("MK|",(VLOOKUP(B7,Dictionary!$A:$B,2,0)),"_CH|",(VLOOKUP(C7,Dictionary!$AV:$AW,2,0)),"_DT|",(VLOOKUP(D7,Dictionary!$P:$Q,2,0)),"_PB|",(VLOOKUP(E7,Dictionary!$G:$H,2,0)),"_FM|",(VLOOKUP(F7,Dictionary!$S:$T,2,0)),"_RT|",(VLOOKUP(G7,Dictionary!$V:$W,2,0)),"_PD|",SUBSTITUTE(SUBSTITUTE(IF(H7="","NONE",H7),"_","-"),"|","-"),"_TG|",(VLOOKUP(I7,Dictionary!$J:$K,2,0)),"_ST|",(VLOOKUP(J7,Dictionary!$M:$N,2,0)),"_TS|",SUBSTITUTE(SUBSTITUTE(IF(K7="","NONE",K7),"_","-"),"|","-"),"_SZ|",(VLOOKUP(L7,Dictionary!$Y:$Z,1,0)),"_AD|",(VLOOKUP(M7,Dictionary!$AB:$AC,2,0)),"_IT|",(VLOOKUP(N7,Dictionary!$BC:$BD,2,0)),IF(O7="","",CONCATENATE("_U1|",SUBSTITUTE(SUBSTITUTE(O7,"_","-"),"|","-"))),IF(P7="","",CONCATENATE("_U2|",SUBSTITUTE(SUBSTITUTE(P7,"_","-"),"|","-"))),IF(Q7="","",CONCATENATE("_U3|",SUBSTITUTE(SUBSTITUTE(Q7,"_","-"),"|","-"))))) -> MK|BR_CH|PSD_DT|CROSS_PB|FCBK_FM|GIF_RT|CPM_PD|DOTZ-10MIL-AZUL_TG|NON_ST|NON_TS|NONE_SZ|1X1_AD|CM1_IT|SOC
B8: Brazil | C8: Paid Social Display | D8: Cross Device/ Screen | E8: Facebook | F8: Carousel | G8: Cost per Thousand | H8: DOTZ-10MIL-AZUL | I8: None | J8: None | L8: 1X1 | M8: Site-Served w/ DCM Tracking | N8: Social | R8: =IF(K8="----","#N/A",CONCATENATE("MK|",(VLOOKUP(B8,Dictionary!$A:$B,2,0)),"_CH|",(VLOOKUP(C8,Dictionary!$AV:$AW,2,0)),"_DT|",(VLOOKUP(D8,Dictionary!$P:$Q,2,0)),"_PB|",(VLOOKUP(E8,Dictionary!$G:$H,2,0)),"_FM|",(VLOOKUP(F8,Dictionary!$S:$T,2,0)),"_RT|",(VLOOKUP(G8,Dictionary!$V:$W,2,0)),"_PD|",SUBSTITUTE(SUBSTITUTE(IF(H8="","NONE",H8),"_","-"),"|","-"),"_TG|",(VLOOKUP(I8,Dictionary!$J:$K,2,0)),"_ST|",(VLOOKUP(J8,Dictionary!$M:$N,2,0)),"_TS|",SUBSTITUTE(SUBSTITUTE(IF(K8="","NONE",K8),"_","-"),"|","-"),"_SZ|",(VLOOKUP(L8,Dictionary!$Y:$Z,1,0)),"_AD|",(VLOOKUP(M8,Dictionary!$AB:$AC,2,0)),"_IT|",(VLOOKUP(N8,Dictionary!$BC:$BD,2,0)),IF(O8="","",CONCATENATE("_U1|",SUBSTITUTE(SUBSTITUTE(O8,"_","-"),"|","-"))),IF(P8="","",CONCATENATE("_U2|",SUBSTITUTE(SUBSTITUTE(P8,"_","-"),"|","-"))),IF(Q8="","",CONCATENATE("_U3|",SUBSTITUTE(SUBSTITUTE(Q8,"_","-"),"|","-"))))) -> MK|BR_CH|PSD_DT|CROSS_PB|FCBK_FM|CAR_RT|CPM_PD|DOTZ-10MIL-AZUL_TG|NON_ST|NON_TS|NONE_SZ|1X1_AD|CM1_IT|SOC
B9: Brazil | C9: Paid Social Display | D9: Cross Device/ Screen | E9: Facebook | F9: Stories | G9: Cost per Thousand | H9: DOTZ-10MIL-AZUL-CAR | I9: None | J9: None | L9: 1X1 | M9: Site-Served w/ DCM Tracking | N9: Social | R9: =IF(K9="----","#N/A",CONCATENATE("MK|",(VLOOKUP(B9,Dictionary!$A:$B,2,0)),"_CH|",(VLOOKUP(C9,Dictionary!$AV:$AW,2,0)),"_DT|",(VLOOKUP(D9,Dictionary!$P:$Q,2,0)),"_PB|",(VLOOKUP(E9,Dictionary!$G:$H,2,0)),"_FM|",(VLOOKUP(F9,Dictionary!$S:$T,2,0)),"_RT|",(VLOOKUP(G9,Dictionary!$V:$W,2,0)),"_PD|",SUBSTITUTE(SUBSTITUTE(IF(H9="","NONE",H9),"_","-"),"|","-"),"_TG|",(VLOOKUP(I9,Dictionary!$J:$K,2,0)),"_ST|",(VLOOKUP(J9,Dictionary!$M:$N,2,0)),"_TS|",SUBSTITUTE(SUBSTITUTE(IF(K9="","NONE",K9),"_","-"),"|","-"),"_SZ|",(VLOOKUP(L9,Dictionary!$Y:$Z,1,0)),"_AD|",(VLOOKUP(M9,Dictionary!$AB:$AC,2,0)),"_IT|",(VLOOKUP(N9,Dictionary!$BC:$BD,2,0)),IF(O9="","",CONCATENATE("_U1|",SUBSTITUTE(SUBSTITUTE(O9,"_","-"),"|","-"))),IF(P9="","",CONCATENATE("_U2|",SUBSTITUTE(SUBSTITUTE(P9,"_","-"),"|","-"))),IF(Q9="","",CONCATENATE("_U3|",SUBSTITUTE(SUBSTITUTE(Q9,"_","-"),"|","-"))))) -> MK|BR_CH|PSD_DT|CROSS_PB|FCBK_FM|STRY_RT|CPM_PD|DOTZ-10MIL-AZUL-CAR_TG|NON_ST|NON_TS|NONE_SZ|1X1_AD|CM1_IT|SOC
B10: Brazil | C10: Paid Social Display | D10: Cross Device/ Screen | E10: Facebook | F10: Link Ad | G10: Cost per Thousand | H10: DOTZ-ZERO-ANUIDADE-AZUL | I10: None | J10: None | L10: 1X1 | M10: Site-Served w/ DCM Tracking | N10: Social | R10: =IF(K10="----","#N/A",CONCATENATE("MK|",(VLOOKUP(B10,Dictionary!$A:$B,2,0)),"_CH|",(VLOOKUP(C10,Dictionary!$AV:$AW,2,0)),"_DT|",(VLOOKUP(D10,Dictionary!$P:$Q,2,0)),"_PB|",(VLOOKUP(E10,Dictionary!$G:$H,2,0)),"_FM|",(VLOOKUP(F10,Dictionary!$S:$T,2,0)),"_RT|",(VLOOKUP(G10,Dictionary!$V:$W,2,0)),"_PD|",SUBSTITUTE(SUBSTITUTE(IF(H10="","NONE",H10),"_","-"),"|","-"),"_TG|",(VLOOKUP(I10,Dictionary!$J:$K,2,0)),"_ST|",(VLOOKUP(J10,Dictionary!$M:$N,2,0)),"_TS|",SUBSTITUTE(SUBSTITUTE(IF(K10="","NONE",K10),"_","-"),"|","-"),"_SZ|",(VLOOKUP(L10,Dictionary!$Y:$Z,1,0)),"_AD|",(VLOOKUP(M10,Dictionary!$AB:$AC,2,0)),"_IT|",(VLOOKUP(N10,Dictionary!$BC:$BD,2,0)),IF(O10="","",CONCATENATE("_U1|",SUBSTITUTE(SUBSTITUTE(O10,"_","-"),"|","-"))),IF(P10="","",CONCATENATE("_U2|",SUBSTITUTE(SUBSTITUTE(P10,"_","-"),"|","-"))),IF(Q10="","",CONCATENATE("_U3|",SUBSTITUTE(SUBSTITUTE(Q10,"_","-"),"|","-"))))) -> MK|BR_CH|PSD_DT|CROSS_PB|FCBK_FM|LNK_RT|CPM_PD|DOTZ-ZERO-ANUIDADE-AZUL_TG|NON_ST|NON_TS|NONE_SZ|1X1_AD|CM1_IT|SOC
B11: Brazil | C11: Paid Social Display | D11: Cross Device/ Screen | E11: Facebook | F11: Link Ad | G11: Cost per Thousand | H11: DOTZ-ZERO-ANUIDADE-AZUL-QUAD | I11: None | J11: None | L11: 1X1 | M11: Site-Served w/ DCM Tracking | N11: Social | R11: =IF(K11="----","#N/A",CONCATENATE("MK|",(VLOOKUP(B11,Dictionary!$A:$B,2,0)),"_CH|",(VLOOKUP(C11,Dictionary!$AV:$AW,2,0)),"_DT|",(VLOOKUP(D11,Dictionary!$P:$Q,2,0)),"_PB|",(VLOOKUP(E11,Dictionary!$G:$H,2,0)),"_FM|",(VLOOKUP(F11,Dictionary!$S:$T,2,0)),"_RT|",(VLOOKUP(G11,Dictionary!$V:$W,2,0)),"_PD|",SUBSTITUTE(SUBSTITUTE(IF(H11="","NONE",H11),"_","-"),"|","-"),"_TG|",(VLOOKUP(I11,Dictionary!$J:$K,2,0)),"_ST|",(VLOOKUP(J11,Dictionary!$M:$N,2,0)),"_TS|",SUBSTITUTE(SUBSTITUTE(IF(K11="","NONE",K11),"_","-"),"|","-"),"_SZ|",(VLOOKUP(L11,Dictionary!$Y:$Z,1,0)),"_AD|",(VLOOKUP(M11,Dictionary!$AB:$AC,2,0)),"_IT|",(VLOOKUP(N11,Dictionary!$BC:$BD,2,0)),IF(O11="","",CONCATENATE("_U1|",SUBSTITUTE(SUBSTITUTE(O11,"_","-"),"|","-"))),IF(P11="","",CONCATENATE("_U2|",SUBSTITUTE(SUBSTITUTE(P11,"_","-"),"|","-"))),IF(Q11="","",CONCATENATE("_U3|",SUBSTITUTE(SUBSTITUTE(Q11,"_","-"),"|","-"))))) -> MK|BR_CH|PSD_DT|CROSS_PB|FCBK_FM|LNK_RT|CPM_PD|DOTZ-ZERO-ANUIDADE-AZUL-QUAD_TG|NON_ST|NON_TS|NONE_SZ|1X1_AD|CM1_IT|SOC
B12: Brazil | C12: Paid Social Display | D12: Cross Device/ Screen | E12: Facebook | F12: GIF | G12: Cost per Thousand | H12: DOTZ-ZERO-ANUIDADE-AZUL | I12: None | J12: None | L12: 1X1 | M12: Site-Served w/ DCM Tracking | N12: Social | R12: =IF(K12="----","#N/A",CONCATENATE("MK|",(VLOOKUP(B12,Dictionary!$A:$B,2,0)),"_CH|",(VLOOKUP(C12,Dictionary!$AV:$AW,2,0)),"_DT|",(VLOOKUP(D12,Dictionary!$P:$Q,2,0)),"_PB|",(VLOOKUP(E12,Dictionary!$G:$H,2,0)),"_FM|",(VLOOKUP(F12,Dictionary!$S:$T,2,0)),"_RT|",(VLOOKUP(G12,Dictionary!$V:$W,2,0)),"_PD|",SUBSTITUTE(SUBSTITUTE(IF(H12="","NONE",H12),"_","-"),"|","-"),"_TG|",(VLOOKUP(I12,Dictionary!$J:$K,2,0)),"_ST|",(VLOOKUP(J12,Dictionary!$M:$N,2,0)),"_TS|",SUBSTITUTE(SUBSTITUTE(IF(K12="","NONE",K12),"_","-"),"|","-"),"_SZ|",(VLOOKUP(L12,Dictionary!$Y:$Z,1,0)),"_AD|",(VLOOKUP(M12,Dictionary!$AB:$AC,2,0)),"_IT|",(VLOOKUP(N12,Dictionary!$BC:$BD,2,0)),IF(O12="","",CONCATENATE("_U1|",SUBSTITUTE(SUBSTITUTE(O12,"_","-"),"|","-"))),IF(P12="","",CONCATENATE("_U2|",SUBSTITUTE(SUBSTITUTE(P12,"_","-"),"|","-"))),IF(Q12="","",CONCATENATE("_U3|",SUBSTITUTE(SUBSTITUTE(Q12,"_","-"),"|","-"))))) -> MK|BR_CH|PSD_DT|CROSS_PB|FCBK_FM|GIF_RT|CPM_PD|DOTZ-ZERO-ANUIDADE-AZUL_TG|NON_ST|NON_TS|NONE_SZ|1X1_AD|CM1_IT|SOC
B13: Brazil | C13: Paid Social Display | D13: Cross Device/ Screen | E13: Facebook | F13: Carousel | G13: Cost per Thousand | H13: DOTZ-ZERO-ANUIDADE-AZUL | I13: None | J13: None | L13: 1X1 | M13: Site-Served w/ DCM Tracking | N13: Social | R13: =IF(K13="----","#N/A",CONCATENATE("MK|",(VLOOKUP(B13,Dictionary!$A:$B,2,0)),"_CH|",(VLOOKUP(C13,Dictionary!$AV:$AW,2,0)),"_DT|",(VLOOKUP(D13,Dictionary!$P:$Q,2,0)),"_PB|",(VLOOKUP(E13,Dictionary!$G:$H,2,0)),"_FM|",(VLOOKUP(F13,Dictionary!$S:$T,2,0)),"_RT|",(VLOOKUP(G13,Dictionary!$V:$W,2,0)),"_PD|",SUBSTITUTE(SUBSTITUTE(IF(H13="","NONE",H13),"_","-"),"|","-"),"_TG|",(VLOOKUP(I13,Dictionary!$J:$K,2,0)),"_ST|",(VLOOKUP(J13,Dictionary!$M:$N,2,0)),"_TS|",SUBSTITUTE(SUBSTITUTE(IF(K13="","NONE",K13),"_","-"),"|","-"),"_SZ|",(VLOOKUP(L13,Dictionary!$Y:$Z,1,0)),"_AD|",(VLOOKUP(M13,Dictionary!$AB:$AC,2,0)),"_IT|",(VLOOKUP(N13,Dictionary!$BC:$BD,2,0)),IF(O13="","",CONCATENATE("_U1|",SUBSTITUTE(SUBSTITUTE(O13,"_","-"),"|","-"))),IF(P13="","",CONCATENATE("_U2|",SUBSTITUTE(SUBSTITUTE(P13,"_","-"),"|","-"))),IF(Q13="","",CONCATENATE("_U3|",SUBSTITUTE(SUBSTITUTE(Q13,"_","-"),"|","-"))))) -> MK|BR_CH|PSD_DT|CROSS_PB|FCBK_FM|CAR_RT|CPM_PD|DOTZ-ZERO-ANUIDADE-AZUL_TG|NON_ST|NON_TS|NONE_SZ|1X1_AD|CM1_IT|SOC
B14: Brazil | C14: Paid Social Display | D14: Cross Device/ Screen | E14: Facebook | F14: Stories | G14: Cost per Thousand | H14: DOTZ-ZERO-ANUIDADE-AZUL-CAR | I14: None | J14: None | L14: 1X1 | M14: Site-Served w/ DCM Tracking | N14: Social | R14: =IF(K14="----","#N/A",CONCATENATE("MK|",(VLOOKUP(B14,Dictionary!$A:$B,2,0)),"_CH|",(VLOOKUP(C14,Dictionary!$AV:$AW,2,0)),"_DT|",(VLOOKUP(D14,Dictionary!$P:$Q,2,0)),"_PB|",(VLOOKUP(E14,Dictionary!$G:$H,2,0)),"_FM|",(VLOOKUP(F14,Dictionary!$S:$T,2,0)),"_RT|",(VLOOKUP(G14,Dictionary!$V:$W,2,0)),"_PD|",SUBSTITUTE(SUBSTITUTE(IF(H14="","NONE",H14),"_","-"),"|","-"),"_TG|",(VLOOKUP(I14,Dictionary!$J:$K,2,0)),"_ST|",(VLOOKUP(J14,Dictionary!$M:$N,2,0)),"_TS|",SUBSTITUTE(SUBSTITUTE(IF(K14="","NONE",K14),"_","-"),"|","-"),"_SZ|",(VLOOKUP(L14,Dictionary!$Y:$Z,1,0)),"_AD|",(VLOOKUP(M14,Dictionary!$AB:$AC,2,0)),"_IT|",(VLOOKUP(N14,Dictionary!$BC:$BD,2,0)),IF(O14="","",CONCATENATE("_U1|",SUBSTITUTE(SUBSTITUTE(O14,"_","-"),"|","-"))),IF(P14="","",CONCATENATE("_U2|",SUBSTITUTE(SUBSTITUTE(P14,"_","-"),"|","-"))),IF(Q14="","",CONCATENATE("_U3|",SUBSTITUTE(SUBSTITUTE(Q14,"_","-"),"|","-"))))) -> MK|BR_CH|PSD_DT|CROSS_PB|FCBK_FM|STRY_RT|CPM_PD|DOTZ-ZERO-ANUIDADE-AZUL-CAR_TG|NON_ST|NON_TS|NONE_SZ|1X1_AD|CM1_IT|SOC
... B46: Brazil | C46: Paid Social Display | D46: Cross Device/ Screen | E46: Facebook | F46: Stories | G46: Cost per Thousand | H46: DOTZ-10MIL-AZUL | I46: None | J46: None | L46: 1X1 | M46: Site-Served w/ DCM Tracking | N46: Social | R46: =IF(K46="----","#N/A",CONCATENATE("MK|",(VLOOKUP(B46,Dictionary!$A:$B,2,0)),"_CH|",(VLOOKUP(C46,Dictionary!$AV:$AW,2,0)),"_DT|",(VLOOKUP(D46,Dictionary!$P:$Q,2,0)),"_PB|",(VLOOKUP(E46,Dictionary!$G:$H,2,0)),"_FM|",(VLOOKUP(F46,Dictionary!$S:$T,2,0)),"_RT|",(VLOOKUP(G46,Dictionary!$V:$W,2,0)),"_PD|",SUBSTITUTE(SUBSTITUTE(IF(H46="","NONE",H46),"_","-"),"|","-"),"_TG|",(VLOOKUP(I46,Dictionary!$J:$K,2,0)),"_ST|",(VLOOKUP(J46,Dictionary!$M:$N,2,0)),"_TS|",SUBSTITUTE(SUBSTITUTE(IF(K46="","NONE",K46),"_","-"),"|","-"),"_SZ|",(VLOOKUP(L46,Dictionary!$Y:$Z,1,0)),"_AD|",(VLOOKUP(M46,Dictionary!$AB:$AC,2,0)),"_IT|",(VLOOKUP(N46,Dictionary!$BC:$BD,2,0)),IF(O46="","",CONCATENATE("_U1|",SUBSTITUTE(SUBSTITUTE(O46,"_","-"),"|","-"))),IF(P46="","",CONCATENATE("_U2|",SUBSTITUTE(SUBSTITUTE(P46,"_","-"),"|","-"))),IF(Q46="","",CONCATENATE("_U3|",SUBSTITUTE(SUBSTITUTE(Q46,"_","-"),"|","-"))))) -> MK|BR_CH|PSD_DT|CROSS_PB|FCBK_FM|STRY_RT|CPM_PD|DOTZ-10MIL-AZUL_TG|NON_ST|NON_TS|NONE_SZ|1X1_AD|CM1_IT|SOC
B47: Brazil | C47: Paid Social Display | D47: Cross Device/ Screen | E47: Facebook | F47: Carousel | G47: Cost per Thousand | H47: DOTZ-10MIL-AZUL | I47: None | J47: None | L47: 1X1 | M47: Site-Served w/ DCM Tracking | N47: Social | O47: ESTATICO | R47: =IF(K47="----","#N/A",CONCATENATE("MK|",(VLOOKUP(B47,Dictionary!$A:$B,2,0)),"_CH|",(VLOOKUP(C47,Dictionary!$AV:$AW,2,0)),"_DT|",(VLOOKUP(D47,Dictionary!$P:$Q,2,0)),"_PB|",(VLOOKUP(E47,Dictionary!$G:$H,2,0)),"_FM|",(VLOOKUP(F47,Dictionary!$S:$T,2,0)),"_RT|",(VLOOKUP(G47,Dictionary!$V:$W,2,0)),"_PD|",SUBSTITUTE(SUBSTITUTE(IF(H47="","NONE",H47),"_","-"),"|","-"),"_TG|",(VLOOKUP(I47,Dictionary!$J:$K,2,0)),"_ST|",(VLOOKUP(J47,Dictionary!$M:$N,2,0)),"_TS|",SUBSTITUTE(SUBSTITUTE(IF(K47="","NONE",K47),"_","-"),"|","-"),"_SZ|",(VLOOKUP(L47,Dictionary!$Y:$Z,1,0)),"_AD|",(VLOOKUP(M47,Dictionary!$AB:$AC,2,0)),"_IT|",(VLOOKUP(N47,Dictionary!$BC:$BD,2,0)),IF(O47="","",CONCATENATE("_U1|",SUBSTITUTE(SUBSTITUTE(O47,"_","-"),"|","-"))),IF(P47="","",CONCATENATE("_U2|",SUBSTITUTE(SUBSTITUTE(P47,"_","-"),"|","-"))),IF(Q47="","",CONCATENATE("_U3|",SUBSTITUTE(SUBSTITUTE(Q47,"_","-"),"|","-"))))) -> MK|BR_CH|PSD_DT|CROSS_PB|FCBK_FM|CAR_RT|CPM_PD|DOTZ-10MIL-AZUL_TG|NON_ST|NON_TS|NONE_SZ|1X1_AD|CM1_IT|SOC_U1|ESTATICO
B48: Brazil | C48: Paid Social Display | D48: Cross Device/ Screen | E48: Facebook | F48: Carousel | G48: Cost per Thousand | H48: DOTZ-ZERO-ANUIDADE-AZUL | I48: None | J48: None | L48: 1X1 | M48: Site-Served w/ DCM Tracking | N48: Social | O48: ESTATICO | R48: =IF(K48="----","#N/A",CONCATENATE("MK|",(VLOOKUP(B48,Dictionary!$A:$B,2,0)),"_CH|",(VLOOKUP(C48,Dictionary!$AV:$AW,2,0)),"_DT|",(VLOOKUP(D48,Dictionary!$P:$Q,2,0)),"_PB|",(VLOOKUP(E48,Dictionary!$G:$H,2,0)),"_FM|",(VLOOKUP(F48,Dictionary!$S:$T,2,0)),"_RT|",(VLOOKUP(G48,Dictionary!$V:$W,2,0)),"_PD|",SUBSTITUTE(SUBSTITUTE(IF(H48="","NONE",H48),"_","-"),"|","-"),"_TG|",(VLOOKUP(I48,Dictionary!$J:$K,2,0)),"_ST|",(VLOOKUP(J48,Dictionary!$M:$N,2,0)),"_TS|",SUBSTITUTE(SUBSTITUTE(IF(K48="","NONE",K48),"_","-"),"|","-"),"_SZ|",(VLOOKUP(L48,Dictionary!$Y:$Z,1,0)),"_AD|",(VLOOKUP(M48,Dictionary!$AB:$AC,2,0)),"_IT|",(VLOOKUP(N48,Dictionary!$BC:$BD,2,0)),IF(O48="","",CONCATENATE("_U1|",SUBSTITUTE(SUBSTITUTE(O48,"_","-"),"|","-"))),IF(P48="","",CONCATENATE("_U2|",SUBSTITUTE(SUBSTITUTE(P48,"_","-"),"|","-"))),IF(Q48="","",CONCATENATE("_U3|",SUBSTITUTE(SUBSTITUTE(Q48,"_","-"),"|","-"))))) -> MK|BR_CH|PSD_DT|CROSS_PB|FCBK_FM|CAR_RT|CPM_PD|DOTZ-ZERO-ANUIDADE-AZUL_TG|NON_ST|NON_TS|NONE_SZ|1X1_AD|CM1_IT|SOC_U1|ESTATICO
B49: Brazil | C49: Paid Social Display | D49: Cross Device/ Screen | E49: Facebook | F49: Carousel | G49: Cost per Thousand | H49: DOTZ-TODOS-BENEFICIOS-AZUL | I49: None | J49: None | L49: 1X1 | M49: Site-Served w/ DCM Tracking | N49: Social | O49: ESTATICO | R49: =IF(K49="----","#N/A",CONCATENATE("MK|",(VLOOKUP(B49,Dictionary!$A:$B,2,0)),"_CH|",(VLOOKUP(C49,Dictionary!$AV:$AW,2,0)),"_DT|",(VLOOKUP(D49,Dictionary!$P:$Q,2,0)),"_PB|",(VLOOKUP(E49,Dictionary!$G:$H,2,0)),"_FM|",(VLOOKUP(F49,Dictionary!$S:$T,2,0)),"_RT|",(VLOOKUP(G49,Dictionary!$V:$W,2,0)),"_PD|",SUBSTITUTE(SUBSTITUTE(IF(H49="","NONE",H49),"_","-"),"|","-"),"_TG|",(VLOOKUP(I49,Dictionary!$J:$K,2,0)),"_ST|",(VLOOKUP(J49,Dictionary!$M:$N,2,0)),"_TS|",SUBSTITUTE(SUBSTITUTE(IF(K49="","NONE",K49),"_","-"),"|","-"),"_SZ|",(VLOOKUP(L49,Dictionary!$Y:$Z,1,0)),"_AD|",(VLOOKUP(M49,Dictionary!$AB:$AC,2,0)),"_IT|",(VLOOKUP(N49,Dictionary!$BC:$BD,2,0)),IF(O49="","",CONCATENATE("_U1|",SUBSTITUTE(SUBSTITUTE(O49,"_","-"),"|","-"))),IF(P49="","",CONCATENATE("_U2|",SUBSTITUTE(SUBSTITUTE(P49,"_","-"),"|","-"))),IF(Q49="","",CONCATENATE("_U3|",SUBSTITUTE(SUBSTITUTE(Q49,"_","-"),"|","-"))))) -> MK|BR_CH|PSD_DT|CROSS_PB|FCBK_FM|CAR_RT|CPM_PD|DOTZ-TODOS-BENEFICIOS-AZUL_TG|NON_ST|NON_TS|NONE_SZ|1X1_AD|CM1_IT|SOC_U1|ESTATICO
B50: Brazil | C50: Paid Social Display | D50: Cross Device/ Screen | E50: Facebook | F50: Carousel | G50: Cost per Thousand | H50: DOTZ-10MIL-AMARELO | I50: None | J50: None | L50: 1X1 | M50: Site-Served w/ DCM Tracking | N50: Social | O50: ESTATICO | R50: =IF(K50="----","#N/A",CONCATENATE("MK|",(VLOOKUP(B50,Dictionary!$A:$B,2,0)),"_CH|",(VLOOKUP(C50,Dictionary!$AV:$AW,2,0)),"_DT|",(VLOOKUP(D50,Dictionary!$P:$Q,2,0)),"_PB|",(VLOOKUP(E50,Dictionary!$G:$H,2,0)),"_FM|",(VLOOKUP(F50,Dictionary!$S:$T,2,0)),"_RT|",(VLOOKUP(G50,Dictionary!$V:$W,2,0)),"_PD|",SUBSTITUTE(SUBSTITUTE(IF(H50="","NONE",H50),"_","-"),"|","-"),"_TG|",(VLOOKUP(I50,Dictionary!$J:$K,2,0)),"_ST|",(VLOOKUP(J50,Dictionary!$M:$N,2,0)),"_TS|",SUBSTITUTE(SUBSTITUTE(IF(K50="","NONE",K50),"_","-"),"|","-"),"_SZ|",(VLOOKUP(L50,Dictionary!$Y:$Z,1,0)),"_AD|",(VLOOKUP(M50,Dictionary!$AB:$AC,2,0)),"_IT|",(VLOOKUP(N50,Dictionary!$BC:$BD,2,0)),IF(O50="","",CONCATENATE("_U1|",SUBSTITUTE(SUBSTITUTE(O50,"_","-"),"|","-"))),IF(P50="","",CONCATENATE("_U2|",SUBSTITUTE(SUBSTITUTE(P50,"_","-"),"|","-"))),IF(Q50="","",CONCATENATE("_U3|",SUBSTITUTE(SUBSTITUTE(Q50,"_","-"),"|","-"))))) -> MK|BR_CH|PSD_DT|CROSS_PB|FCBK_FM|CAR_RT|CPM_PD|DOTZ-10MIL-AMARELO_TG|NON_ST|NON_TS|NONE_SZ|1X1_AD|CM1_IT|SOC_U1|ESTATICO
B51: Brazil | C51: Paid Social Display | D51: Cross Device/ Screen | E51: Facebook | F51: Carousel | G51: Cost per Thousand | H51: DOTZ-ZERO-ANUIDADE-AMARELO | I51: None | J51: None | L51: 1X1 | M51: Site-Served w/ DCM Tracking | N51: Social | O51: ESTATICO | R51: =IF(K51="----","#N/A",CONCATENATE("MK|",(VLOOKUP(B51,Dictionary!$A:$B,2,0)),"_CH|",(VLOOKUP(C51,Dictionary!$AV:$AW,2,0)),"_DT|",(VLOOKUP(D51,Dictionary!$P:$Q,2,0)),"_PB|",(VLOOKUP(E51,Dictionary!$G:$H,2,0)),"_FM|",(VLOOKUP(F51,Dictionary!$S:$T,2,0)),"_RT|",(VLOOKUP(G51,Dictionary!$V:$W,2,0)),"_PD|",SUBSTITUTE(SUBSTITUTE(IF(H51="","NONE",H51),"_","-"),"|","-"),"_TG|",(VLOOKUP(I51,Dictionary!$J:$K,2,0)),"_ST|",(VLOOKUP(J51,Dictionary!$M:$N,2,0)),"_TS|",SUBSTITUTE(SUBSTITUTE(IF(K51="","NONE",K51),"_","-"),"|","-"),"_SZ|",(VLOOKUP(L51,Dictionary!$Y:$Z,1,0)),"_AD|",(VLOOKUP(M51,Dictionary!$AB:$AC,2,0)),"_IT|",(VLOOKUP(N51,Dictionary!$BC:$BD,2,0)),IF(O51="","",CONCATENATE("_U1|",SUBSTITUTE(SUBSTITUTE(O51,"_","-"),"|","-"))),IF(P51="","",CONCATENATE("_U2|",SUBSTITUTE(SUBSTITUTE(P51,"_","-"),"|","-"))),IF(Q51="","",CONCATENATE("_U3|",SUBSTITUTE(SUBSTITUTE(Q51,"_","-"),"|","-"))))) -> MK|BR_CH|PSD_DT|CROSS_PB|FCBK_FM|CAR_RT|CPM_PD|DOTZ-ZERO-ANUIDADE-AMARELO_TG|NON_ST|NON_TS|NONE_SZ|1X1_AD|CM1_IT|SOC_U1|ESTATICO
B52: Brazil | C52: Paid Social Display | D52: Cross Device/ Screen | E52: Facebook | F52: Carousel | G52: Cost per Thousand | H52: DOTZ-TODOS-BENEFICIOS-AMARELO | I52: None | J52: None | L52: 1X1 | M52: Site-Served w/ DCM Tracking | N52: Social | O52: ESTATICO | R52: =IF(K52="----","#N/A",CONCATENATE("MK|",(VLOOKUP(B52,Dictionary!$A:$B,2,0)),"_CH|",(VLOOKUP(C52,Dictionary!$AV:$AW,2,0)),"_DT|",(VLOOKUP(D52,Dictionary!$P:$Q,2,0)),"_PB|",(VLOOKUP(E52,Dictionary!$G:$H,2,0)),"_FM|",(VLOOKUP(F52,Dictionary!$S:$T,2,0)),"_RT|",(VLOOKUP(G52,Dictionary!$V:$W,2,0)),"_PD|",SUBSTITUTE(SUBSTITUTE(IF(H52="","NONE",H52),"_","-"),"|","-"),"_TG|",(VLOOKUP(I52,Dictionary!$J:$K,2,0)),"_ST|",(VLOOKUP(J52,Dictionary!$M:$N,2,0)),"_TS|",SUBSTITUTE(SUBSTITUTE(IF(K52="","NONE",K52),"_","-"),"|","-"),"_SZ|",(VLOOKUP(L52,Dictionary!$Y:$Z,1,0)),"_AD|",(VLOOKUP(M52,Dictionary!$AB:$AC,2,0)),"_IT|",(VLOOKUP(N52,Dictionary!$BC:$BD,2,0)),IF(O52="","",CONCATENATE("_U1|",SUBSTITUTE(SUBSTITUTE(O52,"_","-"),"|","-"))),IF(P52="","",CONCATENATE("_U2|",SUBSTITUTE(SUBSTITUTE(P52,"_","-"),"|","-"))),IF(Q52="","",CONCATENATE("_U3|",SUBSTITUTE(SUBSTITUTE(Q52,"_","-"),"|","-"))))) -> MK|BR_CH|PSD_DT|CROSS_PB|FCBK_FM|CAR_RT|CPM_PD|DOTZ-TODOS-BENEFICIOS-AMARELO_TG|NON_ST|NON_TS|NONE_SZ|1X1_AD|CM1_IT|SOC_U1|ESTATICO
B53: Brazil | C53: Paid Social Display | D53: Cross Device/ Screen | E53: Facebook | F53: Carousel | G53: Cost per Thousand | H53: DOTZ-CONVERSAO-AMARELO | I53: None | J53: None | L53: 1X1 | M53: Site-Served w/ DCM Tracking | N53: Social | O53: ESTATICO | R53: =IF(K53="----","#N/A",CONCATENATE("MK|",(VLOOKUP(B53,Dictionary!$A:$B,2,0)),"_CH|",(VLOOKUP(C53,Dictionary!$AV:$AW,2,0)),"_DT|",(VLOOKUP(D53,Dictionary!$P:$Q,2,0)),"_PB|",(VLOOKUP(E53,Dictionary!$G:$H,2,0)),"_FM|",(VLOOKUP(F53,Dictionary!$S:$T,2,0)),"_RT|",(VLOOKUP(G53,Dictionary!$V:$W,2,0)),"_PD|",SUBSTITUTE(SUBSTITUTE(IF(H53="","NONE",H53),"_","-"),"|","-"),"_TG|",(VLOOKUP(I53,Dictionary!$J:$K,2,0)),"_ST|",(VLOOKUP(J53,Dictionary!$M:$N,2,0)),"_TS|",SUBSTITUTE(SUBSTITUTE(IF(K53="","NONE",K53),"_","-"),"|","-"),"_SZ|",(VLOOKUP(L53,Dictionary!$Y:$Z,1,0)),"_AD|",(VLOOKUP(M53,Dictionary!$AB:$AC,2,0)),"_IT|",(VLOOKUP(N53,Dictionary!$BC:$BD,2,0)),IF(O53="","",CONCATENATE("_U1|",SUBSTITUTE(SUBSTITUTE(O53,"_","-"),"|","-"))),IF(P53="","",CONCATENATE("_U2|",SUBSTITUTE(SUBSTITUTE(P53,"_","-"),"|","-"))),IF(Q53="","",CONCATENATE("_U3|",SUBSTITUTE(SUBSTITUTE(Q53,"_","-"),"|","-"))))) -> MK|BR_CH|PSD_DT|CROSS_PB|FCBK_FM|CAR_RT|CPM_PD|DOTZ-CONVERSAO-AMARELO_TG|NON_ST|NON_TS|NONE_SZ|1X1_AD|CM1_IT|SOC_U1|ESTATICO
B54: Brazil | C54: Programmatic Display | D54: Cross Device/ Screen | E54: Google DV360 | F54: Banner | G54: Cost per Thousand | H54: DOTZ-10MIL-AZUL | I54: None | J54: None | L54: 120x600 | M54: DCM Ad Served | N54: Programmatic Open Exchange | R54: =IF(K54="----","#N/A",CONCATENATE("MK|",(VLOOKUP(B54,Dictionary!$A:$B,2,0)),"_CH|",(VLOOKUP(C54,Dictionary!$AV:$AW,2,0)),"_DT|",(VLOOKUP(D54,Dictionary!$P:$Q,2,0)),"_PB|",(VLOOKUP(E54,Dictionary!$G:$H,2,0)),"_FM|",(VLOOKUP(F54,Dictionary!$S:$T,2,0)),"_RT|",(VLOOKUP(G54,Dictionary!$V:$W,2,0)),"_PD|",SUBSTITUTE(SUBSTITUTE(IF(H54="","NONE",H54),"_","-"),"|","-"),"_TG|",(VLOOKUP(I54,Dictionary!$J:$K,2,0)),"_ST|",(VLOOKUP(J54,Dictionary!$M:$N,2,0)),"_TS|",SUBSTITUTE(SUBSTITUTE(IF(K54="","NONE",K54),"_","-"),"|","-"),"_SZ|",(VLOOKUP(L54,Dictionary!$Y:$Z,1,0)),"_AD|",(VLOOKUP(M54,Dictionary!$AB:$AC,2,0)),"_IT|",(VLOOKUP(N54,Dictionary!$BC:$BD,2,0)),IF(O54="","",CONCATENATE("_U1|",SUBSTITUTE(SUBSTITUTE(O54,"_","-"),"|","-"))),IF(P54="","",CONCATENATE("_U2|",SUBSTITUTE(SUBSTITUTE(P54,"_","-"),"|","-"))),IF(Q54="","",CONCATENATE("_U3|",SUBSTITUTE(SUBSTITUTE(Q54,"_","-"),"|","-"))))) -> MK|BR_CH|PD_DT|CROSS_PB|DV36_FM|BAN_RT|CPM_PD|DOTZ-10MIL-AZUL_TG|NON_ST|NON_TS|NONE_SZ|120x600_AD|CM_IT|POE
B55: Brazil | C55: Programmatic Display | D55: Cross Device/ Screen | E55: Google DV360 | F55: Banner | G55: Cost per Thousand | H55: DOTZ-10MIL-AZUL | I55: None | J55: None | L55: 160x600 | M55: DCM Ad Served | N55: Programmatic Open Exchange | R55: =IF(K55="----","#N/A",CONCATENATE("MK|",(VLOOKUP(B55,Dictionary!$A:$B,2,0)),"_CH|",(VLOOKUP(C55,Dictionary!$AV:$AW,2,0)),"_DT|",(VLOOKUP(D55,Dictionary!$P:$Q,2,0)),"_PB|",(VLOOKUP(E55,Dictionary!$G:$H,2,0)),"_FM|",(VLOOKUP(F55,Dictionary!$S:$T,2,0)),"_RT|",(VLOOKUP(G55,Dictionary!$V:$W,2,0)),"_PD|",SUBSTITUTE(SUBSTITUTE(IF(H55="","NONE",H55),"_","-"),"|","-"),"_TG|",(VLOOKUP(I55,Dictionary!$J:$K,2,0)),"_ST|",(VLOOKUP(J55,Dictionary!$M:$N,2,0)),"_TS|",SUBSTITUTE(SUBSTITUTE(IF(K55="","NONE",K55),"_","-"),"|","-"),"_SZ|",(VLOOKUP(L55,Dictionary!$Y:$Z,1,0)),"_AD|",(VLOOKUP(M55,Dictionary!$AB:$AC,2,0)),"_IT|",(VLOOKUP(N55,Dictionary!$BC:$BD,2,0)),IF(O55="","",CONCATENATE("_U1|",SUBSTITUTE(SUBSTITUTE(O55,"_","-"),"|","-"))),IF(P55="","",CONCATENATE("_U2|",SUBSTITUTE(SUBSTITUTE(P55,"_","-"),"|","-"))),IF(Q55="","",CONCATENATE("_U3|",SUBSTITUTE(SUBSTITUTE(Q55,"_","-"),"|","-"))))) -> MK|BR_CH|PD_DT|CROSS_PB|DV36_FM|BAN_RT|CPM_PD|DOTZ-10MIL-AZUL_TG|NON_ST|NON_TS|NONE_SZ|160x600_AD|CM_IT|POE
B56: Brazil | C56: Programmatic Display | D56: Cross Device/ Screen | E56: Google DV360 | F56: Banner | G56: Cost per Thousand | H56: DOTZ-10MIL-AZUL | I56: None | J56: None | L56: 300x250 | M56: DCM Ad Served | N56: Programmatic Open Exchange | R56: =IF(K56="----","#N/A",CONCATENATE("MK|",(VLOOKUP(B56,Dictionary!$A:$B,2,0)),"_CH|",(VLOOKUP(C56,Dictionary!$AV:$AW,2,0)),"_DT|",(VLOOKUP(D56,Dictionary!$P:$Q,2,0)),"_PB|",(VLOOKUP(E56,Dictionary!$G:$H,2,0)),"_FM|",(VLOOKUP(F56,Dictionary!$S:$T,2,0)),"_RT|",(VLOOKUP(G56,Dictionary!$V:$W,2,0)),"_PD|",SUBSTITUTE(SUBSTITUTE(IF(H56="","NONE",H56),"_","-"),"|","-"),"_TG|",(VLOOKUP(I56,Dictionary!$J:$K,2,0)),"_ST|",(VLOOKUP(J56,Dictionary!$M:$N,2,0)),"_TS|",SUBSTITUTE(SUBSTITUTE(IF(K56="","NONE",K56),"_","-"),"|","-"),"_SZ|",(VLOOKUP(L56,Dictionary!$Y:$Z,1,0)),"_AD|",(VLOOKUP(M56,Dictionary!$AB:$AC,2,0)),"_IT|",(VLOOKUP(N56,Dictionary!$BC:$BD,2,0)),IF(O56="","",CONCATENATE("_U1|",SUBSTITUTE(SUBSTITUTE(O56,"_","-"),"|","-"))),IF(P56="","",CONCATENATE("_U2|",SUBSTITUTE(SUBSTITUTE(P56,"_","-"),"|","-"))),IF(Q56="","",CONCATENATE("_U3|",SUBSTITUTE(SUBSTITUTE(Q56,"_","-"),"|","-"))))) -> MK|BR_CH|PD_DT|CROSS_PB|DV36_FM|BAN_RT|CPM_PD|DOTZ-10MIL-AZUL_TG|NON_ST|NON_TS|NONE_SZ|300x250_AD|CM_IT|POE
B57: Brazil | C57: Programmatic Display | D57: Cross Device/ Screen | E57: Google DV360 | F57: Banner | G57: Cost per Thousand | H57: DOTZ-10MIL-AZUL | I57: None | J57: None | L57: 300x600 | M57: DCM Ad Served | N57: Programmatic Open Exchange | R57: =IF(K57="----","#N/A",CONCATENATE("MK|",(VLOOKUP(B57,Dictionary!$A:$B,2,0)),"_CH|",(VLOOKUP(C57,Dictionary!$AV:$AW,2,0)),"_DT|",(VLOOKUP(D57,Dictionary!$P:$Q,2,0)),"_PB|",(VLOOKUP(E57,Dictionary!$G:$H,2,0)),"_FM|",(VLOOKUP(F57,Dictionary!$S:$T,2,0)),"_RT|",(VLOOKUP(G57,Dictionary!$V:$W,2,0)),"_PD|",SUBSTITUTE(SUBSTITUTE(IF(H57="","NONE",H57),"_","-"),"|","-"),"_TG|",(VLOOKUP(I57,Dictionary!$J:$K,2,0)),"_ST|",(VLOOKUP(J57,Dictionary!$M:$N,2,0)),"_TS|",SUBSTITUTE(SUBSTITUTE(IF(K57="","NONE",K57),"_","-"),"|","-"),"_SZ|",(VLOOKUP(L57,Dictionary!$Y:$Z,1,0)),"_AD|",(VLOOKUP(M57,Dictionary!$AB:$AC,2,0)),"_IT|",(VLOOKUP(N57,Dictionary!$BC:$BD,2,0)),IF(O57="","",CONCATENATE("_U1|",SUBSTITUTE(SUBSTITUTE(O57,"_","-"),"|","-"))),IF(P57="","",CONCATENATE("_U2|",SUBSTITUTE(SUBSTITUTE(P57,"_","-"),"|","-"))),IF(Q57="","",CONCATENATE("_U3|",SUBSTITUTE(SUBSTITUTE(Q57,"_","-"),"|","-"))))) -> MK|BR_CH|PD_DT|CROSS_PB|DV36_FM|BAN_RT|CPM_PD|DOTZ-10MIL-AZUL_TG|NON_ST|NON_TS|NONE_SZ|300x600_AD|CM_IT|POE
B58: Brazil | C58: Programmatic Mobile Display | D58: Cross Device/ Screen | E58: Google DV360 | F58: Banner | G58: Cost per Thousand | H58: DOTZ-10MIL-AZUL | I58: None | J58: None | L58: 320x50 | M58: DCM Ad Served | N58: Programmatic Open Exchange | R58: =IF(K58="----","#N/A",CONCATENATE("MK|",(VLOOKUP(B58,Dictionary!$A:$B,2,0)),"_CH|",(VLOOKUP(C58,Dictionary!$AV:$AW,2,0)),"_DT|",(VLOOKUP(D58,Dictionary!$P:$Q,2,0)),"_PB|",(VLOOKUP(E58,Dictionary!$G:$H,2,0)),"_FM|",(VLOOKUP(F58,Dictionary!$S:$T,2,0)),"_RT|",(VLOOKUP(G58,Dictionary!$V:$W,2,0)),"_PD|",SUBSTITUTE(SUBSTITUTE(IF(H58="","NONE",H58),"_","-"),"|","-"),"_TG|",(VLOOKUP(I58,Dictionary!$J:$K,2,0)),"_ST|",(VLOOKUP(J58,Dictionary!$M:$N,2,0)),"_TS|",SUBSTITUTE(SUBSTITUTE(IF(K58="","NONE",K58),"_","-"),"|","-"),"_SZ|",(VLOOKUP(L58,Dictionary!$Y:$Z,1,0)),"_AD|",(VLOOKUP(M58,Dictionary!$AB:$AC,2,0)),"_IT|",(VLOOKUP(N58,Dictionary!$BC:$BD,2,0)),IF(O58="","",CONCATENATE("_U1|",SUBSTITUTE(SUBSTITUTE(O58,"_","-"),"|","-"))),IF(P58="","",CONCATENATE("_U2|",SUBSTITUTE(SUBSTITUTE(P58,"_","-"),"|","-"))),IF(Q58="","",CONCATENATE("_U3|",SUBSTITUTE(SUBSTITUTE(Q58,"_","-"),"|","-"))))) -> MK|BR_CH|PMD_DT|CROSS_PB|DV36_FM|BAN_RT|CPM_PD|DOTZ-10MIL-AZUL_TG|NON_ST|NON_TS|NONE_SZ|320x50_AD|CM_IT|POE
B59: Brazil | C59: Programmatic Mobile Display | D59: Cross Device/ Screen | E59: Google DV360 | F59: Banner | G59: Cost per Thousand | H59: DOTZ-10MIL-AZUL | I59: None | J59: None | L59: 320x100 | M59: DCM Ad Served | N59: Programmatic Open Exchange | R59: =IF(K59="----","#N/A",CONCATENATE("MK|",(VLOOKUP(B59,Dictionary!$A:$B,2,0)),"_CH|",(VLOOKUP(C59,Dictionary!$AV:$AW,2,0)),"_DT|",(VLOOKUP(D59,Dictionary!$P:$Q,2,0)),"_PB|",(VLOOKUP(E59,Dictionary!$G:$H,2,0)),"_FM|",(VLOOKUP(F59,Dictionary!$S:$T,2,0)),"_RT|",(VLOOKUP(G59,Dictionary!$V:$W,2,0)),"_PD|",SUBSTITUTE(SUBSTITUTE(IF(H59="","NONE",H59),"_","-"),"|","-"),"_TG|",(VLOOKUP(I59,Dictionary!$J:$K,2,0)),"_ST|",(VLOOKUP(J59,Dictionary!$M:$N,2,0)),"_TS|",SUBSTITUTE(SUBSTITUTE(IF(K59="","NONE",K59),"_","-"),"|","-"),"_SZ|",(VLOOKUP(L59,Dictionary!$Y:$Z,1,0)),"_AD|",(VLOOKUP(M59,Dictionary!$AB:$AC,2,0)),"_IT|",(VLOOKUP(N59,Dictionary!$BC:$BD,2,0)),IF(O59="","",CONCATENATE("_U1|",SUBSTITUTE(SUBSTITUTE(O59,"_","-"),"|","-"))),IF(P59="","",CONCATENATE("_U2|",SUBSTITUTE(SUBSTITUTE(P59,"_","-"),"|","-"))),IF(Q59="","",CONCATENATE("_U3|",SUBSTITUTE(SUBSTITUTE(Q59,"_","-"),"|","-"))))) -> MK|BR_CH|PMD_DT|CROSS_PB|DV36_FM|BAN_RT|CPM_PD|DOTZ-10MIL-AZUL_TG|NON_ST|NON_TS|NONE_SZ|320x100_AD|CM_IT|POE
B60: Brazil | C60: Programmatic Display | D60: Cross Device/ Screen | E60: Google DV360 | F60: Banner | G60: Cost per Thousand | H60: DOTZ-10MIL-AZUL | I60: None | J60: None | L60: 728x90 | M60: DCM Ad Served | N60: Programmatic Open Exchange | R60: =IF(K60="----","#N/A",CONCATENATE("MK|",(VLOOKUP(B60,Dictionary!$A:$B,2,0)),"_CH|",(VLOOKUP(C60,Dictionary!$AV:$AW,2,0)),"_DT|",(VLOOKUP(D60,Dictionary!$P:$Q,2,0)),"_PB|",(VLOOKUP(E60,Dictionary!$G:$H,2,0)),"_FM|",(VLOOKUP(F60,Dictionary!$S:$T,2,0)),"_RT|",(VLOOKUP(G60,Dictionary!$V:$W,2,0)),"_PD|",SUBSTITUTE(SUBSTITUTE(IF(H60="","NONE",H60),"_","-"),"|","-"),"_TG|",(VLOOKUP(I60,Dictionary!$J:$K,2,0)),"_ST|",(VLOOKUP(J60,Dictionary!$M:$N,2,0)),"_TS|",SUBSTITUTE(SUBSTITUTE(IF(K60="","NONE",K60),"_","-"),"|","-"),"_SZ|",(VLOOKUP(L60,Dictionary!$Y:$Z,1,0)),"_AD|",(VLOOKUP(M60,Dictionary!$AB:$AC,2,0)),"_IT|",(VLOOKUP(N60,Dictionary!$BC:$BD,2,0)),IF(O60="","",CONCATENATE("_U1|",SUBSTITUTE(SUBSTITUTE(O60,"_","-"),"|","-"))),IF(P60="","",CONCATENATE("_U2|",SUBSTITUTE(SUBSTITUTE(P60,"_","-"),"|","-"))),IF(Q60="","",CONCATENATE("_U3|",SUBSTITUTE(SUBSTITUTE(Q60,"_","-"),"|","-"))))) -> MK|BR_CH|PD_DT|CROSS_PB|DV36_FM|BAN_RT|CPM_PD|DOTZ-10MIL-AZUL_TG|NON_ST|NON_TS|NONE_SZ|728x90_AD|CM_IT|POE
B61: Brazil | C61: Programmatic Display | D61: Cross Device/ Screen | E61: Google DV360 | F61: Banner | G61: Cost per Thousand | H61: DOTZ-ZERO-ANUIDADE-AZUL | I61: None | J61: None | L61: 120x600 | M61: DCM Ad Served | N61: Programmatic Open Exchange | R61: =IF(K61="----","#N/A",CONCATENATE("MK|",(VLOOKUP(B61,Dictionary!$A:$B,2,0)),"_CH|",(VLOOKUP(C61,Dictionary!$AV:$AW,2,0)),"_DT|",(VLOOKUP(D61,Dictionary!$P:$Q,2,0)),"_PB|",(VLOOKUP(E61,Dictionary!$G:$H,2,0)),"_FM|",(VLOOKUP(F61,Dictionary!$S:$T,2,0)),"_RT|",(VLOOKUP(G61,Dictionary!$V:$W,2,0)),"_PD|",SUBSTITUTE(SUBSTITUTE(IF(H61="","NONE",H61),"_","-"),"|","-"),"_TG|",(VLOOKUP(I61,Dictionary!$J:$K,2,0)),"_ST|",(VLOOKUP(J61,Dictionary!$M:$N,2,0)),"_TS|",SUBSTITUTE(SUBSTITUTE(IF(K61="","NONE",K61),"_","-"),"|","-"),"_SZ|",(VLOOKUP(L61,Dictionary!$Y:$Z,1,0)),"_AD|",(VLOOKUP(M61,Dictionary!$AB:$AC,2,0)),"_IT|",(VLOOKUP(N61,Dictionary!$BC:$BD,2,0)),IF(O61="","",CONCATENATE("_U1|",SUBSTITUTE(SUBSTITUTE(O61,"_","-"),"|","-"))),IF(P61="","",CONCATENATE("_U2|",SUBSTITUTE(SUBSTITUTE(P61,"_","-"),"|","-"))),IF(Q61="","",CONCATENATE("_U3|",SUBSTITUTE(SUBSTITUTE(Q61,"_","-"),"|","-"))))) -> MK|BR_CH|PD_DT|CROSS_PB|DV36_FM|BAN_RT|CPM_PD|DOTZ-ZERO-ANUIDADE-AZUL_TG|NON_ST|NON_TS|NONE_SZ|120x600_AD|CM_IT|POE
B62: Brazil | C62: Programmatic Display | D62: Cross Device/ Screen | E62: Google DV360 | F62: Banner | G62: Cost per Thousand | H62: DOTZ-ZERO-ANUIDADE-AZUL | I62: None | J62: None | L62: 160x600 | M62: DCM Ad Served | N62: Programmatic Open Exchange | R62: =IF(K62="----","#N/A",CONCATENATE("MK|",(VLOOKUP(B62,Dictionary!$A:$B,2,0)),"_CH|",(VLOOKUP(C62,Dictionary!$AV:$AW,2,0)),"_DT|",(VLOOKUP(D62,Dictionary!$P:$Q,2,0)),"_PB|",(VLOOKUP(E62,Dictionary!$G:$H,2,0)),"_FM|",(VLOOKUP(F62,Dictionary!$S:$T,2,0)),"_RT|",(VLOOKUP(G62,Dictionary!$V:$W,2,0)),"_PD|",SUBSTITUTE(SUBSTITUTE(IF(H62="","NONE",H62),"_","-"),"|","-"),"_TG|",(VLOOKUP(I62,Dictionary!$J:$K,2,0)),"_ST|",(VLOOKUP(J62,Dictionary!$M:$N,2,0)),"_TS|",SUBSTITUTE(SUBSTITUTE(IF(K62="","NONE",K62),"_","-"),"|","-"),"_SZ|",(VLOOKUP(L62,Dictionary!$Y:$Z,1,0)),"_AD|",(VLOOKUP(M62,Dictionary!$AB:$AC,2,0)),"_IT|",(VLOOKUP(N62,Dictionary!$BC:$BD,2,0)),IF(O62="","",CONCATENATE("_U1|",SUBSTITUTE(SUBSTITUTE(O62,"_","-"),"|","-"))),IF(P62="","",CONCATENATE("_U2|",SUBSTITUTE(SUBSTITUTE(P62,"_","-"),"|","-"))),IF(Q62="","",CONCATENATE("_U3|",SUBSTITUTE(SUBSTITUTE(Q62,"_","-"),"|","-"))))) -> MK|BR_CH|PD_DT|CROSS_PB|DV36_FM|BAN_RT|CPM_PD|DOTZ-ZERO-ANUIDADE-AZUL_TG|NON_ST|NON_TS|NONE_SZ|160x600_AD|CM_IT|POE
B63: Brazil | C63: Programmatic Display | D63: Cross Device/ Screen | E63: Google DV360 | F63: Banner | G63: Cost per Thousand | H63: DOTZ-ZERO-ANUIDADE-AZUL | I63: None | J63: None | L63: 300x250 | M63: DCM Ad Served | N63: Programmatic Open Exchange | R63: =IF(K63="----","#N/A",CONCATENATE("MK|",(VLOOKUP(B63,Dictionary!$A:$B,2,0)),"_CH|",(VLOOKUP(C63,Dictionary!$AV:$AW,2,0)),"_DT|",(VLOOKUP(D63,Dictionary!$P:$Q,2,0)),"_PB|",(VLOOKUP(E63,Dictionary!$G:$H,2,0)),"_FM|",(VLOOKUP(F63,Dictionary!$S:$T,2,0)),"_RT|",(VLOOKUP(G63,Dictionary!$V:$W,2,0)),"_PD|",SUBSTITUTE(SUBSTITUTE(IF(H63="","NONE",H63),"_","-"),"|","-"),"_TG|",(VLOOKUP(I63,Dictionary!$J:$K,2,0)),"_ST|",(VLOOKUP(J63,Dictionary!$M:$N,2,0)),"_TS|",SUBSTITUTE(SUBSTITUTE(IF(K63="","NONE",K63),"_","-"),"|","-"),"_SZ|",(VLOOKUP(L63,Dictionary!$Y:$Z,1,0)),"_AD|",(VLOOKUP(M63,Dictionary!$AB:$AC,2,0)),"_IT|",(VLOOKUP(N63,Dictionary!$BC:$BD,2,0)),IF(O63="","",CONCATENATE("_U1|",SUBSTITUTE(SUBSTITUTE(O63,"_","-"),"|","-"))),IF(P63="","",CONCATENATE("_U2|",SUBSTITUTE(SUBSTITUTE(P63,"_","-"),"|","-"))),IF(Q63="","",CONCATENATE("_U3|",SUBSTITUTE(SUBSTITUTE(Q63,"_","-"),"|","-"))))) -> MK|BR_CH|PD_DT|CROSS_PB|DV36_FM|BAN_RT|CPM_PD|DOTZ-ZERO-ANUIDADE-AZUL_TG|NON_ST|NON_TS|NONE_SZ|300x250_AD|CM_IT|POE
B64: Brazil | C64: Programmatic Display | D64: Cross Device/ Screen | E64: Google DV360 | F64: Banner | G64: Cost per Thousand | H64: DOTZ-ZERO-ANUIDADE-AZUL | I64: None | J64: None | L64: 300x600 | M64: DCM Ad Served | N64: Programmatic Open Exchange | R64: =IF(K64="----","#N/A",CONCATENATE("MK|",(VLOOKUP(B64,Dictionary!$A:$B,2,0)),"_CH|",(VLOOKUP(C64,Dictionary!$AV:$AW,2,0)),"_DT|",(VLOOKUP(D64,Dictionary!$P:$Q,2,0)),"_PB|",(VLOOKUP(E64,Dictionary!$G:$H,2,0)),"_FM|",(VLOOKUP(F64,Dictionary!$S:$T,2,0)),"_RT|",(VLOOKUP(G64,Dictionary!$V:$W,2,0)),"_PD|",SUBSTITUTE(SUBSTITUTE(IF(H64="","NONE",H64),"_","-"),"|","-"),"_TG|",(VLOOKUP(I64,Dictionary!$J:$K,2,0)),"_ST|",(VLOOKUP(J64,Dictionary!$M:$N,2,0)),"_TS|",SUBSTITUTE(SUBSTITUTE(IF(K64="","NONE",K64),"_","-"),"|","-"),"_SZ|",(VLOOKUP(L64,Dictionary!$Y:$Z,1,0)),"_AD|",(VLOOKUP(M64,Dictionary!$AB:$AC,2,0)),"_IT|",(VLOOKUP(N64,Dictionary!$BC:$BD,2,0)),IF(O64="","",CONCATENATE("_U1|",SUBSTITUTE(SUBSTITUTE(O64,"_","-"),"|","-"))),IF(P64="","",CONCATENATE("_U2|",SUBSTITUTE(SUBSTITUTE(P64,"_","-"),"|","-"))),IF(Q64="","",CONCATENATE("_U3|",SUBSTITUTE(SUBSTITUTE(Q64,"_","-"),"|","-"))))) -> MK|BR_CH|PD_DT|CROSS_PB|DV36_FM|BAN_RT|CPM_PD|DOTZ-ZERO-ANUIDADE-AZUL_TG|NON_ST|NON_TS|NONE_SZ|300x600_AD|CM_IT|POE
B65: Brazil | C65: Programmatic Mobile Display | D65: Cross Device/ Screen | E65: Google DV360 | F65: Banner | G65: Cost per Thousand | H65: DOTZ-ZERO-ANUIDADE-AZUL | I65: None | J65: None | L65: 320x50 | M65: DCM Ad Served | N65: Programmatic Open Exchange | R65: =IF(K65="----","#N/A",CONCATENATE("MK|",(VLOOKUP(B65,Dictionary!$A:$B,2,0)),"_CH|",(VLOOKUP(C65,Dictionary!$AV:$AW,2,0)),"_DT|",(VLOOKUP(D65,Dictionary!$P:$Q,2,0)),"_PB|",(VLOOKUP(E65,Dictionary!$G:$H,2,0)),"_FM|",(VLOOKUP(F65,Dictionary!$S:$T,2,0)),"_RT|",(VLOOKUP(G65,Dictionary!$V:$W,2,0)),"_PD|",SUBSTITUTE(SUBSTITUTE(IF(H65="","NONE",H65),"_","-"),"|","-"),"_TG|",(VLOOKUP(I65,Dictionary!$J:$K,2,0)),"_ST|",(VLOOKUP(J65,Dictionary!$M:$N,2,0)),"_TS|",SUBSTITUTE(SUBSTITUTE(IF(K65="","NONE",K65),"_","-"),"|","-"),"_SZ|",(VLOOKUP(L65,Dictionary!$Y:$Z,1,0)),"_AD|",(VLOOKUP(M65,Dictionary!$AB:$AC,2,0)),"_IT|",(VLOOKUP(N65,Dictionary!$BC:$BD,2,0)),IF(O65="","",CONCATENATE("_U1|",SUBSTITUTE(SUBSTITUTE(O65,"_","-"),"|","-"))),IF(P65="","",CONCATENATE("_U2|",SUBSTITUTE(SUBSTITUTE(P65,"_","-"),"|","-"))),IF(Q65="","",CONCATENATE("_U3|",SUBSTITUTE(SUBSTITUTE(Q65,"_","-"),"|","-"))))) -> MK|BR_CH|PMD_DT|CROSS_PB|DV36_FM|BAN_RT|CPM_PD|DOTZ-ZERO-ANUIDADE-AZUL_TG|NON_ST|NON_TS|NONE_SZ|320x50_AD|CM_IT|POE
... B131: Brazil | C131: Paid Social Display | D131: Cross Device/ Screen | E131: Facebook | F131: Stories | G131: Cost per Thousand | H131: DOTZ-DOLAR | I131: None | J131: None | L131: 1X1 | M131: Site-Served w/ DCM Tracking | N131: Social | R131: =IF(K131="----","#N/A",CONCATENATE("MK|",(VLOOKUP(B131,Dictionary!$A:$B,2,0)),"_CH|",(VLOOKUP(C131,Dictionary!$AV:$AW,2,0)),"_DT|",(VLOOKUP(D131,Dictionary!$P:$Q,2,0)),"_PB|",(VLOOKUP(E131,Dictionary!$G:$H,2,0)),"_FM|",(VLOOKUP(F131,Dictionary!$S:$T,2,0)),"_RT|",(VLOOKUP(G131,Dictionary!$V:$W,2,0)),"_PD|",SUBSTITUTE(SUBSTITUTE(IF(H131="","NONE",H131),"_","-"),"|","-"),"_TG|",(VLOOKUP(I131,Dictionary!$J:$K,2,0)),"_ST|",(VLOOKUP(J131,Dictionary!$M:$N,2,0)),"_TS|",SUBSTITUTE(SUBSTITUTE(IF(K131="","NONE",K131),"_","-"),"|","-"),"_SZ|",(VLOOKUP(L131,Dictionary!$Y:$Z,1,0)),"_AD|",(VLOOKUP(M131,Dictionary!$AB:$AC,2,0)),"_IT|",(VLOOKUP(N131,Dictionary!$BC:$BD,2,0)),IF(O131="","",CONCATENATE("_U1|",SUBSTITUTE(SUBSTITUTE(O131,"_","-"),"|","-"))),IF(P131="","",CONCATENATE("_U2|",SUBSTITUTE(SUBSTITUTE(P131,"_","-"),"|","-"))),IF(Q131="","",CONCATENATE("_U3|",SUBSTITUTE(SUBSTITUTE(Q131,"_","-"),"|","-"))))) -> MK|BR_CH|PSD_DT|CROSS_PB|FCBK_FM|STRY_RT|CPM_PD|DOTZ-DOLAR_TG|NON_ST|NON_TS|NONE_SZ|1X1_AD|CM1_IT|SOC
R338: =IF(K338="----","#N/A",CONCATENATE("MK|",(VLOOKUP(B338,Dictionary!$A:$B,2,0)),"_CH|",(VLOOKUP(C338,Dictionary!$AV:$AW,2,0)),"_DT|",(VLOOKUP(D338,Dictionary!$P:$Q,2,0)),"_PB|",(VLOOKUP(E338,Dictionary!$G:$H,2,0)),"_FM|",(VLOOKUP(F338,Dictionary!$S:$T,2,0)),"_RT|",(VLOOKUP(G338,Dictionary!$V:$W,2,0)),"_PD|",SUBSTITUTE(SUBSTITUTE(IF(H338="","NONE",H338),"_","-"),"|","-"),"_TG|",(VLOOKUP(I338,Dictionary!$J:$K,2,0)),"_ST|",(VLOOKUP(J338,Dictionary!$M:$N,2,0)),"_TS|",SUBSTITUTE(SUBSTITUTE(IF(K338="","NONE",K338),"_","-"),"|","-"),"_SZ|",(VLOOKUP(L338,Dictionary!$Y:$Z,1,0)),"_AD|",(VLOOKUP(M338,Dictionary!$AB:$AC,2,0)),"_IT|",(VLOOKUP(N338,Dictionary!$BC:$BD,2,0)),IF(O338="","",CONCATENATE("_U1|",SUBSTITUTE(SUBSTITUTE(O338,"_","-"),"|","-"))),IF(P338="","",CONCATENATE("_U2|",SUBSTITUTE(SUBSTITUTE(P338,"_","-"),"|","-"))),IF(Q338="","",CONCATENATE("_U3|",SUBSTITUTE(SUBSTITUTE(Q338,"_","-"),"|","-"))))) -> #N/A
R339: =IF(K339="----","#N/A",CONCATENATE("MK|",(VLOOKUP(B339,Dictionary!$A:$B,2,0)),"_CH|",(VLOOKUP(C339,Dictionary!$AV:$AW,2,0)),"_DT|",(VLOOKUP(D339,Dictionary!$P:$Q,2,0)),"_PB|",(VLOOKUP(E339,Dictionary!$G:$H,2,0)),"_FM|",(VLOOKUP(F339,Dictionary!$S:$T,2,0)),"_RT|",(VLOOKUP(G339,Dictionary!$V:$W,2,0)),"_PD|",SUBSTITUTE(SUBSTITUTE(IF(H339="","NONE",H339),"_","-"),"|","-"),"_TG|",(VLOOKUP(I339,Dictionary!$J:$K,2,0)),"_ST|",(VLOOKUP(J339,Dictionary!$M:$N,2,0)),"_TS|",SUBSTITUTE(SUBSTITUTE(IF(K339="","NONE",K339),"_","-"),"|","-"),"_SZ|",(VLOOKUP(L339,Dictionary!$Y:$Z,1,0)),"_AD|",(VLOOKUP(M339,Dictionary!$AB:$AC,2,0)),"_IT|",(VLOOKUP(N339,Dictionary!$BC:$BD,2,0)),IF(O339="","",CONCATENATE("_U1|",SUBSTITUTE(SUBSTITUTE(O339,"_","-"),"|","-"))),IF(P339="","",CONCATENATE("_U2|",SUBSTITUTE(SUBSTITUTE(P339,"_","-"),"|","-"))),IF(Q339="","",CONCATENATE("_U3|",SUBSTITUTE(SUBSTITUTE(Q339,"_","-"),"|","-"))))) -> #N/A
R340: =IF(K340="----","#N/A",CONCATENATE("MK|",(VLOOKUP(B340,Dictionary!$A:$B,2,0)),"_CH|",(VLOOKUP(C340,Dictionary!$AV:$AW,2,0)),"_DT|",(VLOOKUP(D340,Dictionary!$P:$Q,2,0)),"_PB|",(VLOOKUP(E340,Dictionary!$G:$H,2,0)),"_FM|",(VLOOKUP(F340,Dictionary!$S:$T,2,0)),"_RT|",(VLOOKUP(G340,Dictionary!$V:$W,2,0)),"_PD|",SUBSTITUTE(SUBSTITUTE(IF(H340="","NONE",H340),"_","-"),"|","-"),"_TG|",(VLOOKUP(I340,Dictionary!$J:$K,2,0)),"_ST|",(VLOOKUP(J340,Dictionary!$M:$N,2,0)),"_TS|",SUBSTITUTE(SUBSTITUTE(IF(K340="","NONE",K340),"_","-"),"|","-"),"_SZ|",(VLOOKUP(L340,Dictionary!$Y:$Z,1,0)),"_AD|",(VLOOKUP(M340,Dictionary!$AB:$AC,2,0)),"_IT|",(VLOOKUP(N340,Dictionary!$BC:$BD,2,0)),IF(O340="","",CONCATENATE("_U1|",SUBSTITUTE(SUBSTITUTE(O340,"_","-"),"|","-"))),IF(P340="","",CONCATENATE("_U2|",SUBSTITUTE(SUBSTITUTE(P340,"_","-"),"|","-"))),IF(Q340="","",CONCATENATE("_U3|",SUBSTITUTE(SUBSTITUTE(Q340,"_","-"),"|","-"))))) -> #N/A
R341: =IF(K341="----","#N/A",CONCATENATE("MK|",(VLOOKUP(B341,Dictionary!$A:$B,2,0)),"_CH|",(VLOOKUP(C341,Dictionary!$AV:$AW,2,0)),"_DT|",(VLOOKUP(D341,Dictionary!$P:$Q,2,0)),"_PB|",(VLOOKUP(E341,Dictionary!$G:$H,2,0)),"_FM|",(VLOOKUP(F341,Dictionary!$S:$T,2,0)),"_RT|",(VLOOKUP(G341,Dictionary!$V:$W,2,0)),"_PD|",SUBSTITUTE(SUBSTITUTE(IF(H341="","NONE",H341),"_","-"),"|","-"),"_TG|",(VLOOKUP(I341,Dictionary!$J:$K,2,0)),"_ST|",(VLOOKUP(J341,Dictionary!$M:$N,2,0)),"_TS|",SUBSTITUTE(SUBSTITUTE(IF(K341="","NONE",K341),"_","-"),"|","-"),"_SZ|",(VLOOKUP(L341,Dictionary!$Y:$Z,1,0)),"_AD|",(VLOOKUP(M341,Dictionary!$AB:$AC,2,0)),"_IT|",(VLOOKUP(N341,Dictionary!$BC:$BD,2,0)),IF(O341="","",CONCATENATE("_U1|",SUBSTITUTE(SUBSTITUTE(O341,"_","-"),"|","-"))),IF(P341="","",CONCATENATE("_U2|",SUBSTITUTE(SUBSTITUTE(P341,"_","-"),"|","-"))),IF(Q341="","",CONCATENATE("_U3|",SUBSTITUTE(SUBSTITUTE(Q341,"_","-"),"|","-"))))) -> #N/A
R342: =IF(K342="----","#N/A",CONCATENATE("MK|",(VLOOKUP(B342,Dictionary!$A:$B,2,0)),"_CH|",(VLOOKUP(C342,Dictionary!$AV:$AW,2,0)),"_DT|",(VLOOKUP(D342,Dictionary!$P:$Q,2,0)),"_PB|",(VLOOKUP(E342,Dictionary!$G:$H,2,0)),"_FM|",(VLOOKUP(F342,Dictionary!$S:$T,2,0)),"_RT|",(VLOOKUP(G342,Dictionary!$V:$W,2,0)),"_PD|",SUBSTITUTE(SUBSTITUTE(IF(H342="","NONE",H342),"_","-"),"|","-"),"_TG|",(VLOOKUP(I342,Dictionary!$J:$K,2,0)),"_ST|",(VLOOKUP(J342,Dictionary!$M:$N,2,0)),"_TS|",SUBSTITUTE(SUBSTITUTE(IF(K342="","NONE",K342),"_","-"),"|","-"),"_SZ|",(VLOOKUP(L342,Dictionary!$Y:$Z,1,0)),"_AD|",(VLOOKUP(M342,Dictionary!$AB:$AC,2,0)),"_IT|",(VLOOKUP(N342,Dictionary!$BC:$BD,2,0)),IF(O342="","",CONCATENATE("_U1|",SUBSTITUTE(SUBSTITUTE(O342,"_","-"),"|","-"))),IF(P342="","",CONCATENATE("_U2|",SUBSTITUTE(SUBSTITUTE(P342,"_","-"),"|","-"))),IF(Q342="","",CONCATENATE("_U3|",SUBSTITUTE(SUBSTITUTE(Q342,"_","-"),"|","-"))))) -> #N/A
R343: =IF(K343="----","#N/A",CONCATENATE("MK|",(VLOOKUP(B343,Dictionary!$A:$B,2,0)),"_CH|",(VLOOKUP(C343,Dictionary!$AV:$AW,2,0)),"_DT|",(VLOOKUP(D343,Dictionary!$P:$Q,2,0)),"_PB|",(VLOOKUP(E343,Dictionary!$G:$H,2,0)),"_FM|",(VLOOKUP(F343,Dictionary!$S:$T,2,0)),"_RT|",(VLOOKUP(G343,Dictionary!$V:$W,2,0)),"_PD|",SUBSTITUTE(SUBSTITUTE(IF(H343="","NONE",H343),"_","-"),"|","-"),"_TG|",(VLOOKUP(I343,Dictionary!$J:$K,2,0)),"_ST|",(VLOOKUP(J343,Dictionary!$M:$N,2,0)),"_TS|",SUBSTITUTE(SUBSTITUTE(IF(K343="","NONE",K343),"_","-"),"|","-"),"_SZ|",(VLOOKUP(L343,Dictionary!$Y:$Z,1,0)),"_AD|",(VLOOKUP(M343,Dictionary!$AB:$AC,2,0)),"_IT|",(VLOOKUP(N343,Dictionary!$BC:$BD,2,0)),IF(O343="","",CONCATENATE("_U1|",SUBSTITUTE(SUBSTITUTE(O343,"_","-"),"|","-"))),IF(P343="","",CONCATENATE("_U2|",SUBSTITUTE(SUBSTITUTE(P343,"_","-"),"|","-"))),IF(Q343="","",CONCATENATE("_U3|",SUBSTITUTE(SUBSTITUTE(Q343,"_","-"),"|","-"))))) -> #N/A
R344: =IF(K344="----","#N/A",CONCATENATE("MK|",(VLOOKUP(B344,Dictionary!$A:$B,2,0)),"_CH|",(VLOOKUP(C344,Dictionary!$AV:$AW,2,0)),"_DT|",(VLOOKUP(D344,Dictionary!$P:$Q,2,0)),"_PB|",(VLOOKUP(E344,Dictionary!$G:$H,2,0)),"_FM|",(VLOOKUP(F344,Dictionary!$S:$T,2,0)),"_RT|",(VLOOKUP(G344,Dictionary!$V:$W,2,0)),"_PD|",SUBSTITUTE(SUBSTITUTE(IF(H344="","NONE",H344),"_","-"),"|","-"),"_TG|",(VLOOKUP(I344,Dictionary!$J:$K,2,0)),"_ST|",(VLOOKUP(J344,Dictionary!$M:$N,2,0)),"_TS|",SUBSTITUTE(SUBSTITUTE(IF(K344="","NONE",K344),"_","-"),"|","-"),"_SZ|",(VLOOKUP(L344,Dictionary!$Y:$Z,1,0)),"_AD|",(VLOOKUP(M344,Dictionary!$AB:$AC,2,0)),"_IT|",(VLOOKUP(N344,Dictionary!$BC:$BD,2,0)),IF(O344="","",CONCATENATE("_U1|",SUBSTITUTE(SUBSTITUTE(O344,"_","-"),"|","-"))),IF(P344="","",CONCATENATE("_U2|",SUBSTITUTE(SUBSTITUTE(P344,"_","-"),"|","-"))),IF(Q344="","",CONCATENATE("_U3|",SUBSTITUTE(SUBSTITUTE(Q344,"_","-"),"|","-"))))) -> #N/A
R345: =IF(K345="----","#N/A",CONCATENATE("MK|",(VLOOKUP(B345,Dictionary!$A:$B,2,0)),"_CH|",(VLOOKUP(C345,Dictionary!$AV:$AW,2,0)),"_DT|",(VLOOKUP(D345,Dictionary!$P:$Q,2,0)),"_PB|",(VLOOKUP(E345,Dictionary!$G:$H,2,0)),"_FM|",(VLOOKUP(F345,Dictionary!$S:$T,2,0)),"_RT|",(VLOOKUP(G345,Dictionary!$V:$W,2,0)),"_PD|",SUBSTITUTE(SUBSTITUTE(IF(H345="","NONE",H345),"_","-"),"|","-"),"_TG|",(VLOOKUP(I345,Dictionary!$J:$K,2,0)),"_ST|",(VLOOKUP(J345,Dictionary!$M:$N,2,0)),"_TS|",SUBSTITUTE(SUBSTITUTE(IF(K345="","NONE",K345),"_","-"),"|","-"),"_SZ|",(VLOOKUP(L345,Dictionary!$Y:$Z,1,0)),"_AD|",(VLOOKUP(M345,Dictionary!$AB:$AC,2,0)),"_IT|",(VLOOKUP(N345,Dictionary!$BC:$BD,2,0)),IF(O345="","",CONCATENATE("_U1|",SUBSTITUTE(SUBSTITUTE(O345,"_","-"),"|","-"))),IF(P345="","",CONCATENATE("_U2|",SUBSTITUTE(SUBSTITUTE(P345,"_","-"),"|","-"))),IF(Q345="","",CONCATENATE("_U3|",SUBSTITUTE(SUBSTITUTE(Q345,"_","-"),"|","-"))))) -> #N/A
R346: =IF(K346="----","#N/A",CONCATENATE("MK|",(VLOOKUP(B346,Dictionary!$A:$B,2,0)),"_CH|",(VLOOKUP(C346,Dictionary!$AV:$AW,2,0)),"_DT|",(VLOOKUP(D346,Dictionary!$P:$Q,2,0)),"_PB|",(VLOOKUP(E346,Dictionary!$G:$H,2,0)),"_FM|",(VLOOKUP(F346,Dictionary!$S:$T,2,0)),"_RT|",(VLOOKUP(G346,Dictionary!$V:$W,2,0)),"_PD|",SUBSTITUTE(SUBSTITUTE(IF(H346="","NONE",H346),"_","-"),"|","-"),"_TG|",(VLOOKUP(I346,Dictionary!$J:$K,2,0)),"_ST|",(VLOOKUP(J346,Dictionary!$M:$N,2,0)),"_TS|",SUBSTITUTE(SUBSTITUTE(IF(K346="","NONE",K346),"_","-"),"|","-"),"_SZ|",(VLOOKUP(L346,Dictionary!$Y:$Z,1,0)),"_AD|",(VLOOKUP(M346,Dictionary!$AB:$AC,2,0)),"_IT|",(VLOOKUP(N346,Dictionary!$BC:$BD,2,0)),IF(O346="","",CONCATENATE("_U1|",SUBSTITUTE(SUBSTITUTE(O346,"_","-"),"|","-"))),IF(P346="","",CONCATENATE("_U2|",SUBSTITUTE(SUBSTITUTE(P346,"_","-"),"|","-"))),IF(Q346="","",CONCATENATE("_U3|",SUBSTITUTE(SUBSTITUTE(Q346,"_","-"),"|","-"))))) -> #N/A
R347: =IF(K347="----","#N/A",CONCATENATE("MK|",(VLOOKUP(B347,Dictionary!$A:$B,2,0)),"_CH|",(VLOOKUP(C347,Dictionary!$AV:$AW,2,0)),"_DT|",(VLOOKUP(D347,Dictionary!$P:$Q,2,0)),"_PB|",(VLOOKUP(E347,Dictionary!$G:$H,2,0)),"_FM|",(VLOOKUP(F347,Dictionary!$S:$T,2,0)),"_RT|",(VLOOKUP(G347,Dictionary!$V:$W,2,0)),"_PD|",SUBSTITUTE(SUBSTITUTE(IF(H347="","NONE",H347),"_","-"),"|","-"),"_TG|",(VLOOKUP(I347,Dictionary!$J:$K,2,0)),"_ST|",(VLOOKUP(J347,Dictionary!$M:$N,2,0)),"_TS|",SUBSTITUTE(SUBSTITUTE(IF(K347="","NONE",K347),"_","-"),"|","-"),"_SZ|",(VLOOKUP(L347,Dictionary!$Y:$Z,1,0)),"_AD|",(VLOOKUP(M347,Dictionary!$AB:$AC,2,0)),"_IT|",(VLOOKUP(N347,Dictionary!$BC:$BD,2,0)),IF(O347="","",CONCATENATE("_U1|",SUBSTITUTE(SUBSTITUTE(O347,"_","-"),"|","-"))),IF(P347="","",CONCATENATE("_U2|",SUBSTITUTE(SUBSTITUTE(P347,"_","-"),"|","-"))),IF(Q347="","",CONCATENATE("_U3|",SUBSTITUTE(SUBSTITUTE(Q347,"_","-"),"|","-"))))) -> #N/A
R348: =IF(K348="----","#N/A",CONCATENATE("MK|",(VLOOKUP(B348,Dictionary!$A:$B,2,0)),"_CH|",(VLOOKUP(C348,Dictionary!$AV:$AW,2,0)),"_DT|",(VLOOKUP(D348,Dictionary!$P:$Q,2,0)),"_PB|",(VLOOKUP(E348,Dictionary!$G:$H,2,0)),"_FM|",(VLOOKUP(F348,Dictionary!$S:$T,2,0)),"_RT|",(VLOOKUP(G348,Dictionary!$V:$W,2,0)),"_PD|",SUBSTITUTE(SUBSTITUTE(IF(H348="","NONE",H348),"_","-"),"|","-"),"_TG|",(VLOOKUP(I348,Dictionary!$J:$K,2,0)),"_ST|",(VLOOKUP(J348,Dictionary!$M:$N,2,0)),"_TS|",SUBSTITUTE(SUBSTITUTE(IF(K348="","NONE",K348),"_","-"),"|","-"),"_SZ|",(VLOOKUP(L348,Dictionary!$Y:$Z,1,0)),"_AD|",(VLOOKUP(M348,Dictionary!$AB:$AC,2,0)),"_IT|",(VLOOKUP(N348,Dictionary!$BC:$BD,2,0)),IF(O348="","",CONCATENATE("_U1|",SUBSTITUTE(SUBSTITUTE(O348,"_","-"),"|","-"))),IF(P348="","",CONCATENATE("_U2|",SUBSTITUTE(SUBSTITUTE(P348,"_","-"),"|","-"))),IF(Q348="","",CONCATENATE("_U3|",SUBSTITUTE(SUBSTITUTE(Q348,"_","-"),"|","-"))))) -> #N/A
R349: =IF(K349="----","#N/A",CONCATENATE("MK|",(VLOOKUP(B349,Dictionary!$A:$B,2,0)),"_CH|",(VLOOKUP(C349,Dictionary!$AV:$AW,2,0)),"_DT|",(VLOOKUP(D349,Dictionary!$P:$Q,2,0)),"_PB|",(VLOOKUP(E349,Dictionary!$G:$H,2,0)),"_FM|",(VLOOKUP(F349,Dictionary!$S:$T,2,0)),"_RT|",(VLOOKUP(G349,Dictionary!$V:$W,2,0)),"_PD|",SUBSTITUTE(SUBSTITUTE(IF(H349="","NONE",H349),"_","-"),"|","-"),"_TG|",(VLOOKUP(I349,Dictionary!$J:$K,2,0)),"_ST|",(VLOOKUP(J349,Dictionary!$M:$N,2,0)),"_TS|",SUBSTITUTE(SUBSTITUTE(IF(K349="","NONE",K349),"_","-"),"|","-"),"_SZ|",(VLOOKUP(L349,Dictionary!$Y:$Z,1,0)),"_AD|",(VLOOKUP(M349,Dictionary!$AB:$AC,2,0)),"_IT|",(VLOOKUP(N349,Dictionary!$BC:$BD,2,0)),IF(O349="","",CONCATENATE("_U1|",SUBSTITUTE(SUBSTITUTE(O349,"_","-"),"|","-"))),IF(P349="","",CONCATENATE("_U2|",SUBSTITUTE(SUBSTITUTE(P349,"_","-"),"|","-"))),IF(Q349="","",CONCATENATE("_U3|",SUBSTITUTE(SUBSTITUTE(Q349,"_","-"),"|","-"))))) -> #N/A
... R792: =IF(K792="----","#N/A",CONCATENATE("MK|",(VLOOKUP(B792,Dictionary!$A:$B,2,0)),"_CH|",(VLOOKUP(C792,Dictionary!$AV:$AW,2,0)),"_DT|",(VLOOKUP(D792,Dictionary!$P:$Q,2,0)),"_PB|",(VLOOKUP(E792,Dictionary!$G:$H,2,0)),"_FM|",(VLOOKUP(F792,Dictionary!$S:$T,2,0)),"_RT|",(VLOOKUP(G792,Dictionary!$V:$W,2,0)),"_PD|",SUBSTITUTE(SUBSTITUTE(IF(H792="","NONE",H792),"_","-"),"|","-"),"_TG|",(VLOOKUP(I792,Dictionary!$J:$K,2,0)),"_ST|",(VLOOKUP(J792,Dictionary!$M:$N,2,0)),"_TS|",SUBSTITUTE(SUBSTITUTE(IF(K792="","NONE",K792),"_","-"),"|","-"),"_SZ|",(VLOOKUP(L792,Dictionary!$Y:$Z,1,0)),"_AD|",(VLOOKUP(M792,Dictionary!$AB:$AC,2,0)),"_IT|",(VLOOKUP(N792,Dictionary!$BC:$BD,2,0)),IF(O792="","",CONCATENATE("_U1|",SUBSTITUTE(SUBSTITUTE(O792,"_","-"),"|","-"))),IF(P792="","",CONCATENATE("_U2|",SUBSTITUTE(SUBSTITUTE(P792,"_","-"),"|","-"))),IF(Q792="","",CONCATENATE("_U3|",SUBSTITUTE(SUBSTITUTE(Q792,"_","-"),"|","-"))))) -> #N/A

Sheet Creative Name
B1: Mandatory Fields | E1: Optional Fields | H1: CRIATIVE NAME
A2: ID | B2: Creative Name (FF) | C2: Creative Exec(List) | D2: Creative Asset Type(List) | E2: U1 | F2: U2 | G2: U3
B3: DOTZ-10MIL | C3: 627x627 | D3: Native | H3: =IF(C3="----","#N/A",CONCATENATE("CV|",SUBSTITUTE(SUBSTITUTE(IF(B3="","NONE",B3),"_","-"),"|","-"),"_","CS|",(VLOOKUP(C3,Dictionary!$Y:$Z,2,FALSE)),"_","CT|",(VLOOKUP(D3,Dictionary!$AE:$AF,2,FALSE)),IF(E3="","",CONCATENATE("_U1|",SUBSTITUTE(SUBSTITUTE(E3,"_","-"),"|","-"))),IF(F3="","",CONCATENATE("_U2|",SUBSTITUTE(SUBSTITUTE(F3,"_","-"),"|","-"))),IF(G3="","",CONCATENATE("_U3|",SUBSTITUTE(SUBSTITUTE(G3,"_","-"),"|","-"))))) -> CV|DOTZ-10MIL_CS|627x627_CT|NAT
B4: DOTZ-TAXA-ZERO | C4: 627x627 | D4: Native | H4: =IF(C4="----","#N/A",CONCATENATE("CV|",SUBSTITUTE(SUBSTITUTE(IF(B4="","NONE",B4),"_","-"),"|","-"),"_","CS|",(VLOOKUP(C4,Dictionary!$Y:$Z,2,FALSE)),"_","CT|",(VLOOKUP(D4,Dictionary!$AE:$AF,2,FALSE)),IF(E4="","",CONCATENATE("_U1|",SUBSTITUTE(SUBSTITUTE(E4,"_","-"),"|","-"))),IF(F4="","",CONCATENATE("_U2|",SUBSTITUTE(SUBSTITUTE(F4,"_","-"),"|","-"))),IF(G4="","",CONCATENATE("_U3|",SUBSTITUTE(SUBSTITUTE(G4,"_","-"),"|","-"))))) -> CV|DOTZ-TAXA-ZERO_CS|627x627_CT|NAT
B5: DOTZ-10MIL-AZUL | C5: 1X1 | D5: FB Link Ad | H5: =IF(C5="----","#N/A",CONCATENATE("CV|",SUBSTITUTE(SUBSTITUTE(IF(B5="","NONE",B5),"_","-"),"|","-"),"_","CS|",(VLOOKUP(C5,Dictionary!$Y:$Z,2,FALSE)),"_","CT|",(VLOOKUP(D5,Dictionary!$AE:$AF,2,FALSE)),IF(E5="","",CONCATENATE("_U1|",SUBSTITUTE(SUBSTITUTE(E5,"_","-"),"|","-"))),IF(F5="","",CONCATENATE("_U2|",SUBSTITUTE(SUBSTITUTE(F5,"_","-"),"|","-"))),IF(G5="","",CONCATENATE("_U3|",SUBSTITUTE(SUBSTITUTE(G5,"_","-"),"|","-"))))) -> CV|DOTZ-10MIL-AZUL_CS|1x1_CT|FLA
B6: DOTZ-10MIL-AZUL-QUAD | C6: 1X1 | D6: FB Link Ad | H6: =IF(C6="----","#N/A",CONCATENATE("CV|",SUBSTITUTE(SUBSTITUTE(IF(B6="","NONE",B6),"_","-"),"|","-"),"_","CS|",(VLOOKUP(C6,Dictionary!$Y:$Z,2,FALSE)),"_","CT|",(VLOOKUP(D6,Dictionary!$AE:$AF,2,FALSE)),IF(E6="","",CONCATENATE("_U1|",SUBSTITUTE(SUBSTITUTE(E6,"_","-"),"|","-"))),IF(F6="","",CONCATENATE("_U2|",SUBSTITUTE(SUBSTITUTE(F6,"_","-"),"|","-"))),IF(G6="","",CONCATENATE("_U3|",SUBSTITUTE(SUBSTITUTE(G6,"_","-"),"|","-"))))) -> CV|DOTZ-10MIL-AZUL-QUAD_CS|1x1_CT|FLA
B7: DOTZ-10MIL-AZUL | C7: 1X1 | D7: FB Gif | H7: =IF(C7="----","#N/A",CONCATENATE("CV|",SUBSTITUTE(SUBSTITUTE(IF(B7="","NONE",B7),"_","-"),"|","-"),"_","CS|",(VLOOKUP(C7,Dictionary!$Y:$Z,2,FALSE)),"_","CT|",(VLOOKUP(D7,Dictionary!$AE:$AF,2,FALSE)),IF(E7="","",CONCATENATE("_U1|",SUBSTITUTE(SUBSTITUTE(E7,"_","-"),"|","-"))),IF(F7="","",CONCATENATE("_U2|",SUBSTITUTE(SUBSTITUTE(F7,"_","-"),"|","-"))),IF(G7="","",CONCATENATE("_U3|",SUBSTITUTE(SUBSTITUTE(G7,"_","-"),"|","-"))))) -> CV|DOTZ-10MIL-AZUL_CS|1x1_CT|FGIF
B8: DOTZ-10MIL-AZUL | C8: 1X1 | D8: FB Carousel | H8: =IF(C8="----","#N/A",CONCATENATE("CV|",SUBSTITUTE(SUBSTITUTE(IF(B8="","NONE",B8),"_","-"),"|","-"),"_","CS|",(VLOOKUP(C8,Dictionary!$Y:$Z,2,FALSE)),"_","CT|",(VLOOKUP(D8,Dictionary!$AE:$AF,2,FALSE)),IF(E8="","",CONCATENATE("_U1|",SUBSTITUTE(SUBSTITUTE(E8,"_","-"),"|","-"))),IF(F8="","",CONCATENATE("_U2|",SUBSTITUTE(SUBSTITUTE(F8,"_","-"),"|","-"))),IF(G8="","",CONCATENATE("_U3|",SUBSTITUTE(SUBSTITUTE(G8,"_","-"),"|","-"))))) -> CV|DOTZ-10MIL-AZUL_CS|1x1_CT|FCR
B9: DOTZ-10MIL-AZUL-CAR | C9: 1X1 | D9: IG Story | H9: =IF(C9="----","#N/A",CONCATENATE("CV|",SUBSTITUTE(SUBSTITUTE(IF(B9="","NONE",B9),"_","-"),"|","-"),"_","CS|",(VLOOKUP(C9,Dictionary!$Y:$Z,2,FALSE)),"_","CT|",(VLOOKUP(D9,Dictionary!$AE:$AF,2,FALSE)),IF(E9="","",CONCATENATE("_U1|",SUBSTITUTE(SUBSTITUTE(E9,"_","-"),"|","-"))),IF(F9="","",CONCATENATE("_U2|",SUBSTITUTE(SUBSTITUTE(F9,"_","-"),"|","-"))),IF(G9="","",CONCATENATE("_U3|",SUBSTITUTE(SUBSTITUTE(G9,"_","-"),"|","-"))))) -> CV|DOTZ-10MIL-AZUL-CAR_CS|1x1_CT|INSSTORY
B10: DOTZ-ZERO-ANUIDADE-AZUL | C10: 1X1 | D10: FB Link Ad | H10: =IF(C10="----","#N/A",CONCATENATE("CV|",SUBSTITUTE(SUBSTITUTE(IF(B10="","NONE",B10),"_","-"),"|","-"),"_","CS|",(VLOOKUP(C10,Dictionary!$Y:$Z,2,FALSE)),"_","CT|",(VLOOKUP(D10,Dictionary!$AE:$AF,2,FALSE)),IF(E10="","",CONCATENATE("_U1|",SUBSTITUTE(SUBSTITUTE(E10,"_","-"),"|","-"))),IF(F10="","",CONCATENATE("_U2|",SUBSTITUTE(SUBSTITUTE(F10,"_","-"),"|","-"))),IF(G10="","",CONCATENATE("_U3|",SUBSTITUTE(SUBSTITUTE(G10,"_","-"),"|","-"))))) -> CV|DOTZ-ZERO-ANUIDADE-AZUL_CS|1x1_CT|FLA
B11: DOTZ-ZERO-ANUIDADE-AZUL-QUAD | C11: 1X1 | D11: FB Link Ad | H11: =IF(C11="----","#N/A",CONCATENATE("CV|",SUBSTITUTE(SUBSTITUTE(IF(B11="","NONE",B11),"_","-"),"|","-"),"_","CS|",(VLOOKUP(C11,Dictionary!$Y:$Z,2,FALSE)),"_","CT|",(VLOOKUP(D11,Dictionary!$AE:$AF,2,FALSE)),IF(E11="","",CONCATENATE("_U1|",SUBSTITUTE(SUBSTITUTE(E11,"_","-"),"|","-"))),IF(F11="","",CONCATENATE("_U2|",SUBSTITUTE(SUBSTITUTE(F11,"_","-"),"|","-"))),IF(G11="","",CONCATENATE("_U3|",SUBSTITUTE(SUBSTITUTE(G11,"_","-"),"|","-"))))) -> CV|DOTZ-ZERO-ANUIDADE-AZUL-QUAD_CS|1x1_CT|FLA
B12: DOTZ-ZERO-ANUIDADE-AZUL | C12: 1X1 | D12: FB Gif | H12: =IF(C12="----","#N/A",CONCATENATE("CV|",SUBSTITUTE(SUBSTITUTE(IF(B12="","NONE",B12),"_","-"),"|","-"),"_","CS|",(VLOOKUP(C12,Dictionary!$Y:$Z,2,FALSE)),"_","CT|",(VLOOKUP(D12,Dictionary!$AE:$AF,2,FALSE)),IF(E12="","",CONCATENATE("_U1|",SUBSTITUTE(SUBSTITUTE(E12,"_","-"),"|","-"))),IF(F12="","",CONCATENATE("_U2|",SUBSTITUTE(SUBSTITUTE(F12,"_","-"),"|","-"))),IF(G12="","",CONCATENATE("_U3|",SUBSTITUTE(SUBSTITUTE(G12,"_","-"),"|","-"))))) -> CV|DOTZ-ZERO-ANUIDADE-AZUL_CS|1x1_CT|FGIF
B13: DOTZ-ZERO-ANUIDADE-AZUL | C13: 1X1 | D13: FB Carousel | H13: =IF(C13="----","#N/A",CONCATENATE("CV|",SUBSTITUTE(SUBSTITUTE(IF(B13="","NONE",B13),"_","-"),"|","-"),"_","CS|",(VLOOKUP(C13,Dictionary!$Y:$Z,2,FALSE)),"_","CT|",(VLOOKUP(D13,Dictionary!$AE:$AF,2,FALSE)),IF(E13="","",CONCATENATE("_U1|",SUBSTITUTE(SUBSTITUTE(E13,"_","-"),"|","-"))),IF(F13="","",CONCATENATE("_U2|",SUBSTITUTE(SUBSTITUTE(F13,"_","-"),"|","-"))),IF(G13="","",CONCATENATE("_U3|",SUBSTITUTE(SUBSTITUTE(G13,"_","-"),"|","-"))))) -> CV|DOTZ-ZERO-ANUIDADE-AZUL_CS|1x1_CT|FCR
B14: DOTZ-ZERO-ANUIDADE-AZUL-CAR | C14: 1X1 | D14: IG Story | H14: =IF(C14="----","#N/A",CONCATENATE("CV|",SUBSTITUTE(SUBSTITUTE(IF(B14="","NONE",B14),"_","-"),"|","-"),"_","CS|",(VLOOKUP(C14,Dictionary!$Y:$Z,2,FALSE)),"_","CT|",(VLOOKUP(D14,Dictionary!$AE:$AF,2,FALSE)),IF(E14="","",CONCATENATE("_U1|",SUBSTITUTE(SUBSTITUTE(E14,"_","-"),"|","-"))),IF(F14="","",CONCATENATE("_U2|",SUBSTITUTE(SUBSTITUTE(F14,"_","-"),"|","-"))),IF(G14="","",CONCATENATE("_U3|",SUBSTITUTE(SUBSTITUTE(G14,"_","-"),"|","-"))))) -> CV|DOTZ-ZERO-ANUIDADE-AZUL-CAR_CS|1x1_CT|INSSTORY
... B46: DOTZ-10MIL-AZUL | C46: 1X1 | D46: IG Story | H46: =IF(C46="----","#N/A",CONCATENATE("CV|",SUBSTITUTE(SUBSTITUTE(IF(B46="","NONE",B46),"_","-"),"|","-"),"_","CS|",(VLOOKUP(C46,Dictionary!$Y:$Z,2,FALSE)),"_","CT|",(VLOOKUP(D46,Dictionary!$AE:$AF,2,FALSE)),IF(E46="","",CONCATENATE("_U1|",SUBSTITUTE(SUBSTITUTE(E46,"_","-"),"|","-"))),IF(F46="","",CONCATENATE("_U2|",SUBSTITUTE(SUBSTITUTE(F46,"_","-"),"|","-"))),IF(G46="","",CONCATENATE("_U3|",SUBSTITUTE(SUBSTITUTE(G46,"_","-"),"|","-"))))) -> CV|DOTZ-10MIL-AZUL_CS|1x1_CT|INSSTORY
B47: DOTZ-10MIL-AZUL | C47: 1X1 | D47: FB Carousel | E47: ESTATICO | H47: =IF(C47="----","#N/A",CONCATENATE("CV|",SUBSTITUTE(SUBSTITUTE(IF(B47="","NONE",B47),"_","-"),"|","-"),"_","CS|",(VLOOKUP(C47,Dictionary!$Y:$Z,2,FALSE)),"_","CT|",(VLOOKUP(D47,Dictionary!$AE:$AF,2,FALSE)),IF(E47="","",CONCATENATE("_U1|",SUBSTITUTE(SUBSTITUTE(E47,"_","-"),"|","-"))),IF(F47="","",CONCATENATE("_U2|",SUBSTITUTE(SUBSTITUTE(F47,"_","-"),"|","-"))),IF(G47="","",CONCATENATE("_U3|",SUBSTITUTE(SUBSTITUTE(G47,"_","-"),"|","-"))))) -> CV|DOTZ-10MIL-AZUL_CS|1x1_CT|FCR_U1|ESTATICO
B48: DOTZ-ZERO-ANUIDADE-AZUL | C48: 1X1 | D48: FB Carousel | E48: ESTATICO | H48: =IF(C48="----","#N/A",CONCATENATE("CV|",SUBSTITUTE(SUBSTITUTE(IF(B48="","NONE",B48),"_","-"),"|","-"),"_","CS|",(VLOOKUP(C48,Dictionary!$Y:$Z,2,FALSE)),"_","CT|",(VLOOKUP(D48,Dictionary!$AE:$AF,2,FALSE)),IF(E48="","",CONCATENATE("_U1|",SUBSTITUTE(SUBSTITUTE(E48,"_","-"),"|","-"))),IF(F48="","",CONCATENATE("_U2|",SUBSTITUTE(SUBSTITUTE(F48,"_","-"),"|","-"))),IF(G48="","",CONCATENATE("_U3|",SUBSTITUTE(SUBSTITUTE(G48,"_","-"),"|","-"))))) -> CV|DOTZ-ZERO-ANUIDADE-AZUL_CS|1x1_CT|FCR_U1|ESTATICO
B49: DOTZ-TODOS-BENEFICIOS-AZUL | C49: 1X1 | D49: FB Carousel | E49: ESTATICO | H49: =IF(C49="----","#N/A",CONCATENATE("CV|",SUBSTITUTE(SUBSTITUTE(IF(B49="","NONE",B49),"_","-"),"|","-"),"_","CS|",(VLOOKUP(C49,Dictionary!$Y:$Z,2,FALSE)),"_","CT|",(VLOOKUP(D49,Dictionary!$AE:$AF,2,FALSE)),IF(E49="","",CONCATENATE("_U1|",SUBSTITUTE(SUBSTITUTE(E49,"_","-"),"|","-"))),IF(F49="","",CONCATENATE("_U2|",SUBSTITUTE(SUBSTITUTE(F49,"_","-"),"|","-"))),IF(G49="","",CONCATENATE("_U3|",SUBSTITUTE(SUBSTITUTE(G49,"_","-"),"|","-"))))) -> CV|DOTZ-TODOS-BENEFICIOS-AZUL_CS|1x1_CT|FCR_U1|ESTATICO
B50: DOTZ-10MIL-AMARELO | C50: 1X1 | D50: FB Carousel | E50: ESTATICO | H50: =IF(C50="----","#N/A",CONCATENATE("CV|",SUBSTITUTE(SUBSTITUTE(IF(B50="","NONE",B50),"_","-"),"|","-"),"_","CS|",(VLOOKUP(C50,Dictionary!$Y:$Z,2,FALSE)),"_","CT|",(VLOOKUP(D50,Dictionary!$AE:$AF,2,FALSE)),IF(E50="","",CONCATENATE("_U1|",SUBSTITUTE(SUBSTITUTE(E50,"_","-"),"|","-"))),IF(F50="","",CONCATENATE("_U2|",SUBSTITUTE(SUBSTITUTE(F50,"_","-"),"|","-"))),IF(G50="","",CONCATENATE("_U3|",SUBSTITUTE(SUBSTITUTE(G50,"_","-"),"|","-"))))) -> CV|DOTZ-10MIL-AMARELO_CS|1x1_CT|FCR_U1|ESTATICO
B51: DOTZ-ZERO-ANUIDADE-AMARELO | C51: 1X1 | D51: FB Carousel | E51: ESTATICO | H51: =IF(C51="----","#N/A",CONCATENATE("CV|",SUBSTITUTE(SUBSTITUTE(IF(B51="","NONE",B51),"_","-"),"|","-"),"_","CS|",(VLOOKUP(C51,Dictionary!$Y:$Z,2,FALSE)),"_","CT|",(VLOOKUP(D51,Dictionary!$AE:$AF,2,FALSE)),IF(E51="","",CONCATENATE("_U1|",SUBSTITUTE(SUBSTITUTE(E51,"_","-"),"|","-"))),IF(F51="","",CONCATENATE("_U2|",SUBSTITUTE(SUBSTITUTE(F51,"_","-"),"|","-"))),IF(G51="","",CONCATENATE("_U3|",SUBSTITUTE(SUBSTITUTE(G51,"_","-"),"|","-"))))) -> CV|DOTZ-ZERO-ANUIDADE-AMARELO_CS|1x1_CT|FCR_U1|ESTATICO
B52: DOTZ-TODOS-BENEFICIOS-AMARELO | C52: 1X1 | D52: FB Carousel | E52: ESTATICO | H52: =IF(C52="----","#N/A",CONCATENATE("CV|",SUBSTITUTE(SUBSTITUTE(IF(B52="","NONE",B52),"_","-"),"|","-"),"_","CS|",(VLOOKUP(C52,Dictionary!$Y:$Z,2,FALSE)),"_","CT|",(VLOOKUP(D52,Dictionary!$AE:$AF,2,FALSE)),IF(E52="","",CONCATENATE("_U1|",SUBSTITUTE(SUBSTITUTE(E52,"_","-"),"|","-"))),IF(F52="","",CONCATENATE("_U2|",SUBSTITUTE(SUBSTITUTE(F52,"_","-"),"|","-"))),IF(G52="","",CONCATENATE("_U3|",SUBSTITUTE(SUBSTITUTE(G52,"_","-"),"|","-"))))) -> CV|DOTZ-TODOS-BENEFICIOS-AMARELO_CS|1x1_CT|FCR_U1|ESTATICO
B53: DOTZ-CONVERSAO-AMARELO | C53: 1X1 | D53: FB Carousel | E53: ESTATICO | H53: =IF(C53="----","#N/A",CONCATENATE("CV|",SUBSTITUTE(SUBSTITUTE(IF(B53="","NONE",B53),"_","-"),"|","-"),"_","CS|",(VLOOKUP(C53,Dictionary!$Y:$Z,2,FALSE)),"_","CT|",(VLOOKUP(D53,Dictionary!$AE:$AF,2,FALSE)),IF(E53="","",CONCATENATE("_U1|",SUBSTITUTE(SUBSTITUTE(E53,"_","-"),"|","-"))),IF(F53="","",CONCATENATE("_U2|",SUBSTITUTE(SUBSTITUTE(F53,"_","-"),"|","-"))),IF(G53="","",CONCATENATE("_U3|",SUBSTITUTE(SUBSTITUTE(G53,"_","-"),"|","-"))))) -> CV|DOTZ-CONVERSAO-AMARELO_CS|1x1_CT|FCR_U1|ESTATICO
B54: DOTZ-10MIL-AZUL | C54: 120x600 | D54: Creative asset built in HTML5 | H54: =IF(C54="----","#N/A",CONCATENATE("CV|",SUBSTITUTE(SUBSTITUTE(IF(B54="","NONE",B54),"_","-"),"|","-"),"_","CS|",(VLOOKUP(C54,Dictionary!$Y:$Z,2,FALSE)),"_","CT|",(VLOOKUP(D54,Dictionary!$AE:$AF,2,FALSE)),IF(E54="","",CONCATENATE("_U1|",SUBSTITUTE(SUBSTITUTE(E54,"_","-"),"|","-"))),IF(F54="","",CONCATENATE("_U2|",SUBSTITUTE(SUBSTITUTE(F54,"_","-"),"|","-"))),IF(G54="","",CONCATENATE("_U3|",SUBSTITUTE(SUBSTITUTE(G54,"_","-"),"|","-"))))) -> CV|DOTZ-10MIL-AZUL_CS|120x600_CT|HTML5
B55: DOTZ-10MIL-AZUL | C55: 160x600 | D55: Creative asset built in HTML5 | H55: =IF(C55="----","#N/A",CONCATENATE("CV|",SUBSTITUTE(SUBSTITUTE(IF(B55="","NONE",B55),"_","-"),"|","-"),"_","CS|",(VLOOKUP(C55,Dictionary!$Y:$Z,2,FALSE)),"_","CT|",(VLOOKUP(D55,Dictionary!$AE:$AF,2,FALSE)),IF(E55="","",CONCATENATE("_U1|",SUBSTITUTE(SUBSTITUTE(E55,"_","-"),"|","-"))),IF(F55="","",CONCATENATE("_U2|",SUBSTITUTE(SUBSTITUTE(F55,"_","-"),"|","-"))),IF(G55="","",CONCATENATE("_U3|",SUBSTITUTE(SUBSTITUTE(G55,"_","-"),"|","-"))))) -> CV|DOTZ-10MIL-AZUL_CS|160x600_CT|HTML5
B56: DOTZ-10MIL-AZUL | C56: 300x250 | D56: Creative asset built in HTML5 | H56: =IF(C56="----","#N/A",CONCATENATE("CV|",SUBSTITUTE(SUBSTITUTE(IF(B56="","NONE",B56),"_","-"),"|","-"),"_","CS|",(VLOOKUP(C56,Dictionary!$Y:$Z,2,FALSE)),"_","CT|",(VLOOKUP(D56,Dictionary!$AE:$AF,2,FALSE)),IF(E56="","",CONCATENATE("_U1|",SUBSTITUTE(SUBSTITUTE(E56,"_","-"),"|","-"))),IF(F56="","",CONCATENATE("_U2|",SUBSTITUTE(SUBSTITUTE(F56,"_","-"),"|","-"))),IF(G56="","",CONCATENATE("_U3|",SUBSTITUTE(SUBSTITUTE(G56,"_","-"),"|","-"))))) -> CV|DOTZ-10MIL-AZUL_CS|300x250_CT|HTML5
B57: DOTZ-10MIL-AZUL | C57: 300x600 | D57: Creative asset built in HTML5 | H57: =IF(C57="----","#N/A",CONCATENATE("CV|",SUBSTITUTE(SUBSTITUTE(IF(B57="","NONE",B57),"_","-"),"|","-"),"_","CS|",(VLOOKUP(C57,Dictionary!$Y:$Z,2,FALSE)),"_","CT|",(VLOOKUP(D57,Dictionary!$AE:$AF,2,FALSE)),IF(E57="","",CONCATENATE("_U1|",SUBSTITUTE(SUBSTITUTE(E57,"_","-"),"|","-"))),IF(F57="","",CONCATENATE("_U2|",SUBSTITUTE(SUBSTITUTE(F57,"_","-"),"|","-"))),IF(G57="","",CONCATENATE("_U3|",SUBSTITUTE(SUBSTITUTE(G57,"_","-"),"|","-"))))) -> CV|DOTZ-10MIL-AZUL_CS|300x600_CT|HTML5
B58: DOTZ-10MIL-AZUL | C58: 320x50 | D58: Creative asset built in HTML5 | H58: =IF(C58="----","#N/A",CONCATENATE("CV|",SUBSTITUTE(SUBSTITUTE(IF(B58="","NONE",B58),"_","-"),"|","-"),"_","CS|",(VLOOKUP(C58,Dictionary!$Y:$Z,2,FALSE)),"_","CT|",(VLOOKUP(D58,Dictionary!$AE:$AF,2,FALSE)),IF(E58="","",CONCATENATE("_U1|",SUBSTITUTE(SUBSTITUTE(E58,"_","-"),"|","-"))),IF(F58="","",CONCATENATE("_U2|",SUBSTITUTE(SUBSTITUTE(F58,"_","-"),"|","-"))),IF(G58="","",CONCATENATE("_U3|",SUBSTITUTE(SUBSTITUTE(G58,"_","-"),"|","-"))))) -> CV|DOTZ-10MIL-AZUL_CS|320x50_CT|HTML5
B59: DOTZ-10MIL-AZUL | C59: 320x100 | D59: Creative asset built in HTML5 | H59: =IF(C59="----","#N/A",CONCATENATE("CV|",SUBSTITUTE(SUBSTITUTE(IF(B59="","NONE",B59),"_","-"),"|","-"),"_","CS|",(VLOOKUP(C59,Dictionary!$Y:$Z,2,FALSE)),"_","CT|",(VLOOKUP(D59,Dictionary!$AE:$AF,2,FALSE)),IF(E59="","",CONCATENATE("_U1|",SUBSTITUTE(SUBSTITUTE(E59,"_","-"),"|","-"))),IF(F59="","",CONCATENATE("_U2|",SUBSTITUTE(SUBSTITUTE(F59,"_","-"),"|","-"))),IF(G59="","",CONCATENATE("_U3|",SUBSTITUTE(SUBSTITUTE(G59,"_","-"),"|","-"))))) -> CV|DOTZ-10MIL-AZUL_CS|320x100_CT|HTML5
B60: DOTZ-10MIL-AZUL | C60: 728x90 | D60: Creative asset built in HTML5 | H60: =IF(C60="----","#N/A",CONCATENATE("CV|",SUBSTITUTE(SUBSTITUTE(IF(B60="","NONE",B60),"_","-"),"|","-"),"_","CS|",(VLOOKUP(C60,Dictionary!$Y:$Z,2,FALSE)),"_","CT|",(VLOOKUP(D60,Dictionary!$AE:$AF,2,FALSE)),IF(E60="","",CONCATENATE("_U1|",SUBSTITUTE(SUBSTITUTE(E60,"_","-"),"|","-"))),IF(F60="","",CONCATENATE("_U2|",SUBSTITUTE(SUBSTITUTE(F60,"_","-"),"|","-"))),IF(G60="","",CONCATENATE("_U3|",SUBSTITUTE(SUBSTITUTE(G60,"_","-"),"|","-"))))) -> CV|DOTZ-10MIL-AZUL_CS|728x90_CT|HTML5
B61: DOTZ-ZERO-ANUIDADE-AZUL | C61: 120x600 | D61: Creative asset built in HTML5 | H61: =IF(C61="----","#N/A",CONCATENATE("CV|",SUBSTITUTE(SUBSTITUTE(IF(B61="","NONE",B61),"_","-"),"|","-"),"_","CS|",(VLOOKUP(C61,Dictionary!$Y:$Z,2,FALSE)),"_","CT|",(VLOOKUP(D61,Dictionary!$AE:$AF,2,FALSE)),IF(E61="","",CONCATENATE("_U1|",SUBSTITUTE(SUBSTITUTE(E61,"_","-"),"|","-"))),IF(F61="","",CONCATENATE("_U2|",SUBSTITUTE(SUBSTITUTE(F61,"_","-"),"|","-"))),IF(G61="","",CONCATENATE("_U3|",SUBSTITUTE(SUBSTITUTE(G61,"_","-"),"|","-"))))) -> CV|DOTZ-ZERO-ANUIDADE-AZUL_CS|120x600_CT|HTML5
B62: DOTZ-ZERO-ANUIDADE-AZUL | C62: 160x600 | D62: Creative asset built in HTML5 | H62: =IF(C62="----","#N/A",CONCATENATE("CV|",SUBSTITUTE(SUBSTITUTE(IF(B62="","NONE",B62),"_","-"),"|","-"),"_","CS|",(VLOOKUP(C62,Dictionary!$Y:$Z,2,FALSE)),"_","CT|",(VLOOKUP(D62,Dictionary!$AE:$AF,2,FALSE)),IF(E62="","",CONCATENATE("_U1|",SUBSTITUTE(SUBSTITUTE(E62,"_","-"),"|","-"))),IF(F62="","",CONCATENATE("_U2|",SUBSTITUTE(SUBSTITUTE(F62,"_","-"),"|","-"))),IF(G62="","",CONCATENATE("_U3|",SUBSTITUTE(SUBSTITUTE(G62,"_","-"),"|","-"))))) -> CV|DOTZ-ZERO-ANUIDADE-AZUL_CS|160x600_CT|HTML5
B63: DOTZ-ZERO-ANUIDADE-AZUL | C63: 300x250 | D63: Creative asset built in HTML5 | H63: =IF(C63="----","#N/A",CONCATENATE("CV|",SUBSTITUTE(SUBSTITUTE(IF(B63="","NONE",B63),"_","-"),"|","-"),"_","CS|",(VLOOKUP(C63,Dictionary!$Y:$Z,2,FALSE)),"_","CT|",(VLOOKUP(D63,Dictionary!$AE:$AF,2,FALSE)),IF(E63="","",CONCATENATE("_U1|",SUBSTITUTE(SUBSTITUTE(E63,"_","-"),"|","-"))),IF(F63="","",CONCATENATE("_U2|",SUBSTITUTE(SUBSTITUTE(F63,"_","-"),"|","-"))),IF(G63="","",CONCATENATE("_U3|",SUBSTITUTE(SUBSTITUTE(G63,"_","-"),"|","-"))))) -> CV|DOTZ-ZERO-ANUIDADE-AZUL_CS|300x250_CT|HTML5
B64: DOTZ-ZERO-ANUIDADE-AZUL | C64: 300x600 | D64: Creative asset built in HTML5 | H64: =IF(C64="----","#N/A",CONCATENATE("CV|",SUBSTITUTE(SUBSTITUTE(IF(B64="","NONE",B64),"_","-"),"|","-"),"_","CS|",(VLOOKUP(C64,Dictionary!$Y:$Z,2,FALSE)),"_","CT|",(VLOOKUP(D64,Dictionary!$AE:$AF,2,FALSE)),IF(E64="","",CONCATENATE("_U1|",SUBSTITUTE(SUBSTITUTE(E64,"_","-"),"|","-"))),IF(F64="","",CONCATENATE("_U2|",SUBSTITUTE(SUBSTITUTE(F64,"_","-"),"|","-"))),IF(G64="","",CONCATENATE("_U3|",SUBSTITUTE(SUBSTITUTE(G64,"_","-"),"|","-"))))) -> CV|DOTZ-ZERO-ANUIDADE-AZUL_CS|300x600_CT|HTML5
B65: DOTZ-ZERO-ANUIDADE-AZUL | C65: 320x50 | D65: Creative asset built in HTML5 | H65: =IF(C65="----","#N/A",CONCATENATE("CV|",SUBSTITUTE(SUBSTITUTE(IF(B65="","NONE",B65),"_","-"),"|","-"),"_","CS|",(VLOOKUP(C65,Dictionary!$Y:$Z,2,FALSE)),"_","CT|",(VLOOKUP(D65,Dictionary!$AE:$AF,2,FALSE)),IF(E65="","",CONCATENATE("_U1|",SUBSTITUTE(SUBSTITUTE(E65,"_","-"),"|","-"))),IF(F65="","",CONCATENATE("_U2|",SUBSTITUTE(SUBSTITUTE(F65,"_","-"),"|","-"))),IF(G65="","",CONCATENATE("_U3|",SUBSTITUTE(SUBSTITUTE(G65,"_","-"),"|","-"))))) -> CV|DOTZ-ZERO-ANUIDADE-AZUL_CS|320x50_CT|HTML5
... B131: DOTZ-DOLAR | C131: 1X1 | D131: IG Story | H131: =IF(C131="----","#N/A",CONCATENATE("CV|",SUBSTITUTE(SUBSTITUTE(IF(B131="","NONE",B131),"_","-"),"|","-"),"_","CS|",(VLOOKUP(C131,Dictionary!$Y:$Z,2,FALSE)),"_","CT|",(VLOOKUP(D131,Dictionary!$AE:$AF,2,FALSE)),IF(E131="","",CONCATENATE("_U1|",SUBSTITUTE(SUBSTITUTE(E131,"_","-"),"|","-"))),IF(F131="","",CONCATENATE("_U2|",SUBSTITUTE(SUBSTITUTE(F131,"_","-"),"|","-"))),IF(G131="","",CONCATENATE("_U3|",SUBSTITUTE(SUBSTITUTE(G131,"_","-"),"|","-"))))) -> CV|DOTZ-DOLAR_CS|1x1_CT|INSSTORY

Sheet Bruna Editing - Creative Name
B1: Mandatory Fields | E1: Optional Fields | H1: CAMPAIGN NAME
A2: ID | B2: Creative Name (FF) | C2: Creative Exec(List) | D2: Creative Asset Type(List) | E2: U1 | F2: U2 | G2: U3
A3: 235541867 | B3: VDV-MERCHANT-DECOLAR-15OFF | C3: 1X1 | D3: FB Link Ad | E3: FAMILIA-TRAPICHE | H3: =IF(C3="----","#N/A",CONCATENATE("CV|",SUBSTITUTE(SUBSTITUTE(IF(B3="","NONE",B3),"_","-"),"|","-"),"_","CS|",(VLOOKUP(C3,Dictionary!$Y:$Z,2,FALSE)),"_","CT|",(VLOOKUP(D3,Dictionary!$AE:$AF,2,FALSE)),IF(E3="","",CONCATENATE("_U1|",SUBSTITUTE(SUBSTITUTE(E3,"_","-"),"|","-"))),IF(F3="","",CONCATENATE("_U2|",SUBSTITUTE(SUBSTITUTE(F3,"_","-"),"|","-"))),IF(G3="","",CONCATENATE("_U3|",SUBSTITUTE(SUBSTITUTE(G3,"_","-"),"|","-"))))) -> CV|VDV-MERCHANT-DECOLAR-15OFF_CS|1x1_CT|FLA_U1|FAMILIA-TRAPICHE
A4: 239028840 | B4: VDV-MERCHANT-GOL-REDES-SOCIAIS | C4: 1X1 | D4: FB Carousel | H4: =IF(C4="----","#N/A",CONCATENATE("CV|",SUBSTITUTE(SUBSTITUTE(IF(B4="","NONE",B4),"_","-"),"|","-"),"_","CS|",(VLOOKUP(C4,Dictionary!$Y:$Z,2,FALSE)),"_","CT|",(VLOOKUP(D4,Dictionary!$AE:$AF,2,FALSE)),IF(E4="","",CONCATENATE("_U1|",SUBSTITUTE(SUBSTITUTE(E4,"_","-"),"|","-"))),IF(F4="","",CONCATENATE("_U2|",SUBSTITUTE(SUBSTITUTE(F4,"_","-"),"|","-"))),IF(G4="","",CONCATENATE("_U3|",SUBSTITUTE(SUBSTITUTE(G4,"_","-"),"|","-"))))) -> CV|VDV-MERCHANT-GOL-REDES-SOCIAIS_CS|1x1_CT|FCR
A5: 240843175 | B5: VDV-MERCHANT-GOL | C5: 627x627 | D5: Banner Static (JPG/GIF) | F5: VERIZON | H5: =IF(C5="----","#N/A",CONCATENATE("CV|",SUBSTITUTE(SUBSTITUTE(IF(B5="","NONE",B5),"_","-"),"|","-"),"_","CS|",(VLOOKUP(C5,Dictionary!$Y:$Z,2,FALSE)),"_","CT|",(VLOOKUP(D5,Dictionary!$AE:$AF,2,FALSE)),IF(E5="","",CONCATENATE("_U1|",SUBSTITUTE(SUBSTITUTE(E5,"_","-"),"|","-"))),IF(F5="","",CONCATENATE("_U2|",SUBSTITUTE(SUBSTITUTE(F5,"_","-"),"|","-"))),IF(G5="","",CONCATENATE("_U3|",SUBSTITUTE(SUBSTITUTE(G5,"_","-"),"|","-"))))) -> CV|VDV-MERCHANT-GOL_CS|627x627_CT|BAN_U2|VERIZON
A6: 242870616 | B6: VDV-MERCHANT-NATURA | C6: 320x50 | D6: Banner Static (JPG/GIF) | F6: ADSMOVIL | H6: =IF(C6="----","#N/A",CONCATENATE("CV|",SUBSTITUTE(SUBSTITUTE(IF(B6="","NONE",B6),"_","-"),"|","-"),"_","CS|",(VLOOKUP(C6,Dictionary!$Y:$Z,2,FALSE)),"_","CT|",(VLOOKUP(D6,Dictionary!$AE:$AF,2,FALSE)),IF(E6="","",CONCATENATE("_U1|",SUBSTITUTE(SUBSTITUTE(E6,"_","-"),"|","-"))),IF(F6="","",CONCATENATE("_U2|",SUBSTITUTE(SUBSTITUTE(F6,"_","-"),"|","-"))),IF(G6="","",CONCATENATE("_U3|",SUBSTITUTE(SUBSTITUTE(G6,"_","-"),"|","-"))))) -> CV|VDV-MERCHANT-NATURA_CS|320x50_CT|BAN_U2|ADSMOVIL
A7: 245600938 | B7: VDV-MERCHANT-DECOLAR-15OFF | C7: 1X1 | D7: FB Link Ad | E7: PREDIOS | H7: =IF(C7="----","#N/A",CONCATENATE("CV|",SUBSTITUTE(SUBSTITUTE(IF(B7="","NONE",B7),"_","-"),"|","-"),"_","CS|",(VLOOKUP(C7,Dictionary!$Y:$Z,2,FALSE)),"_","CT|",(VLOOKUP(D7,Dictionary!$AE:$AF,2,FALSE)),IF(E7="","",CONCATENATE("_U1|",SUBSTITUTE(SUBSTITUTE(E7,"_","-"),"|","-"))),IF(F7="","",CONCATENATE("_U2|",SUBSTITUTE(SUBSTITUTE(F7,"_","-"),"|","-"))),IF(G7="","",CONCATENATE("_U3|",SUBSTITUTE(SUBSTITUTE(G7,"_","-"),"|","-"))))) -> CV|VDV-MERCHANT-DECOLAR-15OFF_CS|1x1_CT|FLA_U1|PREDIOS
A8: 245600986 | B8: VDV-MERCHANT-DECOLAR-15OFF | C8: 1X1 | D8: FB Link Ad | E8: CAMPO | H8: =IF(C8="----","#N/A",CONCATENATE("CV|",SUBSTITUTE(SUBSTITUTE(IF(B8="","NONE",B8),"_","-"),"|","-"),"_","CS|",(VLOOKUP(C8,Dictionary!$Y:$Z,2,FALSE)),"_","CT|",(VLOOKUP(D8,Dictionary!$AE:$AF,2,FALSE)),IF(E8="","",CONCATENATE("_U1|",SUBSTITUTE(SUBSTITUTE(E8,"_","-"),"|","-"))),IF(F8="","",CONCATENATE("_U2|",SUBSTITUTE(SUBSTITUTE(F8,"_","-"),"|","-"))),IF(G8="","",CONCATENATE("_U3|",SUBSTITUTE(SUBSTITUTE(G8,"_","-"),"|","-"))))) -> CV|VDV-MERCHANT-DECOLAR-15OFF_CS|1x1_CT|FLA_U1|CAMPO
A9: 245601013 | B9: VDV-MERCHANT-DECOLAR-15OFF | C9: 1X1 | D9: FB Link Ad | E9: MAR | H9: =IF(C9="----","#N/A",CONCATENATE("CV|",SUBSTITUTE(SUBSTITUTE(IF(B9="","NONE",B9),"_","-"),"|","-"),"_","CS|",(VLOOKUP(C9,Dictionary!$Y:$Z,2,FALSE)),"_","CT|",(VLOOKUP(D9,Dictionary!$AE:$AF,2,FALSE)),IF(E9="","",CONCATENATE("_U1|",SUBSTITUTE(SUBSTITUTE(E9,"_","-"),"|","-"))),IF(F9="","",CONCATENATE("_U2|",SUBSTITUTE(SUBSTITUTE(F9,"_","-"),"|","-"))),IF(G9="","",CONCATENATE("_U3|",SUBSTITUTE(SUBSTITUTE(G9,"_","-"),"|","-"))))) -> CV|VDV-MERCHANT-DECOLAR-15OFF_CS|1x1_CT|FLA_U1|MAR
A10: 246942068 | B10: VDV-PROMONACIONAL | C10: 1X1 | D10: FB Link Ad | E10: AMARELO | H10: =IF(C10="----","#N/A",CONCATENATE("CV|",SUBSTITUTE(SUBSTITUTE(IF(B10="","NONE",B10),"_","-"),"|","-"),"_","CS|",(VLOOKUP(C10,Dictionary!$Y:$Z,2,FALSE)),"_","CT|",(VLOOKUP(D10,Dictionary!$AE:$AF,2,FALSE)),IF(E10="","",CONCATENATE("_U1|",SUBSTITUTE(SUBSTITUTE(E10,"_","-"),"|","-"))),IF(F10="","",CONCATENATE("_U2|",SUBSTITUTE(SUBSTITUTE(F10,"_","-"),"|","-"))),IF(G10="","",CONCATENATE("_U3|",SUBSTITUTE(SUBSTITUTE(G10,"_","-"),"|","-"))))) -> CV|VDV-PROMONACIONAL_CS|1x1_CT|FLA_U1|AMARELO
A11: 248336396 | B11: VDV-MOVIDA | C11: 1X1 | D11: FB Carousel | E11: OFERTAEDUCACIONAL | H11: =IF(C11="----","#N/A",CONCATENATE("CV|",SUBSTITUTE(SUBSTITUTE(IF(B11="","NONE",B11),"_","-"),"|","-"),"_","CS|",(VLOOKUP(C11,Dictionary!$Y:$Z,2,FALSE)),"_","CT|",(VLOOKUP(D11,Dictionary!$AE:$AF,2,FALSE)),IF(E11="","",CONCATENATE("_U1|",SUBSTITUTE(SUBSTITUTE(E11,"_","-"),"|","-"))),IF(F11="","",CONCATENATE("_U2|",SUBSTITUTE(SUBSTITUTE(F11,"_","-"),"|","-"))),IF(G11="","",CONCATENATE("_U3|",SUBSTITUTE(SUBSTITUTE(G11,"_","-"),"|","-"))))) -> CV|VDV-MOVIDA_CS|1x1_CT|FCR_U1|OFERTAEDUCACIONAL
A12: 249133270 | B12: VDV-PROMONACIONAL | C12: 1X1 | D12: IG Story | E12: PAGUECOMVISA | H12: =IF(C12="----","#N/A",CONCATENATE("CV|",SUBSTITUTE(SUBSTITUTE(IF(B12="","NONE",B12),"_","-"),"|","-"),"_","CS|",(VLOOKUP(C12,Dictionary!$Y:$Z,2,FALSE)),"_","CT|",(VLOOKUP(D12,Dictionary!$AE:$AF,2,FALSE)),IF(E12="","",CONCATENATE("_U1|",SUBSTITUTE(SUBSTITUTE(E12,"_","-"),"|","-"))),IF(F12="","",CONCATENATE("_U2|",SUBSTITUTE(SUBSTITUTE(F12,"_","-"),"|","-"))),IF(G12="","",CONCATENATE("_U3|",SUBSTITUTE(SUBSTITUTE(G12,"_","-"),"|","-"))))) -> CV|VDV-PROMONACIONAL_CS|1x1_CT|INSSTORY_U1|PAGUECOMVISA
A13: 249651979 | B13: VDV-PROMONACIONAL | C13: 1X1 | D13: FB Link Ad | E13: PARTICIPE | H13: =IF(C13="----","#N/A",CONCATENATE("CV|",SUBSTITUTE(SUBSTITUTE(IF(B13="","NONE",B13),"_","-"),"|","-"),"_","CS|",(VLOOKUP(C13,Dictionary!$Y:$Z,2,FALSE)),"_","CT|",(VLOOKUP(D13,Dictionary!$AE:$AF,2,FALSE)),IF(E13="","",CONCATENATE("_U1|",SUBSTITUTE(SUBSTITUTE(E13,"_","-"),"|","-"))),IF(F13="","",CONCATENATE("_U2|",SUBSTITUTE(SUBSTITUTE(F13,"_","-"),"|","-"))),IF(G13="","",CONCATENATE("_U3|",SUBSTITUTE(SUBSTITUTE(G13,"_","-"),"|","-"))))) -> CV|VDV-PROMONACIONAL_CS|1x1_CT|FLA_U1|PARTICIPE
A14: 249651985 | B14: VDV-PROMONACIONAL | C14: 1X1 | D14: FB Carousel | E14: PARTICIPE | H14: =IF(C14="----","#N/A",CONCATENATE("CV|",SUBSTITUTE(SUBSTITUTE(IF(B14="","NONE",B14),"_","-"),"|","-"),"_","CS|",(VLOOKUP(C14,Dictionary!$Y:$Z,2,FALSE)),"_","CT|",(VLOOKUP(D14,Dictionary!$AE:$AF,2,FALSE)),IF(E14="","",CONCATENATE("_U1|",SUBSTITUTE(SUBSTITUTE(E14,"_","-"),"|","-"))),IF(F14="","",CONCATENATE("_U2|",SUBSTITUTE(SUBSTITUTE(F14,"_","-"),"|","-"))),IF(G14="","",CONCATENATE("_U3|",SUBSTITUTE(SUBSTITUTE(G14,"_","-"),"|","-"))))) -> CV|VDV-PROMONACIONAL_CS|1x1_CT|FCR_U1|PARTICIPE
A15: 249651991 | B15: VDV-PROMONACIONAL | C15: 1X1 | D15: FB Gif | E15: CADASTRE-SE | H15: =IF(C15="----","#N/A",CONCATENATE("CV|",SUBSTITUTE(SUBSTITUTE(IF(B15="","NONE",B15),"_","-"),"|","-"),"_","CS|",(VLOOKUP(C15,Dictionary!$Y:$Z,2,FALSE)),"_","CT|",(VLOOKUP(D15,Dictionary!$AE:$AF,2,FALSE)),IF(E15="","",CONCATENATE("_U1|",SUBSTITUTE(SUBSTITUTE(E15,"_","-"),"|","-"))),IF(F15="","",CONCATENATE("_U2|",SUBSTITUTE(SUBSTITUTE(F15,"_","-"),"|","-"))),IF(G15="","",CONCATENATE("_U3|",SUBSTITUTE(SUBSTITUTE(G15,"_","-"),"|","-"))))) -> CV|VDV-PROMONACIONAL_CS|1x1_CT|FGIF_U1|CADASTRE-SE
A16: 249609130 | B16: VDV-MERCHANT-NETSHOES | C16: 1X1 | D16: FB Carousel | H16: =IF(C16="----","#N/A",CONCATENATE("CV|",SUBSTITUTE(SUBSTITUTE(IF(B16="","NONE",B16),"_","-"),"|","-"),"_","CS|",(VLOOKUP(C16,Dictionary!$Y:$Z,2,FALSE)),"_","CT|",(VLOOKUP(D16,Dictionary!$AE:$AF,2,FALSE)),IF(E16="","",CONCATENATE("_U1|",SUBSTITUTE(SUBSTITUTE(E16,"_","-"),"|","-"))),IF(F16="","",CONCATENATE("_U2|",SUBSTITUTE(SUBSTITUTE(F16,"_","-"),"|","-"))),IF(G16="","",CONCATENATE("_U3|",SUBSTITUTE(SUBSTITUTE(G16,"_","-"),"|","-"))))) -> CV|VDV-MERCHANT-NETSHOES_CS|1x1_CT|FCR
A17: 249687215 | B17: VDV-PROMONACIONAL | C17: Video :6 | D17: Youtube non-skippable | E17: BUMPER-AD | H17: =IF(C17="----","#N/A",CONCATENATE("CV|",SUBSTITUTE(SUBSTITUTE(IF(B17="","NONE",B17),"_","-"),"|","-"),"_","CS|",(VLOOKUP(C17,Dictionary!$Y:$Z,2,FALSE)),"_","CT|",(VLOOKUP(D17,Dictionary!$AE:$AF,2,FALSE)),IF(E17="","",CONCATENATE("_U1|",SUBSTITUTE(SUBSTITUTE(E17,"_","-"),"|","-"))),IF(F17="","",CONCATENATE("_U2|",SUBSTITUTE(SUBSTITUTE(F17,"_","-"),"|","-"))),IF(G17="","",CONCATENATE("_U3|",SUBSTITUTE(SUBSTITUTE(G17,"_","-"),"|","-"))))) -> CV|VDV-PROMONACIONAL_CS|VID:6_CT|YTNSK_U1|BUMPER-AD
A18: 249663197 | B18: VDV-PROMONACIONAL | C18: 627x627 | D18: Banner Static (JPG/GIF) | F18: VERIZON | H18: =IF(C18="----","#N/A",CONCATENATE("CV|",SUBSTITUTE(SUBSTITUTE(IF(B18="","NONE",B18),"_","-"),"|","-"),"_","CS|",(VLOOKUP(C18,Dictionary!$Y:$Z,2,FALSE)),"_","CT|",(VLOOKUP(D18,Dictionary!$AE:$AF,2,FALSE)),IF(E18="","",CONCATENATE("_U1|",SUBSTITUTE(SUBSTITUTE(E18,"_","-"),"|","-"))),IF(F18="","",CONCATENATE("_U2|",SUBSTITUTE(SUBSTITUTE(F18,"_","-"),"|","-"))),IF(G18="","",CONCATENATE("_U3|",SUBSTITUTE(SUBSTITUTE(G18,"_","-"),"|","-"))))) -> CV|VDV-PROMONACIONAL_CS|627x627_CT|BAN_U2|VERIZON
A19: 251011278 | B19: VDV-PROMONACIONAL | C19: 1X1 | D19: FB Gif | E19: PRAIA-PARTICIPE | H19: =IF(C19="----","#N/A",CONCATENATE("CV|",SUBSTITUTE(SUBSTITUTE(IF(B19="","NONE",B19),"_","-"),"|","-"),"_","CS|",(VLOOKUP(C19,Dictionary!$Y:$Z,2,FALSE)),"_","CT|",(VLOOKUP(D19,Dictionary!$AE:$AF,2,FALSE)),IF(E19="","",CONCATENATE("_U1|",SUBSTITUTE(SUBSTITUTE(E19,"_","-"),"|","-"))),IF(F19="","",CONCATENATE("_U2|",SUBSTITUTE(SUBSTITUTE(F19,"_","-"),"|","-"))),IF(G19="","",CONCATENATE("_U3|",SUBSTITUTE(SUBSTITUTE(G19,"_","-"),"|","-"))))) -> CV|VDV-PROMONACIONAL_CS|1x1_CT|FGIF_U1|PRAIA-PARTICIPE
A20: 251011296 | B20: VDV-PROMONACIONAL | C20: 1X1 | D20: FB Link Ad | E20: CAMPING-CADASTRE-SE | H20: =IF(C20="----","#N/A",CONCATENATE("CV|",SUBSTITUTE(SUBSTITUTE(IF(B20="","NONE",B20),"_","-"),"|","-"),"_","CS|",(VLOOKUP(C20,Dictionary!$Y:$Z,2,FALSE)),"_","CT|",(VLOOKUP(D20,Dictionary!$AE:$AF,2,FALSE)),IF(E20="","",CONCATENATE("_U1|",SUBSTITUTE(SUBSTITUTE(E20,"_","-"),"|","-"))),IF(F20="","",CONCATENATE("_U2|",SUBSTITUTE(SUBSTITUTE(F20,"_","-"),"|","-"))),IF(G20="","",CONCATENATE("_U3|",SUBSTITUTE(SUBSTITUTE(G20,"_","-"),"|","-"))))) -> CV|VDV-PROMONACIONAL_CS|1x1_CT|FLA_U1|CAMPING-CADASTRE-SE
A21: 251011302 | B21: VDV-PROMONACIONAL | C21: 1X1 | D21: FB Gif | E21: CAMPING-CADASTRE-SE | H21: =IF(C21="----","#N/A",CONCATENATE("CV|",SUBSTITUTE(SUBSTITUTE(IF(B21="","NONE",B21),"_","-"),"|","-"),"_","CS|",(VLOOKUP(C21,Dictionary!$Y:$Z,2,FALSE)),"_","CT|",(VLOOKUP(D21,Dictionary!$AE:$AF,2,FALSE)),IF(E21="","",CONCATENATE("_U1|",SUBSTITUTE(SUBSTITUTE(E21,"_","-"),"|","-"))),IF(F21="","",CONCATENATE("_U2|",SUBSTITUTE(SUBSTITUTE(F21,"_","-"),"|","-"))),IF(G21="","",CONCATENATE("_U3|",SUBSTITUTE(SUBSTITUTE(G21,"_","-"),"|","-"))))) -> CV|VDV-PROMONACIONAL_CS|1x1_CT|FGIF_U1|CAMPING-CADASTRE-SE
A22: 251155108 | B22: VDV-PROMONACIONAL | C22: 627x627 | D22: Banner Static (JPG/GIF) | E22: CAMPO | F22: VERIZON | H22: =IF(C22="----","#N/A",CONCATENATE("CV|",SUBSTITUTE(SUBSTITUTE(IF(B22="","NONE",B22),"_","-"),"|","-"),"_","CS|",(VLOOKUP(C22,Dictionary!$Y:$Z,2,FALSE)),"_","CT|",(VLOOKUP(D22,Dictionary!$AE:$AF,2,FALSE)),IF(E22="","",CONCATENATE("_U1|",SUBSTITUTE(SUBSTITUTE(E22,"_","-"),"|","-"))),IF(F22="","",CONCATENATE("_U2|",SUBSTITUTE(SUBSTITUTE(F22,"_","-"),"|","-"))),IF(G22="","",CONCATENATE("_U3|",SUBSTITUTE(SUBSTITUTE(G22,"_","-"),"|","-"))))) -> CV|VDV-PROMONACIONAL_CS|627x627_CT|BAN_U1|CAMPO_U2|VERIZON
A23: 251155096 | B23: VDV-PROMONACIONAL | C23: 627x627 | D23: Banner Static (JPG/GIF) | E23: PRAIA | F23: VERIZON | H23: =IF(C23="----","#N/A",CONCATENATE("CV|",SUBSTITUTE(SUBSTITUTE(IF(B23="","NONE",B23),"_","-"),"|","-"),"_","CS|",(VLOOKUP(C23,Dictionary!$Y:$Z,2,FALSE)),"_","CT|",(VLOOKUP(D23,Dictionary!$AE:$AF,2,FALSE)),IF(E23="","",CONCATENATE("_U1|",SUBSTITUTE(SUBSTITUTE(E23,"_","-"),"|","-"))),IF(F23="","",CONCATENATE("_U2|",SUBSTITUTE(SUBSTITUTE(F23,"_","-"),"|","-"))),IF(G23="","",CONCATENATE("_U3|",SUBSTITUTE(SUBSTITUTE(G23,"_","-"),"|","-"))))) -> CV|VDV-PROMONACIONAL_CS|627x627_CT|BAN_U1|PRAIA_U2|VERIZON
A24: 251155096 | B24: VDV-PROMONACIONAL | C24: 627x627 | D24: Banner Static (JPG/GIF) | E24: PRAIA | F24: VERIZON | H24: =IF(C24="----","#N/A",CONCATENATE("CV|",SUBSTITUTE(SUBSTITUTE(IF(B24="","NONE",B24),"_","-"),"|","-"),"_","CS|",(VLOOKUP(C24,Dictionary!$Y:$Z,2,FALSE)),"_","CT|",(VLOOKUP(D24,Dictionary!$AE:$AF,2,FALSE)),IF(E24="","",CONCATENATE("_U1|",SUBSTITUTE(SUBSTITUTE(E24,"_","-"),"|","-"))),IF(F24="","",CONCATENATE("_U2|",SUBSTITUTE(SUBSTITUTE(F24,"_","-"),"|","-"))),IF(G24="","",CONCATENATE("_U3|",SUBSTITUTE(SUBSTITUTE(G24,"_","-"),"|","-"))))) -> CV|VDV-PROMONACIONAL_CS|627x627_CT|BAN_U1|PRAIA_U2|VERIZON
A25: 251155108 | B25: VDV-PROMONACIONAL | C25: 627x627 | D25: Banner Static (JPG/GIF) | E25: CAMPO | F25: VERIZON | H25: =IF(C25="----","#N/A",CONCATENATE("CV|",SUBSTITUTE(SUBSTITUTE(IF(B25="","NONE",B25),"_","-"),"|","-"),"_","CS|",(VLOOKUP(C25,Dictionary!$Y:$Z,2,FALSE)),"_","CT|",(VLOOKUP(D25,Dictionary!$AE:$AF,2,FALSE)),IF(E25="","",CONCATENATE("_U1|",SUBSTITUTE(SUBSTITUTE(E25,"_","-"),"|","-"))),IF(F25="","",CONCATENATE("_U2|",SUBSTITUTE(SUBSTITUTE(F25,"_","-"),"|","-"))),IF(G25="","",CONCATENATE("_U3|",SUBSTITUTE(SUBSTITUTE(G25,"_","-"),"|","-"))))) -> CV|VDV-PROMONACIONAL_CS|627x627_CT|BAN_U1|CAMPO_U2|VERIZON
A26: 251254944 | B26: VDV-MERCHANT-MOVIDA-20OFF | C26: 1X1 | D26: FB Link Ad | E26: QUADRADO | H26: =IF(C26="----","#N/A",CONCATENATE("CV|",SUBSTITUTE(SUBSTITUTE(IF(B26="","NONE",B26),"_","-"),"|","-"),"_","CS|",(VLOOKUP(C26,Dictionary!$Y:$Z,2,FALSE)),"_","CT|",(VLOOKUP(D26,Dictionary!$AE:$AF,2,FALSE)),IF(E26="","",CONCATENATE("_U1|",SUBSTITUTE(SUBSTITUTE(E26,"_","-"),"|","-"))),IF(F26="","",CONCATENATE("_U2|",SUBSTITUTE(SUBSTITUTE(F26,"_","-"),"|","-"))),IF(G26="","",CONCATENATE("_U3|",SUBSTITUTE(SUBSTITUTE(G26,"_","-"),"|","-"))))) -> CV|VDV-MERCHANT-MOVIDA-20OFF_CS|1x1_CT|FLA_U1|QUADRADO
A27: 251272710 | B27: VDV-MERCHANT-MOVIDA-20OFF | C27: 1X1 | D27: FB Link Ad | E27: RETANGULAR | H27: =IF(C27="----","#N/A",CONCATENATE("CV|",SUBSTITUTE(SUBSTITUTE(IF(B27="","NONE",B27),"_","-"),"|","-"),"_","CS|",(VLOOKUP(C27,Dictionary!$Y:$Z,2,FALSE)),"_","CT|",(VLOOKUP(D27,Dictionary!$AE:$AF,2,FALSE)),IF(E27="","",CONCATENATE("_U1|",SUBSTITUTE(SUBSTITUTE(E27,"_","-"),"|","-"))),IF(F27="","",CONCATENATE("_U2|",SUBSTITUTE(SUBSTITUTE(F27,"_","-"),"|","-"))),IF(G27="","",CONCATENATE("_U3|",SUBSTITUTE(SUBSTITUTE(G27,"_","-"),"|","-"))))) -> CV|VDV-MERCHANT-MOVIDA-20OFF_CS|1x1_CT|FLA_U1|RETANGULAR
A28: 251270277 | B28: VDV-MERCHANT-MOVIDA-20OFF | C28: 1X1 | D28: FB Carousel | H28: =IF(C28="----","#N/A",CONCATENATE("CV|",SUBSTITUTE(SUBSTITUTE(IF(B28="","NONE",B28),"_","-"),"|","-"),"_","CS|",(VLOOKUP(C28,Dictionary!$Y:$Z,2,FALSE)),"_","CT|",(VLOOKUP(D28,Dictionary!$AE:$AF,2,FALSE)),IF(E28="","",CONCATENATE("_U1|",SUBSTITUTE(SUBSTITUTE(E28,"_","-"),"|","-"))),IF(F28="","",CONCATENATE("_U2|",SUBSTITUTE(SUBSTITUTE(F28,"_","-"),"|","-"))),IF(G28="","",CONCATENATE("_U3|",SUBSTITUTE(SUBSTITUTE(G28,"_","-"),"|","-"))))) -> CV|VDV-MERCHANT-MOVIDA-20OFF_CS|1x1_CT|FCR
A29: 251272737 | B29: VDV-MERCHANT-MOVIDA-20OFF | C29: 1X1 | D29: IG Story | H29: =IF(C29="----","#N/A",CONCATENATE("CV|",SUBSTITUTE(SUBSTITUTE(IF(B29="","NONE",B29),"_","-"),"|","-"),"_","CS|",(VLOOKUP(C29,Dictionary!$Y:$Z,2,FALSE)),"_","CT|",(VLOOKUP(D29,Dictionary!$AE:$AF,2,FALSE)),IF(E29="","",CONCATENATE("_U1|",SUBSTITUTE(SUBSTITUTE(E29,"_","-"),"|","-"))),IF(F29="","",CONCATENATE("_U2|",SUBSTITUTE(SUBSTITUTE(F29,"_","-"),"|","-"))),IF(G29="","",CONCATENATE("_U3|",SUBSTITUTE(SUBSTITUTE(G29,"_","-"),"|","-"))))) -> CV|VDV-MERCHANT-MOVIDA-20OFF_CS|1x1_CT|INSSTORY
A30: 251351886 | B30: VDV-PROMONACIONAL | C30: Video | D30: Video General | E30: PRAIA-KV-FERIAS | H30: =IF(C30="----","#N/A",CONCATENATE("CV|",SUBSTITUTE(SUBSTITUTE(IF(B30="","NONE",B30),"_","-"),"|","-"),"_","CS|",(VLOOKUP(C30,Dictionary!$Y:$Z,2,FALSE)),"_","CT|",(VLOOKUP(D30,Dictionary!$AE:$AF,2,FALSE)),IF(E30="","",CONCATENATE("_U1|",SUBSTITUTE(SUBSTITUTE(E30,"_","-"),"|","-"))),IF(F30="","",CONCATENATE("_U2|",SUBSTITUTE(SUBSTITUTE(F30,"_","-"),"|","-"))),IF(G30="","",CONCATENATE("_U3|",SUBSTITUTE(SUBSTITUTE(G30,"_","-"),"|","-"))))) -> CV|VDV-PROMONACIONAL_CS|VID_CT|VGEN_U1|PRAIA-KV-FERIAS
A31: 251343159 | B31: VDV-PROMONACIONAL | C31: Video :6 | D31: Youtube non-skippable | H31: =IF(C31="----","#N/A",CONCATENATE("CV|",SUBSTITUTE(SUBSTITUTE(IF(B31="","NONE",B31),"_","-"),"|","-"),"_","CS|",(VLOOKUP(C31,Dictionary!$Y:$Z,2,FALSE)),"_","CT|",(VLOOKUP(D31,Dictionary!$AE:$AF,2,FALSE)),IF(E31="","",CONCATENATE("_U1|",SUBSTITUTE(SUBSTITUTE(E31,"_","-"),"|","-"))),IF(F31="","",CONCATENATE("_U2|",SUBSTITUTE(SUBSTITUTE(F31,"_","-"),"|","-"))),IF(G31="","",CONCATENATE("_U3|",SUBSTITUTE(SUBSTITUTE(G31,"_","-"),"|","-"))))) -> CV|VDV-PROMONACIONAL_CS|VID:6_CT|YTNSK
A32: 251415409 | B32: VDV-EDUCACIONAL | C32: 1X1 | D32: IG Story | E32: DESCONTO | H32: =IF(C32="----","#N/A",CONCATENATE("CV|",SUBSTITUTE(SUBSTITUTE(IF(B32="","NONE",B32),"_","-"),"|","-"),"_","CS|",(VLOOKUP(C32,Dictionary!$Y:$Z,2,FALSE)),"_","CT|",(VLOOKUP(D32,Dictionary!$AE:$AF,2,FALSE)),IF(E32="","",CONCATENATE("_U1|",SUBSTITUTE(SUBSTITUTE(E32,"_","-"),"|","-"))),IF(F32="","",CONCATENATE("_U2|",SUBSTITUTE(SUBSTITUTE(F32,"_","-"),"|","-"))),IF(G32="","",CONCATENATE("_U3|",SUBSTITUTE(SUBSTITUTE(G32,"_","-"),"|","-"))))) -> CV|VDV-EDUCACIONAL_CS|1x1_CT|INSSTORY_U1|DESCONTO
A33: 251415754 | B33: VDV-EDUCACIONAL | C33: 1X1 | D33: IG Story | E33: VIAGEM-OFERTA | H33: =IF(C33="----","#N/A",CONCATENATE("CV|",SUBSTITUTE(SUBSTITUTE(IF(B33="","NONE",B33),"_","-"),"|","-"),"_","CS|",(VLOOKUP(C33,Dictionary!$Y:$Z,2,FALSE)),"_","CT|",(VLOOKUP(D33,Dictionary!$AE:$AF,2,FALSE)),IF(E33="","",CONCATENATE("_U1|",SUBSTITUTE(SUBSTITUTE(E33,"_","-"),"|","-"))),IF(F33="","",CONCATENATE("_U2|",SUBSTITUTE(SUBSTITUTE(F33,"_","-"),"|","-"))),IF(G33="","",CONCATENATE("_U3|",SUBSTITUTE(SUBSTITUTE(G33,"_","-"),"|","-"))))) -> CV|VDV-EDUCACIONAL_CS|1x1_CT|INSSTORY_U1|VIAGEM-OFERTA
A34: 251524148 | B34: VDV-EDUCACIONAL | C34: 300x250 | D34: Banner Static (JPG/GIF) | E34: CREDITO | F34: DV360 | H34: =IF(C34="----","#N/A",CONCATENATE("CV|",SUBSTITUTE(SUBSTITUTE(IF(B34="","NONE",B34),"_","-"),"|","-"),"_","CS|",(VLOOKUP(C34,Dictionary!$Y:$Z,2,FALSE)),"_","CT|",(VLOOKUP(D34,Dictionary!$AE:$AF,2,FALSE)),IF(E34="","",CONCATENATE("_U1|",SUBSTITUTE(SUBSTITUTE(E34,"_","-"),"|","-"))),IF(F34="","",CONCATENATE("_U2|",SUBSTITUTE(SUBSTITUTE(F34,"_","-"),"|","-"))),IF(G34="","",CONCATENATE("_U3|",SUBSTITUTE(SUBSTITUTE(G34,"_","-"),"|","-"))))) -> CV|VDV-EDUCACIONAL_CS|300x250_CT|BAN_U1|CREDITO_U2|DV360
A35: 251422685 | B35: VDV-MERCHANT-RAPPI | C35: 1X1 | D35: FB Link Ad | E35: RETANGULAR | F35: VERDE | H35: =IF(C35="----","#N/A",CONCATENATE("CV|",SUBSTITUTE(SUBSTITUTE(IF(B35="","NONE",B35),"_","-"),"|","-"),"_","CS|",(VLOOKUP(C35,Dictionary!$Y:$Z,2,FALSE)),"_","CT|",(VLOOKUP(D35,Dictionary!$AE:$AF,2,FALSE)),IF(E35="","",CONCATENATE("_U1|",SUBSTITUTE(SUBSTITUTE(E35,"_","-"),"|","-"))),IF(F35="","",CONCATENATE("_U2|",SUBSTITUTE(SUBSTITUTE(F35,"_","-"),"|","-"))),IF(G35="","",CONCATENATE("_U3|",SUBSTITUTE(SUBSTITUTE(G35,"_","-"),"|","-"))))) -> CV|VDV-MERCHANT-RAPPI_CS|1x1_CT|FLA_U1|RETANGULAR_U2|VERDE
A36: 251830933 | B36: VDV-EDUCACIONAL | C36: 160x600 | D36: Banner Static (JPG/GIF) | E36: CREDITO | F36: DV360 | H36: =IF(C36="----","#N/A",CONCATENATE("CV|",SUBSTITUTE(SUBSTITUTE(IF(B36="","NONE",B36),"_","-"),"|","-"),"_","CS|",(VLOOKUP(C36,Dictionary!$Y:$Z,2,FALSE)),"_","CT|",(VLOOKUP(D36,Dictionary!$AE:$AF,2,FALSE)),IF(E36="","",CONCATENATE("_U1|",SUBSTITUTE(SUBSTITUTE(E36,"_","-"),"|","-"))),IF(F36="","",CONCATENATE("_U2|",SUBSTITUTE(SUBSTITUTE(F36,"_","-"),"|","-"))),IF(G36="","",CONCATENATE("_U3|",SUBSTITUTE(SUBSTITUTE(G36,"_","-"),"|","-"))))) -> CV|VDV-EDUCACIONAL_CS|160x600_CT|BAN_U1|CREDITO_U2|DV360
A37: 251831053 | B37: VDV-EDUCACIONAL | C37: 300x600 | D37: Banner Static (JPG/GIF) | E37: CREDITO | F37: DV360 | H37: =IF(C37="----","#N/A",CONCATENATE("CV|",SUBSTITUTE(SUBSTITUTE(IF(B37="","NONE",B37),"_","-"),"|","-"),"_","CS|",(VLOOKUP(C37,Dictionary!$Y:$Z,2,FALSE)),"_","CT|",(VLOOKUP(D37,Dictionary!$AE:$AF,2,FALSE)),IF(E37="","",CONCATENATE("_U1|",SUBSTITUTE(SUBSTITUTE(E37,"_","-"),"|","-"))),IF(F37="","",CONCATENATE("_U2|",SUBSTITUTE(SUBSTITUTE(F37,"_","-"),"|","-"))),IF(G37="","",CONCATENATE("_U3|",SUBSTITUTE(SUBSTITUTE(G37,"_","-"),"|","-"))))) -> CV|VDV-EDUCACIONAL_CS|300x600_CT|BAN_U1|CREDITO_U2|DV360
A38: 251522756 | B38: VDV-EDUCACIONAL | C38: 970x250 | D38: Banner Static (JPG/GIF) | E38: CREDITO | F38: DV360 | H38: =IF(C38="----","#N/A",CONCATENATE("CV|",SUBSTITUTE(SUBSTITUTE(IF(B38="","NONE",B38),"_","-"),"|","-"),"_","CS|",(VLOOKUP(C38,Dictionary!$Y:$Z,2,FALSE)),"_","CT|",(VLOOKUP(D38,Dictionary!$AE:$AF,2,FALSE)),IF(E38="","",CONCATENATE("_U1|",SUBSTITUTE(SUBSTITUTE(E38,"_","-"),"|","-"))),IF(F38="","",CONCATENATE("_U2|",SUBSTITUTE(SUBSTITUTE(F38,"_","-"),"|","-"))),IF(G38="","",CONCATENATE("_U3|",SUBSTITUTE(SUBSTITUTE(G38,"_","-"),"|","-"))))) -> CV|VDV-EDUCACIONAL_CS|970x250_CT|BAN_U1|CREDITO_U2|DV360
A39: 251703248 | B39: VDV-EDUCACIONAL | C39: 300x250 | D39: Banner Static (JPG/GIF) | F39: VERIZON | H39: =IF(C39="----","#N/A",CONCATENATE("CV|",SUBSTITUTE(SUBSTITUTE(IF(B39="","NONE",B39),"_","-"),"|","-"),"_","CS|",(VLOOKUP(C39,Dictionary!$Y:$Z,2,FALSE)),"_","CT|",(VLOOKUP(D39,Dictionary!$AE:$AF,2,FALSE)),IF(E39="","",CONCATENATE("_U1|",SUBSTITUTE(SUBSTITUTE(E39,"_","-"),"|","-"))),IF(F39="","",CONCATENATE("_U2|",SUBSTITUTE(SUBSTITUTE(F39,"_","-"),"|","-"))),IF(G39="","",CONCATENATE("_U3|",SUBSTITUTE(SUBSTITUTE(G39,"_","-"),"|","-"))))) -> CV|VDV-EDUCACIONAL_CS|300x250_CT|BAN_U2|VERIZON
A40: 251698928 | B40: VDV-EDUCACIONAL | C40: 300x600 | D40: Banner Static (JPG/GIF) | F40: DV360 | H40: =IF(C40="----","#N/A",CONCATENATE("CV|",SUBSTITUTE(SUBSTITUTE(IF(B40="","NONE",B40),"_","-"),"|","-"),"_","CS|",(VLOOKUP(C40,Dictionary!$Y:$Z,2,FALSE)),"_","CT|",(VLOOKUP(D40,Dictionary!$AE:$AF,2,FALSE)),IF(E40="","",CONCATENATE("_U1|",SUBSTITUTE(SUBSTITUTE(E40,"_","-"),"|","-"))),IF(F40="","",CONCATENATE("_U2|",SUBSTITUTE(SUBSTITUTE(F40,"_","-"),"|","-"))),IF(G40="","",CONCATENATE("_U3|",SUBSTITUTE(SUBSTITUTE(G40,"_","-"),"|","-"))))) -> CV|VDV-EDUCACIONAL_CS|300x600_CT|BAN_U2|DV360
A41: 251696792 | B41: VDV-EDUCACIONAL | C41: 160x600 | D41: Banner Static (JPG/GIF) | F41: DV360 | H41: =IF(C41="----","#N/A",CONCATENATE("CV|",SUBSTITUTE(SUBSTITUTE(IF(B41="","NONE",B41),"_","-"),"|","-"),"_","CS|",(VLOOKUP(C41,Dictionary!$Y:$Z,2,FALSE)),"_","CT|",(VLOOKUP(D41,Dictionary!$AE:$AF,2,FALSE)),IF(E41="","",CONCATENATE("_U1|",SUBSTITUTE(SUBSTITUTE(E41,"_","-"),"|","-"))),IF(F41="","",CONCATENATE("_U2|",SUBSTITUTE(SUBSTITUTE(F41,"_","-"),"|","-"))),IF(G41="","",CONCATENATE("_U3|",SUBSTITUTE(SUBSTITUTE(G41,"_","-"),"|","-"))))) -> CV|VDV-EDUCACIONAL_CS|160x600_CT|BAN_U2|DV360
A42: 252103032 | B42: VDV-EDUCACIONAL | C42: 300x250 | D42: Banner Static (JPG/GIF) | F42: DV360 | H42: =IF(C42="----","#N/A",CONCATENATE("CV|",SUBSTITUTE(SUBSTITUTE(IF(B42="","NONE",B42),"_","-"),"|","-"),"_","CS|",(VLOOKUP(C42,Dictionary!$Y:$Z,2,FALSE)),"_","CT|",(VLOOKUP(D42,Dictionary!$AE:$AF,2,FALSE)),IF(E42="","",CONCATENATE("_U1|",SUBSTITUTE(SUBSTITUTE(E42,"_","-"),"|","-"))),IF(F42="","",CONCATENATE("_U2|",SUBSTITUTE(SUBSTITUTE(F42,"_","-"),"|","-"))),IF(G42="","",CONCATENATE("_U3|",SUBSTITUTE(SUBSTITUTE(G42,"_","-"),"|","-"))))) -> CV|VDV-EDUCACIONAL_CS|300x250_CT|BAN_U2|DV360
A43: 252103536 | B43: VDV-EDUCACIONAL | C43: 970x250 | D43: Banner Static (JPG/GIF) | F43: DV360 | H43: =IF(C43="----","#N/A",CONCATENATE("CV|",SUBSTITUTE(SUBSTITUTE(IF(B43="","NONE",B43),"_","-"),"|","-"),"_","CS|",(VLOOKUP(C43,Dictionary!$Y:$Z,2,FALSE)),"_","CT|",(VLOOKUP(D43,Dictionary!$AE:$AF,2,FALSE)),IF(E43="","",CONCATENATE("_U1|",SUBSTITUTE(SUBSTITUTE(E43,"_","-"),"|","-"))),IF(F43="","",CONCATENATE("_U2|",SUBSTITUTE(SUBSTITUTE(F43,"_","-"),"|","-"))),IF(G43="","",CONCATENATE("_U3|",SUBSTITUTE(SUBSTITUTE(G43,"_","-"),"|","-"))))) -> CV|VDV-EDUCACIONAL_CS|970x250_CT|BAN_U2|DV360
A44: 252102792 | B44: VDV-EDUCACIONAL | C44: 160x600 | D44: Banner Static (JPG/GIF) | F44: VERIZON | H44: =IF(C44="----","#N/A",CONCATENATE("CV|",SUBSTITUTE(SUBSTITUTE(IF(B44="","NONE",B44),"_","-"),"|","-"),"_","CS|",(VLOOKUP(C44,Dictionary!$Y:$Z,2,FALSE)),"_","CT|",(VLOOKUP(D44,Dictionary!$AE:$AF,2,FALSE)),IF(E44="","",CONCATENATE("_U1|",SUBSTITUTE(SUBSTITUTE(E44,"_","-"),"|","-"))),IF(F44="","",CONCATENATE("_U2|",SUBSTITUTE(SUBSTITUTE(F44,"_","-"),"|","-"))),IF(G44="","",CONCATENATE("_U3|",SUBSTITUTE(SUBSTITUTE(G44,"_","-"),"|","-"))))) -> CV|VDV-EDUCACIONAL_CS|160x600_CT|BAN_U2|VERIZON
A45: 252105414 | B45: VDV-EDUCACIONAL | C45: 300x600 | D45: Banner Static (JPG/GIF) | F45: VERIZON | H45: =IF(C45="----","#N/A",CONCATENATE("CV|",SUBSTITUTE(SUBSTITUTE(IF(B45="","NONE",B45),"_","-"),"|","-"),"_","CS|",(VLOOKUP(C45,Dictionary!$Y:$Z,2,FALSE)),"_","CT|",(VLOOKUP(D45,Dictionary!$AE:$AF,2,FALSE)),IF(E45="","",CONCATENATE("_U1|",SUBSTITUTE(SUBSTITUTE(E45,"_","-"),"|","-"))),IF(F45="","",CONCATENATE("_U2|",SUBSTITUTE(SUBSTITUTE(F45,"_","-"),"|","-"))),IF(G45="","",CONCATENATE("_U3|",SUBSTITUTE(SUBSTITUTE(G45,"_","-"),"|","-"))))) -> CV|VDV-EDUCACIONAL_CS|300x600_CT|BAN_U2|VERIZON
A46: 252132775 | B46: VDV-EDUCACIONAL | C46: 1X1 | D46: FB Gif | E46: DEBITO-COMPRAS-MOBILE | H46: =IF(C46="----","#N/A",CONCATENATE("CV|",SUBSTITUTE(SUBSTITUTE(IF(B46="","NONE",B46),"_","-"),"|","-"),"_","CS|",(VLOOKUP(C46,Dictionary!$Y:$Z,2,FALSE)),"_","CT|",(VLOOKUP(D46,Dictionary!$AE:$AF,2,FALSE)),IF(E46="","",CONCATENATE("_U1|",SUBSTITUTE(SUBSTITUTE(E46,"_","-"),"|","-"))),IF(F46="","",CONCATENATE("_U2|",SUBSTITUTE(SUBSTITUTE(F46,"_","-"),"|","-"))),IF(G46="","",CONCATENATE("_U3|",SUBSTITUTE(SUBSTITUTE(G46,"_","-"),"|","-"))))) -> CV|VDV-EDUCACIONAL_CS|1x1_CT|FGIF_U1|DEBITO-COMPRAS-MOBILE
A47: 252202866 | B47: VDV-EDUCACIONAL | C47: 1X1 | D47: IG Story | E47: DEBITO | H47: =IF(C47="----","#N/A",CONCATENATE("CV|",SUBSTITUTE(SUBSTITUTE(IF(B47="","NONE",B47),"_","-"),"|","-"),"_","CS|",(VLOOKUP(C47,Dictionary!$Y:$Z,2,FALSE)),"_","CT|",(VLOOKUP(D47,Dictionary!$AE:$AF,2,FALSE)),IF(E47="","",CONCATENATE("_U1|",SUBSTITUTE(SUBSTITUTE(E47,"_","-"),"|","-"))),IF(F47="","",CONCATENATE("_U2|",SUBSTITUTE(SUBSTITUTE(F47,"_","-"),"|","-"))),IF(G47="","",CONCATENATE("_U3|",SUBSTITUTE(SUBSTITUTE(G47,"_","-"),"|","-"))))) -> CV|VDV-EDUCACIONAL_CS|1x1_CT|INSSTORY_U1|DEBITO
A48: 251876717 | B48: VDV-MERCHANT-RAPPI | C48: 1X1 | D48: IG Story | E48: LARANJA | H48: =IF(C48="----","#N/A",CONCATENATE("CV|",SUBSTITUTE(SUBSTITUTE(IF(B48="","NONE",B48),"_","-"),"|","-"),"_","CS|",(VLOOKUP(C48,Dictionary!$Y:$Z,2,FALSE)),"_","CT|",(VLOOKUP(D48,Dictionary!$AE:$AF,2,FALSE)),IF(E48="","",CONCATENATE("_U1|",SUBSTITUTE(SUBSTITUTE(E48,"_","-"),"|","-"))),IF(F48="","",CONCATENATE("_U2|",SUBSTITUTE(SUBSTITUTE(F48,"_","-"),"|","-"))),IF(G48="","",CONCATENATE("_U3|",SUBSTITUTE(SUBSTITUTE(G48,"_","-"),"|","-"))))) -> CV|VDV-MERCHANT-RAPPI_CS|1x1_CT|INSSTORY_U1|LARANJA
A49: 251876690 | B49: VDV-MERCHANT-RAPPI | C49: 1X1 | D49: FB Link Ad | E49: QUADRADO | H49: =IF(C49="----","#N/A",CONCATENATE("CV|",SUBSTITUTE(SUBSTITUTE(IF(B49="","NONE",B49),"_","-"),"|","-"),"_","CS|",(VLOOKUP(C49,Dictionary!$Y:$Z,2,FALSE)),"_","CT|",(VLOOKUP(D49,Dictionary!$AE:$AF,2,FALSE)),IF(E49="","",CONCATENATE("_U1|",SUBSTITUTE(SUBSTITUTE(E49,"_","-"),"|","-"))),IF(F49="","",CONCATENATE("_U2|",SUBSTITUTE(SUBSTITUTE(F49,"_","-"),"|","-"))),IF(G49="","",CONCATENATE("_U3|",SUBSTITUTE(SUBSTITUTE(G49,"_","-"),"|","-"))))) -> CV|VDV-MERCHANT-RAPPI_CS|1x1_CT|FLA_U1|QUADRADO
A50: 252293266 | B50: VDV-MERCHANT-CAMICADO-10OFF | C50: 1X1 | D50: FB Carousel | H50: =IF(C50="----","#N/A",CONCATENATE("CV|",SUBSTITUTE(SUBSTITUTE(IF(B50="","NONE",B50),"_","-"),"|","-"),"_","CS|",(VLOOKUP(C50,Dictionary!$Y:$Z,2,FALSE)),"_","CT|",(VLOOKUP(D50,Dictionary!$AE:$AF,2,FALSE)),IF(E50="","",CONCATENATE("_U1|",SUBSTITUTE(SUBSTITUTE(E50,"_","-"),"|","-"))),IF(F50="","",CONCATENATE("_U2|",SUBSTITUTE(SUBSTITUTE(F50,"_","-"),"|","-"))),IF(G50="","",CONCATENATE("_U3|",SUBSTITUTE(SUBSTITUTE(G50,"_","-"),"|","-"))))) -> CV|VDV-MERCHANT-CAMICADO-10OFF_CS|1x1_CT|FCR
A51: 252207496 | B51: VDV-MERCHANT-RAPPI | C51: 1X1 | D51: FB Link Ad | E51: RETANGULAR | H51: =IF(C51="----","#N/A",CONCATENATE("CV|",SUBSTITUTE(SUBSTITUTE(IF(B51="","NONE",B51),"_","-"),"|","-"),"_","CS|",(VLOOKUP(C51,Dictionary!$Y:$Z,2,FALSE)),"_","CT|",(VLOOKUP(D51,Dictionary!$AE:$AF,2,FALSE)),IF(E51="","",CONCATENATE("_U1|",SUBSTITUTE(SUBSTITUTE(E51,"_","-"),"|","-"))),IF(F51="","",CONCATENATE("_U2|",SUBSTITUTE(SUBSTITUTE(F51,"_","-"),"|","-"))),IF(G51="","",CONCATENATE("_U3|",SUBSTITUTE(SUBSTITUTE(G51,"_","-"),"|","-"))))) -> CV|VDV-MERCHANT-RAPPI_CS|1x1_CT|FLA_U1|RETANGULAR
A52: 252144842 | B52: VDV-MERCHANT-NETSHOES-20OFF | C52: 1X1 | D52: FB Link Ad | E52: QUADRADO | H52: =IF(C52="----","#N/A",CONCATENATE("CV|",SUBSTITUTE(SUBSTITUTE(IF(B52="","NONE",B52),"_","-"),"|","-"),"_","CS|",(VLOOKUP(C52,Dictionary!$Y:$Z,2,FALSE)),"_","CT|",(VLOOKUP(D52,Dictionary!$AE:$AF,2,FALSE)),IF(E52="","",CONCATENATE("_U1|",SUBSTITUTE(SUBSTITUTE(E52,"_","-"),"|","-"))),IF(F52="","",CONCATENATE("_U2|",SUBSTITUTE(SUBSTITUTE(F52,"_","-"),"|","-"))),IF(G52="","",CONCATENATE("_U3|",SUBSTITUTE(SUBSTITUTE(G52,"_","-"),"|","-"))))) -> CV|VDV-MERCHANT-NETSHOES-20OFF_CS|1x1_CT|FLA_U1|QUADRADO
A53: 252613815 | B53: VCO-MERCHANT-GPA | C53: 300x600 | D53: Banner Static (JPG/GIF) | E53: FRETEGRATIS | H53: =IF(C53="----","#N/A",CONCATENATE("CV|",SUBSTITUTE(SUBSTITUTE(IF(B53="","NONE",B53),"_","-"),"|","-"),"_","CS|",(VLOOKUP(C53,Dictionary!$Y:$Z,2,FALSE)),"_","CT|",(VLOOKUP(D53,Dictionary!$AE:$AF,2,FALSE)),IF(E53="","",CONCATENATE("_U1|",SUBSTITUTE(SUBSTITUTE(E53,"_","-"),"|","-"))),IF(F53="","",CONCATENATE("_U2|",SUBSTITUTE(SUBSTITUTE(F53,"_","-"),"|","-"))),IF(G53="","",CONCATENATE("_U3|",SUBSTITUTE(SUBSTITUTE(G53,"_","-"),"|","-"))))) -> CV|VCO-MERCHANT-GPA_CS|300x600_CT|BAN_U1|FRETEGRATIS
A54: 252206129 | B54: VCO-MERCHANT-GPA | C54: 300x250 | D54: Banner Static (JPG/GIF) | E54: FRETEGRATIS | H54: =IF(C54="----","#N/A",CONCATENATE("CV|",SUBSTITUTE(SUBSTITUTE(IF(B54="","NONE",B54),"_","-"),"|","-"),"_","CS|",(VLOOKUP(C54,Dictionary!$Y:$Z,2,FALSE)),"_","CT|",(VLOOKUP(D54,Dictionary!$AE:$AF,2,FALSE)),IF(E54="","",CONCATENATE("_U1|",SUBSTITUTE(SUBSTITUTE(E54,"_","-"),"|","-"))),IF(F54="","",CONCATENATE("_U2|",SUBSTITUTE(SUBSTITUTE(F54,"_","-"),"|","-"))),IF(G54="","",CONCATENATE("_U3|",SUBSTITUTE(SUBSTITUTE(G54,"_","-"),"|","-"))))) -> CV|VCO-MERCHANT-GPA_CS|300x250_CT|BAN_U1|FRETEGRATIS
A55: 252617688 | B55: VCO-MERCHANT-GPA | C55: 970x250 | D55: Banner Static (JPG/GIF) | E55: FRETEGRATIS | H55: =IF(C55="----","#N/A",CONCATENATE("CV|",SUBSTITUTE(SUBSTITUTE(IF(B55="","NONE",B55),"_","-"),"|","-"),"_","CS|",(VLOOKUP(C55,Dictionary!$Y:$Z,2,FALSE)),"_","CT|",(VLOOKUP(D55,Dictionary!$AE:$AF,2,FALSE)),IF(E55="","",CONCATENATE("_U1|",SUBSTITUTE(SUBSTITUTE(E55,"_","-"),"|","-"))),IF(F55="","",CONCATENATE("_U2|",SUBSTITUTE(SUBSTITUTE(F55,"_","-"),"|","-"))),IF(G55="","",CONCATENATE("_U3|",SUBSTITUTE(SUBSTITUTE(G55,"_","-"),"|","-"))))) -> CV|VCO-MERCHANT-GPA_CS|970x250_CT|BAN_U1|FRETEGRATIS
A56: 252563791 | B56: VCO-MERCHANT-GPA | C56: 160x600 | D56: Banner Static (JPG/GIF) | E56: FRETEGRATIS | H56: =IF(C56="----","#N/A",CONCATENATE("CV|",SUBSTITUTE(SUBSTITUTE(IF(B56="","NONE",B56),"_","-"),"|","-"),"_","CS|",(VLOOKUP(C56,Dictionary!$Y:$Z,2,FALSE)),"_","CT|",(VLOOKUP(D56,Dictionary!$AE:$AF,2,FALSE)),IF(E56="","",CONCATENATE("_U1|",SUBSTITUTE(SUBSTITUTE(E56,"_","-"),"|","-"))),IF(F56="","",CONCATENATE("_U2|",SUBSTITUTE(SUBSTITUTE(F56,"_","-"),"|","-"))),IF(G56="","",CONCATENATE("_U3|",SUBSTITUTE(SUBSTITUTE(G56,"_","-"),"|","-"))))) -> CV|VCO-MERCHANT-GPA_CS|160x600_CT|BAN_U1|FRETEGRATIS
A57: 252741885 | B57: VDV-PROMONACIONAL | C57: 1X1 | D57: FB Carousel | E57: DIADOSPAIS | H57: =IF(C57="----","#N/A",CONCATENATE("CV|",SUBSTITUTE(SUBSTITUTE(IF(B57="","NONE",B57),"_","-"),"|","-"),"_","CS|",(VLOOKUP(C57,Dictionary!$Y:$Z,2,FALSE)),"_","CT|",(VLOOKUP(D57,Dictionary!$AE:$AF,2,FALSE)),IF(E57="","",CONCATENATE("_U1|",SUBSTITUTE(SUBSTITUTE(E57,"_","-"),"|","-"))),IF(F57="","",CONCATENATE("_U2|",SUBSTITUTE(SUBSTITUTE(F57,"_","-"),"|","-"))),IF(G57="","",CONCATENATE("_U3|",SUBSTITUTE(SUBSTITUTE(G57,"_","-"),"|","-"))))) -> CV|VDV-PROMONACIONAL_CS|1x1_CT|FCR_U1|DIADOSPAIS
A58: 252412997 | B58: VDV-MERCHANT-NETSHOES-15OFF | C58: 1X1 | D58: FB Carousel | H58: =IF(C58="----","#N/A",CONCATENATE("CV|",SUBSTITUTE(SUBSTITUTE(IF(B58="","NONE",B58),"_","-"),"|","-"),"_","CS|",(VLOOKUP(C58,Dictionary!$Y:$Z,2,FALSE)),"_","CT|",(VLOOKUP(D58,Dictionary!$AE:$AF,2,FALSE)),IF(E58="","",CONCATENATE("_U1|",SUBSTITUTE(SUBSTITUTE(E58,"_","-"),"|","-"))),IF(F58="","",CONCATENATE("_U2|",SUBSTITUTE(SUBSTITUTE(F58,"_","-"),"|","-"))),IF(G58="","",CONCATENATE("_U3|",SUBSTITUTE(SUBSTITUTE(G58,"_","-"),"|","-"))))) -> CV|VDV-MERCHANT-NETSHOES-15OFF_CS|1x1_CT|FCR
A59: 252942147 | B59: VDV-PROMONACIONAL | C59: 1X1 | D59: FB Carousel | E59: PARTICIPE-PAGUECOMVISA | H59: =IF(C59="----","#N/A",CONCATENATE("CV|",SUBSTITUTE(SUBSTITUTE(IF(B59="","NONE",B59),"_","-"),"|","-"),"_","CS|",(VLOOKUP(C59,Dictionary!$Y:$Z,2,FALSE)),"_","CT|",(VLOOKUP(D59,Dictionary!$AE:$AF,2,FALSE)),IF(E59="","",CONCATENATE("_U1|",SUBSTITUTE(SUBSTITUTE(E59,"_","-"),"|","-"))),IF(F59="","",CONCATENATE("_U2|",SUBSTITUTE(SUBSTITUTE(F59,"_","-"),"|","-"))),IF(G59="","",CONCATENATE("_U3|",SUBSTITUTE(SUBSTITUTE(G59,"_","-"),"|","-"))))) -> CV|VDV-PROMONACIONAL_CS|1x1_CT|FCR_U1|PARTICIPE-PAGUECOMVISA
A60: 252876919 | B60: VDV-PROMONACIONAL | C60: 1X1 | D60: IG Story | E60: PARTICIPE-PAGUECOMVISA | H60: =IF(C60="----","#N/A",CONCATENATE("CV|",SUBSTITUTE(SUBSTITUTE(IF(B60="","NONE",B60),"_","-"),"|","-"),"_","CS|",(VLOOKUP(C60,Dictionary!$Y:$Z,2,FALSE)),"_","CT|",(VLOOKUP(D60,Dictionary!$AE:$AF,2,FALSE)),IF(E60="","",CONCATENATE("_U1|",SUBSTITUTE(SUBSTITUTE(E60,"_","-"),"|","-"))),IF(F60="","",CONCATENATE("_U2|",SUBSTITUTE(SUBSTITUTE(F60,"_","-"),"|","-"))),IF(G60="","",CONCATENATE("_U3|",SUBSTITUTE(SUBSTITUTE(G60,"_","-"),"|","-"))))) -> CV|VDV-PROMONACIONAL_CS|1x1_CT|INSSTORY_U1|PARTICIPE-PAGUECOMVISA
A61: 252741885 | B61: VDV-PROMONACIONAL | C61: 1X1 | D61: FB Carousel | E61: DIADOSPAIS | H61: =IF(C61="----","#N/A",CONCATENATE("CV|",SUBSTITUTE(SUBSTITUTE(IF(B61="","NONE",B61),"_","-"),"|","-"),"_","CS|",(VLOOKUP(C61,Dictionary!$Y:$Z,2,FALSE)),"_","CT|",(VLOOKUP(D61,Dictionary!$AE:$AF,2,FALSE)),IF(E61="","",CONCATENATE("_U1|",SUBSTITUTE(SUBSTITUTE(E61,"_","-"),"|","-"))),IF(F61="","",CONCATENATE("_U2|",SUBSTITUTE(SUBSTITUTE(F61,"_","-"),"|","-"))),IF(G61="","",CONCATENATE("_U3|",SUBSTITUTE(SUBSTITUTE(G61,"_","-"),"|","-"))))) -> CV|VDV-PROMONACIONAL_CS|1x1_CT|FCR_U1|DIADOSPAIS
A62: 252515498 | B62: VDV-PROMONACIONAL | C62: 1X1 | D62: FB Gif | E62: PARTICIPE-PAGUECOMVISA | H62: =IF(C62="----","#N/A",CONCATENATE("CV|",SUBSTITUTE(SUBSTITUTE(IF(B62="","NONE",B62),"_","-"),"|","-"),"_","CS|",(VLOOKUP(C62,Dictionary!$Y:$Z,2,FALSE)),"_","CT|",(VLOOKUP(D62,Dictionary!$AE:$AF,2,FALSE)),IF(E62="","",CONCATENATE("_U1|",SUBSTITUTE(SUBSTITUTE(E62,"_","-"),"|","-"))),IF(F62="","",CONCATENATE("_U2|",SUBSTITUTE(SUBSTITUTE(F62,"_","-"),"|","-"))),IF(G62="","",CONCATENATE("_U3|",SUBSTITUTE(SUBSTITUTE(G62,"_","-"),"|","-"))))) -> CV|VDV-PROMONACIONAL_CS|1x1_CT|FGIF_U1|PARTICIPE-PAGUECOMVISA
A63: 252515468 | B63: VDV-PROMONACIONAL | C63: 1X1 | D63: FB Link Ad | E63: PARTICIPE-PAGUECOMVISA | H63: =IF(C63="----","#N/A",CONCATENATE("CV|",SUBSTITUTE(SUBSTITUTE(IF(B63="","NONE",B63),"_","-"),"|","-"),"_","CS|",(VLOOKUP(C63,Dictionary!$Y:$Z,2,FALSE)),"_","CT|",(VLOOKUP(D63,Dictionary!$AE:$AF,2,FALSE)),IF(E63="","",CONCATENATE("_U1|",SUBSTITUTE(SUBSTITUTE(E63,"_","-"),"|","-"))),IF(F63="","",CONCATENATE("_U2|",SUBSTITUTE(SUBSTITUTE(F63,"_","-"),"|","-"))),IF(G63="","",CONCATENATE("_U3|",SUBSTITUTE(SUBSTITUTE(G63,"_","-"),"|","-"))))) -> CV|VDV-PROMONACIONAL_CS|1x1_CT|FLA_U1|PARTICIPE-PAGUECOMVISA
A64: 252760903 | B64: VDV-MERCHANT-NETSHOES-15OFF | C64: 1X1 | D64: FB Link Ad | E64: QUADRADO | H64: =IF(C64="----","#N/A",CONCATENATE("CV|",SUBSTITUTE(SUBSTITUTE(IF(B64="","NONE",B64),"_","-"),"|","-"),"_","CS|",(VLOOKUP(C64,Dictionary!$Y:$Z,2,FALSE)),"_","CT|",(VLOOKUP(D64,Dictionary!$AE:$AF,2,FALSE)),IF(E64="","",CONCATENATE("_U1|",SUBSTITUTE(SUBSTITUTE(E64,"_","-"),"|","-"))),IF(F64="","",CONCATENATE("_U2|",SUBSTITUTE(SUBSTITUTE(F64,"_","-"),"|","-"))),IF(G64="","",CONCATENATE("_U3|",SUBSTITUTE(SUBSTITUTE(G64,"_","-"),"|","-"))))) -> CV|VDV-MERCHANT-NETSHOES-15OFF_CS|1x1_CT|FLA_U1|QUADRADO
A65: 252858643 | B65: VCO-MERCHANT-GOL | C65: 300x250 | D65: Banner Static (JPG/GIF) | E65: WIFI | F65: DV360 | H65: =IF(C65="----","#N/A",CONCATENATE("CV|",SUBSTITUTE(SUBSTITUTE(IF(B65="","NONE",B65),"_","-"),"|","-"),"_","CS|",(VLOOKUP(C65,Dictionary!$Y:$Z,2,FALSE)),"_","CT|",(VLOOKUP(D65,Dictionary!$AE:$AF,2,FALSE)),IF(E65="","",CONCATENATE("_U1|",SUBSTITUTE(SUBSTITUTE(E65,"_","-"),"|","-"))),IF(F65="","",CONCATENATE("_U2|",SUBSTITUTE(SUBSTITUTE(F65,"_","-"),"|","-"))),IF(G65="","",CONCATENATE("_U3|",SUBSTITUTE(SUBSTITUTE(G65,"_","-"),"|","-"))))) -> CV|VCO-MERCHANT-GOL_CS|300x250_CT|BAN_U1|WIFI_U2|DV360
A66: 252859840 | B66: VCO-MERCHANT-GOL | C66: 300x600 | D66: Banner Static (JPG/GIF) | E66: WIFI | F66: DV360 | H66: =IF(C66="----","#N/A",CONCATENATE("CV|",SUBSTITUTE(SUBSTITUTE(IF(B66="","NONE",B66),"_","-"),"|","-"),"_","CS|",(VLOOKUP(C66,Dictionary!$Y:$Z,2,FALSE)),"_","CT|",(VLOOKUP(D66,Dictionary!$AE:$AF,2,FALSE)),IF(E66="","",CONCATENATE("_U1|",SUBSTITUTE(SUBSTITUTE(E66,"_","-"),"|","-"))),IF(F66="","",CONCATENATE("_U2|",SUBSTITUTE(SUBSTITUTE(F66,"_","-"),"|","-"))),IF(G66="","",CONCATENATE("_U3|",SUBSTITUTE(SUBSTITUTE(G66,"_","-"),"|","-"))))) -> CV|VCO-MERCHANT-GOL_CS|300x600_CT|BAN_U1|WIFI_U2|DV360
A67: 252686396 | B67: VDV-MERCHANT-DECOLAR | C67: 160x600 | D67: Banner Static (JPG/GIF) | E67: CAMPO | F67: VERIZON | H67: =IF(C67="----","#N/A",CONCATENATE("CV|",SUBSTITUTE(SUBSTITUTE(IF(B67="","NONE",B67),"_","-"),"|","-"),"_","CS|",(VLOOKUP(C67,Dictionary!$Y:$Z,2,FALSE)),"_","CT|",(VLOOKUP(D67,Dictionary!$AE:$AF,2,FALSE)),IF(E67="","",CONCATENATE("_U1|",SUBSTITUTE(SUBSTITUTE(E67,"_","-"),"|","-"))),IF(F67="","",CONCATENATE("_U2|",SUBSTITUTE(SUBSTITUTE(F67,"_","-"),"|","-"))),IF(G67="","",CONCATENATE("_U3|",SUBSTITUTE(SUBSTITUTE(G67,"_","-"),"|","-"))))) -> CV|VDV-MERCHANT-DECOLAR_CS|160x600_CT|BAN_U1|CAMPO_U2|VERIZON
A68: 253127703 | B68: VDV-MERCHANT-DECOLAR | C68: 300x250 | D68: Banner Static (JPG/GIF) | E68: CAMPO | F68: VERIZON | H68: =IF(C68="----","#N/A",CONCATENATE("CV|",SUBSTITUTE(SUBSTITUTE(IF(B68="","NONE",B68),"_","-"),"|","-"),"_","CS|",(VLOOKUP(C68,Dictionary!$Y:$Z,2,FALSE)),"_","CT|",(VLOOKUP(D68,Dictionary!$AE:$AF,2,FALSE)),IF(E68="","",CONCATENATE("_U1|",SUBSTITUTE(SUBSTITUTE(E68,"_","-"),"|","-"))),IF(F68="","",CONCATENATE("_U2|",SUBSTITUTE(SUBSTITUTE(F68,"_","-"),"|","-"))),IF(G68="","",CONCATENATE("_U3|",SUBSTITUTE(SUBSTITUTE(G68,"_","-"),"|","-"))))) -> CV|VDV-MERCHANT-DECOLAR_CS|300x250_CT|BAN_U1|CAMPO_U2|VERIZON
A69: 252686405 | B69: VDV-MERCHANT-DECOLAR | C69: 970x250 | D69: Banner Static (JPG/GIF) | E69: CAMPO | F69: VERIZON | H69: =IF(C69="----","#N/A",CONCATENATE("CV|",SUBSTITUTE(SUBSTITUTE(IF(B69="","NONE",B69),"_","-"),"|","-"),"_","CS|",(VLOOKUP(C69,Dictionary!$Y:$Z,2,FALSE)),"_","CT|",(VLOOKUP(D69,Dictionary!$AE:$AF,2,FALSE)),IF(E69="","",CONCATENATE("_U1|",SUBSTITUTE(SUBSTITUTE(E69,"_","-"),"|","-"))),IF(F69="","",CONCATENATE("_U2|",SUBSTITUTE(SUBSTITUTE(F69,"_","-"),"|","-"))),IF(G69="","",CONCATENATE("_U3|",SUBSTITUTE(SUBSTITUTE(G69,"_","-"),"|","-"))))) -> CV|VDV-MERCHANT-DECOLAR_CS|970x250_CT|BAN_U1|CAMPO_U2|VERIZON
A70: 253158993 | B70: VDV-MERCHANT-DECOLAR | C70: 160x600 | D70: Banner Static (JPG/GIF) | E70: PREDIO | F70: VERIZON | H70: =IF(C70="----","#N/A",CONCATENATE("CV|",SUBSTITUTE(SUBSTITUTE(IF(B70="","NONE",B70),"_","-"),"|","-"),"_","CS|",(VLOOKUP(C70,Dictionary!$Y:$Z,2,FALSE)),"_","CT|",(VLOOKUP(D70,Dictionary!$AE:$AF,2,FALSE)),IF(E70="","",CONCATENATE("_U1|",SUBSTITUTE(SUBSTITUTE(E70,"_","-"),"|","-"))),IF(F70="","",CONCATENATE("_U2|",SUBSTITUTE(SUBSTITUTE(F70,"_","-"),"|","-"))),IF(G70="","",CONCATENATE("_U3|",SUBSTITUTE(SUBSTITUTE(G70,"_","-"),"|","-"))))) -> CV|VDV-MERCHANT-DECOLAR_CS|160x600_CT|BAN_U1|PREDIO_U2|VERIZON
A71: 253065304 | B71: VDV-MERCHANT-DECOLAR | C71: 300x600 | D71: Banner Static (JPG/GIF) | E71: PREDIO | F71: VERIZON | H71: =IF(C71="----","#N/A",CONCATENATE("CV|",SUBSTITUTE(SUBSTITUTE(IF(B71="","NONE",B71),"_","-"),"|","-"),"_","CS|",(VLOOKUP(C71,Dictionary!$Y:$Z,2,FALSE)),"_","CT|",(VLOOKUP(D71,Dictionary!$AE:$AF,2,FALSE)),IF(E71="","",CONCATENATE("_U1|",SUBSTITUTE(SUBSTITUTE(E71,"_","-"),"|","-"))),IF(F71="","",CONCATENATE("_U2|",SUBSTITUTE(SUBSTITUTE(F71,"_","-"),"|","-"))),IF(G71="","",CONCATENATE("_U3|",SUBSTITUTE(SUBSTITUTE(G71,"_","-"),"|","-"))))) -> CV|VDV-MERCHANT-DECOLAR_CS|300x600_CT|BAN_U1|PREDIO_U2|VERIZON
A72: 253064854 | B72: VDV-MERCHANT-DECOLAR | C72: 300x250 | D72: Banner Static (JPG/GIF) | E72: MAR | F72: VERIZON | H72: =IF(C72="----","#N/A",CONCATENATE("CV|",SUBSTITUTE(SUBSTITUTE(IF(B72="","NONE",B72),"_","-"),"|","-"),"_","CS|",(VLOOKUP(C72,Dictionary!$Y:$Z,2,FALSE)),"_","CT|",(VLOOKUP(D72,Dictionary!$AE:$AF,2,FALSE)),IF(E72="","",CONCATENATE("_U1|",SUBSTITUTE(SUBSTITUTE(E72,"_","-"),"|","-"))),IF(F72="","",CONCATENATE("_U2|",SUBSTITUTE(SUBSTITUTE(F72,"_","-"),"|","-"))),IF(G72="","",CONCATENATE("_U3|",SUBSTITUTE(SUBSTITUTE(G72,"_","-"),"|","-"))))) -> CV|VDV-MERCHANT-DECOLAR_CS|300x250_CT|BAN_U1|MAR_U2|VERIZON
A73: 253065295 | B73: VDV-MERCHANT-DECOLAR | C73: 300x250 | D73: Banner Static (JPG/GIF) | E73: PREDIO | F73: VERIZON | H73: =IF(C73="----","#N/A",CONCATENATE("CV|",SUBSTITUTE(SUBSTITUTE(IF(B73="","NONE",B73),"_","-"),"|","-"),"_","CS|",(VLOOKUP(C73,Dictionary!$Y:$Z,2,FALSE)),"_","CT|",(VLOOKUP(D73,Dictionary!$AE:$AF,2,FALSE)),IF(E73="","",CONCATENATE("_U1|",SUBSTITUTE(SUBSTITUTE(E73,"_","-"),"|","-"))),IF(F73="","",CONCATENATE("_U2|",SUBSTITUTE(SUBSTITUTE(F73,"_","-"),"|","-"))),IF(G73="","",CONCATENATE("_U3|",SUBSTITUTE(SUBSTITUTE(G73,"_","-"),"|","-"))))) -> CV|VDV-MERCHANT-DECOLAR_CS|300x250_CT|BAN_U1|PREDIO_U2|VERIZON
A74: 253065316 | B74: VDV-MERCHANT-DECOLAR | C74: 970x250 | D74: Banner Static (JPG/GIF) | E74: PREDIO | F74: VERIZON | H74: =IF(C74="----","#N/A",CONCATENATE("CV|",SUBSTITUTE(SUBSTITUTE(IF(B74="","NONE",B74),"_","-"),"|","-"),"_","CS|",(VLOOKUP(C74,Dictionary!$Y:$Z,2,FALSE)),"_","CT|",(VLOOKUP(D74,Dictionary!$AE:$AF,2,FALSE)),IF(E74="","",CONCATENATE("_U1|",SUBSTITUTE(SUBSTITUTE(E74,"_","-"),"|","-"))),IF(F74="","",CONCATENATE("_U2|",SUBSTITUTE(SUBSTITUTE(F74,"_","-"),"|","-"))),IF(G74="","",CONCATENATE("_U3|",SUBSTITUTE(SUBSTITUTE(G74,"_","-"),"|","-"))))) -> CV|VDV-MERCHANT-DECOLAR_CS|970x250_CT|BAN_U1|PREDIO_U2|VERIZON
A75: 253065325 | B75: VDV-MERCHANT-DECOLAR | C75: 160x600 | D75: Banner Static (JPG/GIF) | E75: MAR | F75: VERIZON | H75: =IF(C75="----","#N/A",CONCATENATE("CV|",SUBSTITUTE(SUBSTITUTE(IF(B75="","NONE",B75),"_","-"),"|","-"),"_","CS|",(VLOOKUP(C75,Dictionary!$Y:$Z,2,FALSE)),"_","CT|",(VLOOKUP(D75,Dictionary!$AE:$AF,2,FALSE)),IF(E75="","",CONCATENATE("_U1|",SUBSTITUTE(SUBSTITUTE(E75,"_","-"),"|","-"))),IF(F75="","",CONCATENATE("_U2|",SUBSTITUTE(SUBSTITUTE(F75,"_","-"),"|","-"))),IF(G75="","",CONCATENATE("_U3|",SUBSTITUTE(SUBSTITUTE(G75,"_","-"),"|","-"))))) -> CV|VDV-MERCHANT-DECOLAR_CS|160x600_CT|BAN_U1|MAR_U2|VERIZON
A76: 252712010 | B76: VDV-MERCHANT-DECOLAR | C76: 970x250 | D76: Banner Static (JPG/GIF) | E76: MAR | F76: VERIZON | H76: =IF(C76="----","#N/A",CONCATENATE("CV|",SUBSTITUTE(SUBSTITUTE(IF(B76="","NONE",B76),"_","-"),"|","-"),"_","CS|",(VLOOKUP(C76,Dictionary!$Y:$Z,2,FALSE)),"_","CT|",(VLOOKUP(D76,Dictionary!$AE:$AF,2,FALSE)),IF(E76="","",CONCATENATE("_U1|",SUBSTITUTE(SUBSTITUTE(E76,"_","-"),"|","-"))),IF(F76="","",CONCATENATE("_U2|",SUBSTITUTE(SUBSTITUTE(F76,"_","-"),"|","-"))),IF(G76="","",CONCATENATE("_U3|",SUBSTITUTE(SUBSTITUTE(G76,"_","-"),"|","-"))))) -> CV|VDV-MERCHANT-DECOLAR_CS|970x250_CT|BAN_U1|MAR_U2|VERIZON
... A78: 253064878 | B78: VDV-MERCHANT-DECOLAR | C78: 300x600 | D78: Banner Static (JPG/GIF) | E78: MAR | F78: VERIZON | H78: =IF(C78="----","#N/A",CONCATENATE("CV|",SUBSTITUTE(SUBSTITUTE(IF(B78="","NONE",B78),"_","-"),"|","-"),"_","CS|",(VLOOKUP(C78,Dictionary!$Y:$Z,2,FALSE)),"_","CT|",(VLOOKUP(D78,Dictionary!$AE:$AF,2,FALSE)),IF(E78="","",CONCATENATE("_U1|",SUBSTITUTE(SUBSTITUTE(E78,"_","-"),"|","-"))),IF(F78="","",CONCATENATE("_U2|",SUBSTITUTE(SUBSTITUTE(F78,"_","-"),"|","-"))),IF(G78="","",CONCATENATE("_U3|",SUBSTITUTE(SUBSTITUTE(G78,"_","-"),"|","-"))))) -> CV|VDV-MERCHANT-DECOLAR_CS|300x600_CT|BAN_U1|MAR_U2|VERIZON
A79: 253118213 | B79: VDV-PROMONACIONAL | C79: 1X1 | D79: FB Gif | E79: GANHADORES | H79: =IF(C79="----","#N/A",CONCATENATE("CV|",SUBSTITUTE(SUBSTITUTE(IF(B79="","NONE",B79),"_","-"),"|","-"),"_","CS|",(VLOOKUP(C79,Dictionary!$Y:$Z,2,FALSE)),"_","CT|",(VLOOKUP(D79,Dictionary!$AE:$AF,2,FALSE)),IF(E79="","",CONCATENATE("_U1|",SUBSTITUTE(SUBSTITUTE(E79,"_","-"),"|","-"))),IF(F79="","",CONCATENATE("_U2|",SUBSTITUTE(SUBSTITUTE(F79,"_","-"),"|","-"))),IF(G79="","",CONCATENATE("_U3|",SUBSTITUTE(SUBSTITUTE(G79,"_","-"),"|","-"))))) -> CV|VDV-PROMONACIONAL_CS|1x1_CT|FGIF_U1|GANHADORES
A80: 253561005 | B80: VDV-PROMONACIONAL | C80: 1X1 | D80: FB Link Ad | E80: GANHADORES | H80: =IF(C80="----","#N/A",CONCATENATE("CV|",SUBSTITUTE(SUBSTITUTE(IF(B80="","NONE",B80),"_","-"),"|","-"),"_","CS|",(VLOOKUP(C80,Dictionary!$Y:$Z,2,FALSE)),"_","CT|",(VLOOKUP(D80,Dictionary!$AE:$AF,2,FALSE)),IF(E80="","",CONCATENATE("_U1|",SUBSTITUTE(SUBSTITUTE(E80,"_","-"),"|","-"))),IF(F80="","",CONCATENATE("_U2|",SUBSTITUTE(SUBSTITUTE(F80,"_","-"),"|","-"))),IF(G80="","",CONCATENATE("_U3|",SUBSTITUTE(SUBSTITUTE(G80,"_","-"),"|","-"))))) -> CV|VDV-PROMONACIONAL_CS|1x1_CT|FLA_U1|GANHADORES
A81: 253116236 | B81: VDV-PROMONACIONAL | C81: 1X1 | D81: IG Story | E81: GANHADORES | H81: =IF(C81="----","#N/A",CONCATENATE("CV|",SUBSTITUTE(SUBSTITUTE(IF(B81="","NONE",B81),"_","-"),"|","-"),"_","CS|",(VLOOKUP(C81,Dictionary!$Y:$Z,2,FALSE)),"_","CT|",(VLOOKUP(D81,Dictionary!$AE:$AF,2,FALSE)),IF(E81="","",CONCATENATE("_U1|",SUBSTITUTE(SUBSTITUTE(E81,"_","-"),"|","-"))),IF(F81="","",CONCATENATE("_U2|",SUBSTITUTE(SUBSTITUTE(F81,"_","-"),"|","-"))),IF(G81="","",CONCATENATE("_U3|",SUBSTITUTE(SUBSTITUTE(G81,"_","-"),"|","-"))))) -> CV|VDV-PROMONACIONAL_CS|1x1_CT|INSSTORY_U1|GANHADORES
A82: 253832721 | B82: VDV-MERCHANT-DECOLAR | C82: 1X1 | D82: IG Story | E82: PRAIA | H82: =IF(C82="----","#N/A",CONCATENATE("CV|",SUBSTITUTE(SUBSTITUTE(IF(B82="","NONE",B82),"_","-"),"|","-"),"_","CS|",(VLOOKUP(C82,Dictionary!$Y:$Z,2,FALSE)),"_","CT|",(VLOOKUP(D82,Dictionary!$AE:$AF,2,FALSE)),IF(E82="","",CONCATENATE("_U1|",SUBSTITUTE(SUBSTITUTE(E82,"_","-"),"|","-"))),IF(F82="","",CONCATENATE("_U2|",SUBSTITUTE(SUBSTITUTE(F82,"_","-"),"|","-"))),IF(G82="","",CONCATENATE("_U3|",SUBSTITUTE(SUBSTITUTE(G82,"_","-"),"|","-"))))) -> CV|VDV-MERCHANT-DECOLAR_CS|1x1_CT|INSSTORY_U1|PRAIA
A83: 253832718 | B83: VDV-MERCHANT-DECOLAR | C83: 1X1 | D83: FB Link Ad | E83: PRAIA | H83: =IF(C83="----","#N/A",CONCATENATE("CV|",SUBSTITUTE(SUBSTITUTE(IF(B83="","NONE",B83),"_","-"),"|","-"),"_","CS|",(VLOOKUP(C83,Dictionary!$Y:$Z,2,FALSE)),"_","CT|",(VLOOKUP(D83,Dictionary!$AE:$AF,2,FALSE)),IF(E83="","",CONCATENATE("_U1|",SUBSTITUTE(SUBSTITUTE(E83,"_","-"),"|","-"))),IF(F83="","",CONCATENATE("_U2|",SUBSTITUTE(SUBSTITUTE(F83,"_","-"),"|","-"))),IF(G83="","",CONCATENATE("_U3|",SUBSTITUTE(SUBSTITUTE(G83,"_","-"),"|","-"))))) -> CV|VDV-MERCHANT-DECOLAR_CS|1x1_CT|FLA_U1|PRAIA
A84: 253832715 | B84: VDV-MERCHANT-DECOLAR | C84: 1X1 | D84: FB Carousel | E84: PRAIA | H84: =IF(C84="----","#N/A",CONCATENATE("CV|",SUBSTITUTE(SUBSTITUTE(IF(B84="","NONE",B84),"_","-"),"|","-"),"_","CS|",(VLOOKUP(C84,Dictionary!$Y:$Z,2,FALSE)),"_","CT|",(VLOOKUP(D84,Dictionary!$AE:$AF,2,FALSE)),IF(E84="","",CONCATENATE("_U1|",SUBSTITUTE(SUBSTITUTE(E84,"_","-"),"|","-"))),IF(F84="","",CONCATENATE("_U2|",SUBSTITUTE(SUBSTITUTE(F84,"_","-"),"|","-"))),IF(G84="","",CONCATENATE("_U3|",SUBSTITUTE(SUBSTITUTE(G84,"_","-"),"|","-"))))) -> CV|VDV-MERCHANT-DECOLAR_CS|1x1_CT|FCR_U1|PRAIA
A85: 253832712 | B85: VDV-MERCHANT-DECOLAR | C85: 1X1 | D85: FB Gif | E85: PRAIA | H85: =IF(C85="----","#N/A",CONCATENATE("CV|",SUBSTITUTE(SUBSTITUTE(IF(B85="","NONE",B85),"_","-"),"|","-"),"_","CS|",(VLOOKUP(C85,Dictionary!$Y:$Z,2,FALSE)),"_","CT|",(VLOOKUP(D85,Dictionary!$AE:$AF,2,FALSE)),IF(E85="","",CONCATENATE("_U1|",SUBSTITUTE(SUBSTITUTE(E85,"_","-"),"|","-"))),IF(F85="","",CONCATENATE("_U2|",SUBSTITUTE(SUBSTITUTE(F85,"_","-"),"|","-"))),IF(G85="","",CONCATENATE("_U3|",SUBSTITUTE(SUBSTITUTE(G85,"_","-"),"|","-"))))) -> CV|VDV-MERCHANT-DECOLAR_CS|1x1_CT|FGIF_U1|PRAIA
A86: 253832709 | B86: VDV-MERCHANT-DECOLAR | C86: 1X1 | D86: IG Story | E86: MONTANHA | H86: =IF(C86="----","#N/A",CONCATENATE("CV|",SUBSTITUTE(SUBSTITUTE(IF(B86="","NONE",B86),"_","-"),"|","-"),"_","CS|",(VLOOKUP(C86,Dictionary!$Y:$Z,2,FALSE)),"_","CT|",(VLOOKUP(D86,Dictionary!$AE:$AF,2,FALSE)),IF(E86="","",CONCATENATE("_U1|",SUBSTITUTE(SUBSTITUTE(E86,"_","-"),"|","-"))),IF(F86="","",CONCATENATE("_U2|",SUBSTITUTE(SUBSTITUTE(F86,"_","-"),"|","-"))),IF(G86="","",CONCATENATE("_U3|",SUBSTITUTE(SUBSTITUTE(G86,"_","-"),"|","-"))))) -> CV|VDV-MERCHANT-DECOLAR_CS|1x1_CT|INSSTORY_U1|MONTANHA
A87: 253832706 | B87: VDV-MERCHANT-DECOLAR | C87: 1X1 | D87: FB Link Ad | E87: MONTANHA | H87: =IF(C87="----","#N/A",CONCATENATE("CV|",SUBSTITUTE(SUBSTITUTE(IF(B87="","NONE",B87),"_","-"),"|","-"),"_","CS|",(VLOOKUP(C87,Dictionary!$Y:$Z,2,FALSE)),"_","CT|",(VLOOKUP(D87,Dictionary!$AE:$AF,2,FALSE)),IF(E87="","",CONCATENATE("_U1|",SUBSTITUTE(SUBSTITUTE(E87,"_","-"),"|","-"))),IF(F87="","",CONCATENATE("_U2|",SUBSTITUTE(SUBSTITUTE(F87,"_","-"),"|","-"))),IF(G87="","",CONCATENATE("_U3|",SUBSTITUTE(SUBSTITUTE(G87,"_","-"),"|","-"))))) -> CV|VDV-MERCHANT-DECOLAR_CS|1x1_CT|FLA_U1|MONTANHA
A88: 253832703 | B88: VDV-MERCHANT-DECOLAR | C88: 1X1 | D88: FB Carousel | E88: MONTANHA | H88: =IF(C88="----","#N/A",CONCATENATE("CV|",SUBSTITUTE(SUBSTITUTE(IF(B88="","NONE",B88),"_","-"),"|","-"),"_","CS|",(VLOOKUP(C88,Dictionary!$Y:$Z,2,FALSE)),"_","CT|",(VLOOKUP(D88,Dictionary!$AE:$AF,2,FALSE)),IF(E88="","",CONCATENATE("_U1|",SUBSTITUTE(SUBSTITUTE(E88,"_","-"),"|","-"))),IF(F88="","",CONCATENATE("_U2|",SUBSTITUTE(SUBSTITUTE(F88,"_","-"),"|","-"))),IF(G88="","",CONCATENATE("_U3|",SUBSTITUTE(SUBSTITUTE(G88,"_","-"),"|","-"))))) -> CV|VDV-MERCHANT-DECOLAR_CS|1x1_CT|FCR_U1|MONTANHA
A89: 253832700 | B89: VDV-MERCHANT-DECOLAR | C89: 1X1 | D89: FB Gif | E89: MONTANHA | H89: =IF(C89="----","#N/A",CONCATENATE("CV|",SUBSTITUTE(SUBSTITUTE(IF(B89="","NONE",B89),"_","-"),"|","-"),"_","CS|",(VLOOKUP(C89,Dictionary!$Y:$Z,2,FALSE)),"_","CT|",(VLOOKUP(D89,Dictionary!$AE:$AF,2,FALSE)),IF(E89="","",CONCATENATE("_U1|",SUBSTITUTE(SUBSTITUTE(E89,"_","-"),"|","-"))),IF(F89="","",CONCATENATE("_U2|",SUBSTITUTE(SUBSTITUTE(F89,"_","-"),"|","-"))),IF(G89="","",CONCATENATE("_U3|",SUBSTITUTE(SUBSTITUTE(G89,"_","-"),"|","-"))))) -> CV|VDV-MERCHANT-DECOLAR_CS|1x1_CT|FGIF_U1|MONTANHA
A90: 253472006 | B90: VDV-PROMONACIONAL | C90: 1200x627 | D90: Native | E90: KV-AMARELO | H90: =IF(C90="----","#N/A",CONCATENATE("CV|",SUBSTITUTE(SUBSTITUTE(IF(B90="","NONE",B90),"_","-"),"|","-"),"_","CS|",(VLOOKUP(C90,Dictionary!$Y:$Z,2,FALSE)),"_","CT|",(VLOOKUP(D90,Dictionary!$AE:$AF,2,FALSE)),IF(E90="","",CONCATENATE("_U1|",SUBSTITUTE(SUBSTITUTE(E90,"_","-"),"|","-"))),IF(F90="","",CONCATENATE("_U2|",SUBSTITUTE(SUBSTITUTE(F90,"_","-"),"|","-"))),IF(G90="","",CONCATENATE("_U3|",SUBSTITUTE(SUBSTITUTE(G90,"_","-"),"|","-"))))) -> CV|VDV-PROMONACIONAL_CS|1200x627_CT|NAT_U1|KV-AMARELO
... A99: 254166021 | B99: VDV-MERCHANT-ZATTINI-15OFF | C99: 1X1 | D99: IG Story | E99: FEMININO | H99: =IF(C99="----","#N/A",CONCATENATE("CV|",SUBSTITUTE(SUBSTITUTE(IF(B99="","NONE",B99),"_","-"),"|","-"),"_","CS|",(VLOOKUP(C99,Dictionary!$Y:$Z,2,FALSE)),"_","CT|",(VLOOKUP(D99,Dictionary!$AE:$AF,2,FALSE)),IF(E99="","",CONCATENATE("_U1|",SUBSTITUTE(SUBSTITUTE(E99,"_","-"),"|","-"))),IF(F99="","",CONCATENATE("_U2|",SUBSTITUTE(SUBSTITUTE(F99,"_","-"),"|","-"))),IF(G99="","",CONCATENATE("_U3|",SUBSTITUTE(SUBSTITUTE(G99,"_","-"),"|","-"))))) -> CV|VDV-MERCHANT-ZATTINI-15OFF_CS|1x1_CT|INSSTORY_U1|FEMININO
A100: 253822499 | B100: VDV-PROMONACIONAL | C100: 627x627 | D100: Native | E100: KVAMARELO | F100: TESTE-DSP | H100: =IF(C100="----","#N/A",CONCATENATE("CV|",SUBSTITUTE(SUBSTITUTE(IF(B100="","NONE",B100),"_","-"),"|","-"),"_","CS|",(VLOOKUP(C100,Dictionary!$Y:$Z,2,FALSE)),"_","CT|",(VLOOKUP(D100,Dictionary!$AE:$AF,2,FALSE)),IF(E100="","",CONCATENATE("_U1|",SUBSTITUTE(SUBSTITUTE(E100,"_","-"),"|","-"))),IF(F100="","",CONCATENATE("_U2|",SUBSTITUTE(SUBSTITUTE(F100,"_","-"),"|","-"))),IF(G100="","",CONCATENATE("_U3|",SUBSTITUTE(SUBSTITUTE(G100,"_","-"),"|","-"))))) -> CV|VDV-PROMONACIONAL_CS|627x627_CT|NAT_U1|KVAMARELO_U2|TESTE-DSP
A101: 254745531 | B101: VDV-MERCHANT-DECOLAR | C101: 1X1 | D101: FB Link Ad | E101: OPORTUNIDADE-PISCINA | H101: =IF(C101="----","#N/A",CONCATENATE("CV|",SUBSTITUTE(SUBSTITUTE(IF(B101="","NONE",B101),"_","-"),"|","-"),"_","CS|",(VLOOKUP(C101,Dictionary!$Y:$Z,2,FALSE)),"_","CT|",(VLOOKUP(D101,Dictionary!$AE:$AF,2,FALSE)),IF(E101="","",CONCATENATE("_U1|",SUBSTITUTE(SUBSTITUTE(E101,"_","-"),"|","-"))),IF(F101="","",CONCATENATE("_U2|",SUBSTITUTE(SUBSTITUTE(F101,"_","-"),"|","-"))),IF(G101="","",CONCATENATE("_U3|",SUBSTITUTE(SUBSTITUTE(G101,"_","-"),"|","-"))))) -> CV|VDV-MERCHANT-DECOLAR_CS|1x1_CT|FLA_U1|OPORTUNIDADE-PISCINA
A102: 254380280 | B102: VDV-PROMONACIONAL | C102: 1X1 | D102: IG Story | E102: CHANCECHANCE-FUTEBOL | H102: =IF(C102="----","#N/A",CONCATENATE("CV|",SUBSTITUTE(SUBSTITUTE(IF(B102="","NONE",B102),"_","-"),"|","-"),"_","CS|",(VLOOKUP(C102,Dictionary!$Y:$Z,2,FALSE)),"_","CT|",(VLOOKUP(D102,Dictionary!$AE:$AF,2,FALSE)),IF(E102="","",CONCATENATE("_U1|",SUBSTITUTE(SUBSTITUTE(E102,"_","-"),"|","-"))),IF(F102="","",CONCATENATE("_U2|",SUBSTITUTE(SUBSTITUTE(F102,"_","-"),"|","-"))),IF(G102="","",CONCATENATE("_U3|",SUBSTITUTE(SUBSTITUTE(G102,"_","-"),"|","-"))))) -> CV|VDV-PROMONACIONAL_CS|1x1_CT|INSSTORY_U1|CHANCECHANCE-FUTEBOL
A103: 254380283 | B103: VDV-PROMONACIONAL | C103: 1X1 | D103: IG Story | E103: CHANCECHANCE-BASQUETE | H103: =IF(C103="----","#N/A",CONCATENATE("CV|",SUBSTITUTE(SUBSTITUTE(IF(B103="","NONE",B103),"_","-"),"|","-"),"_","CS|",(VLOOKUP(C103,Dictionary!$Y:$Z,2,FALSE)),"_","CT|",(VLOOKUP(D103,Dictionary!$AE:$AF,2,FALSE)),IF(E103="","",CONCATENATE("_U1|",SUBSTITUTE(SUBSTITUTE(E103,"_","-"),"|","-"))),IF(F103="","",CONCATENATE("_U2|",SUBSTITUTE(SUBSTITUTE(F103,"_","-"),"|","-"))),IF(G103="","",CONCATENATE("_U3|",SUBSTITUTE(SUBSTITUTE(G103,"_","-"),"|","-"))))) -> CV|VDV-PROMONACIONAL_CS|1x1_CT|INSSTORY_U1|CHANCECHANCE-BASQUETE
A104: 254860515 | B104: VDV-PROMONACIONAL | C104: 1X1 | D104: FB Link Ad | E104: CHANCECHANCE-BOCEJO | H104: =IF(C104="----","#N/A",CONCATENATE("CV|",SUBSTITUTE(SUBSTITUTE(IF(B104="","NONE",B104),"_","-"),"|","-"),"_","CS|",(VLOOKUP(C104,Dictionary!$Y:$Z,2,FALSE)),"_","CT|",(VLOOKUP(D104,Dictionary!$AE:$AF,2,FALSE)),IF(E104="","",CONCATENATE("_U1|",SUBSTITUTE(SUBSTITUTE(E104,"_","-"),"|","-"))),IF(F104="","",CONCATENATE("_U2|",SUBSTITUTE(SUBSTITUTE(F104,"_","-"),"|","-"))),IF(G104="","",CONCATENATE("_U3|",SUBSTITUTE(SUBSTITUTE(G104,"_","-"),"|","-"))))) -> CV|VDV-PROMONACIONAL_CS|1x1_CT|FLA_U1|CHANCECHANCE-BOCEJO
A105: 254860518 | B105: VDV-PROMONACIONAL | C105: 1X1 | D105: FB Gif | E105: CHANCECHANCE-BASQUETE | H105: =IF(C105="----","#N/A",CONCATENATE("CV|",SUBSTITUTE(SUBSTITUTE(IF(B105="","NONE",B105),"_","-"),"|","-"),"_","CS|",(VLOOKUP(C105,Dictionary!$Y:$Z,2,FALSE)),"_","CT|",(VLOOKUP(D105,Dictionary!$AE:$AF,2,FALSE)),IF(E105="","",CONCATENATE("_U1|",SUBSTITUTE(SUBSTITUTE(E105,"_","-"),"|","-"))),IF(F105="","",CONCATENATE("_U2|",SUBSTITUTE(SUBSTITUTE(F105,"_","-"),"|","-"))),IF(G105="","",CONCATENATE("_U3|",SUBSTITUTE(SUBSTITUTE(G105,"_","-"),"|","-"))))) -> CV|VDV-PROMONACIONAL_CS|1x1_CT|FGIF_U1|CHANCECHANCE-BASQUETE
A106: 254860521 | B106: VDV-PROMONACIONAL | C106: 1X1 | D106: FB Carousel | E106: CHANCECHANCE-VOZDEBEBE | H106: =IF(C106="----","#N/A",CONCATENATE("CV|",SUBSTITUTE(SUBSTITUTE(IF(B106="","NONE",B106),"_","-"),"|","-"),"_","CS|",(VLOOKUP(C106,Dictionary!$Y:$Z,2,FALSE)),"_","CT|",(VLOOKUP(D106,Dictionary!$AE:$AF,2,FALSE)),IF(E106="","",CONCATENATE("_U1|",SUBSTITUTE(SUBSTITUTE(E106,"_","-"),"|","-"))),IF(F106="","",CONCATENATE("_U2|",SUBSTITUTE(SUBSTITUTE(F106,"_","-"),"|","-"))),IF(G106="","",CONCATENATE("_U3|",SUBSTITUTE(SUBSTITUTE(G106,"_","-"),"|","-"))))) -> CV|VDV-PROMONACIONAL_CS|1x1_CT|FCR_U1|CHANCECHANCE-VOZDEBEBE
A107: 254860524 | B107: VDV-PROMONACIONAL | C107: 1X1 | D107: FB Carousel | E107: CHANCECHANCE-BOCEJO | H107: =IF(C107="----","#N/A",CONCATENATE("CV|",SUBSTITUTE(SUBSTITUTE(IF(B107="","NONE",B107),"_","-"),"|","-"),"_","CS|",(VLOOKUP(C107,Dictionary!$Y:$Z,2,FALSE)),"_","CT|",(VLOOKUP(D107,Dictionary!$AE:$AF,2,FALSE)),IF(E107="","",CONCATENATE("_U1|",SUBSTITUTE(SUBSTITUTE(E107,"_","-"),"|","-"))),IF(F107="","",CONCATENATE("_U2|",SUBSTITUTE(SUBSTITUTE(F107,"_","-"),"|","-"))),IF(G107="","",CONCATENATE("_U3|",SUBSTITUTE(SUBSTITUTE(G107,"_","-"),"|","-"))))) -> CV|VDV-PROMONACIONAL_CS|1x1_CT|FCR_U1|CHANCECHANCE-BOCEJO
A108: 254862021 | B108: VDV-PROMONACIONAL | C108: Video :6 | D108: Youtube non-skippable | E108: CHANCECHANCE | H108: =IF(C108="----","#N/A",CONCATENATE("CV|",SUBSTITUTE(SUBSTITUTE(IF(B108="","NONE",B108),"_","-"),"|","-"),"_","CS|",(VLOOKUP(C108,Dictionary!$Y:$Z,2,FALSE)),"_","CT|",(VLOOKUP(D108,Dictionary!$AE:$AF,2,FALSE)),IF(E108="","",CONCATENATE("_U1|",SUBSTITUTE(SUBSTITUTE(E108,"_","-"),"|","-"))),IF(F108="","",CONCATENATE("_U2|",SUBSTITUTE(SUBSTITUTE(F108,"_","-"),"|","-"))),IF(G108="","",CONCATENATE("_U3|",SUBSTITUTE(SUBSTITUTE(G108,"_","-"),"|","-"))))) -> CV|VDV-PROMONACIONAL_CS|VID:6_CT|YTNSK_U1|CHANCECHANCE
A109: 254746266 | B109: VDV-MERCHANT-DECOLAR | C109: 1X1 | D109: FB Gif | E109: OPORTUNIDADE-PISCINA | H109: =IF(C109="----","#N/A",CONCATENATE("CV|",SUBSTITUTE(SUBSTITUTE(IF(B109="","NONE",B109),"_","-"),"|","-"),"_","CS|",(VLOOKUP(C109,Dictionary!$Y:$Z,2,FALSE)),"_","CT|",(VLOOKUP(D109,Dictionary!$AE:$AF,2,FALSE)),IF(E109="","",CONCATENATE("_U1|",SUBSTITUTE(SUBSTITUTE(E109,"_","-"),"|","-"))),IF(F109="","",CONCATENATE("_U2|",SUBSTITUTE(SUBSTITUTE(F109,"_","-"),"|","-"))),IF(G109="","",CONCATENATE("_U3|",SUBSTITUTE(SUBSTITUTE(G109,"_","-"),"|","-"))))) -> CV|VDV-MERCHANT-DECOLAR_CS|1x1_CT|FGIF_U1|OPORTUNIDADE-PISCINA
...

Sheet AdOps
H1: Legenda das cores
I2: Automático
I3: Preenchido pela Mídia
A4: Cliente: | B4: Visa | I4: Preenchido pela opec
A5: Advertiser | B5: VISA_BR_Brand/Other_BBDO
A6: Campanha: | B6: MK|BR_CN|DOTZ_MN|NONE_YQ|20Q1Q4_CP|5020004460_SP|NA_AC|CMKT
A8: Ação | B8: Status AdOps | C8: Data | D8: Data Final | E8: Servido por | F8: Status Mídia Visa | G8: Advertiser/Veículo | H8: Tipo de compra | I8: Creative Size | J8: Placement | K8: Creative | L8: Creative p/ renomear | M8: URL | N8: URL Final Parametrizada
A9: Manter/No Ar | B9: Criado 13/12 | C9: 43536 | D9: 44105 | E9: portal | G9: VERIZON | H9: CPM | I9: ='Placement (DCM)'!L3 -> 627x627 | J9: ='Placement (DCM)'!R3 -> MK|BR_CH|PD_DT|MWIA_PB|VER_FM|NAT_RT|CPM_PD|DOTZ-10MIL_TG|NON_ST|NON_TS|NONE_SZ|627x627_AD|CM1_IT|OO | K9: ='Creative Name'!H3 -> CV|DOTZ-10MIL_CS|627x627_CT|NAT | L9: =SUBSTITUTE(K9,"|","^") -> CV^DOTZ-10MIL_CS^627x627_CT^NAT | M9: https://cartaodotz.dotz.com.br/ | N9: =CONCATENATE(M9,"?utm_source=",G9,"&utm_medium=","ADS","&utm_campaign=",J9,"&utm_content=",K9) -> https://cartaodotz.dotz.com.br/?utm_source=VERIZON&utm_medium=ADS&utm_campaign=MK|BR_CH|PD_DT|MWIA_PB|VER_FM|NAT_RT|CPM_PD|DOTZ-10MIL_TG|NON_ST|NON_TS|NONE_SZ|627x627_AD|CM1_IT|OO&utm_content=CV|DOTZ-10MIL_CS|627x627_CT|NAT
A10: Manter/No Ar | B10: Criado 13/12 | C10: 43536 | D10: 44105 | E10: portal | G10: VERIZON | H10: CPM | I10: ='Placement (DCM)'!L4 -> 627x627 | J10: ='Placement (DCM)'!R4 -> MK|BR_CH|PD_DT|CROSS_PB|VER_FM|NAT_RT|CPM_PD|DOTZ-TAXA-ZERO_TG|NON_ST|NON_TS|NONE_SZ|627x627_AD|CM1_IT|OO | K10: ='Creative Name'!H4 -> CV|DOTZ-TAXA-ZERO_CS|627x627_CT|NAT | L10: =SUBSTITUTE(K10,"|","^") -> CV^DOTZ-TAXA-ZERO_CS^627x627_CT^NAT | M10: https://cartaodotz.dotz.com.br/ | N10: =CONCATENATE(M10,"?utm_source=",G10,"&utm_medium=","ADS","&utm_campaign=",J10,"&utm_content=",K10) -> https://cartaodotz.dotz.com.br/?utm_source=VERIZON&utm_medium=ADS&utm_campaign=MK|BR_CH|PD_DT|CROSS_PB|VER_FM|NAT_RT|CPM_PD|DOTZ-TAXA-ZERO_TG|NON_ST|NON_TS|NONE_SZ|627x627_AD|CM1_IT|OO&utm_content=CV|DOTZ-TAXA-ZERO_CS|627x627_CT|NAT
A11: Manter/No Ar | B11: Enviado 09/03 | Atualizado 29/05 | Atualizado 28/10 | C11: 44077 | D11: 44197 | E11: portal | G11: FACEBOOK | H11: CPM | I11: ='Placement (DCM)'!L5 -> 1X1 | J11: ='Placement (DCM)'!R5 -> MK|BR_CH|PSD_DT|CROSS_PB|FCBK_FM|LNK_RT|CPM_PD|DOTZ-10MIL-AZUL_TG|NON_ST|NON_TS|NONE_SZ|1X1_AD|CM1_IT|SOC | K11: ='Creative Name'!H5 -> CV|DOTZ-10MIL-AZUL_CS|1x1_CT|FLA | L11: =SUBSTITUTE(K11,"|","^") -> CV^DOTZ-10MIL-AZUL_CS^1x1_CT^FLA | M11: https://cartaodotz.dotz.com.br/dotz-bb | N11: =CONCATENATE(M11,"?utm_source=",G11,"&utm_medium=","ADS","&utm_campaign=",J11,"&utm_content=",K11) -> https://cartaodotz.dotz.com.br/dotz-bb?utm_source=FACEBOOK&utm_medium=ADS&utm_campaign=MK|BR_CH|PSD_DT|CROSS_PB|FCBK_FM|LNK_RT|CPM_PD|DOTZ-10MIL-AZUL_TG|NON_ST|NON_TS|NONE_SZ|1X1_AD|CM1_IT|SOC&utm_content=CV|DOTZ-10MIL-AZUL_CS|1x1_CT|FLA
A12: Manter/No Ar | B12: Enviado 09/03 | Atualizado 29/05 | Atualizado 28/10 | C12: 44077 | D12: 44197 | E12: portal | G12: FACEBOOK | H12: CPM | I12: ='Placement (DCM)'!L6 -> 1X1 | J12: ='Placement (DCM)'!R6 -> MK|BR_CH|PSD_DT|CROSS_PB|FCBK_FM|LNK_RT|CPM_PD|DOTZ-10MIL-AZUL-QUAD_TG|NON_ST|NON_TS|NONE_SZ|1X1_AD|CM1_IT|SOC | K12: ='Creative Name'!H6 -> CV|DOTZ-10MIL-AZUL-QUAD_CS|1x1_CT|FLA | L12: =SUBSTITUTE(K12,"|","^") -> CV^DOTZ-10MIL-AZUL-QUAD_CS^1x1_CT^FLA | M12: https://cartaodotz.dotz.com.br/dotz-bb | N12: =CONCATENATE(M12,"?utm_source=",G12,"&utm_medium=","ADS","&utm_campaign=",J12,"&utm_content=",K12) -> https://cartaodotz.dotz.com.br/dotz-bb?utm_source=FACEBOOK&utm_medium=ADS&utm_campaign=MK|BR_CH|PSD_DT|CROSS_PB|FCBK_FM|LNK_RT|CPM_PD|DOTZ-10MIL-AZUL-QUAD_TG|NON_ST|NON_TS|NONE_SZ|1X1_AD|CM1_IT|SOC&utm_content=CV|DOTZ-10MIL-AZUL-QUAD_CS|1x1_CT|FLA
A13: Manter/No Ar | B13: Enviado 09/03 | Atualizado 29/05 | Atualizado 28/10 | C13: 44077 | D13: 44197 | E13: portal | G13: FACEBOOK | H13: CPM | I13: ='Placement (DCM)'!L7 -> 1X1 | J13: ='Placement (DCM)'!R7 -> MK|BR_CH|PSD_DT|CROSS_PB|FCBK_FM|GIF_RT|CPM_PD|DOTZ-10MIL-AZUL_TG|NON_ST|NON_TS|NONE_SZ|1X1_AD|CM1_IT|SOC | K13: ='Creative Name'!H7 -> CV|DOTZ-10MIL-AZUL_CS|1x1_CT|FGIF | L13: =SUBSTITUTE(K13,"|","^") -> CV^DOTZ-10MIL-AZUL_CS^1x1_CT^FGIF | M13: https://cartaodotz.dotz.com.br/dotz-bb | N13: =CONCATENATE(M13,"?utm_source=",G13,"&utm_medium=","ADS","&utm_campaign=",J13,"&utm_content=",K13) -> https://cartaodotz.dotz.com.br/dotz-bb?utm_source=FACEBOOK&utm_medium=ADS&utm_campaign=MK|BR_CH|PSD_DT|CROSS_PB|FCBK_FM|GIF_RT|CPM_PD|DOTZ-10MIL-AZUL_TG|NON_ST|NON_TS|NONE_SZ|1X1_AD|CM1_IT|SOC&utm_content=CV|DOTZ-10MIL-AZUL_CS|1x1_CT|FGIF
A14: Manter/No Ar | B14: Enviado 09/03 | Atualizado 29/05 | Atualizado 28/10 | C14: 44077 | D14: 44197 | E14: portal | G14: FACEBOOK | H14: CPM | I14: ='Placement (DCM)'!L8 -> 1X1 | J14: ='Placement (DCM)'!R8 -> MK|BR_CH|PSD_DT|CROSS_PB|FCBK_FM|CAR_RT|CPM_PD|DOTZ-10MIL-AZUL_TG|NON_ST|NON_TS|NONE_SZ|1X1_AD|CM1_IT|SOC | K14: ='Creative Name'!H8 -> CV|DOTZ-10MIL-AZUL_CS|1x1_CT|FCR | L14: =SUBSTITUTE(K14,"|","^") -> CV^DOTZ-10MIL-AZUL_CS^1x1_CT^FCR | M14: https://cartaodotz.dotz.com.br/dotz-bb | N14: =CONCATENATE(M14,"?utm_source=",G14,"&utm_medium=","ADS","&utm_campaign=",J14,"&utm_content=",K14) -> https://cartaodotz.dotz.com.br/dotz-bb?utm_source=FACEBOOK&utm_medium=ADS&utm_campaign=MK|BR_CH|PSD_DT|CROSS_PB|FCBK_FM|CAR_RT|CPM_PD|DOTZ-10MIL-AZUL_TG|NON_ST|NON_TS|NONE_SZ|1X1_AD|CM1_IT|SOC&utm_content=CV|DOTZ-10MIL-AZUL_CS|1x1_CT|FCR
A15: Manter/No Ar | B15: Enviado 09/03 | Atualizado 29/05 | Atualizado 28/10 | C15: 44077 | D15: 44197 | E15: portal | G15: FACEBOOK | H15: CPM | I15: ='Placement (DCM)'!L9 -> 1X1 | J15: ='Placement (DCM)'!R9 -> MK|BR_CH|PSD_DT|CROSS_PB|FCBK_FM|STRY_RT|CPM_PD|DOTZ-10MIL-AZUL-CAR_TG|NON_ST|NON_TS|NONE_SZ|1X1_AD|CM1_IT|SOC | K15: ='Creative Name'!H9 -> CV|DOTZ-10MIL-AZUL-CAR_CS|1x1_CT|INSSTORY | L15: =SUBSTITUTE(K15,"|","^") -> CV^DOTZ-10MIL-AZUL-CAR_CS^1x1_CT^INSSTORY | M15: https://cartaodotz.dotz.com.br/dotz-bb | N15: =CONCATENATE(M15,"?utm_source=",G15,"&utm_medium=","ADS","&utm_campaign=",J15,"&utm_content=",K15) -> https://cartaodotz.dotz.com.br/dotz-bb?utm_source=FACEBOOK&utm_medium=ADS&utm_campaign=MK|BR_CH|PSD_DT|CROSS_PB|FCBK_FM|STRY_RT|CPM_PD|DOTZ-10MIL-AZUL-CAR_TG|NON_ST|NON_TS|NONE_SZ|1X1_AD|CM1_IT|SOC&utm_content=CV|DOTZ-10MIL-AZUL-CAR_CS|1x1_CT|INSSTORY
A16: Manter/No Ar | B16: Enviado 09/03 | Atualizado 29/05 | Atualizado 28/10 | C16: 44077 | D16: 44197 | E16: portal | G16: FACEBOOK | H16: CPM | I16: ='Placement (DCM)'!L10 -> 1X1 | J16: ='Placement (DCM)'!R10 -> MK|BR_CH|PSD_DT|CROSS_PB|FCBK_FM|LNK_RT|CPM_PD|DOTZ-ZERO-ANUIDADE-AZUL_TG|NON_ST|NON_TS|NONE_SZ|1X1_AD|CM1_IT|SOC | K16: ='Creative Name'!H10 -> CV|DOTZ-ZERO-ANUIDADE-AZUL_CS|1x1_CT|FLA | L16: =SUBSTITUTE(K16,"|","^") -> CV^DOTZ-ZERO-ANUIDADE-AZUL_CS^1x1_CT^FLA | M16: https://cartaodotz.dotz.com.br/dotz-bb | N16: =CONCATENATE(M16,"?utm_source=",G16,"&utm_medium=","ADS","&utm_campaign=",J16,"&utm_content=",K16) -> https://cartaodotz.dotz.com.br/dotz-bb?utm_source=FACEBOOK&utm_medium=ADS&utm_campaign=MK|BR_CH|PSD_DT|CROSS_PB|FCBK_FM|LNK_RT|CPM_PD|DOTZ-ZERO-ANUIDADE-AZUL_TG|NON_ST|NON_TS|NONE_SZ|1X1_AD|CM1_IT|SOC&utm_content=CV|DOTZ-ZERO-ANUIDADE-AZUL_CS|1x1_CT|FLA
A17: Manter/No Ar | B17: Enviado 09/03 | Atualizado 29/05 | Atualizado 28/10 | C17: 44077 | D17: 44197 | E17: portal | G17: FACEBOOK | H17: CPM | I17: ='Placement (DCM)'!L11 -> 1X1 | J17: ='Placement (DCM)'!R11 -> MK|BR_CH|PSD_DT|CROSS_PB|FCBK_FM|LNK_RT|CPM_PD|DOTZ-ZERO-ANUIDADE-AZUL-QUAD_TG|NON_ST|NON_TS|NONE_SZ|1X1_AD|CM1_IT|SOC | K17: ='Creative Name'!H11 -> CV|DOTZ-ZERO-ANUIDADE-AZUL-QUAD_CS|1x1_CT|FLA | L17: =SUBSTITUTE(K17,"|","^") -> CV^DOTZ-ZERO-ANUIDADE-AZUL-QUAD_CS^1x1_CT^FLA | M17: https://cartaodotz.dotz.com.br/dotz-bb | N17: =CONCATENATE(M17,"?utm_source=",G17,"&utm_medium=","ADS","&utm_campaign=",J17,"&utm_content=",K17) -> https://cartaodotz.dotz.com.br/dotz-bb?utm_source=FACEBOOK&utm_medium=ADS&utm_campaign=MK|BR_CH|PSD_DT|CROSS_PB|FCBK_FM|LNK_RT|CPM_PD|DOTZ-ZERO-ANUIDADE-AZUL-QUAD_TG|NON_ST|NON_TS|NONE_SZ|1X1_AD|CM1_IT|SOC&utm_content=CV|DOTZ-ZERO-ANUIDADE-AZUL-QUAD_CS|1x1_CT|FLA
A18: Manter/No Ar | B18: Enviado 09/03 | Atualizado 29/05 | Atualizado 28/10 | C18: 44077 | D18: 44197 | E18: portal | G18: FACEBOOK | H18: CPM | I18: ='Placement (DCM)'!L12 -> 1X1 | J18: ='Placement (DCM)'!R12 -> MK|BR_CH|PSD_DT|CROSS_PB|FCBK_FM|GIF_RT|CPM_PD|DOTZ-ZERO-ANUIDADE-AZUL_TG|NON_ST|NON_TS|NONE_SZ|1X1_AD|CM1_IT|SOC | K18: ='Creative Name'!H12 -> CV|DOTZ-ZERO-ANUIDADE-AZUL_CS|1x1_CT|FGIF | L18: =SUBSTITUTE(K18,"|","^") -> CV^DOTZ-ZERO-ANUIDADE-AZUL_CS^1x1_CT^FGIF | M18: https://cartaodotz.dotz.com.br/dotz-bb | N18: =CONCATENATE(M18,"?utm_source=",G18,"&utm_medium=","ADS","&utm_campaign=",J18,"&utm_content=",K18) -> https://cartaodotz.dotz.com.br/dotz-bb?utm_source=FACEBOOK&utm_medium=ADS&utm_campaign=MK|BR_CH|PSD_DT|CROSS_PB|FCBK_FM|GIF_RT|CPM_PD|DOTZ-ZERO-ANUIDADE-AZUL_TG|NON_ST|NON_TS|NONE_SZ|1X1_AD|CM1_IT|SOC&utm_content=CV|DOTZ-ZERO-ANUIDADE-AZUL_CS|1x1_CT|FGIF
A19: Manter/No Ar | B19: Enviado 09/03 | Atualizado 29/05 | Atualizado 28/10 | C19: 44077 | D19: 44197 | E19: portal | G19: FACEBOOK | H19: CPM | I19: ='Placement (DCM)'!L13 -> 1X1 | J19: ='Placement (DCM)'!R13 -> MK|BR_CH|PSD_DT|CROSS_PB|FCBK_FM|CAR_RT|CPM_PD|DOTZ-ZERO-ANUIDADE-AZUL_TG|NON_ST|NON_TS|NONE_SZ|1X1_AD|CM1_IT|SOC | K19: ='Creative Name'!H13 -> CV|DOTZ-ZERO-ANUIDADE-AZUL_CS|1x1_CT|FCR | L19: =SUBSTITUTE(K19,"|","^") -> CV^DOTZ-ZERO-ANUIDADE-AZUL_CS^1x1_CT^FCR | M19: https://cartaodotz.dotz.com.br/dotz-bb | N19: =CONCATENATE(M19,"?utm_source=",G19,"&utm_medium=","ADS","&utm_campaign=",J19,"&utm_content=",K19) -> https://cartaodotz.dotz.com.br/dotz-bb?utm_source=FACEBOOK&utm_medium=ADS&utm_campaign=MK|BR_CH|PSD_DT|CROSS_PB|FCBK_FM|CAR_RT|CPM_PD|DOTZ-ZERO-ANUIDADE-AZUL_TG|NON_ST|NON_TS|NONE_SZ|1X1_AD|CM1_IT|SOC&utm_content=CV|DOTZ-ZERO-ANUIDADE-AZUL_CS|1x1_CT|FCR
A20: Manter/No Ar | B20: Enviado 09/03 | Atualizado 29/05 | Atualizado 28/10 | C20: 44077 | D20: 44197 | E20: portal | G20: FACEBOOK | H20: CPM | I20: ='Placement (DCM)'!L14 -> 1X1 | J20: ='Placement (DCM)'!R14 -> MK|BR_CH|PSD_DT|CROSS_PB|FCBK_FM|STRY_RT|CPM_PD|DOTZ-ZERO-ANUIDADE-AZUL-CAR_TG|NON_ST|NON_TS|NONE_SZ|1X1_AD|CM1_IT|SOC | K20: ='Creative Name'!H14 -> CV|DOTZ-ZERO-ANUIDADE-AZUL-CAR_CS|1x1_CT|INSSTORY | L20: =SUBSTITUTE(K20,"|","^") -> CV^DOTZ-ZERO-ANUIDADE-AZUL-CAR_CS^1x1_CT^INSSTORY | M20: https://cartaodotz.dotz.com.br/dotz-bb | N20: =CONCATENATE(M20,"?utm_source=",G20,"&utm_medium=","ADS","&utm_campaign=",J20,"&utm_content=",K20) -> https://cartaodotz.dotz.com.br/dotz-bb?utm_source=FACEBOOK&utm_medium=ADS&utm_campaign=MK|BR_CH|PSD_DT|CROSS_PB|FCBK_FM|STRY_RT|CPM_PD|DOTZ-ZERO-ANUIDADE-AZUL-CAR_TG|NON_ST|NON_TS|NONE_SZ|1X1_AD|CM1_IT|SOC&utm_content=CV|DOTZ-ZERO-ANUIDADE-AZUL-CAR_CS|1x1_CT|INSSTORY
... A52: Manter/No Ar | B52: Criado 10/03 | Atualizado 29/05 | Atualizado 28/10 | C52: 44107 | D52: 44197 | E52: portal | G52: FACEBOOK | H52: CPM | I52: ='Placement (DCM)'!L46 -> 1X1 | J52: ='Placement (DCM)'!R46 -> MK|BR_CH|PSD_DT|CROSS_PB|FCBK_FM|STRY_RT|CPM_PD|DOTZ-10MIL-AZUL_TG|NON_ST|NON_TS|NONE_SZ|1X1_AD|CM1_IT|SOC | K52: ='Creative Name'!H46 -> CV|DOTZ-10MIL-AZUL_CS|1x1_CT|INSSTORY | L52: =SUBSTITUTE(K52,"|","^") -> CV^DOTZ-10MIL-AZUL_CS^1x1_CT^INSSTORY | M52: https://cartaodotz.dotz.com.br/dotz-bb | N52: =CONCATENATE(M52,"?utm_source=",G52,"&utm_medium=","ADS","&utm_campaign=",J52,"&utm_content=",K52) -> https://cartaodotz.dotz.com.br/dotz-bb?utm_source=FACEBOOK&utm_medium=ADS&utm_campaign=MK|BR_CH|PSD_DT|CROSS_PB|FCBK_FM|STRY_RT|CPM_PD|DOTZ-10MIL-AZUL_TG|NON_ST|NON_TS|NONE_SZ|1X1_AD|CM1_IT|SOC&utm_content=CV|DOTZ-10MIL-AZUL_CS|1x1_CT|INSSTORY
A53: Manter/No Ar | B53: Enviado 13/03 | Atualizado 29/05 | Atualizado 28/10 | C53: 13/03/2020 | D53: 44197 | E53: portal | G53: FACEBOOK | H53: CPM | I53: ='Placement (DCM)'!L47 -> 1X1 | J53: ='Placement (DCM)'!R47 -> MK|BR_CH|PSD_DT|CROSS_PB|FCBK_FM|CAR_RT|CPM_PD|DOTZ-10MIL-AZUL_TG|NON_ST|NON_TS|NONE_SZ|1X1_AD|CM1_IT|SOC_U1|ESTATICO | K53: ='Creative Name'!H47 -> CV|DOTZ-10MIL-AZUL_CS|1x1_CT|FCR_U1|ESTATICO | L53: =SUBSTITUTE(K53,"|","^") -> CV^DOTZ-10MIL-AZUL_CS^1x1_CT^FCR_U1^ESTATICO | M53: https://cartaodotz.dotz.com.br/dotz-bb | N53: =CONCATENATE(M53,"?utm_source=",G53,"&utm_medium=","ADS","&utm_campaign=",J53,"&utm_content=",K53) -> https://cartaodotz.dotz.com.br/dotz-bb?utm_source=FACEBOOK&utm_medium=ADS&utm_campaign=MK|BR_CH|PSD_DT|CROSS_PB|FCBK_FM|CAR_RT|CPM_PD|DOTZ-10MIL-AZUL_TG|NON_ST|NON_TS|NONE_SZ|1X1_AD|CM1_IT|SOC_U1|ESTATICO&utm_content=CV|DOTZ-10MIL-AZUL_CS|1x1_CT|FCR_U1|ESTATICO
A54: Manter/No Ar | B54: Enviado 13/03 | Atualizado 29/05 | Atualizado 28/10 | C54: 13/03/2020 | D54: 44197 | E54: portal | G54: FACEBOOK | H54: CPM | I54: ='Placement (DCM)'!L48 -> 1X1 | J54: ='Placement (DCM)'!R48 -> MK|BR_CH|PSD_DT|CROSS_PB|FCBK_FM|CAR_RT|CPM_PD|DOTZ-ZERO-ANUIDADE-AZUL_TG|NON_ST|NON_TS|NONE_SZ|1X1_AD|CM1_IT|SOC_U1|ESTATICO | K54: ='Creative Name'!H48 -> CV|DOTZ-ZERO-ANUIDADE-AZUL_CS|1x1_CT|FCR_U1|ESTATICO | L54: =SUBSTITUTE(K54,"|","^") -> CV^DOTZ-ZERO-ANUIDADE-AZUL_CS^1x1_CT^FCR_U1^ESTATICO | M54: https://cartaodotz.dotz.com.br/dotz-bb | N54: =CONCATENATE(M54,"?utm_source=",G54,"&utm_medium=","ADS","&utm_campaign=",J54,"&utm_content=",K54) -> https://cartaodotz.dotz.com.br/dotz-bb?utm_source=FACEBOOK&utm_medium=ADS&utm_campaign=MK|BR_CH|PSD_DT|CROSS_PB|FCBK_FM|CAR_RT|CPM_PD|DOTZ-ZERO-ANUIDADE-AZUL_TG|NON_ST|NON_TS|NONE_SZ|1X1_AD|CM1_IT|SOC_U1|ESTATICO&utm_content=CV|DOTZ-ZERO-ANUIDADE-AZUL_CS|1x1_CT|FCR_U1|ESTATICO
A55: Manter/No Ar | B55: Enviado 13/03 | Atualizado 29/05 | Atualizado 28/10 | C55: 13/03/2020 | D55: 44197 | E55: portal | G55: FACEBOOK | H55: CPM | I55: ='Placement (DCM)'!L49 -> 1X1 | J55: ='Placement (DCM)'!R49 -> MK|BR_CH|PSD_DT|CROSS_PB|FCBK_FM|CAR_RT|CPM_PD|DOTZ-TODOS-BENEFICIOS-AZUL_TG|NON_ST|NON_TS|NONE_SZ|1X1_AD|CM1_IT|SOC_U1|ESTATICO | K55: ='Creative Name'!H49 -> CV|DOTZ-TODOS-BENEFICIOS-AZUL_CS|1x1_CT|FCR_U1|ESTATICO | L55: =SUBSTITUTE(K55,"|","^") -> CV^DOTZ-TODOS-BENEFICIOS-AZUL_CS^1x1_CT^FCR_U1^ESTATICO | M55: https://cartaodotz.dotz.com.br/dotz-bb | N55: =CONCATENATE(M55,"?utm_source=",G55,"&utm_medium=","ADS","&utm_campaign=",J55,"&utm_content=",K55) -> https://cartaodotz.dotz.com.br/dotz-bb?utm_source=FACEBOOK&utm_medium=ADS&utm_campaign=MK|BR_CH|PSD_DT|CROSS_PB|FCBK_FM|CAR_RT|CPM_PD|DOTZ-TODOS-BENEFICIOS-AZUL_TG|NON_ST|NON_TS|NONE_SZ|1X1_AD|CM1_IT|SOC_U1|ESTATICO&utm_content=CV|DOTZ-TODOS-BENEFICIOS-AZUL_CS|1x1_CT|FCR_U1|ESTATICO
A56: Manter/No Ar | B56: Enviado 13/03 | Atualizado 29/05 | Atualizado 28/10 | C56: 13/03/2020 | D56: 44197 | E56: portal | G56: FACEBOOK | H56: CPM | I56: ='Placement (DCM)'!L50 -> 1X1 | J56: ='Placement (DCM)'!R50 -> MK|BR_CH|PSD_DT|CROSS_PB|FCBK_FM|CAR_RT|CPM_PD|DOTZ-10MIL-AMARELO_TG|NON_ST|NON_TS|NONE_SZ|1X1_AD|CM1_IT|SOC_U1|ESTATICO | K56: ='Creative Name'!H50 -> CV|DOTZ-10MIL-AMARELO_CS|1x1_CT|FCR_U1|ESTATICO | L56: =SUBSTITUTE(K56,"|","^") -> CV^DOTZ-10MIL-AMARELO_CS^1x1_CT^FCR_U1^ESTATICO | M56: https://cartaodotz.dotz.com.br/dotz-bb | N56: =CONCATENATE(M56,"?utm_source=",G56,"&utm_medium=","ADS","&utm_campaign=",J56,"&utm_content=",K56) -> https://cartaodotz.dotz.com.br/dotz-bb?utm_source=FACEBOOK&utm_medium=ADS&utm_campaign=MK|BR_CH|PSD_DT|CROSS_PB|FCBK_FM|CAR_RT|CPM_PD|DOTZ-10MIL-AMARELO_TG|NON_ST|NON_TS|NONE_SZ|1X1_AD|CM1_IT|SOC_U1|ESTATICO&utm_content=CV|DOTZ-10MIL-AMARELO_CS|1x1_CT|FCR_U1|ESTATICO
A57: Manter/No Ar | B57: Enviado 13/03 | Atualizado 29/05 | Atualizado 28/10 | C57: 13/03/2020 | D57: 44197 | E57: portal | G57: FACEBOOK | H57: CPM | I57: ='Placement (DCM)'!L51 -> 1X1 | J57: ='Placement (DCM)'!R51 -> MK|BR_CH|PSD_DT|CROSS_PB|FCBK_FM|CAR_RT|CPM_PD|DOTZ-ZERO-ANUIDADE-AMARELO_TG|NON_ST|NON_TS|NONE_SZ|1X1_AD|CM1_IT|SOC_U1|ESTATICO | K57: ='Creative Name'!H51 -> CV|DOTZ-ZERO-ANUIDADE-AMARELO_CS|1x1_CT|FCR_U1|ESTATICO | L57: =SUBSTITUTE(K57,"|","^") -> CV^DOTZ-ZERO-ANUIDADE-AMARELO_CS^1x1_CT^FCR_U1^ESTATICO | M57: https://cartaodotz.dotz.com.br/dotz-bb | N57: =CONCATENATE(M57,"?utm_source=",G57,"&utm_medium=","ADS","&utm_campaign=",J57,"&utm_content=",K57) -> https://cartaodotz.dotz.com.br/dotz-bb?utm_source=FACEBOOK&utm_medium=ADS&utm_campaign=MK|BR_CH|PSD_DT|CROSS_PB|FCBK_FM|CAR_RT|CPM_PD|DOTZ-ZERO-ANUIDADE-AMARELO_TG|NON_ST|NON_TS|NONE_SZ|1X1_AD|CM1_IT|SOC_U1|ESTATICO&utm_content=CV|DOTZ-ZERO-ANUIDADE-AMARELO_CS|1x1_CT|FCR_U1|ESTATICO
A58: Manter/No Ar | B58: Enviado 13/03 | Atualizado 29/05 | Atualizado 28/10 | C58: 13/03/2020 | D58: 44197 | E58: portal | G58: FACEBOOK | H58: CPM | I58: ='Placement (DCM)'!L52 -> 1X1 | J58: ='Placement (DCM)'!R52 -> MK|BR_CH|PSD_DT|CROSS_PB|FCBK_FM|CAR_RT|CPM_PD|DOTZ-TODOS-BENEFICIOS-AMARELO_TG|NON_ST|NON_TS|NONE_SZ|1X1_AD|CM1_IT|SOC_U1|ESTATICO | K58: ='Creative Name'!H52 -> CV|DOTZ-TODOS-BENEFICIOS-AMARELO_CS|1x1_CT|FCR_U1|ESTATICO | L58: =SUBSTITUTE(K58,"|","^") -> CV^DOTZ-TODOS-BENEFICIOS-AMARELO_CS^1x1_CT^FCR_U1^ESTATICO | M58: https://cartaodotz.dotz.com.br/dotz-bb | N58: =CONCATENATE(M58,"?utm_source=",G58,"&utm_medium=","ADS","&utm_campaign=",J58,"&utm_content=",K58) -> https://cartaodotz.dotz.com.br/dotz-bb?utm_source=FACEBOOK&utm_medium=ADS&utm_campaign=MK|BR_CH|PSD_DT|CROSS_PB|FCBK_FM|CAR_RT|CPM_PD|DOTZ-TODOS-BENEFICIOS-AMARELO_TG|NON_ST|NON_TS|NONE_SZ|1X1_AD|CM1_IT|SOC_U1|ESTATICO&utm_content=CV|DOTZ-TODOS-BENEFICIOS-AMARELO_CS|1x1_CT|FCR_U1|ESTATICO
A59: Manter/No Ar | B59: Enviado 13/03 | Atualizado 29/05 | Atualizado 28/10 | C59: 13/03/2020 | D59: 44197 | E59: portal | G59: FACEBOOK | H59: CPM | I59: ='Placement (DCM)'!L53 -> 1X1 | J59: ='Placement (DCM)'!R53 -> MK|BR_CH|PSD_DT|CROSS_PB|FCBK_FM|CAR_RT|CPM_PD|DOTZ-CONVERSAO-AMARELO_TG|NON_ST|NON_TS|NONE_SZ|1X1_AD|CM1_IT|SOC_U1|ESTATICO | K59: ='Creative Name'!H53 -> CV|DOTZ-CONVERSAO-AMARELO_CS|1x1_CT|FCR_U1|ESTATICO | L59: =SUBSTITUTE(K59,"|","^") -> CV^DOTZ-CONVERSAO-AMARELO_CS^1x1_CT^FCR_U1^ESTATICO | M59: https://cartaodotz.dotz.com.br/dotz-bb | N59: =CONCATENATE(M59,"?utm_source=",G59,"&utm_medium=","ADS","&utm_campaign=",J59,"&utm_content=",K59) -> https://cartaodotz.dotz.com.br/dotz-bb?utm_source=FACEBOOK&utm_medium=ADS&utm_campaign=MK|BR_CH|PSD_DT|CROSS_PB|FCBK_FM|CAR_RT|CPM_PD|DOTZ-CONVERSAO-AMARELO_TG|NON_ST|NON_TS|NONE_SZ|1X1_AD|CM1_IT|SOC_U1|ESTATICO&utm_content=CV|DOTZ-CONVERSAO-AMARELO_CS|1x1_CT|FCR_U1|ESTATICO
J60: ='Placement (DCM)'!R54 -> MK|BR_CH|PD_DT|CROSS_PB|DV36_FM|BAN_RT|CPM_PD|DOTZ-10MIL-AZUL_TG|NON_ST|NON_TS|NONE_SZ|120x600_AD|CM_IT|POE | K60: =#REF! -> #REF! | L60: =SUBSTITUTE(K60,"|","^") -> #REF! | M60: https://cartaodotz.dotz.com.br/ | N60: =CONCATENATE(M60,"?utm_source=",G60,"&utm_medium=","ADS","&utm_campaign=",J60,"&utm_content=",K60) -> #REF!
A61: Manter/No Ar | B61: Criado 19/03 | Atualizado 29/05 | Atualizado 28/10 | C61: 19/03/2020 | D61: 44197 | E61: adserver | G61: DV360 | H61: CPM | I61: ='Placement (DCM)'!L54 -> 120x600 | J61: ='Placement (DCM)'!R54 -> MK|BR_CH|PD_DT|CROSS_PB|DV36_FM|BAN_RT|CPM_PD|DOTZ-10MIL-AZUL_TG|NON_ST|NON_TS|NONE_SZ|120x600_AD|CM_IT|POE | K61: ='Creative Name'!H54 -> CV|DOTZ-10MIL-AZUL_CS|120x600_CT|HTML5 | L61: =SUBSTITUTE(K61,"|","^") -> CV^DOTZ-10MIL-AZUL_CS^120x600_CT^HTML5 | M61: https://cartaodotz.dotz.com.br/dotz-bb | N61: =CONCATENATE(M61,"?utm_source=",G61,"&utm_medium=","ADS","&utm_campaign=",J61,"&utm_content=",K61) -> https://cartaodotz.dotz.com.br/dotz-bb?utm_source=DV360&utm_medium=ADS&utm_campaign=MK|BR_CH|PD_DT|CROSS_PB|DV36_FM|BAN_RT|CPM_PD|DOTZ-10MIL-AZUL_TG|NON_ST|NON_TS|NONE_SZ|120x600_AD|CM_IT|POE&utm_content=CV|DOTZ-10MIL-AZUL_CS|120x600_CT|HTML5
A62: Manter/No Ar | B62: Criado 19/03 | Atualizado 29/05 | Atualizado 28/10 | C62: 19/03/2020 | D62: 44197 | E62: adserver | G62: DV360 | H62: CPM | I62: ='Placement (DCM)'!L55 -> 160x600 | J62: ='Placement (DCM)'!R55 -> MK|BR_CH|PD_DT|CROSS_PB|DV36_FM|BAN_RT|CPM_PD|DOTZ-10MIL-AZUL_TG|NON_ST|NON_TS|NONE_SZ|160x600_AD|CM_IT|POE | K62: ='Creative Name'!H55 -> CV|DOTZ-10MIL-AZUL_CS|160x600_CT|HTML5 | L62: =SUBSTITUTE(K62,"|","^") -> CV^DOTZ-10MIL-AZUL_CS^160x600_CT^HTML5 | M62: https://cartaodotz.dotz.com.br/dotz-bb | N62: =CONCATENATE(M62,"?utm_source=",G62,"&utm_medium=","ADS","&utm_campaign=",J62,"&utm_content=",K62) -> https://cartaodotz.dotz.com.br/dotz-bb?utm_source=DV360&utm_medium=ADS&utm_campaign=MK|BR_CH|PD_DT|CROSS_PB|DV36_FM|BAN_RT|CPM_PD|DOTZ-10MIL-AZUL_TG|NON_ST|NON_TS|NONE_SZ|160x600_AD|CM_IT|POE&utm_content=CV|DOTZ-10MIL-AZUL_CS|160x600_CT|HTML5
A63: Manter/No Ar | B63: Criado 19/03 | Atualizado 29/05 | Atualizado 28/10 | C63: 19/03/2020 | D63: 44197 | E63: adserver | G63: DV360 | H63: CPM | I63: ='Placement (DCM)'!L56 -> 300x250 | J63: ='Placement (DCM)'!R56 -> MK|BR_CH|PD_DT|CROSS_PB|DV36_FM|BAN_RT|CPM_PD|DOTZ-10MIL-AZUL_TG|NON_ST|NON_TS|NONE_SZ|300x250_AD|CM_IT|POE | K63: ='Creative Name'!H56 -> CV|DOTZ-10MIL-AZUL_CS|300x250_CT|HTML5 | L63: =SUBSTITUTE(K63,"|","^") -> CV^DOTZ-10MIL-AZUL_CS^300x250_CT^HTML5 | M63: https://cartaodotz.dotz.com.br/dotz-bb | N63: =CONCATENATE(M63,"?utm_source=",G63,"&utm_medium=","ADS","&utm_campaign=",J63,"&utm_content=",K63) -> https://cartaodotz.dotz.com.br/dotz-bb?utm_source=DV360&utm_medium=ADS&utm_campaign=MK|BR_CH|PD_DT|CROSS_PB|DV36_FM|BAN_RT|CPM_PD|DOTZ-10MIL-AZUL_TG|NON_ST|NON_TS|NONE_SZ|300x250_AD|CM_IT|POE&utm_content=CV|DOTZ-10MIL-AZUL_CS|300x250_CT|HTML5
A64: Manter/No Ar | B64: Criado 19/03 | Atualizado 29/05 | Atualizado 28/10 | C64: 19/03/2020 | D64: 44197 | E64: adserver | G64: DV360 | H64: CPM | I64: ='Placement (DCM)'!L57 -> 300x600 | J64: ='Placement (DCM)'!R57 -> MK|BR_CH|PD_DT|CROSS_PB|DV36_FM|BAN_RT|CPM_PD|DOTZ-10MIL-AZUL_TG|NON_ST|NON_TS|NONE_SZ|300x600_AD|CM_IT|POE | K64: ='Creative Name'!H57 -> CV|DOTZ-10MIL-AZUL_CS|300x600_CT|HTML5 | L64: =SUBSTITUTE(K64,"|","^") -> CV^DOTZ-10MIL-AZUL_CS^300x600_CT^HTML5 | M64: https://cartaodotz.dotz.com.br/dotz-bb | N64: =CONCATENATE(M64,"?utm_source=",G64,"&utm_medium=","ADS","&utm_campaign=",J64,"&utm_content=",K64) -> https://cartaodotz.dotz.com.br/dotz-bb?utm_source=DV360&utm_medium=ADS&utm_campaign=MK|BR_CH|PD_DT|CROSS_PB|DV36_FM|BAN_RT|CPM_PD|DOTZ-10MIL-AZUL_TG|NON_ST|NON_TS|NONE_SZ|300x600_AD|CM_IT|POE&utm_content=CV|DOTZ-10MIL-AZUL_CS|300x600_CT|HTML5
A65: Manter/No Ar | B65: Criado 19/03 | Atualizado 29/05 | Atualizado 28/10 | C65: 19/03/2020 | D65: 44197 | E65: adserver | G65: DV360 | H65: CPM | I65: ='Placement (DCM)'!L58 -> 320x50 | J65: ='Placement (DCM)'!R58 -> MK|BR_CH|PMD_DT|CROSS_PB|DV36_FM|BAN_RT|CPM_PD|DOTZ-10MIL-AZUL_TG|NON_ST|NON_TS|NONE_SZ|320x50_AD|CM_IT|POE | K65: ='Creative Name'!H58 -> CV|DOTZ-10MIL-AZUL_CS|320x50_CT|HTML5 | L65: =SUBSTITUTE(K65,"|","^") -> CV^DOTZ-10MIL-AZUL_CS^320x50_CT^HTML5 | M65: https://cartaodotz.dotz.com.br/dotz-bb | N65: =CONCATENATE(M65,"?utm_source=",G65,"&utm_medium=","ADS","&utm_campaign=",J65,"&utm_content=",K65) -> https://cartaodotz.dotz.com.br/dotz-bb?utm_source=DV360&utm_medium=ADS&utm_campaign=MK|BR_CH|PMD_DT|CROSS_PB|DV36_FM|BAN_RT|CPM_PD|DOTZ-10MIL-AZUL_TG|NON_ST|NON_TS|NONE_SZ|320x50_AD|CM_IT|POE&utm_content=CV|DOTZ-10MIL-AZUL_CS|320x50_CT|HTML5
A66: Manter/No Ar | B66: Criado 19/03 | Atualizado 29/05 | Atualizado 28/10 | C66: 19/03/2020 | D66: 44197 | E66: adserver | G66: DV360 | H66: CPM | I66: ='Placement (DCM)'!L59 -> 320x100 | J66: ='Placement (DCM)'!R59 -> MK|BR_CH|PMD_DT|CROSS_PB|DV36_FM|BAN_RT|CPM_PD|DOTZ-10MIL-AZUL_TG|NON_ST|NON_TS|NONE_SZ|320x100_AD|CM_IT|POE | K66: ='Creative Name'!H59 -> CV|DOTZ-10MIL-AZUL_CS|320x100_CT|HTML5 | L66: =SUBSTITUTE(K66,"|","^") -> CV^DOTZ-10MIL-AZUL_CS^320x100_CT^HTML5 | M66: https://cartaodotz.dotz.com.br/dotz-bb | N66: =CONCATENATE(M66,"?utm_source=",G66,"&utm_medium=","ADS","&utm_campaign=",J66,"&utm_content=",K66) -> https://cartaodotz.dotz.com.br/dotz-bb?utm_source=DV360&utm_medium=ADS&utm_campaign=MK|BR_CH|PMD_DT|CROSS_PB|DV36_FM|BAN_RT|CPM_PD|DOTZ-10MIL-AZUL_TG|NON_ST|NON_TS|NONE_SZ|320x100_AD|CM_IT|POE&utm_content=CV|DOTZ-10MIL-AZUL_CS|320x100_CT|HTML5
A67: Manter/No Ar | B67: Criado 19/03 | Atualizado 29/05 | Atualizado 28/10 | C67: 19/03/2020 | D67: 44197 | E67: adserver | G67: DV360 | H67: CPM | I67: ='Placement (DCM)'!L60 -> 728x90 | J67: ='Placement (DCM)'!R60 -> MK|BR_CH|PD_DT|CROSS_PB|DV36_FM|BAN_RT|CPM_PD|DOTZ-10MIL-AZUL_TG|NON_ST|NON_TS|NONE_SZ|728x90_AD|CM_IT|POE | K67: ='Creative Name'!H60 -> CV|DOTZ-10MIL-AZUL_CS|728x90_CT|HTML5 | L67: =SUBSTITUTE(K67,"|","^") -> CV^DOTZ-10MIL-AZUL_CS^728x90_CT^HTML5 | M67: https://cartaodotz.dotz.com.br/dotz-bb | N67: =CONCATENATE(M67,"?utm_source=",G67,"&utm_medium=","ADS","&utm_campaign=",J67,"&utm_content=",K67) -> https://cartaodotz.dotz.com.br/dotz-bb?utm_source=DV360&utm_medium=ADS&utm_campaign=MK|BR_CH|PD_DT|CROSS_PB|DV36_FM|BAN_RT|CPM_PD|DOTZ-10MIL-AZUL_TG|NON_ST|NON_TS|NONE_SZ|728x90_AD|CM_IT|POE&utm_content=CV|DOTZ-10MIL-AZUL_CS|728x90_CT|HTML5
A68: Manter/No Ar | B68: Criado 19/03 | Atualizado 29/05 | Atualizado 28/10 | C68: 19/03/2020 | D68: 44197 | E68: adserver | G68: DV360 | H68: CPM | I68: ='Placement (DCM)'!L61 -> 120x600 | J68: ='Placement (DCM)'!R61 -> MK|BR_CH|PD_DT|CROSS_PB|DV36_FM|BAN_RT|CPM_PD|DOTZ-ZERO-ANUIDADE-AZUL_TG|NON_ST|NON_TS|NONE_SZ|120x600_AD|CM_IT|POE | K68: ='Creative Name'!H61 -> CV|DOTZ-ZERO-ANUIDADE-AZUL_CS|120x600_CT|HTML5 | L68: =SUBSTITUTE(K68,"|","^") -> CV^DOTZ-ZERO-ANUIDADE-AZUL_CS^120x600_CT^HTML5 | M68: https://cartaodotz.dotz.com.br/dotz-bb | N68: =CONCATENATE(M68,"?utm_source=",G68,"&utm_medium=","ADS","&utm_campaign=",J68,"&utm_content=",K68) -> https://cartaodotz.dotz.com.br/dotz-bb?utm_source=DV360&utm_medium=ADS&utm_campaign=MK|BR_CH|PD_DT|CROSS_PB|DV36_FM|BAN_RT|CPM_PD|DOTZ-ZERO-ANUIDADE-AZUL_TG|NON_ST|NON_TS|NONE_SZ|120x600_AD|CM_IT|POE&utm_content=CV|DOTZ-ZERO-ANUIDADE-AZUL_CS|120x600_CT|HTML5
A69: Manter/No Ar | B69: Criado 19/03 | Atualizado 29/05 | Atualizado 28/10 | C69: 19/03/2020 | D69: 44197 | E69: adserver | G69: DV360 | H69: CPM | I69: ='Placement (DCM)'!L62 -> 160x600 | J69: ='Placement (DCM)'!R62 -> MK|BR_CH|PD_DT|CROSS_PB|DV36_FM|BAN_RT|CPM_PD|DOTZ-ZERO-ANUIDADE-AZUL_TG|NON_ST|NON_TS|NONE_SZ|160x600_AD|CM_IT|POE | K69: ='Creative Name'!H62 -> CV|DOTZ-ZERO-ANUIDADE-AZUL_CS|160x600_CT|HTML5 | L69: =SUBSTITUTE(K69,"|","^") -> CV^DOTZ-ZERO-ANUIDADE-AZUL_CS^160x600_CT^HTML5 | M69: https://cartaodotz.dotz.com.br/dotz-bb | N69: =CONCATENATE(M69,"?utm_source=",G69,"&utm_medium=","ADS","&utm_campaign=",J69,"&utm_content=",K69) -> https://cartaodotz.dotz.com.br/dotz-bb?utm_source=DV360&utm_medium=ADS&utm_campaign=MK|BR_CH|PD_DT|CROSS_PB|DV36_FM|BAN_RT|CPM_PD|DOTZ-ZERO-ANUIDADE-AZUL_TG|NON_ST|NON_TS|NONE_SZ|160x600_AD|CM_IT|POE&utm_content=CV|DOTZ-ZERO-ANUIDADE-AZUL_CS|160x600_CT|HTML5
A70: Manter/No Ar | B70: Criado 19/03 | Atualizado 29/05 | Atualizado 28/10 | C70: 19/03/2020 | D70: 44197 | E70: adserver | G70: DV360 | H70: CPM | I70: ='Placement (DCM)'!L63 -> 300x250 | J70: ='Placement (DCM)'!R63 -> MK|BR_CH|PD_DT|CROSS_PB|DV36_FM|BAN_RT|CPM_PD|DOTZ-ZERO-ANUIDADE-AZUL_TG|NON_ST|NON_TS|NONE_SZ|300x250_AD|CM_IT|POE | K70: ='Creative Name'!H63 -> CV|DOTZ-ZERO-ANUIDADE-AZUL_CS|300x250_CT|HTML5 | L70: =SUBSTITUTE(K70,"|","^") -> CV^DOTZ-ZERO-ANUIDADE-AZUL_CS^300x250_CT^HTML5 | M70: https://cartaodotz.dotz.com.br/dotz-bb | N70: =CONCATENATE(M70,"?utm_source=",G70,"&utm_medium=","ADS","&utm_campaign=",J70,"&utm_content=",K70) -> https://cartaodotz.dotz.com.br/dotz-bb?utm_source=DV360&utm_medium=ADS&utm_campaign=MK|BR_CH|PD_DT|CROSS_PB|DV36_FM|BAN_RT|CPM_PD|DOTZ-ZERO-ANUIDADE-AZUL_TG|NON_ST|NON_TS|NONE_SZ|300x250_AD|CM_IT|POE&utm_content=CV|DOTZ-ZERO-ANUIDADE-AZUL_CS|300x250_CT|HTML5
A71: Manter/No Ar | B71: Criado 19/03 | Atualizado 29/05 | Atualizado 28/10 | C71: 19/03/2020 | D71: 44197 | E71: adserver | G71: DV360 | H71: CPM | I71: ='Placement (DCM)'!L64 -> 300x600 | J71: ='Placement (DCM)'!R64 -> MK|BR_CH|PD_DT|CROSS_PB|DV36_FM|BAN_RT|CPM_PD|DOTZ-ZERO-ANUIDADE-AZUL_TG|NON_ST|NON_TS|NONE_SZ|300x600_AD|CM_IT|POE | K71: ='Creative Name'!H64 -> CV|DOTZ-ZERO-ANUIDADE-AZUL_CS|300x600_CT|HTML5 | L71: =SUBSTITUTE(K71,"|","^") -> CV^DOTZ-ZERO-ANUIDADE-AZUL_CS^300x600_CT^HTML5 | M71: https://cartaodotz.dotz.com.br/dotz-bb | N71: =CONCATENATE(M71,"?utm_source=",G71,"&utm_medium=","ADS","&utm_campaign=",J71,"&utm_content=",K71) -> https://cartaodotz.dotz.com.br/dotz-bb?utm_source=DV360&utm_medium=ADS&utm_campaign=MK|BR_CH|PD_DT|CROSS_PB|DV36_FM|BAN_RT|CPM_PD|DOTZ-ZERO-ANUIDADE-AZUL_TG|NON_ST|NON_TS|NONE_SZ|300x600_AD|CM_IT|POE&utm_content=CV|DOTZ-ZERO-ANUIDADE-AZUL_CS|300x600_CT|HTML5
A72: Manter/No Ar | B72: Criado 19/03 | Atualizado 29/05 | Atualizado 28/10 | C72: 19/03/2020 | D72: 44197 | E72: adserver | G72: DV360 | H72: CPM | I72: ='Placement (DCM)'!L65 -> 320x50 | J72: ='Placement (DCM)'!R65 -> MK|BR_CH|PMD_DT|CROSS_PB|DV36_FM|BAN_RT|CPM_PD|DOTZ-ZERO-ANUIDADE-AZUL_TG|NON_ST|NON_TS|NONE_SZ|320x50_AD|CM_IT|POE | K72: ='Creative Name'!H65 -> CV|DOTZ-ZERO-ANUIDADE-AZUL_CS|320x50_CT|HTML5 | L72: =SUBSTITUTE(K72,"|","^") -> CV^DOTZ-ZERO-ANUIDADE-AZUL_CS^320x50_CT^HTML5 | M72: https://cartaodotz.dotz.com.br/dotz-bb | N72: =CONCATENATE(M72,"?utm_source=",G72,"&utm_medium=","ADS","&utm_campaign=",J72,"&utm_content=",K72) -> https://cartaodotz.dotz.com.br/dotz-bb?utm_source=DV360&utm_medium=ADS&utm_campaign=MK|BR_CH|PMD_DT|CROSS_PB|DV36_FM|BAN_RT|CPM_PD|DOTZ-ZERO-ANUIDADE-AZUL_TG|NON_ST|NON_TS|NONE_SZ|320x50_AD|CM_IT|POE&utm_content=CV|DOTZ-ZERO-ANUIDADE-AZUL_CS|320x50_CT|HTML5
... A130: Manter/No Ar | B130: Criado 19/03 | Atualizado 29/05 | Atualizado 28/10 | C130: 19/03/2020 | D130: 44197 | E130: adserver | G130: VERIZON | H130: CPM | I130: ='Placement (DCM)'!L123 -> 728x90 | J130: ='Placement (DCM)'!R123 -> MK|BR_CH|PD_DT|CROSS_PB|VER_FM|BAN_RT|CPM_PD|DOTZ-ZERO-CONVERSAO-AZUL_TG|NON_ST|NON_TS|NONE_SZ|728x90_AD|CM1_IT|OO | K130: ='Creative Name'!H123 -> CV|DOTZ-ZERO-CONVERSAO-AZUL_CS|728x90_CT|HTML5 | L130: =SUBSTITUTE(K130,"|","^") -> CV^DOTZ-ZERO-CONVERSAO-AZUL_CS^728x90_CT^HTML5 | M130: https://cartaodotz.dotz.com.br/dotz-bb | N130: =CONCATENATE(M130,"?utm_source=",G130,"&utm_medium=","ADS","&utm_campaign=",J130,"&utm_content=",K130) -> https://cartaodotz.dotz.com.br/dotz-bb?utm_source=VERIZON&utm_medium=ADS&utm_campaign=MK|BR_CH|PD_DT|CROSS_PB|VER_FM|BAN_RT|CPM_PD|DOTZ-ZERO-CONVERSAO-AZUL_TG|NON_ST|NON_TS|NONE_SZ|728x90_AD|CM1_IT|OO&utm_content=CV|DOTZ-ZERO-CONVERSAO-AZUL_CS|728x90_CT|HTML5
A131: Manter/No Ar | B131: Criado 19/03 | Atualizado 29/05 | Atualizado 28/10 | C131: 19/03/2020 | D131: 44197 | E131: portal | G131: VERIZON | H131: CPC | I131: 1X1 | J131: ='Placement (DCM)'!R124 -> MK|BR_CH|PD_DT|CROSS_PB|VER_FM|NAT_RT|CPC_PD|DOTZ-ZERO-CONVERSAO-AZUL_TG|NON_ST|NON_TS|NONE_SZ|1200x627_AD|CM1_IT|OO | K131: ='Creative Name'!H124 -> CV|DOTZ-ZERO-CONVERSAO-AZUL_CS|1200x627_CT|NAT | L131: =SUBSTITUTE(K131,"|","^") -> CV^DOTZ-ZERO-CONVERSAO-AZUL_CS^1200x627_CT^NAT | M131: https://cartaodotz.dotz.com.br/dotz-bb | N131: =CONCATENATE(M131,"?utm_source=",G131,"&utm_medium=","ADS","&utm_campaign=",J131,"&utm_content=",K131) -> https://cartaodotz.dotz.com.br/dotz-bb?utm_source=VERIZON&utm_medium=ADS&utm_campaign=MK|BR_CH|PD_DT|CROSS_PB|VER_FM|NAT_RT|CPC_PD|DOTZ-ZERO-CONVERSAO-AZUL_TG|NON_ST|NON_TS|NONE_SZ|1200x627_AD|CM1_IT|OO&utm_content=CV|DOTZ-ZERO-CONVERSAO-AZUL_CS|1200x627_CT|NAT
A132: Manter/No Ar | B132: Criado 19/03 | Atualizado 29/05 | Atualizado 28/10 | C132: 19/03/2020 | D132: 44197 | E132: portal | G132: VERIZON | H132: CPC | I132: 1X1 | J132: ='Placement (DCM)'!R125 -> MK|BR_CH|PD_DT|CROSS_PB|VER_FM|NAT_RT|CPC_PD|DOTZ-ZERO-CONVERSAO-AZUL_TG|NON_ST|NON_TS|NONE_SZ|627x627_AD|CM1_IT|OO | K132: ='Creative Name'!H125 -> CV|DOTZ-ZERO-CONVERSAO-AZUL_CS|627x627_CT|NAT | L132: =SUBSTITUTE(K132,"|","^") -> CV^DOTZ-ZERO-CONVERSAO-AZUL_CS^627x627_CT^NAT | M132: https://cartaodotz.dotz.com.br/dotz-bb | N132: =CONCATENATE(M132,"?utm_source=",G132,"&utm_medium=","ADS","&utm_campaign=",J132,"&utm_content=",K132) -> https://cartaodotz.dotz.com.br/dotz-bb?utm_source=VERIZON&utm_medium=ADS&utm_campaign=MK|BR_CH|PD_DT|CROSS_PB|VER_FM|NAT_RT|CPC_PD|DOTZ-ZERO-CONVERSAO-AZUL_TG|NON_ST|NON_TS|NONE_SZ|627x627_AD|CM1_IT|OO&utm_content=CV|DOTZ-ZERO-CONVERSAO-AZUL_CS|627x627_CT|NAT
A133: Manter/No Ar | B133: Criado 19/03 | Atualizado 29/05 | Atualizado 28/10 | C133: 19/03/2020 | D133: 44197 | E133: portal | G133: VERIZON | H133: CPC | I133: 1X1 | J133: ='Placement (DCM)'!R126 -> MK|BR_CH|PD_DT|CROSS_PB|VER_FM|NAT_RT|CPC_PD|DOTZ-ZERO-ANUIDADE-HUMANIZADO_TG|NON_ST|NON_TS|NONE_SZ|1200x627_AD|CM1_IT|OO | K133: ='Creative Name'!H126 -> CV|DOTZ-ZERO-ANUIDADE-HUMANIZADO_CS|1200x627_CT|NAT | L133: =SUBSTITUTE(K133,"|","^") -> CV^DOTZ-ZERO-ANUIDADE-HUMANIZADO_CS^1200x627_CT^NAT | M133: https://cartaodotz.dotz.com.br/dotz-bb | N133: =CONCATENATE(M133,"?utm_source=",G133,"&utm_medium=","ADS","&utm_campaign=",J133,"&utm_content=",K133) -> https://cartaodotz.dotz.com.br/dotz-bb?utm_source=VERIZON&utm_medium=ADS&utm_campaign=MK|BR_CH|PD_DT|CROSS_PB|VER_FM|NAT_RT|CPC_PD|DOTZ-ZERO-ANUIDADE-HUMANIZADO_TG|NON_ST|NON_TS|NONE_SZ|1200x627_AD|CM1_IT|OO&utm_content=CV|DOTZ-ZERO-ANUIDADE-HUMANIZADO_CS|1200x627_CT|NAT
A134: Manter/No Ar | B134: Criado 19/03 | Atualizado 29/05 | Atualizado 28/10 | C134: 19/03/2020 | D134: 44197 | E134: portal | G134: VERIZON | H134: CPC | I134: 1X1 | J134: ='Placement (DCM)'!R127 -> MK|BR_CH|PD_DT|CROSS_PB|VER_FM|NAT_RT|CPC_PD|DOTZ-ZERO-ANUIDADE-HUMANIZADO_TG|NON_ST|NON_TS|NONE_SZ|627x627_AD|CM1_IT|OO | K134: ='Creative Name'!H127 -> CV|DOTZ-ZERO-ANUIDADE-HUMANIZADO_CS|627x627_CT|NAT | L134: =SUBSTITUTE(K134,"|","^") -> CV^DOTZ-ZERO-ANUIDADE-HUMANIZADO_CS^627x627_CT^NAT | M134: https://cartaodotz.dotz.com.br/dotz-bb | N134: =CONCATENATE(M134,"?utm_source=",G134,"&utm_medium=","ADS","&utm_campaign=",J134,"&utm_content=",K134) -> https://cartaodotz.dotz.com.br/dotz-bb?utm_source=VERIZON&utm_medium=ADS&utm_campaign=MK|BR_CH|PD_DT|CROSS_PB|VER_FM|NAT_RT|CPC_PD|DOTZ-ZERO-ANUIDADE-HUMANIZADO_TG|NON_ST|NON_TS|NONE_SZ|627x627_AD|CM1_IT|OO&utm_content=CV|DOTZ-ZERO-ANUIDADE-HUMANIZADO_CS|627x627_CT|NAT
A135: Manter/No Ar | B135: Criado 19/03 | Atualizado 29/05 | Atualizado 28/10 | C135: 19/03/2020 | D135: 44197 | E135: portal | G135: VERIZON | H135: CPC | I135: 1X1 | J135: ='Placement (DCM)'!R128 -> MK|BR_CH|PD_DT|CROSS_PB|VER_FM|NAT_RT|CPC_PD|DOTZ-10MIL-HUMANIZADO_TG|NON_ST|NON_TS|NONE_SZ|1200x627_AD|CM1_IT|OO | K135: ='Creative Name'!H128 -> CV|DOTZ-10MIL-HUMANIZADO_CS|1200x627_CT|NAT | L135: =SUBSTITUTE(K135,"|","^") -> CV^DOTZ-10MIL-HUMANIZADO_CS^1200x627_CT^NAT | M135: https://cartaodotz.dotz.com.br/dotz-bb | N135: =CONCATENATE(M135,"?utm_source=",G135,"&utm_medium=","ADS","&utm_campaign=",J135,"&utm_content=",K135) -> https://cartaodotz.dotz.com.br/dotz-bb?utm_source=VERIZON&utm_medium=ADS&utm_campaign=MK|BR_CH|PD_DT|CROSS_PB|VER_FM|NAT_RT|CPC_PD|DOTZ-10MIL-HUMANIZADO_TG|NON_ST|NON_TS|NONE_SZ|1200x627_AD|CM1_IT|OO&utm_content=CV|DOTZ-10MIL-HUMANIZADO_CS|1200x627_CT|NAT
A136: Manter/No Ar | B136: Criado 19/03 | Atualizado 29/05 | Atualizado 28/10 | C136: 19/03/2020 | D136: 44197 | E136: portal | G136: VERIZON | H136: CPC | I136: 1X1 | J136: ='Placement (DCM)'!R129 -> MK|BR_CH|PD_DT|CROSS_PB|VER_FM|NAT_RT|CPC_PD|DOTZ-10MIL-HUMANIZADO_TG|NON_ST|NON_TS|NONE_SZ|627x627_AD|CM1_IT|OO | K136: ='Creative Name'!H129 -> CV|DOTZ-10MIL-HUMANIZADO_CS|627x627_CT|NAT | L136: =SUBSTITUTE(K136,"|","^") -> CV^DOTZ-10MIL-HUMANIZADO_CS^627x627_CT^NAT | M136: https://cartaodotz.dotz.com.br/dotz-bb | N136: =CONCATENATE(M136,"?utm_source=",G136,"&utm_medium=","ADS","&utm_campaign=",J136,"&utm_content=",K136) -> https://cartaodotz.dotz.com.br/dotz-bb?utm_source=VERIZON&utm_medium=ADS&utm_campaign=MK|BR_CH|PD_DT|CROSS_PB|VER_FM|NAT_RT|CPC_PD|DOTZ-10MIL-HUMANIZADO_TG|NON_ST|NON_TS|NONE_SZ|627x627_AD|CM1_IT|OO&utm_content=CV|DOTZ-10MIL-HUMANIZADO_CS|627x627_CT|NAT
A137: Manter/No Ar | B137: Enviado 02/06 | Atualizado 28/10 | C137: 43867 | D137: 44197 | E137: portal | G137: FACEBOOK | H137: CPM | I137: 1X1 | J137: ='Placement (DCM)'!R130 -> MK|BR_CH|PSD_DT|CROSS_PB|FCBK_FM|LNK_RT|CPM_PD|DOTZ-DOLAR_TG|NON_ST|NON_TS|NONE_SZ|1X1_AD|CM1_IT|SOC | K137: ='Creative Name'!H130 -> CV|DOTZ-DOLAR_CS|1x1_CT|FLA | L137: =SUBSTITUTE(K137,"|","^") -> CV^DOTZ-DOLAR_CS^1x1_CT^FLA | M137: https://cartaodotz.dotz.com.br/dotz-bb | N137: =CONCATENATE(M137,"?utm_source=",G137,"&utm_medium=","ADS","&utm_campaign=",J137,"&utm_content=",K137) -> https://cartaodotz.dotz.com.br/dotz-bb?utm_source=FACEBOOK&utm_medium=ADS&utm_campaign=MK|BR_CH|PSD_DT|CROSS_PB|FCBK_FM|LNK_RT|CPM_PD|DOTZ-DOLAR_TG|NON_ST|NON_TS|NONE_SZ|1X1_AD|CM1_IT|SOC&utm_content=CV|DOTZ-DOLAR_CS|1x1_CT|FLA
A138: Manter/No Ar | B138: Enviado 02/06 | Atualizado 28/10 | C138: 43867 | D138: 44197 | E138: portal | G138: FACEBOOK | H138: CPM | I138: 1X1 | J138: ='Placement (DCM)'!R131 -> MK|BR_CH|PSD_DT|CROSS_PB|FCBK_FM|STRY_RT|CPM_PD|DOTZ-DOLAR_TG|NON_ST|NON_TS|NONE_SZ|1X1_AD|CM1_IT|SOC | K138: ='Creative Name'!H131 -> CV|DOTZ-DOLAR_CS|1x1_CT|INSSTORY | L138: =SUBSTITUTE(K138,"|","^") -> CV^DOTZ-DOLAR_CS^1x1_CT^INSSTORY | M138: https://cartaodotz.dotz.com.br/dotz-bb | N138: =CONCATENATE(M138,"?utm_source=",G138,"&utm_medium=","ADS","&utm_campaign=",J138,"&utm_content=",K138) -> https://cartaodotz.dotz.com.br/dotz-bb?utm_source=FACEBOOK&utm_medium=ADS&utm_campaign=MK|BR_CH|PSD_DT|CROSS_PB|FCBK_FM|STRY_RT|CPM_PD|DOTZ-DOLAR_TG|NON_ST|NON_TS|NONE_SZ|1X1_AD|CM1_IT|SOC&utm_content=CV|DOTZ-DOLAR_CS|1x1_CT|INSSTORY
J139: ='Placement (DCM)'!R132 | K139: ='Creative Name'!H132
J140: ='Placement (DCM)'!R133 | K140: ='Creative Name'!H133
J141: ='Placement (DCM)'!R134 | K141: ='Creative Name'!H134
J142: ='Placement (DCM)'!R135 | K142: ='Creative Name'!H135
J143: ='Placement (DCM)'!R136 | K143: ='Creative Name'!H136
