Workbook
Name Costing_Model_Code: 'Data Validations'!$Y$2:$Y$24
Name Detailed_Targeting: 'Data Validations'!$AE$2:$AE$153
Name Detailed_Targeting_Code: 'Data Validations'!$AF$2:$AF$153
Name Format: 'Data Validations'!$O$2:$O$135
Name Formatandcode: 'Data Validations'!$O$2:$P$135
Name From: #REF!
Name Influencer: 'Data Validations'!$O$47:$O$50
Name KPI: 'Data Validations'!$H$2:$H$41
Name KPI_Codes: 'Data Validations'!$I$2:$I$41
Name KPIAndCodes: 'Data Validations'!$H$2:$I$40
Name Native: 'Data Validations'!$O$53:$O$135
Name Objectiveandcodes: 'Data Validations'!$D$2:$E$4
Name Objectives: 'Data Validations'!$D$2:$D$4
Name Partnerandcode: 'Data Validations'!$R$3:$S$205
Name Partnertypeandcode: 'Data Validations'!$U$2:$V$23
Name Primary_Targeting_Segment: 'Data Validations'!$AA$2:$AA$141
Name Primary_Targeting_Segment_Code: 'Data Validations'!$AB$2:$AB$141
Name Products: 'Data Validations'!$A$2:$A$195
Name Productsandcodes: 'Data Validations'!$A$2:$B$195
Name Reach: 'Data Validations'!$H$2:$H$9
Name Reaction: 'Data Validations'!$H$20:$H$29
Name Relevance: 'Data Validations'!$H$10:$H$19
Name Search: 'Data Validations'!$O$63:$O$65
Name Size: #REF!
Name SocialDisplay: 'Data Validations'!$O$66:$O$67
Name SocialVideo: 'Data Validations'!$O$68:$O$72
Name Tacticsandcode: 'Data Validations'!$AA$2:$AB$93
Name To: #REF!
Name Video: 'Data Validations'!$O$76:$O$79
Name Year: #REF!

Sheet Placement Name Generator
B2: Platform | D2: Level
B3: DV360 | D3: Line Item (If audiences or format are not split at line item, use 'na' option)
B4: DV360 | D4: Ad Group
B5: Social | D5: Ad Set
B7: Market | C7: Market Code | D7: Sub-Product | E7: Sub-Product Code | F7: Campaign Name Label | G7: Language | H7: Language Code | I7: Business Strategy | J7: Platform | K7: Platform Code | L7: Priority Partner | M7: Priority Partner Code | N7: Buy Type | O7: buy type code | P7: Costing model | Q7: Costing Model Code | R7: Campaign Type | S7: Addressable Code | T7: Audience type | U7: audience type code | V7: Audience Name | W7: Audience Name Code | X7: Data type | Y7: Objective | Z7: Optimisation | AA7: opt code | AB7: Placement Type | AC7: Format | AD7: Device | AE7: Ad Tag Size | AF7: Dimensions/length | AG7: Free Form | AH7: Unique Code (EG Placement ID) | AI7: Concatenation | AJ7: Hyphen | AK7: TAG - DO NOT MAKE MANUAL EDITS | AL7: Character Count (Max Recommended = 256)
A8: EXAMPLE ► | B8: United Kingdom | C8: =IFERROR(VLOOKUP(B8,Table37[#All],2,FALSE),"") -> GB | D8: Extra Gum | E8: =IFERROR(VLOOKUP(D8,'Campaign DV Lookups (2)'!$D$2:$E$207,2,FALSE),"") -> EXG | F8: p1-2023-w&s | G8: English | H8: =IFERROR(VLOOKUP(G8,'Essence DV Lookups'!$A$3:$B$95,2,FALSE),"") -> en | I8: NA | J8: Amazon | K8: =IFERROR(VLOOKUP(J8,'Essence DV Lookups'!$H$3:$I$18,2,FALSE),"") -> AM | L8: Amazon | M8: =IFERROR(VLOOKUP(L8,'Data Validations'!$R$1:$S$227,2,FALSE),"") -> AMZ | N8: auction | O8: =VLOOKUP(N8,'Essence DV Lookups'!L4:$M$9,2,FALSE) -> auction | P8: Cost Per Thousand | Q8: =VLOOKUP(P8,'Data Validations'!$X$2:$Y$24,2,FALSE) -> CPM | R8: biddable-data driven audience | S8: =IFERROR(VLOOKUP(R8,'Essence DV Lookups'!$P$4:$Q$15,2,FALSE),"") -> bid-dda | T8: interest | U8: =IFERROR(VLOOKUP(T8,'Essence DV Lookups'!$U$3:$V$21,2,FALSE),"") -> interest | V8: professionals | W8: =VLOOKUP(V8,'Essence DV Lookups'!$Y$3:$Z$435,2,FALSE) -> pro | X8: 2pd | Y8: Awareness | Z8: Reach | AA8: =VLOOKUP(Z8,'Essence DV Lookups'!$AF$3:$AG$13,2,FALSE) -> reach | AB8: bumpers | AC8: video | AD8: Cross Device | AE8: na | AF8: 6s | AG8: Nervous Energized-Business Size - 51+ employees - Lifestyle-work | AH8: na | AI8: =IF(COUNTIF(B8:AH8,"")>0,"Not Valid",_xlfn.CONCAT(C8,"_",E8,"_",F8,"_",H8,"_",I8,"_",K8,"_",M8,"_",O8,"_",Q8,"_",S8,"_",U8,"_",W8,"_",X8,"_",Y8,"_",AA8,"_",AB8,"_",AC8,"_",AD8,"_",AE8,"_",AF8,"_",AG8,"_",AH8)) -> GB_EXG_p1-2023-w&s_en_NA_AM_AMZ_auction_CPM_bid-dda_interest_pro_2pd_Awareness_reach_bumpers_video_Cross Device_na_6s_Nervous Energized-Business Size - 51+ employees - Lifestyle-work_na | AJ8: =SUBSTITUTE(AI8," ","-") -> GB_EXG_p1-2023-w&s_en_NA_AM_AMZ_auction_CPM_bid-dda_interest_pro_2pd_Awareness_reach_bumpers_video_Cross-Device_na_6s_Nervous-Energized-Business-Size---51+-employees---Lifestyle-work_na | AK8: =LOWER(AJ8) -> gb_exg_p1-2023-w&s_en_na_am_amz_auction_cpm_bid-dda_interest_pro_2pd_awareness_reach_bumpers_video_cross-device_na_6s_nervous-energized-business-size---51+-employees---lifestyle-work_na | AL8: =LEN(AK8) -> 185
A9: EXAMPLE ► | B9: UAE | C9: =IFERROR(VLOOKUP(B9,Table37[#All],2,FALSE),"") -> AE | D9: Wafer | E9: =IFERROR(VLOOKUP(D9,'Campaign DV Lookups (2)'!$D$2:$E$208,2,FALSE),"") -> WAF | F9: p1-vnp | G9: Portuguese | H9: =IFERROR(VLOOKUP(G9,'Essence DV Lookups'!$A$3:$B$95,2,FALSE),"") -> pt | I9: NA | J9: meta | K9: =IFERROR(VLOOKUP(J9,'Essence DV Lookups'!$H$3:$I$18,2,FALSE),"") -> MT | L9: Pinterest | M9: =IFERROR(VLOOKUP(L9,'Data Validations'!$R$1:$S$227,2,FALSE),"") -> PIN | N9: Other | O9: =VLOOKUP(N9,'Essence DV Lookups'!L4:$M$9,2,FALSE) -> oth | P9: Cost Per Click | Q9: =VLOOKUP(P9,'Data Validations'!$X$2:$Y$24,2,FALSE) -> CPC | R9: biddable-data driven audience | S9: =IFERROR(VLOOKUP(R9,'Essence DV Lookups'!$P$4:$Q$15,2,FALSE),"") -> bid-dda | T9: interest | U9: =IFERROR(VLOOKUP(T9,'Essence DV Lookups'!$U$3:$V$21,2,FALSE),"") -> interest | V9: Music | W9: =VLOOKUP(V9,'Essence DV Lookups'!$Y$3:$Z$435,2,FALSE) -> mus | X9: NA | Y9: Awareness | Z9: Views | AA9: =VLOOKUP(Z9,'Essence DV Lookups'!$AF$3:$AG$13,2,FALSE) -> views | AB9: hybrid | AC9: hybrid | AD9: Cross Device | AE9: na | AF9: na | AG9: na | AH9: na | AI9: =IF(COUNTIF(B9:AH9,"")>0,"Not Valid",_xlfn.CONCAT(C9,"_",E9,"_",F9,"_",H9,"_",I9,"_",K9,"_",M9,"_",O9,"_",Q9,"_",S9,"_",U9,"_",W9,"_",X9,"_",Y9,"_",AA9,"_",AB9,"_",AC9,"_",AD9,"_",AE9,"_",AF9,"_",AG9,"_",AH9)) -> AE_WAF_p1-vnp_pt_NA_MT_PIN_oth_CPC_bid-dda_interest_mus_NA_Awareness_views_hybrid_hybrid_Cross Device_na_na_na_na | AJ9: =SUBSTITUTE(AI9," ","-") -> AE_WAF_p1-vnp_pt_NA_MT_PIN_oth_CPC_bid-dda_interest_mus_NA_Awareness_views_hybrid_hybrid_Cross-Device_na_na_na_na | AK9: =LOWER(AJ9) -> ae_waf_p1-vnp_pt_na_mt_pin_oth_cpc_bid-dda_interest_mus_na_awareness_views_hybrid_hybrid_cross-device_na_na_na_na | AL9: =LEN(AK9) -> 113

Sheet Glossary
B3: Field Name | C3: Question | D3: Answer
B4: SUB-PRODUCT | C4: When should I select the sub-product vs overall parent product? | D4: The overall parent product is available as an option when the campaign is due to feature multiple products – for example, a D2C campaign that features multiple sub-products
B5: STRATEGY | C5: What does SEE/THINK/DO/CARE apply to? | D5: The overall campaign/business strategy for Pet Nutrition: see = awareness think = consideration do = conversion care = retention
B6: BUYING TYPE | C6: I’m buying via Reach & Frequency on social – what does that fall under? | D6: Reserved
B7: AUDIENCE TYPE | C7: I’m using “x” or “y” targeting type – what should I choose? | D7: Interest – this will be your standard ‘detailed’ targeting on Meta, or affinity targeting on YouTube Keyword – using specific terms, e.g for use on Twitter, Pinterest, Tik Tok Demo-only – this is when no additional targeting is overlaid to age/gender Behavioural – data categorised by specific actions, like being in-market for a product/purchase behaviour Retargeting – Targeting previously exposed audiences (from a previous campaign, or our websites) Lookalikes – Prospecting audiences built off existing data/remarketing pools (e.g video viewers of a previous campaign). AKA Similar Audiences on Google Contextual – Targeting specific publishers/pages/videos for our ads instead of using data e.g YouTube Select Lineups Life Events – (Or Detailed Demographic) e.g married, parent, retirement Location – when only location data is used to target a user There are also hybrid combinations when needed
B8: Audience Name | C8: When should I use the age brackets (A16-24) vs the generation name (e.g Gen Z) | D8: Generation names/labels should be used when additional data is used to identify them.
B9: DATA TYPE | C9: What should I choose for “x” or “y” scenario | D9: The overall campaign strategy: 1PD – any audience that is directly targeting or using Mars’ owned data, e.g website audiences, MAIDs, video viewers, shopify audiences 2PD – everything platform-based, e.g interests, keywords, affinity etc 3PD – data provided from an external party not native to the platform, e.g liveramp NA - for media buys that use no audience data only
B10: OBJECTIVE | C10: What should I choose here? | D10: What is selected in-platform, e.g conversions - despite what you are optimizing/buying on
B11: PLACEMENT | C11: What should I choose here? | D11: The placements selected in the campaign – if we are running multiple placements in one ad set on meta, then hybrid should be selected
B12: DIMENSIONS/LENGTH & AD TAG SIZE | C12: What should I choose here at ad set/line item level? | D12: There is an n/a value to select here when building for biddable platforms
B13: CREATIVE NAME | C13: What should I choose here? | D13: The creative name field is where you would place the file name of the asset received from creative teams – e.g ‘fruityflavour-shuffleboard’
B14: CAMPAIGN TYPE | C14: What are the differences between the options? | D14: Data Driven Audiences & Moments leveraging data for audience creation (e.g Facebook Interests) Non-Addressable Broad audiences without leveraging data (e.g demo-only, 18+) Addressable Data Driven HVC and/or Moments, with audience-based creative

Sheet Essence DV Lookups
A1: Language | E1: Strategy | H1: Platform | L1: buy type | P1: Addressable | U1: Audience Type | Y1: Audience Name | AB1: Data Type | AD1: Objective | AF1: Optimization | AJ1: Placement Type | AL1: Format | AN1: Device | AP1: Ad Tag Size | AR1: (DCM only)dimensions/length
Y2: Audience Name | Z2: Audience Name Code | AB2: data type | AD2: Objective | AF2: Optimisation | AG2: opt code | AJ2: placement type
A3: language | B3: language code | E3: strategy | H3: platform | I3: Platform Code | L3: Buy Type | M3: buy type code | P3: addressable | Q3: addressable code | U3: Audience type | V3: audience type code | Y3: na | Z3: na | AB3: 1pd | AD3: Awareness | AF3: Reach | AG3: reach | AJ3: bumpers | AL3: format | AN3: device | AP3: Ad Tag Size | AR3: (DCM only)dimensions/length
A4: (Afan) Oromo | B4: om | E4: see | H4: dv36o | I4: DV360 | L4: auction | M4: auction | P4: biddable-addressable | Q4: bid-adr | U4: demo-only | V4: demo-only | Y4: 13-17 | Z4: 13-17 | AB4: 2pd | AD4: Views | AF4: Ad Recall | AG4: ad-recall | AJ4: preroll | AL4: animated banner | AN4: Mobile | AP4: na | AR4: na
A5: Afrikaans | B5: af | E5: think | H5: meta | I5: MT | L5: reserved | M5: reserved | P5: biddable-data driven audience | Q5: bid-dda | U5: interest | V5: interest | Y5: 13-24 | Z5: 13-24 | AB5: 3pd | AD5: Engagement | AF5: Views | AG5: views | AJ5: trueview | AL5: skins | AN5: Desktop | AP5: 0x0 | AR5: 6s
A6: Albanian | B6: al | E6: do | H6: snap | I6: SN | L6: programmatic guaranteed | M6: pg | P6: biddable-non addressable | Q6: bid-nadr | U6: behavioural | V6: behavioural | Y6: 13-34 | Z6: 13-34 | AB6: NA | AD6: Traffic | AF6: Engagement | AG6: eng | AJ6: newsfeed | AL6: text ad | AN6: Cross Device | AP6: 1024x66 | AR6: 7s
A7: Albanian | B7: sq | E7: care | H7: Amazon | I7: AM | L7: private marketplace | M7: pmp | P7: biddable - icj | Q7: bid-icj | U7: life events | V7: life-event | Y7: 13-44 | Z7: 13-44 | AD7: Leads | AF7: Outbound Clicks | AG7: clicks | AJ7: non-skip | AL7: audio | AN7: Connected TV | AP7: 1024x768 | AR7: 10s
A8: Amharic | B8: am | E8: NA | H8: Pinterest | I8: PT | L8: open exchange | M8: ox | P8: biddable-addressable-icj | Q8: bid-adr-icj | U8: retargeting | V8: rtg | Y8: 13-54 | Z8: 13-54 | AD8: App Install | AF8: Landing Page Views | AG8: lpv | AJ8: stories | AL8: video | AN8: Digital OOH | AP8: 1024x90 | AR8: 12s
A9: Arabic | B9: ar | H9: Tiktok | I9: TT | L9: Other | M9: oth | P9: direct-addressable | Q9: dir-adr | U9: contextual | V9: contextual | Y9: 13plus | Z9: 13plus | AD9: Conversions | AF9: Add To Cart | AG9: atc | AJ9: feed | AL9: static | AN9: E-mails | AP9: 120x20 | AR9: 14s
A10: Armenian | B10: hy | H10: bing | I10: BN | P10: direct-data driven audience | Q10: dir-dda | U10: lookalikes | V10: lal | Y10: 15-17 | Z10: 15-17 | AF10: Purchases | AG10: purchases | AJ10: post | AL10: carousel | AN10: Gaming Console | AP10: 120x240 | AR10: 15s
A11: Assamese | B11: as | H11: google ads | I11: GA | P11: direct-non addressable | Q11: dir-nadr | U11: keyword | V11: keyword | Y11: 15-24 | Z11: 15-24 | AF11: Leads | AG11: leads | AJ11: instream | AL11: dynamic | AN11: Mobile | AP11: 120x60 | AR11: 20s
A12: Azerbaijani | B12: az | H12: twitter | I12: TW | P12: direct-icj | Q12: dir-icj | U12: weather | V12: weather | Y12: 15-34 | Z12: 15-34 | AF12: Catalog Sales | AG12: catalog | AJ12: reels | AL12: hybrid | AN12: Mobile in app | AP12: 120x600 | AR12: 40s
A13: Basque | B13: eu | H13: reddit | I13: RD | P13: direct-addressable-icj | Q13: dir-adr-icj | U13: location-specific | V13: location | Y13: 15-44 | Z13: 15-44 | AF13: Return on Ad Spend | AG13: roas | AJ13: hybrid | AN13: Mobile Web | AP13: 120x90 | AR13: 30splus
A14: Bengali; Bangla | B14: bn | H14: beeswax | I14: BW | U14: interest & behavioural | V14: int-behav | Y14: 15-54 | Z14: 15-54 | AJ14: commercials | AN14: Multiplatform | AP14: 1248x702 | AR14: na
A15: Bulgarian | B15: bg | H15: linkedin | I15: LI | U15: interest & keywords | V15: int-kws | Y15: 15plus | Z15: 15plus | AJ15: camera | AN15: Tablet | AP15: 125x125 | AR15: 160x600
A16: Byelorussian | B16: be | H16: tradedesk | I16: TD | U16: interest & life events | V16: int-life | Y16: 18-24 | Z16: 18-24 | AJ16: shopping | AN16: Tablet in app | AP16: 1280x100 | AR16: 300x250
A17: Cambodian | B17: km | H17: direct | I17: DI | U17: behavioural & keywords | V17: behav-kws | Y17: 18-34 | Z17: 18-34 | AJ17: text ads | AN17: Tablet Web | AP17: 1280x720 | AR17: 728x90
A18: Catalan | B18: ca | H18: Other | I18: OT | U18: behavioural & life events | V18: behav-life | Y18: 18-44 | Z18: 18-44 | AJ18: discovery | AN18: Wearables | AP18: 1280x970 | AR18: 1x1
A19: Chinese | B19: zh | U19: location & behavioural | V19: behav-location | Y19: 18-54 | Z19: 18-54 | AJ19: pmax | AP19: 1290x680 | AR19: 88x31
A20: cornish | B20: kw | Y20: 18plus | Z20: 18plus | AJ20: other | AP20: 1600x320 | AR20: 120x20
A21: Croatian | B21: hr | Y21: 25-34 | Z21: 25-34 | AJ21: sponsored-product | AP21: 1608x850 | AR21: 120x60
A22: Czech | B22: cs | Y22: 24-44 | Z22: 24-44 | AJ22: sponsored-brand | AP22: 160x600 | AR22: 120x90
A23: Danish | B23: da | Y23: 25-54 | Z23: 25-54 | AJ23: sponsored-display | AP23: 168x28 | AR23: 120x240
A24: Dutch | B24: nl | Y24: 25-65plus | Z24: 25-65plus | AP24: 1712x136 | AR24: 120x600
A25: English | B25: en | Y25: 35-44 | Z25: 35-44 | AP25: 180x150 | AR25: 125x125
A26: Estonian | B26: et | Y26: 35-54 | Z26: 35-54 | AP26: 180x180 | AR26: 168x28
A27: Faeroese | B27: fo | Y27: 35plus | Z27: 35plus | AP27: 1920x1080 | AR27: 180x150
A28: Finnish | B28: fi | Y28: 54plus | Z28: 54plus | AP28: 1x1 | AR28: 216x36
A29: French | B29: fr | Y29: 65plus | Z29: 65plus | AP29: 210x185 | AR29: 234x60
A30: Galician | B30: gl | Y30: m13-17 | Z30: m13-17 | AP30: 216x36 | AR30: 240x400
A31: Georgian | B31: ka | Y31: m13-24 | Z31: m13-24 | AP31: 234x60 | AR31: 250x250
A32: German | B32: de | Y32: m13-34 | Z32: m13-34 | AP32: 240x400 | AR32: 300x50
A33: Greek | B33: el | Y33: m13-44 | Z33: m13-44 | AP33: 250x200 | AR33: 300x100
A34: Greenlandic | B34: kl | Y34: m13-54 | Z34: m13-54 | AP34: 250x250 | AR34: 300x600
A35: Gujarati | B35: gu | Y35: m13plus | Z35: m13plus | AP35: 250x50 | AR35: 300x1050
... A77: Slovak | B77: sk | Y77: f35-44 | Z77: f35-44 | AP77: 985x60 | AR77: 600x90
A78: Slovenian | B78: sl | Y78: f35-54 | Z78: f35-54 | AR78: 480x320
A79: Somali | B79: so | Y79: f35plus | Z79: f35plus | AR79: 1280x970
A80: Spanish | B80: es | Y80: f54plus | Z80: f54plus | AR80: 640x360
A81: Swahili | B81: sw | Y81: f65plus | Z81: f65plus | AR81: 1280x720
A82: Swedish | B82: sv | Y82: website-pageviewers | Z82: web-view | AR82: 640x100
A83: Swiss German | B83: gsw | Y83: website-purchasers | Z83: web-purch | AR83: 1024x768
A84: Tamil | B84: ta | Y84: website- adds-to-cart | Z84: web-atc | AR84: 768x1024
A85: Tegulu | B85: te | Y85: website-combined | Z85: web-com | AR85: 640x640
A86: Thai | B86: th | Y86: website-pageviewers-cat | Z86: web-cat | AR86: 630x920
A87: Tibetan | B87: bo | Y87: website-pageviewers-dog | Z87: web-dog | AR87: 800x435
A88: Tigrinya | B88: ti | Y88: website-pageviewers-cat-lookalikes | Z88: web-cat-lal
A89: Turkish | B89: tr | Y89: website-pageviewers-dog-lookalikes | Z89: web-dog-lal
A90: Ukrainian | B90: uk | Y90: website-pageviewers-lookalikes | Z90: web-lal
A91: Urdu | B91: ur | Y91: crm | Z91: crm
A92: Uzbek | B92: uz | Y92: shopify | Z92: shp
A93: Vietnamese | B93: vi | Y93: platform video-viewers | Z93: pla-vid
A94: Welsh | B94: cy | Y94: platform engagers | Z94: pla-eng
A95: Zulu | B95: zu | Y95: platform combined remarketing | Z95: pla-com
Y96: maids-dog | Z96: mds-dog
Y97: maids-cat | Z97: mds-cat
Y98: maids-combined | Z98: mds-com
Y99: maids-dog-lookalikes | Z99: mds-d-lal
Y100: maids-cat-lookalikes | Z100: mds-c-lal
Y101: maids-combined-lookalikes | Z101: mds-dc-lal
Y102: parents | Z102: par
Y103: professionals | Z103: pro
Y104: students | Z104: stu
Y105: gen-z | Z105: gnz
Y106: millenials | Z106: mil
Y107: primary shopper | Z107: pms
... Y547: Goog-Dog-45+ Establishing / Following a hygiene & health routine (incl. supplements) | Z547: gdevd07

Sheet Change Log
B2: Change Log
B3: Date
B4: Amends | C4: 44897 | D4: 44900 | E4: 44904
C5: Added N/A options for audience name for flexbility with Youtube activations via DV360 | D5: Added TVP publisher | E5: Removed blank options from Device
C6: Added N/A to Data Type for non-data driven audiences | E6: Cleaned up Hidden Tabs
C7: Removed spaces between values for dimension/asset length fields
C8: Removed hybrid as an option for device (cross-device to be used instead)

Sheet Campaign DV Lookups (2)
R1: Sub Product to Segment | V1: Country to Region | Z1: Sub-Product to Portfolio | AD1: Segment Lookup | AG1: Region to Region Code | AK1: Portfolio to Code LU | AQ1: Essence DV Options
A2: Country code Values | B2: Country code | C2: Country | D2: Sub-Product | E2: Sub-Product Code | G2: Month | H2: Year | K2: Media Types | L2: Media Type Lookup | O2: Mars Period | R2: Sub-Product | S2: Segment | V2: Country | W2: Region | Z2: Product | AA2: Pet Portfolio | AD2: Segment | AE2: Segment Code | AG2: Region | AH2: Region Code | AK2: Pet Portfolio | AL2: Portfolio Code | AN2: portfolio code | AQ2: business channel | AS2: media channel | AU2: objective | AW2: addressable | AX2: addressable code
A3: AE | B3: AE | C3: UAE | D3: 1 in 6 | E3: OIS | F3: 43466 | G3: 1 | H3: 2010 | I3: 10 | K3: Added Value | L3: AV | O3: P1 | R3: 1 in 6 | S3: MW | V3: Canada | W3: US | Z3: Temptations | AA3: Not Petcare | AD3: MW | AE3: mw | AG3: US | AH3: US | AK3: Not Petcare | AL3: NP | AN3: care-treat | AQ3: Brand | AS3: social | AU3: reach | AW3: biddable-addressable | AX3: bid-adr
A4: AL | B4: AL | C4: Albania | D4: 5 Gum | E4: GM5 | G4: 2 | H4: 2011 | I4: 11 | K4: Advanced/Connected TV | L4: CTV | O4: P2 | R4: 5 Gum | S4: MW | V4: United Kingdom | W4: Europe 1 | Z4: Oral Care | AA4: Not Petcare | AD4: Petcare | AE4: pn | AG4: Europe 1 | AH4: EUR1 | AK4: Cat Portfolio | AL4: CP | AN4: dog-mm | AQ4: D2C | AS4: olv | AU4: views | AW4: biddable-data driven audience | AX4: bid-dda
A5: AR | B5: AR | C5: Argentina | D5: Adoption | E5: ADP | G5: 3 | H5: 2012 | I5: 12 | K5: Amplification | L5: AMP | O5: P3 | R5: Adoption | S5: Petcare | V5: Denmark | W5: Europe 1 | Z5: Ben’s Original RTH | AA5: Not Petcare | AD5: Royal Canin | AE5: rc | AG5: Asia | AH5: ASIA | AK5: Dog Portfolio | AL5: DP | AN5: cat-mml | AQ5: DCOM | AS5: display | AU5: engagement | AW5: biddable-non addressable | AX5: bid-nadr
A6: AT | B6: AT | C6: Austria | D6: Advance | E6: ADV | G6: 4 | H6: 2013 | I6: 13 | K6: Audio Streaming | L6: AS | O6: P4 | R6: Advance | S6: Petcare | V6: USA | W6: US | Z6: Iams Cat | AA6: Not Petcare | AD6: Food | AE6: food | AG6: META | AH6: META | AK6: Care & Treats | AL6: CT | AN6: sph | AQ6: Sales | AS6: ppc | AU6: traffic | AW6: biddable - icj | AX6: bid-icj
A7: AU | B7: AU | C7: Australia | D7: Airwaves | E7: WAV | G7: 5 | H7: 2014 | I7: 14 | K7: Broadcaster VoD | L7: BVO | O7: P5 | R7: Airwaves | S7: MW | V7: Germany | W7: Europe 1 | Z7: Iams Dog | AA7: Not Petcare | AD7: Kind | AE7: Kind | AG7: China | AH7: CHINA | AK7: Premium and Health | AL7: PH | AN7: Ferret | AS7: ecom | AU7: Leads | AW7: biddable-addressable-icj | AX7: bid-adr-icj
A8: AZ | B8: AZ | C8: Azerbaijan | D8: Alert | E8: ALR | G8: 6 | H8: 2015 | I8: 15 | K8: Bus | L8: BUS | O8: P6 | R8: Alert | S8: MW | V8: Finland | W8: Europe 1 | Z8: Mars | AA8: Not Petcare | AD8: Mars, Inc. | AE8: inc | AG8: Australia | AH8: AUS | AN8: Fish | AS8: influencer | AU8: app install | AW8: direct-addressable | AX8: dir-adr
A9: BA | B9: BA | C9: Bosnia | D9: All Themes | E9: ALL | G9: 7 | H9: 2016 | I9: 16 | K9: Cinema | L9: CNM | O9: P7 | R9: All Themes | S9: Royal Canin | V9: Sweden | W9: Europe 1 | Z9: 5 Gum | AA9: Not Petcare | AG9: LATAM | AH9: LATAM | AN9: choc | AU9: conversions | AW9: direct-data driven audience | AX9: dir-dda
A10: BE | B10: BE | C10: Belgium | D10: Almond and coconut | E10: ANC | G10: 8 | H10: 2017 | I10: 17 | K10: Contracts | L10: CTS | O10: P8 | R10: Altoids | S10: MW | V10: Ireland | W10: Europe 1 | Z10: M&Ms | AA10: Not Petcare | AG10: Europe 2 | AH10: EUR2 | AN10: conf | AW10: direct-non addressable | AX10: dir-nadr
A11: BG | B11: BG | C11: Bulgaria | D11: Altoids | E11: ALT | G11: 9 | H11: 2018 | I11: 18 | K11: Couponing | L11: CPN | O11: P9 | R11: Balisto | S11: MW | V11: Japan | W11: Asia | Z11: Whiskas | AA11: Not Petcare | AG11: India | AH11: INDIA | AN11: Gum | AW11: direct-icj | AX11: dir-icj
A12: BH | B12: BH | C12: Bahrain | D12: American Heritage | E12: AMH | G12: 10 | H12: 2019 | I12: 19 | K12: Digital | L12: DGT | O12: P10 | R12: Birth and Growth | S12: Royal Canin | V12: KSA | W12: META | Z12: Whiskas Wet | AA12: Not Petcare | AG12: Russia | AH12: RUS | AN12: ice-cream | AW12: direct-addressable-icj | AX12: dir-adr-icj
A13: BR | B13: BR | C13: Brazil | D13: Balisto | E13: BAL | G13: 11 | H13: 2020 | I13: 20 | K13: Digital Display | L13: DD | O13: P11 | R13: Bites | S13: MW | V13: Taiwan | W13: Asia | Z13: Cesar | AA13: Not Petcare | AN13: mints
A14: BY | B14: BY | C14: Belarus | D14: Ben’s Original | E14: UBN | G14: 12 | H14: 2021 | I14: 21 | K14: Digital Partnership | L14: DP | O14: P12 | R14: Boomer | S14: MW | V14: China | W14: China | Z14: Pedigree Dry | AA14: Not Petcare | AN14: other
A15: CA | B15: CA | C15: Canada | D15: Ben’s Original Beginner’s | E15: UBB | H15: 2022 | I15: 22 | K15: Digital VOD | L15: DVO | O15: P13 | R15: Bounty | S15: MW | V15: Austria | W15: Europe 1 | Z15: Dolmio | AA15: Not Petcare | AN15: sub-snacks
A16: CH | B16: CH | C16: Switzerland | D16: Ben’s Original BIB | E16: UBI | H16: 2023 | I16: 23 | K16: DVD | L16: DVD | R16: Breed | S16: Royal Canin | V16: Norway | W16: Europe 1 | Z16: Snickers | AA16: Not Petcare | AN16: rth
A17: CL | B17: CL | C17: Chile | D17: Ben’s Original Hero Meals | E17: UBH | H17: 2024 | I17: 24 | K17: E-Commerce | L17: EC | R17: Care & Sensitivities | S17: Royal Canin | V17: Australia | W17: Australia | Z17: Skittles | AA17: Not Petcare | AN17: mf-hs
A18: CN | B18: CN | C18: China | D18: Ben’s Original RTH | E18: UBR | H18: 2025 | I18: 25 | K18: Hispanic Digital OOH | L18: HDO | R18: Catisfactions | S18: Petcare | V18: Mexico | W18: LATAM | Z18: DoubleMint Mints | AA18: Not Petcare | AN18: mf-fs
A19: CO | B19: CO | C19: Colombia | D19: Ben’s Original Sauces | E19: UBS | H19: 2026 | I19: 26 | K19: Hispanic Magazines | L19: HM | R19: Catsan | S19: Petcare | V19: France | W19: Europe 1 | Z19: Extra Gum | AA19: Not Petcare | AN19: dolmio
A20: CR | B20: CR | C20: Costa Rica | D20: Ben’s Original Twinpot | E20: UBT | H20: 2027 | I20: 27 | K20: Hispanic Online Video | L20: HOV | R20: Celebrations | S20: MW | V20: Spain | W20: Europe 1 | Z20: Twix | AA20: Not Petcare | AN20: tb
A21: CZ | B21: CZ | C21: Czech Republic | D21: Birth and Growth | E21: BAG | H21: 2028 | I21: 28 | K21: Hispanic OOH | L21: HOH | R21: Cesar | S21: Petcare | V21: Poland | W21: Europe 2 | Z21: Juicy Fruit | AA21: Not Petcare | AN21: tb-fs
A22: DE | B22: DE | C22: Germany | D22: Biscrok | E22: BIS | H22: 2029 | I22: 29 | K22: Hispanic Paid Social Video | L22: HSV | R22: Chappi | S22: Petcare | V22: Puerto Rico | W22: LATAM | Z22: Nutro | AA22: Not Petcare | AN22: soc
A23: DK | B23: DK | C23: Denmark | D23: Bites | E23: BIT | H23: 2030 | I23: 30 | K23: Hispanic Spot Radio | L23: HSR | R23: CocoaVia | S23: Food | V23: Vietnam | W23: Asia | Z23: Airwaves | AA23: Not Petcare | AN23: dry
A24: DO | B24: DO | C24: Dominican Republic | D24: Blueberry almond | E24: BLA | K24: Hispanic TV | L24: HTV | R24: Combos | S24: MW | V24: Gulf | W24: META | Z24: Ben’s Original BIB | AA24: Not Petcare
A25: EC | B25: EC | C25: Ecuador | D25: Blueberry vanilla and cashew | E25: BVC | K25: Magazines | L25: M | R25: Consideration | S25: Royal Canin | V25: India | W25: India | Z25: Eukanuba | AA25: Not Petcare
A26: EE | B26: EE | C26: Estonia | D26: Boomer | E26: BOM | K26: Magazines + Newspapers | L26: MNN | R26: Cool Air | S26: MW | V26: Netherlands | W26: Europe 1 | Z26: Altoids | AA26: Not Petcare
A27: EG | B27: EG | C27: Egypt | D27: Bounty | E27: BOU | K27: Malls | L27: MAL | R27: Crave | S27: Petcare | V27: Ukraine | W27: Russia | Z27: DoubleMint Gum | AA27: Not Petcare
A28: ES | B28: ES | C28: Spain | D28: Breed | E28: BRE | K28: Mobile Display | L28: MD | R28: Crispy | S28: MW | V28: Switzerland | W28: Europe 1 | Z28: Eclipse Gum | AA28: Not Petcare
A29: FI | B29: FI | C29: Finland | D29: Caramel almond and sea salt | E29: CSS | K29: Mobile Video | L29: MV | R29: Dine | S29: Petcare | V29: Russia | W29: Russia | Z29: LifeSaver Mints | AA29: Not Petcare
A30: FR | B30: FR | C30: France | D30: Care & Sensitivities | E30: CAS | K30: Newspapers | L30: NP | R30: Dolmio | S30: Food | V30: Portugal | W30: Europe 1 | Z30: Excel Mints | AA30: Not Petcare
A31: GB | B31: GB | C31: United Kingdom | D31: Catisfactions | E31: CAF | K31: Non Measured TV | L31: NMT | R31: DoubleMint Gum | S31: MW | V31: Korea | W31: Asia | Z31: Celebrations | AA31: Not Petcare
A32: GE | B32: GE | C32: Georgia | D32: Catsan | E32: CAT | K32: Online Video | L32: OV | R32: DoubleMint Mints | S32: MW | V32: Argentina | W32: LATAM | Z32: Greenies | AA32: Not Petcare
A33: GR | B33: GR | C33: Greece | D33: Celebrations | E33: CEL | K33: OOH Video | L33: OHV | R33: Dove / Galaxy | S33: MW | V33: Thailand | W33: Asia | Z33: Ben’s Original | AA33: Not Petcare
A34: GT | B34: GT | C34: Guatemala | D34: Cesar | E34: CES | K34: Other | L34: OTH | R34: Dreamies | S34: Petcare | V34: Romania | W34: Europe 2 | Z34: Royal Canin | AA34: Not Petcare
A35: Gulf | B35: Gulf | C35: Gulf | D35: Champ Dry | E35: CHD | K35: Other (OOH) | L35: OOH | R35: Ebly | S35: Food | V35: Turkey | W35: META | Z35: Ice Cream | AA35: Not Petcare
... A60: NO | B60: NO | C60: Norway | D60: Eliott | E60: ELL | K60: TV | L60: TV | R60: Ice Cream | S60: MW | V60: Belarus | W60: Russia | Z60: Sheba | AA60: Not Petcare
A61: NZ | B61: NZ | C61: New Zealand | D61: Enterprise | E61: ENT | R61: Institutional | S61: Petcare | V61: New Zealand | W61: Australia | Z61: Jumbone | AA61: Not Petcare
A62: OM | B62: OM | C62: Oman | D62: Ethel M | E62: ETM | R62: IWOM | S62: Petcare | V62: Costa Rica | W62: LATAM | Z62: COOL AIR | AA62: Not Petcare
A63: PA | B63: PA | C63: Panama | D63: Eukanuba | E63: EUK | R63: James Wellbeloved | S63: Petcare | V63: Panama | W63: LATAM | Z63: Suzi Wan | AA63: Not Petcare
A64: PE | B64: PE | C64: Peru | D64: Excel Drops | E64: ECD | R64: Jewels | S64: MW | V64: Bosnia | W64: Europe 2 | Z64: Catsan | AA64: Not Petcare
A65: PH | B65: PH | C65: Philippines | D65: Excel Gum | E65: ECG | R65: Juicy Fruit | S65: MW | V65: Slovenia | W65: Europe 2 | Z65: Orbit Base | AA65: Not Petcare
A66: PL | B66: PL | C66: Poland | D66: Excel Mints | E66: ECM | R66: Juicy Fruit + Starburst Flavours | S66: MW | V66: Israel | W66: Europe 2 | Z66: Crispy | AA66: Not Petcare
A67: PR | B67: PR | C67: Puerto Rico | D67: Exelcat | E67: EXE | R67: Kalkan | S67: Petcare | V67: Guatemala | W67: LATAM | Z67: Extra Prof | AA67: Not Petcare
A68: PT | B68: PT | C68: Portugal | D68: Extra Gum | E68: EXG | R68: Kan Tong | S68: Food | V68: Dominican Republic | W68: LATAM | Z68: Multibrand | AA68: Not Petcare
A69: QA | B69: QA | C69: Qatar | D69: Extra Mints | E69: EXM | R69: Kitekat | S69: Petcare | V69: Serbia | W69: Europe 2 | Z69: Balisto | AA69: Not Petcare
A70: RO | B70: RO | C70: Romania | D70: Extra Prof | E70: EXP | R70: KiteKat, Perfect Fit, Frolic, Natusan | S70: Petcare | V70: Montenegro | W70: Europe 2 | Z70: Miracoli | AA70: Not Petcare
A71: RS | B71: RS | C71: Serbia | D71: Flutes | E71: FLU | R71: Korkunov | S71: MW | V71: Albania | W71: Europe 2 | Z71: Korkunov | AA71: Not Petcare
A72: RU | B72: RU | C72: Russia | D72: Food Digital Pot | E72: FDP | R72: LifeSaver Gummies | S72: MW | V72: Macedonia | W72: Europe 2 | Z72: Whiskas Pouch | AA72: Not Petcare
... A83: US | B83: US | C83: USA | D83: Honey oat | E83: HOO | R83: Masterfoods Functional | S83: Food | V83: Uruguay | W83: LATAM | Z83: KiteKat, Perfect Fit, Frolic, Natusan | AA83: Not Petcare
A84: VN | B84: VN | C84: Vietnam | D84: Honey roasted nuts and sea salt | E84: HRS | R84: Meaty Treats | S84: Petcare | Z84: James Wellbeloved | AA84: Premium and Health
A85: XK | B85: XK | C85: Kosovo | D85: Hubba Bubba | E85: HUB | R85: Milky way | S85: MW | Z85: 3Musketeers | AA85: Not Petcare
A86: YE | B86: YE | C86: Yemen | D86: Iams Cat | E86: ICT | R86: Minstrels | S86: MW | Z86: Adoption | AA86: Not Petcare
A87: ZA | B87: ZA | C87: South Africa | D87: Iams Cat and Dog | E87: ICD | R87: Miracoli | S87: Food | Z87: Whiskas | AA87: Cat Portfolio
D88: Iams Dog | E88: IDG | R88: Misfits | S88: Petcare | Z88: Vital Protection | AA88: Not Petcare
D89: Ice Cream | E89: ICE | R89: Multibrand | S89: MW | Z89: Meaty Treats | AA89: Not Petcare
D90: Institutional | E90: INT | R90: My Dog | S90: Petcare | Z90: Lucas | AA90: Not Petcare
D91: IWOM | E91: IWO | R91: Natural Choice | S91: Petcare | Z91: Goodness Knows | AA91: Not Petcare
D92: James Wellbeloved | E92: JWB | R92: Natural Defense | S92: Petcare | Z92: Bounty | AA92: Not Petcare
D93: Jewels | E93: JEW | R93: Nutro | S93: Petcare | Z93: Institutional | AA93: Not Petcare
D94: Juicy Fruit | E94: JFT | R94: Optimum | S94: Petcare | Z94: Orbit Oral Health Care | AA94: Not Petcare
D95: Juicy Fruit + Starburst Flavours | E95: JFS | R95: Orbit Base | S95: MW | Z95: Greenies | AA95: Premium and Health
D96: Jumbone | E96: JUM | R96: Orbit Bottle | S96: MW | Z96: My Dog | AA96: Not Petcare
D97: Kalkan | E97: KAL | R97: Orbit Gum | S97: MW | Z97: Dine | AA97: Not Petcare
D98: Kan Tong | E98: KAN | R98: Orbit Mints | S98: MW | Z98: Optimum | AA98: Not Petcare
D99: Karma | E99: KAR | R99: Orbit Oral Health Care | S99: MW | Z99: Schmackos | AA99: Not Petcare
... D112: Lockets | E112: LOC | R112: PODs | S112: MW | Z112: Dine | AA112: Cat Portfolio
D113: Loose | R113: ProManage | S113: Petcare | Z113: My Dog | AA113: Dog Portfolio
D114: Loose | E114: LOO | R114: Raising The Bar | S114: MW | Z114: MasterFoods | AA114: Not Petcare
D115: Lubimchik | E115: LUB | R115: Ripple | S115: MW | Z115: Extra Mints | AA115: Not Petcare
D116: Lucas | E116: LUC | R116: Royal Canin | S116: Royal Canin | Z116: MaltEaster | AA116: Not Petcare
D117: M&M’S Minis | E117: MMM | R117: Royco | S117: Food | Z117: Golden Eggs | AA117: Not Petcare
D118: M&M’S Mix | E118: MMX | R118: Schmackos | S118: Petcare | Z118: Cesar | AA118: Dog Portfolio
D119: M&Ms | E119: MMS | R119: Seasonal | S119: MW | Z119: Whiskas C&T | AA119: Cat Portfolio
D120: M&Ms Fudge Brownies | E120: MFB | R120: Seeds of Change | S120: Food | Z120: ProManage | AA120: Dog Portfolio
D121: M&Ms Seasonal | E121: MMSS | R121: Sheba | S121: Petcare | Z121: Ebly | AA121: Not Petcare
D122: Madagascar vanilla almond | E122: MVA | R122: Skittles | S122: MW | Z122: Bites | AA122: Not Petcare
D123: MaltEaster | E123: MAE | R123: Skwinkles | S123: MW | Z123: Orbit Professional | AA123: Not Petcare
D124: Maltesers | E124: MAL | R124: Snickers | S124: MW | Z124: Combos | AA124: Not Petcare
D125: Maple glazed pecan and sea salt | E125: MGS | R125: Snickers Miniatures | S125: MW | Z125: Advance | AA125: Premium and Health
... D170: Seeds of Change | E170: SOC | R170: Dark chocolate nuts and sea salt | S170: Kind | Z170: Exelcat | AA170: Cat Portfolio
D171: Sheba | E171: SHE | R171: Madagascar vanilla almond | S171: Kind | AA171: Not Petcare
D172: Skittles | E172: SKT | R172: Maple glazed pecan and sea salt | S172: Kind | Z172: Karma | AA172: Dog Portfolio
D173: Skittles Gummies | E173: SKG | R173: Almond and coconut | S173: Kind | Z173: Kind Protein Bars | AA173: Not Petcare
D174: Skittles Halloween | E174: SKH | R174: Blueberry vanilla and cashew | S174: Kind | Z174: Pedigree Adoption Drive | AA174: Dog Portfolio
D175: Skwinkles | E175: SKW | R175: Honey roasted nuts and sea salt | S175: Kind | Z175: Adoption | AA175: Dog Portfolio
D176: Snickers | E176: SNI | R176: Blueberry almond | S176: Kind | Z176: Wrigley Multi-brand | AA176: Not Petcare
D177: Snickers Ice Cream Core | E177: SICC | R177: Honey oat | S177: Kind | Z177: For Paws | AA177: Dog Portfolio
D178: Snickers Ice Cream Peanut Brownie | E178: SICPB | R178: Peanut butter | S178: Kind | Z178: Iams Cat and Dog | AA178: Not Petcare
D179: Snickers Miniatures | E179: SNM | R179: Double dark chocolate | S179: Kind | Z179: 1 in 6 | AA179: Not Petcare
D180: Snickers Nut Brownie | E180: SNB | R180: Crunchy peanut butter | S180: Kind
D181: Starburst | E181: STB | R181: Toasted caramel nut | S181: Kind
D182: Starburst Gummies | E182: STG | R182: Treat Town | S182: MW
D183: Starburst Minis | E183: STM | R183: Dentastix | S183: Petcare
D184: Starburst Seasonal | E184: SBS | R184: M&Ms Fudge Brownies | S184: MW
D185: Sticks | E185: STC | R185: Chocolate Multi-brand | S185: MW
D186: Sugus | E186: SUG | R186: Wrigley Multi-brand | S186: MW
D187: Suzi Wan | E187: SUW | R187: Petcare Multi-brand | S187: Petcare
D188: Tailored Nutrition | E188: TAN | R188: Food Multi-brand | S188: Food
D189: Tasty Bite | E189: TAB | R189: Champ Dry | S189: Petcare
D190: Temptations | E190: TEM | R190: Karma | S190: Petcare
...

Sheet Alpha-2 Reference Sheet
A1: Country | B1: Country code
A2: UAE | B2: AE
A3: Albania | B3: AL
A4: Argentina | B4: AR
A5: Austria | B5: AT
A6: Australia | B6: AU
A7: Azerbaijan | B7: AZ
A8: Bosnia | B8: BA
A9: Belgium | B9: BE
A10: Bulgaria | B10: BG
A11: Bahrain | B11: BH
A12: Brazil | B12: BR
... A86: South Africa | B86: ZA

Sheet Data Validations
A1: Sub-Product | B1: Sub-Product Code | D1: Objective | E1: Objective | G1: Objective | H1: KPI | I1: KPI Code | K1: Channel | L1: Channel Code | N1: Channel | O1: Format | P1: Format Code | R1: Priority Partner | S1: Partner Code | U1: Partner Type | V1: Partner Type Code | X1: Costing model | Y1: Costing model Code | AA1: Primary Targeting Segment | AB1: Primary Targeting Segment Code | AE1: Detailed Targeting | AF1: Detailed Targeting Code
A2: Adoption | B2: ADP | D2: Reach | E2: REC | G2: Relevance | H2: Bounce Rate | I2: BR | K2: Audio | L2: AUD | O2: 0x0 | P2: 0x0 | R2: Not Applicable | S2: NA | U2: Content Syndication | V2: CON | X2: Added Value | Y2: AV | AA2: 13+ | AB2: 13-49 | AE2: 18+, Demo Only | AF2: 18+DO
A3: Advance | B3: ADV | D3: Reaction | E3: REA | H3: Brand Awareness | I3: BA | K3: Display | L3: DIS | O3: 1024x1280 | P3: 1024x1280 | R3: 365 Scores | S3: 365 | U3: Coupon | V3: CPN | X3: Cost Per Acquisition | Y3: CPA | AA3: 13-34 | AE3: 1P CRM | AF3: 1PCRM
A4: All Themes | B4: ALL | D4: Relevance | E4: REL | G4: Reaction | H4: Click Through Rate | I4: CTR | K4: eCommerce | L4: ECO | O4: 1024x768 | P4: 1024x768 | R4: 9Honey | S4: 9HO | U4: Entertainment | V4: ENT | X4: Cost Per Click | Y4: CPC | AA4: 13-35 | AB4: 13-35 | AE4: 1P Mars Cat | AF4: 1PMC
A5: Alert | B5: ALR | G5: Relevance | H5: Clicks | I5: CLC | K5: Email | L5: EMA | O5: 1064x1536 | P5: 1064x1536 | R5: ABC | S5: ABC | U5: Gaming | V5: GAM | X5: Cost Per Completed View | Y5: CPCV | AA5: 13-49 | AE5: 1P Mars Dog | AF5: 1PMD
A6: Altoids | B6: ALT | H6: Conversion | I6: CVN | K6: Influencer | L6: INF | O6: 1080x1080 | P6: 1080x1080 | R6: Acast | S6: ACA | U6: Keyword | V6: KWD | X6: Cost Per Engagement | Y6: CPE | AA6: 13-54 | AE6: 1P Mars Pet | AF6: 1PMP
A7: American Heritage | B7: AMH | G7: Reaction | H7: Conversion Rate | I7: CVR | K7: Native | L7: NAT | O7: 1080x1920 | P7: 1080x1920 | R7: Adaptive Media | S7: AMG | U7: Lead Gen | V7: LGN | X7: Cost Per Games Session | Y7: CPGS | AA7: 13-55 | AB7: 13-65+ | AE7: 2nd Party Data/Native Platform Targeting | AF7: 2PD/NPT
A8: Almond and coconut | B8: ANC | G8: Relevance | H8: Cost Per Acquisition | I8: CPA | K8: Search | L8: SEA | O8: 1200x400 | P8: 1200x400 | R8: AdColony | S8: ADC | U8: Lifestyle | V8: LIFE | X8: Cost Per Install | Y8: CPI | AA8: 13-65+ | AE8: 3P Cat Product Purchaser | AF8: 3PCPP
A9: Birth and Growth | B9: BAG | H9: Cost Per Add to Cart | I9: CPATC | K9: SocialDisplay | L9: SPD | O9: 120x240 | P9: 120x240 | R9: Adelphic | S9: ADL | U9: Music | V9: MUS | X9: Cost Per Lead | Y9: CPL | AA9: 14-35 | AE9: 3P Dog Product Purchaser | AF9: 3PDPP
A10: Balisto | B10: BAL | G10: Reaction | H10: Cost Per Click | I10: CPC | K10: SocialVideo | L10: SPV | O10: 120x60 | P10: 120x60 | R10: Admixer | S10: ADM | U10: Network | V10: NET | X10: Cost Per Thousand | Y10: CPM | AA10: 14-50 | AB10: 14-50 | AE10: 3P Walmart Proximity + Kind Portfolio Buyers | AF10: 3PWPKPB
A11: Biscrok | B11: BIS | G11: Reaction | H11: Cost Per Engagement | I11: CPE | K11: Video | L11: VID | O11: 120x600 | P11: 120x600 | R11: Adot | S11: ADT | U11: News | V11: NEW | X11: Cost Per Reach Point | Y11: CPRP | AA11: 14-51 | AE11: 3P Walmart Visitors + Interests | AF11: 3PWVI
A12: Bites | B12: BIT | H12: Cost Per Landing Page View | I12: CPLPV | O12: 120x90 | P12: 120x90 | R12: Adpartner | S12: ADPA | U12: OverTheTopMedia | V12: OTT | X12: Cost Per Unit | Y12: CPU | AA12: 14-59 | AE12: 3rd Party Audience | AF12: 3PA
A13: Blueberry almond | B13: BLA | G13: Relevance | H13: Cost Per Lead | I13: CPL | O13: 125x125 | P13: 125x125 | R13: ADpick | S13: ADPI | U13: Parenting | V13: PAR | X13: Cost Per Unique View | Y13: CPUL | AA13: 15-24 | AE13: Active/Exercise Interests | AF13: A/EI
A14: Boomer | B14: BOM | H14: Cost Per Reach Point | I14: CPRP | O14: 1280x100 | P14: 1280x100 | R14: Adult Swim | S14: ASM | U14: Portal | V14: POR | X14: Cost Per View | Y14: CPV | AA14: 15-25 | AB14: 15-25 | AE14: Adjacent Interests | AF14: AI
A15: Bounty | B15: BOU | G15: Reaction | H15: Cost Per Thousand | I15: CPM | O15: 1280x720 | P15: 1280x720 | R15: Aftonbladet | S15: AFB | U15: Programmatic | V15: PRO | X15: Dynamic Cost Per Click | Y15: DCPC | AA15: 15-34 | AE15: Adopted a Cat/Looking to adopt a Cat | AF15: ACLAC
A16: Breed | B16: BRE | G16: Reach | H16: Cost Per Unit | I16: CPU | O16: 1400x400 | P16: 1400x400 | R16: Aki | S16: AKI | U16: Programmatic – PG | V16: PRG | X16: Dynamic Cost Per Thousand | Y16: DCPM | AA16: 15-35 | AB16: 15-35 | AE16: Affinity/Behavior Targeting | AF16: A/BT
A17: Blueberry vanilla and cashew | B17: BVC | G17: Relevance | H17: Cost Per View | I17: CPV | O17: 1400x500 | P17: 1400x500 | R17: Allegro | S17: ALG | U17: Programmatic – PMP | V17: PMP | X17: Dynamic Cost Per Incremental Visitor | Y17: dCPIV | AA17: 15-39 | AE17: ANC Past Video Viewers | AF17: ANCPVV
A18: Catisfactions | B18: CAF | H18: Detail Page View Rate | I18: DPVR | O18: 1440x600 | P18: 1440x600 | R18: Amazon | S18: AMZ | U18: Retail | V18: RET | X18: Dynamic Cost Per Completed View | Y18: dCPCV | AA18: 15-44 | AE18: Audio Everywhere - Holiday Shoppers Gift Givers Home Entertainers | AF18: AEHSGGHE
A19: Care & Sensitivities | B19: CAS | G19: Reaction | H19: Engagement Rate | I19: ENR | O19: 1600x400 | P19: 1600x400 | R19: Anghami | S19: ANG | U19: Social Media | V19: SOC | X19: Dynamic Cost Per View | Y19: DCPV | AA19: 15-45 | AE19: Big Dog Owners | AF19: BDO
A20: Catsan | B20: CAT | G20: Relevance | H20: Fee | I20: Fee | O20: 160x160 | P20: 160x160 | R20: AstraOne | S20: ASO | U20: Sports | V20: SPO | X20: Fee | Y20: FEE | AA20: 15-49 | AE20: Brand Buyer | AF20: BB
A21: CocoaVia | B21: CCV | G21: Relevance | H21: Impression Share | I21: IS | O21: 160x60 | P21: 160x60 | R21: AtMedia | S21: ATM | U21: TV | V21: TV | X21: Flat | Y21: Flat | AA21: 15-54 | AE21: Broad, Demo Only | AF21: BRDO
A22: Chocolate Digital Pot | B22: CDP | G22: Reaction | H22: Impressions | I22: IMP | O22: 160x600 | P22: 160x600 | R22: Avito | S22: AVT | U22: Utility | V22: UTL | X22: Other | Y22: Other | AA22: 15-55 | AB22: 15-55 | AE22: Brownie Equity | AF22: BE
A23: Celebrations | B23: CEL | G23: Reach | H23: Installs | I23: INS | O23: 163x32 | P23: 163x32 | R23: Axel Springer Media | S23: ASM | U23: Pet site | V23: PET | X23: Cost Per Viewable Thousand | Y23: VCPM | AA23: 15-59 | AE23: Candy Interests | AF23: CANI
A24: Cesar | B24: CES | G24: Reaction | H24: Open Rate | I24: OPR | O24: 180x150 | P24: 180x150 | R24: B Media | S24: BME | X24: View Through Cost Per Thousand | Y24: VtCPM | AA24: 15-60 | AE24: Cat + Dog interest | AF24: CDI
A25: Chappi | B25: CHA | G25: Reach | H25: Position | I25: POS | O25: 1920x1080 | P25: 1920x1080 | R25: Baofeng | S25: BAO | AA25: 15-64 | AE25: Cat Affinity | AF25: CA
A26: Champ Dry | B26: CHD | H26: Quality Score | I26: QUS | O26: 1920x1084 | P26: 1920x1084 | R26: Bauer Media | S26: BAU | AA26: 16-25 | AE26: Cat Brand Food Buyers | AF26: CBFB
A27: Cool Air | B27: COA | H27: Reach | I27: Reach | O27: 1920x1085 | P27: 1920x1085 | R27: Bazaar Voice | S27: BAV | AA27: 16-49 | AB27: 16-49 | AE27: Cat Brand Treats Buyers | AF27: CBTB
A28: Consideration | B28: COD | H28: Relevance | I28: REL | O28: 1920x1086 | P28: 1920x1086 | R28: Beeswax | S28: BW | AA28: 16-50 | AE28: Cat Category Food Buyers | AF28: CCFB
A29: Conejos | B29: COJ | G29: Relevance | H29: ROAS | I29: ROAS | O29: 1920x1087 | P29: 1920x1087 | R29: Betoota Advocate | S29: BTO | AA29: 16-54 | AE29: Cat Category Treats Buyers | AF29: CCTB
A30: Combos | B30: COM | G30: Reaction | H30: Sales | I30: SAL | O30: 1x1 | P30: 1x1 | R30: Bing | S30: BIN | AA30: 16-55 | AE30: Cat channels | AF30: CC
A31: Crunchy peanut butter | B31: CPB | G31: Reach | H31: Samples | I31: SMP | O31: 234x60 | P31: 234x60 | R31: Blis | S31: BLS | AA31: 16-56 | AE31: Cat interests | AF31: CI
A32: PK | B32: CPK | G32: Relevance | H32: Subscribers | I32: SUB | O32: 2400x200 | P32: 2400x200 | R32: Blis Miroma | S32: BLM | AA32: 18-24 | AE32: Cat interests and keywords | AF32: CIAK
A33: Crispy | B33: CRI | G33: Reaction | H33: Total Reach | I33: TOR | O33: 240x400 | P33: 240x400 | R33: Blix | S33: BLX | AA33: 18-34 | AB33: 18-34 | AE33: Cat keywords | AF33: CK
A34: Crave | B34: CRV | G34: Relevance | H34: Traffic | I34: TRA | O34: 250x250 | P34: 250x250 | R34: Brat | S34: BRT | AA34: 18-35 | AE34: Cat Lovers, New Cat Owners, Future Cat Owners | AF34: CLNCOFCO
A35: CSR Initiative | B35: CSR | H35: Unique Views | I35: UQV | O35: 300x250 | P35: 300x250 | R35: Broadsheet | S35: BRS | AA35: 18-36 | AE35: Cat Owners | AF35: CO
A36: Caramel almond and sea salt | B36: CSS | G36: Reach | H36: Video Completes | I36: VC | O36: 300x50 | P36: 300x50 | R36: Buzzfeed | S36: BUZ | AA36: 18-39 | AE36: Category Buyer | AF36: CB
A37: Dark chocolate nuts and sea salt | B37: DCS | H37: Video Completion Rate | I37: VCR | O37: 300x600 | P37: 300x600 | R37: CBS | S37: CBS | AA37: 18-40 | AE37: Chocolate interests | AF37: CHOI
A38: Double dark chocolate | B38: DDC | G38: Reach | H38: Viewability | I38: VIW | O38: 320x100 | P38: 320x100 | R38: CBS All Access | S38: CBA | AA38: 18-44 | AB38: 18-44 | AE38: Connections Targeting | AF38: CT
A39: Dove / Galaxy Ice Cream | B39: DGIC | G39: Reaction | H39: Viewable CPM | I39: VCPM | O39: 320x480 | P39: 320x480 | R39: CBS Sports | S39: CSP | AA39: 18-45 | AE39: D2C (Direct to consumer) | AF39: D2C
A40: Dove High Cacao | B40: DHC | H40: Views | I40: VWS | O40: 320x50 | P40: 320x50 | R40: Central Media Sales | S40: CMS | AA40: 18-45+ | AE40: Dates | AF40: DAT
A41: Dine | B41: DIN | H41: View-Through CPM | I41: VtCPM | O41: 336x280 | P41: 336x280 | R41: Channel Factory | S41: CF | AA41: 18-49 | AB41: 18-49 | AE41: Dog Affinity | AF41: DA
A42: DoubleMint Gum | B42: DMG | G42: Reach | H42: View-Through Rate | I42: VTR | O42: 3840x1080 | P42: 3840x1080 | R42: Cinema Premium | S42: CIP | AA42: 18-54 | AB42: 18-54 | AE42: Dog Brand Dry Food Buyers | AF42: DBDFB
A43: DoubleMint Mints | B43: DMM | O43: 414x125 | P43: 414x125 | R43: CMT | S43: CMT | AA43: 18-54+ | AE43: Dog Brand Food Buyers | AF43: DBFB
A44: Dolmio | B44: DOL | O44: 444x250 | P44: 444x250 | R44: Collective | S44: CLL | AA44: 18-55 | AB44: 18-55 | AE44: Dog Brand Treats Buyers | AF44: DBTB
A45: Dreamies | B45: DRE | O45: 450X350 | P45: 450X350 | R45: Collective Miroma | S45: CLM | AA45: 18-60 | AB45: 18-60 | AE45: Dog Brand Wet Food Buyers | AF45: DBWFB
A46: Dove / Galaxy | B46: DSG | O46: 468x60 | P46: 468x60 | R46: Complex | S46: COM | AA46: 18-65+ | AB46: 18-65+ | AE46: Dog Category Dry Food Buyers | AF46: DCDFB
A47: Ebly | B47: EBL | O47: 600x150 | P47: 600x150 | R47: Convenience Store | S47: CON | AA47: 18-85 | AB47: 18-85 | AE47: Dog Category Food Buyers | AF47: DCFB
A48: Excel Drops | B48: ECD | O48: 600x600 | P48: 600x600 | R48: Criteo | S48: CRIT | AA48: 1P Mix | AB48: 1P Mix | AE48: Dog Category Keywords | AF48: DCK
A49: Excel Gum | B49: ECG | O49: 627x627 | P49: 627x627 | R49: CTC | S49: CTC | AA49: 20+ | AE49: Dog Category Treats Buyers | AF49: DCTB
A50: Excel Mints | B50: ECM | O50: 640x360 | P50: 640x360 | R50: CW | S50: CW | AA50: 20-49 | AB50: 20-65+ | AE50: Dog Category Wet Food Buyers | AF50: DCWFB
A51: Eclipse Gum | B51: EGM | O51: 640x500 | P51: 640x500 | R51: Dailymotion | S51: DLM | AA51: 20-65+ | AE51: Dog interests | AF51: DI
A52: Eliott | B52: ELL | O52: 640x640 | P52: 640x640 | R52: Digital Venture | S52: DV | AA52: 21-54 | AE52: Dog interests and keywords | AF52: DIAK
A53: Eclipse Mints | B53: EMT | O53: 700x40 | P53: 700x40 | R53: DIO | S53: DIO | AA53: 25-34 | AB53: 20+ | AE53: Dog keywords | AF53: DK
A54: Enterprise | B54: ENT | O54: 720x186 | P54: 720x186 | R54: Discovery | S54: DIS | AA54: 25-44 | AB54: 25-54 | AE54: Dog Lovers, New Dog Owners, Future Dog Owners | AF54: DLNDOFDO
A55: Ethel M | B55: ETM | O55: 728x90 | P55: 728x90 | R55: Disney | S55: DSN | AA55: 25-54 | AE55: Dog Owners | AF55: DO
A56: Eukanuba | B56: EUK | O56: 760x760 | P56: 760x760 | R56: DMS | S56: DMS | AA56: 2P | AB56: 2P | AE56: E Sport Content | AF56: ESCT
A57: Exelcat | B57: EXE | O57: 840x400 | P57: 840x400 | R57: Dot Dash | S57: DD | AA57: 2PD | AB57: 2PD | AE57: Everyday Treating | AF57: ET
A58: Extra Gum | B58: EXG | O58: 88x31 | P58: 88x31 | R58: DV360 | S58: DV360 | AA58: 35-44 | AB58: 3P | AE58: Fathers Day | AF58: FD
A59: Extra Mints | B59: EXM | O59: 970x250 | P59: 970x250 | R59: EA Sports | S59: EAS | AA59: 35-54 | AB59: 3PD | AE59: Food Keywords | AF59: FK
A60: Extra Prof | B60: EXP | O60: 970x250 | P60: 970x250 | R60: ebay | S60: EBA | AA60: 3P | AE60: Gaming | AF60: GM
A61: Food Digital Pot | B61: FDP | O61: 970x66 | P61: 970x66 | R61: E-contenta | S61: ECO | AA61: 3PD | AE61: Genre | AF61: GR
A62: Flutes | B62: FLU | O62: 970x90 | P62: 970x90 | R62: Edadeal | S62: EDAD | AA62: 45-54 | AE62: Healthy Eating Interests | AF62: HEI
A63: For Paws | O63: 9x16 | P63: 9x16 | R63: Edelman | S63: EDAM | AA63: A12-39 | AB63: A12-39 | AE63: Heartland - Equity | AF63: HE
A64: Freedent | B64: FRE | O64: Audio | P64: AUD | R64: ESPN | S64: ESPN | AA64: A13-25 | AB64: A13-25 | AE64: Heartland - Outdoor Life | AF64: HOL
A65: Frolic | B65: FRO | O65: Bumper | P65: BPR | R65: ETtoday | S65: ETT | AA65: A13-35 | AB65: A13-35 | AE65: Heartland - Work/Road Life | AF65: HWRL
A66: Galaxy/Dove Fruit | B66: GAL | O66: Canvas | P66: CAN | R66: Facebook | S66: FCB | AA66: A13-49 | AB66: A13-49 | AE66: Hispanic | AF66: HSP
A67: Gum Disposal Awareness | B67: GDA | O67: Carousel | P67: CAR | R67: Facebook & Instagram | S67: FBI | AA67: A13-49 Spanish Language | AB67: A13-49SL | AE67: Holiday Cultural Relevance | AF67: HCR
A68: Gifting | B68: GIT | O68: Carousel | R68: Fandom | S68: FND | AA68: A15+ | AE68: Hunting Interests | AF68: HI
A69: Goodness Knows | B69: GKS | O69: Carousel with Video | R69: Finecast | S69: FIN | AA69: A18+ | AB69: A18+ | AE69: Interest Targeting | AF69: IT
A70: 5 Gum | B70: GM5 | O70: Collection Ad | P70: CA | R70: Fitatu | S70: FIT | AA70: A18+ LAL of EthelM Purchasers | AB70: A18+LALOEMP | AE70: Kitten Interests | AF70: KIT
A71: Golden Eggs | B71: GOL | O71: Collection and Carousel Ad | R71: Flaire | S71: FLA | AA71: A18+ Previous EthelM Purchasers+Previous EthelM Engagers+EthelM Site Retargeting | AB71: A18+PEMPPEMEEMSR | AE71: Latin | AF71: LT
A72: Greenies | B72: GRN | O72: Digital Display | P72: DISP | R72: FourSquare | S72: fsq | AA72: A18-44 | AB72: A18-49 | AE72: Latin Playlist | AF72: LTPLY
A73: Honey oat | B73: HOO | O73: Display | R73: FOX | S73: FOX | AA73: A18-49 | AE73: Latinx Affinity | AF73: LATXAF
A74: Honey roasted nuts and sea salt | B74: HRS | O74: DOOH | R74: Funny or Die | S74: FOD | AA74: A18-49 Candy Interests | AB74: A18-49CI | AE74: Life Event/Demographic Targeting | AF74: LE/DT
A75: Hubba Bubba | B75: HUB | O75: eCommerce Display | P75: DISP | R75: Globmobi | S75: GLO | AA75: A18-49 Snacking Interests | AB75: A18-49SI | AE75: Local | AF75: LCL
A76: Iams Cat and Dog | B76: ICD | O76: eCommerce Text | P76: TXT | R76: Goal.com | S76: GOA | AA76: A18-49 Spanish Language | AB76: A18-49SL | AE76: Lookalikes | AF76: LAL
A77: Ice Cream | B77: ICE | O77: Email | P77: EMA | R77: Goldbach Audience Austria GmbH | S77: GAAG | AA77: A18-60 | AB77: A18-60 | AE77: Lunes Perrito | AF77: LUNPER
A78: Iams Cat | B78: ICT | O78: Email Logo | P78: LOG | R78: Go-Media | S78: GOM | AA78: A18-65+ | AB78: A18-65+ | AE78: Moving | AF78: MOV
A79: Iams Dog | B79: IDG | O79: Email Text | P79: TXT | R79: Google | S79: GOG | AA79: A25+ | AB79: A25+ | AE79: Music Enthusiast | AF79: ME
A80: Institutional | B80: INT | O80: Hyper Link | P80: HPL | R80: Google + Yandex | S80: GYA | AA80: A25-49 | AE80: NA | AF80: NA
A81: IWOM | B81: IWO | O81: Image | P81: IMG | R81: Google Display Network | S81: GDN | AA81: A25-54 | AB81: A25-54GIRMLRI | AE81: National | AF81: NTL
A82: Jewels | B82: JEW | O82: In-feed | P82: INF | R82: GoPuff | S82: GOP | AA82: A25-54 - Geotargeted-In relationship/Married-Love/Romance Interests | AB82: A25-54LAG | AE82: NFL Fans | AF82: NFL
A83: Juicy Fruit + Starburst Flavours | B83: JFS | O83: Influencer Display | P83: DISP | R83: GPMD | S83: GPMD | AA83: A25-54 - LA Geotargeted | AB83: A35+ | AE83: Nutrition | AF83: NUT
A84: Juicy Fruit | B84: JFT | O84: Influencer Text | P84: TXT | R84: Gree Lifestyle | S84: GRE | AA84: A35+ | AE84: Oral Care | AF84: OC
A85: Jumbone | B85: JUM | O85: Influencer Video | P85: VID | R85: Grocery Magnet | S85: GRM | AA85: Adoption interests | AE85: P2+ | AF85: P2+
A86: James Wellbeloved | B86: JWB | O86: Instream | P86: INS | R86: Groundtruth | S86: grd | AA86: Affinity Targeting | AB86: AFT | AE86: Parents | AF86: PAR
A87: Kalkan | B87: KAL | O87: Interstitial | P87: INT | R87: Group Nine | S87: GRN | AA87: all15-49 | AB87: BET | AE87: Past FB/IG Engagers | AF87: PFB/IGE
A88: Kan Tong | B88: KAN | O88: Link Ad | P88: LA | R88: GroupM | S88: GRPM | AA88: Behavioral | AE88: Past FB/IG Engagers LAL | AF88: PFB/IGELAL
A89: Karma | B89: KAR | O89: Listing | P89: LIST | R89: GroupNine | S89: GRN | AA89: Cat + Dog interests | AE89: Past Video Viewers | AF89: PVV
A90: Kind Breakfast Bars | B90: KBB | O90: Native Display | P90: DISP | R90: GumGum | S90: GG | AA90: Cat + Dog Owners | AB90: CE | AE90: Pet Interest | AF90: PI
A91: Kind Bark | B91: KBK | O91: Native Logo | P91: LOG | R91: Hallmark | S91: HM | AA91: Cat Enthusiasts | AE91: PGS - Seasonal | AF91: PGSS
A92: Kind Bars | B92: KBS | O92: Native Text | P92: TXT | R92: Holler | S92: HOL | AA92: Cat lovers | AB92: CO | AE92: Pixel Targeting/Custom Audiences | AF92: PT/CA
A93: Kind Frozen Bars | B93: KFB | O93: Native Video | P93: VID | R93: HOTStar | S93: HOT | AA93: Cat Owners | AB93: COM | AE93: Placement | AF93: PLA
A94: Kind Frozen Pints | B94: KFP | O94: News Feed and Stories | P94: NFAS | R94: Hulu | S94: HULU | AA94: Competitive Conquesting | AB94: COT | AE94: Playlist | AF94: PLY
A95: Kind Frozen | B95: KFZ | O95: Non-Skippable Video | P95: NVID | R95: Hybrid | S95: HYB | AA95: Contextual | AB95: CRT | AE95: Pride | AF95: PRI
A96: Kitekat | B96: KIT | O96: Other | P96: Other | R96: iHeart | S96: IHR | AA96: Creative Retargeting | AB96: CSA | AE96: Primary Grocery Shopper | AF96: PGS
A97: Korkunov | B97: KOK | O97: Outstream | P97: OUT | R97: imdb | S97: imdb | AA97: Custom Affinity | AB97: CIT | AE97: Professionals | AF97: PRO
A98: Kind Protein Bars | B98: KPB | O98: Package | P98: PAC | R98: Imgur | S98: IMG | AA98: Custom Intent | AB98: CSM | AE98: Protein | AF98: PTN
A99: KiteKat, Perfect Fit, Frolic, Natusan | B99: KPF | O99: Photo Ad | P99: PA | R99: IMHO | S99: IMHO | AA99: Custom Segment Targeting | AB99: DYP | AE99: Puppy + Kitten Interests | AF99: PKI
A100: LifeSaver Gummies | B100: LIG | O100: Preroll | R100: Inca | S100: INCA | AA100: Day Parting | AE100: Puppy Interests | AF100: PUI
...

Sheet DB Entry Sheet (Engineers Only)
A1: NCKPI | B1: NCFormat | Z1: NCKPI | AA1: Comma | AB1: Quote | AC1: B_Open | AD1: B_Close
A2: =AC2&AB2&"NCKPI"&AB2&AA2&AB2&'Data Validations'!I2&'DB Entry Sheet (Engineers Only)'!AB2&'DB Entry Sheet (Engineers Only)'!AA2&'DB Entry Sheet (Engineers Only)'!AB2&'Data Validations'!H2&'DB Entry Sheet (Engineers Only)'!AB2&'DB Entry Sheet (Engineers Only)'!AD2 -> ('NCKPI', 'BR', 'Bounce Rate'), | B2: =AC2&AB2&"NCKPI"&AB2&AA2&AB2&'Data Validations'!P2&'DB Entry Sheet (Engineers Only)'!AB2&'DB Entry Sheet (Engineers Only)'!AA2&'DB Entry Sheet (Engineers Only)'!AB2&'Data Validations'!O2&'DB Entry Sheet (Engineers Only)'!AB2&'DB Entry Sheet (Engineers Only)'!AD2 -> ('NCKPI', '0x0', '0x0'), | AA2: , | AB2: ' | AC2: ( | AD2: ),
A3: =AC3&AB3&"NCKPI"&AB3&AA3&AB3&'Data Validations'!I3&'DB Entry Sheet (Engineers Only)'!AB3&'DB Entry Sheet (Engineers Only)'!AA3&'DB Entry Sheet (Engineers Only)'!AB3&'Data Validations'!H3&'DB Entry Sheet (Engineers Only)'!AB3&'DB Entry Sheet (Engineers Only)'!AD3 -> ('NCKPI', 'BA', 'Brand Awareness'), | B3: =AC3&AB3&"NCKPI"&AB3&AA3&AB3&'Data Validations'!P3&'DB Entry Sheet (Engineers Only)'!AB3&'DB Entry Sheet (Engineers Only)'!AA3&'DB Entry Sheet (Engineers Only)'!AB3&'Data Validations'!O3&'DB Entry Sheet (Engineers Only)'!AB3&'DB Entry Sheet (Engineers Only)'!AD3 -> ('NCKPI', '1024x1280', '1024x1280'), | AA3: , | AB3: ' | AC3: ( | AD3: ),
A4: =AC4&AB4&"NCKPI"&AB4&AA4&AB4&'Data Validations'!I4&'DB Entry Sheet (Engineers Only)'!AB4&'DB Entry Sheet (Engineers Only)'!AA4&'DB Entry Sheet (Engineers Only)'!AB4&'Data Validations'!H4&'DB Entry Sheet (Engineers Only)'!AB4&'DB Entry Sheet (Engineers Only)'!AD4 -> ('NCKPI', 'CTR', 'Click Through Rate'), | B4: =AC4&AB4&"NCKPI"&AB4&AA4&AB4&'Data Validations'!P4&'DB Entry Sheet (Engineers Only)'!AB4&'DB Entry Sheet (Engineers Only)'!AA4&'DB Entry Sheet (Engineers Only)'!AB4&'Data Validations'!O4&'DB Entry Sheet (Engineers Only)'!AB4&'DB Entry Sheet (Engineers Only)'!AD4 -> ('NCKPI', '1024x768', '1024x768'), | AA4: , | AB4: ' | AC4: ( | AD4: ),
A5: =AC5&AB5&"NCKPI"&AB5&AA5&AB5&'Data Validations'!I5&'DB Entry Sheet (Engineers Only)'!AB5&'DB Entry Sheet (Engineers Only)'!AA5&'DB Entry Sheet (Engineers Only)'!AB5&'Data Validations'!H5&'DB Entry Sheet (Engineers Only)'!AB5&'DB Entry Sheet (Engineers Only)'!AD5 -> ('NCKPI', 'CLC', 'Clicks'), | B5: =AC5&AB5&"NCKPI"&AB5&AA5&AB5&'Data Validations'!P5&'DB Entry Sheet (Engineers Only)'!AB5&'DB Entry Sheet (Engineers Only)'!AA5&'DB Entry Sheet (Engineers Only)'!AB5&'Data Validations'!O5&'DB Entry Sheet (Engineers Only)'!AB5&'DB Entry Sheet (Engineers Only)'!AD5 -> ('NCKPI', '1064x1536', '1064x1536'), | AA5: , | AB5: ' | AC5: ( | AD5: ),
A6: =AC6&AB6&"NCKPI"&AB6&AA6&AB6&'Data Validations'!I6&'DB Entry Sheet (Engineers Only)'!AB6&'DB Entry Sheet (Engineers Only)'!AA6&'DB Entry Sheet (Engineers Only)'!AB6&'Data Validations'!H6&'DB Entry Sheet (Engineers Only)'!AB6&'DB Entry Sheet (Engineers Only)'!AD6 -> ('NCKPI', 'CVN', 'Conversion'), | B6: =AC6&AB6&"NCKPI"&AB6&AA6&AB6&'Data Validations'!P6&'DB Entry Sheet (Engineers Only)'!AB6&'DB Entry Sheet (Engineers Only)'!AA6&'DB Entry Sheet (Engineers Only)'!AB6&'Data Validations'!O6&'DB Entry Sheet (Engineers Only)'!AB6&'DB Entry Sheet (Engineers Only)'!AD6 -> ('NCKPI', '1080x1080', '1080x1080'), | AA6: , | AB6: ' | AC6: ( | AD6: ),
A7: =AC7&AB7&"NCKPI"&AB7&AA7&AB7&'Data Validations'!I7&'DB Entry Sheet (Engineers Only)'!AB7&'DB Entry Sheet (Engineers Only)'!AA7&'DB Entry Sheet (Engineers Only)'!AB7&'Data Validations'!H7&'DB Entry Sheet (Engineers Only)'!AB7&'DB Entry Sheet (Engineers Only)'!AD7 -> ('NCKPI', 'CVR', 'Conversion Rate'), | B7: =AC7&AB7&"NCKPI"&AB7&AA7&AB7&'Data Validations'!P7&'DB Entry Sheet (Engineers Only)'!AB7&'DB Entry Sheet (Engineers Only)'!AA7&'DB Entry Sheet (Engineers Only)'!AB7&'Data Validations'!O7&'DB Entry Sheet (Engineers Only)'!AB7&'DB Entry Sheet (Engineers Only)'!AD7 -> ('NCKPI', '1080x1920', '1080x1920'), | AA7: , | AB7: ' | AC7: ( | AD7: ),
A8: =AC8&AB8&"NCKPI"&AB8&AA8&AB8&'Data Validations'!I8&'DB Entry Sheet (Engineers Only)'!AB8&'DB Entry Sheet (Engineers Only)'!AA8&'DB Entry Sheet (Engineers Only)'!AB8&'Data Validations'!H8&'DB Entry Sheet (Engineers Only)'!AB8&'DB Entry Sheet (Engineers Only)'!AD8 -> ('NCKPI', 'CPA', 'Cost Per Acquisition'), | B8: =AC8&AB8&"NCKPI"&AB8&AA8&AB8&'Data Validations'!P8&'DB Entry Sheet (Engineers Only)'!AB8&'DB Entry Sheet (Engineers Only)'!AA8&'DB Entry Sheet (Engineers Only)'!AB8&'Data Validations'!O8&'DB Entry Sheet (Engineers Only)'!AB8&'DB Entry Sheet (Engineers Only)'!AD8 -> ('NCKPI', '1200x400', '1200x400'), | AA8: , | AB8: ' | AC8: ( | AD8: ),
A9: =AC9&AB9&"NCKPI"&AB9&AA9&AB9&'Data Validations'!I9&'DB Entry Sheet (Engineers Only)'!AB9&'DB Entry Sheet (Engineers Only)'!AA9&'DB Entry Sheet (Engineers Only)'!AB9&'Data Validations'!H9&'DB Entry Sheet (Engineers Only)'!AB9&'DB Entry Sheet (Engineers Only)'!AD9 -> ('NCKPI', 'CPATC', 'Cost Per Add to Cart '), | B9: =AC9&AB9&"NCKPI"&AB9&AA9&AB9&'Data Validations'!P9&'DB Entry Sheet (Engineers Only)'!AB9&'DB Entry Sheet (Engineers Only)'!AA9&'DB Entry Sheet (Engineers Only)'!AB9&'Data Validations'!O9&'DB Entry Sheet (Engineers Only)'!AB9&'DB Entry Sheet (Engineers Only)'!AD9 -> ('NCKPI', '120x240', '120x240'), | AA9: , | AB9: ' | AC9: ( | AD9: ),
A10: =AC10&AB10&"NCKPI"&AB10&AA10&AB10&'Data Validations'!I10&'DB Entry Sheet (Engineers Only)'!AB10&'DB Entry Sheet (Engineers Only)'!AA10&'DB Entry Sheet (Engineers Only)'!AB10&'Data Validations'!H10&'DB Entry Sheet (Engineers Only)'!AB10&'DB Entry Sheet (Engineers Only)'!AD10 -> ('NCKPI', 'CPC', 'Cost Per Click'), | B10: =AC10&AB10&"NCKPI"&AB10&AA10&AB10&'Data Validations'!P10&'DB Entry Sheet (Engineers Only)'!AB10&'DB Entry Sheet (Engineers Only)'!AA10&'DB Entry Sheet (Engineers Only)'!AB10&'Data Validations'!O10&'DB Entry Sheet (Engineers Only)'!AB10&'DB Entry Sheet (Engineers Only)'!AD10 -> ('NCKPI', '120x60', '120x60'), | AA10: , | AB10: ' | AC10: ( | AD10: ),
A11: =AC11&AB11&"NCKPI"&AB11&AA11&AB11&'Data Validations'!I11&'DB Entry Sheet (Engineers Only)'!AB11&'DB Entry Sheet (Engineers Only)'!AA11&'DB Entry Sheet (Engineers Only)'!AB11&'Data Validations'!H11&'DB Entry Sheet (Engineers Only)'!AB11&'DB Entry Sheet (Engineers Only)'!AD11 -> ('NCKPI', 'CPE', 'Cost Per Engagement'), | B11: =AC11&AB11&"NCKPI"&AB11&AA11&AB11&'Data Validations'!P11&'DB Entry Sheet (Engineers Only)'!AB11&'DB Entry Sheet (Engineers Only)'!AA11&'DB Entry Sheet (Engineers Only)'!AB11&'Data Validations'!O11&'DB Entry Sheet (Engineers Only)'!AB11&'DB Entry Sheet (Engineers Only)'!AD11 -> ('NCKPI', '120x600', '120x600'), | AA11: , | AB11: ' | AC11: ( | AD11: ),
A12: =AC12&AB12&"NCKPI"&AB12&AA12&AB12&'Data Validations'!I12&'DB Entry Sheet (Engineers Only)'!AB12&'DB Entry Sheet (Engineers Only)'!AA12&'DB Entry Sheet (Engineers Only)'!AB12&'Data Validations'!H12&'DB Entry Sheet (Engineers Only)'!AB12&'DB Entry Sheet (Engineers Only)'!AD12 -> ('NCKPI', 'CPLPV', 'Cost Per Landing Page View'), | B12: =AC12&AB12&"NCKPI"&AB12&AA12&AB12&'Data Validations'!P12&'DB Entry Sheet (Engineers Only)'!AB12&'DB Entry Sheet (Engineers Only)'!AA12&'DB Entry Sheet (Engineers Only)'!AB12&'Data Validations'!O12&'DB Entry Sheet (Engineers Only)'!AB12&'DB Entry Sheet (Engineers Only)'!AD12 -> ('NCKPI', '120x90', '120x90'), | AA12: , | AB12: ' | AC12: ( | AD12: ),
A13: =AC13&AB13&"NCKPI"&AB13&AA13&AB13&'Data Validations'!I13&'DB Entry Sheet (Engineers Only)'!AB13&'DB Entry Sheet (Engineers Only)'!AA13&'DB Entry Sheet (Engineers Only)'!AB13&'Data Validations'!H13&'DB Entry Sheet (Engineers Only)'!AB13&'DB Entry Sheet (Engineers Only)'!AD13 -> ('NCKPI', 'CPL', 'Cost Per Lead'), | B13: =AC13&AB13&"NCKPI"&AB13&AA13&AB13&'Data Validations'!P13&'DB Entry Sheet (Engineers Only)'!AB13&'DB Entry Sheet (Engineers Only)'!AA13&'DB Entry Sheet (Engineers Only)'!AB13&'Data Validations'!O13&'DB Entry Sheet (Engineers Only)'!AB13&'DB Entry Sheet (Engineers Only)'!AD13 -> ('NCKPI', '125x125', '125x125'), | AA13: , | AB13: ' | AC13: ( | AD13: ),
... A117: =AC117&AB117&"NCKPI"&AB117&AA117&AB117&'Data Validations'!I117&'DB Entry Sheet (Engineers Only)'!AB117&'DB Entry Sheet (Engineers Only)'!AA117&'DB Entry Sheet (Engineers Only)'!AB117&'Data Validations'!H117&'DB Entry Sheet (Engineers Only)'!AB117&'DB Entry Sheet (Engineers Only)'!AD117 -> ('NCKPI', '', ''), | B117: =AC117&AB117&"NCKPI"&AB117&AA117&AB117&'Data Validations'!P117&'DB Entry Sheet (Engineers Only)'!AB117&'DB Entry Sheet (Engineers Only)'!AA117&'DB Entry Sheet (Engineers Only)'!AB117&'Data Validations'!O117&'DB Entry Sheet (Engineers Only)'!AB117&'DB Entry Sheet (Engineers Only)'!AD117 -> ('NCKPI', 'VIDSKIPP', 'Social Video click-to-play sound on Skippable'), | AA117: , | AB117: ' | AC117: ( | AD117: ),
B118: =AC118&AB118&"NCKPI"&AB118&AA118&AB118&'Data Validations'!P118&'DB Entry Sheet (Engineers Only)'!AB118&'DB Entry Sheet (Engineers Only)'!AA118&'DB Entry Sheet (Engineers Only)'!AB118&'Data Validations'!O118&'DB Entry Sheet (Engineers Only)'!AB118&'DB Entry Sheet (Engineers Only)'!AD118 -> ('NCKPI', 'SPO', 'Sponsorship'), | AA118: , | AB118: ' | AC118: ( | AD118: ),
B119: =AC119&AB119&"NCKPI"&AB119&AA119&AB119&'Data Validations'!P119&'DB Entry Sheet (Engineers Only)'!AB119&'DB Entry Sheet (Engineers Only)'!AA119&'DB Entry Sheet (Engineers Only)'!AB119&'Data Validations'!O119&'DB Entry Sheet (Engineers Only)'!AB119&'DB Entry Sheet (Engineers Only)'!AD119 -> ('NCKPI', '', 'Static Promopost'), | AA119: , | AB119: ' | AC119: ( | AD119: ),
B120: =AC120&AB120&"NCKPI"&AB120&AA120&AB120&'Data Validations'!P120&'DB Entry Sheet (Engineers Only)'!AB120&'DB Entry Sheet (Engineers Only)'!AA120&'DB Entry Sheet (Engineers Only)'!AB120&'Data Validations'!O120&'DB Entry Sheet (Engineers Only)'!AB120&'DB Entry Sheet (Engineers Only)'!AD120 -> ('NCKPI', '', 'Static Stories'), | AA120: , | AB120: ' | AC120: ( | AD120: ),
B121: =AC121&AB121&"NCKPI"&AB121&AA121&AB121&'Data Validations'!P121&'DB Entry Sheet (Engineers Only)'!AB121&'DB Entry Sheet (Engineers Only)'!AA121&'DB Entry Sheet (Engineers Only)'!AB121&'Data Validations'!O121&'DB Entry Sheet (Engineers Only)'!AB121&'DB Entry Sheet (Engineers Only)'!AD121 -> ('NCKPI', '', 'Stories'), | AA121: , | AB121: ' | AC121: ( | AD121: ),
B122: =AC122&AB122&"NCKPI"&AB122&AA122&AB122&'Data Validations'!P122&'DB Entry Sheet (Engineers Only)'!AB122&'DB Entry Sheet (Engineers Only)'!AA122&'DB Entry Sheet (Engineers Only)'!AB122&'Data Validations'!O122&'DB Entry Sheet (Engineers Only)'!AB122&'DB Entry Sheet (Engineers Only)'!AD122 -> ('NCKPI', '', 'Stories Carousel'), | AA122: , | AB122: ' | AC122: ( | AD122: ),
B123: =AC123&AB123&"NCKPI"&AB123&AA123&AB123&'Data Validations'!P123&'DB Entry Sheet (Engineers Only)'!AB123&'DB Entry Sheet (Engineers Only)'!AA123&'DB Entry Sheet (Engineers Only)'!AB123&'Data Validations'!O123&'DB Entry Sheet (Engineers Only)'!AB123&'DB Entry Sheet (Engineers Only)'!AD123 -> ('NCKPI', '', 'Stories Carousel with Video'), | AA123: , | AB123: ' | AC123: ( | AD123: ),
B124: =AC124&AB124&"NCKPI"&AB124&AA124&AB124&'Data Validations'!P124&'DB Entry Sheet (Engineers Only)'!AB124&'DB Entry Sheet (Engineers Only)'!AA124&'DB Entry Sheet (Engineers Only)'!AB124&'Data Validations'!O124&'DB Entry Sheet (Engineers Only)'!AB124&'DB Entry Sheet (Engineers Only)'!AD124 -> ('NCKPI', 'TV', 'True View'), | AA124: , | AB124: ' | AC124: ( | AD124: ),
B125: =AC125&AB125&"NCKPI"&AB125&AA125&AB125&'Data Validations'!P125&'DB Entry Sheet (Engineers Only)'!AB125&'DB Entry Sheet (Engineers Only)'!AA125&'DB Entry Sheet (Engineers Only)'!AB125&'Data Validations'!O125&'DB Entry Sheet (Engineers Only)'!AB125&'DB Entry Sheet (Engineers Only)'!AD125 -> ('NCKPI', 'TVA', 'True View for Action'), | AA125: , | AB125: ' | AC125: ( | AD125: ),
B126: =AC126&AB126&"NCKPI"&AB126&AA126&AB126&'Data Validations'!P126&'DB Entry Sheet (Engineers Only)'!AB126&'DB Entry Sheet (Engineers Only)'!AA126&'DB Entry Sheet (Engineers Only)'!AB126&'Data Validations'!O126&'DB Entry Sheet (Engineers Only)'!AB126&'DB Entry Sheet (Engineers Only)'!AD126 -> ('NCKPI', 'TVR', 'True View for Reach'), | AA126: , | AB126: ' | AC126: ( | AD126: ),
B127: =AC127&AB127&"NCKPI"&AB127&AA127&AB127&'Data Validations'!P127&'DB Entry Sheet (Engineers Only)'!AB127&'DB Entry Sheet (Engineers Only)'!AA127&'DB Entry Sheet (Engineers Only)'!AB127&'Data Validations'!O127&'DB Entry Sheet (Engineers Only)'!AB127&'DB Entry Sheet (Engineers Only)'!AD127 -> ('NCKPI', 'VID', 'Video'), | AA127: , | AB127: ' | AC127: ( | AD127: ),
B128: =AC128&AB128&"NCKPI"&AB128&AA128&AB128&'Data Validations'!P128&'DB Entry Sheet (Engineers Only)'!AB128&'DB Entry Sheet (Engineers Only)'!AA128&'DB Entry Sheet (Engineers Only)'!AB128&'Data Validations'!O128&'DB Entry Sheet (Engineers Only)'!AB128&'DB Entry Sheet (Engineers Only)'!AD128 -> ('NCKPI', 'VIDAPSON', 'Video auto-play sound off Non-Skippable'), | AA128: , | AB128: ' | AC128: ( | AD128: ),
B129: =AC129&AB129&"NCKPI"&AB129&AA129&AB129&'Data Validations'!P129&'DB Entry Sheet (Engineers Only)'!AB129&'DB Entry Sheet (Engineers Only)'!AA129&'DB Entry Sheet (Engineers Only)'!AB129&'Data Validations'!O129&'DB Entry Sheet (Engineers Only)'!AB129&'DB Entry Sheet (Engineers Only)'!AD129 -> ('NCKPI', 'VIDAPSOS', 'Video auto-play sound off Skippable'), | AA129: , | AB129: ' | AC129: ( | AD129: ),
... B159: =AC159&AB159&"NCKPI"&AB159&AA159&AB159&'Data Validations'!P159&'DB Entry Sheet (Engineers Only)'!AB159&'DB Entry Sheet (Engineers Only)'!AA159&'DB Entry Sheet (Engineers Only)'!AB159&'Data Validations'!O159&'DB Entry Sheet (Engineers Only)'!AB159&'DB Entry Sheet (Engineers Only)'!AD159 -> ('NCKPI', '', ''), | AA159: , | AB159: ' | AC159: ( | AD159: ),
AA160: , | AB160: ' | AC160: ( | AD160: ),
AA161: , | AB161: ' | AC161: ( | AD161: ),
AA162: , | AB162: ' | AC162: ( | AD162: ),
AA163: , | AB163: ' | AC163: ( | AD163: ),
AA164: , | AB164: ' | AC164: ( | AD164: ),
AA165: , | AB165: ' | AC165: ( | AD165: ),
AA166: , | AB166: ' | AC166: ( | AD166: ),
AA167: , | AB167: ' | AC167: ( | AD167: ),
AA168: , | AB168: ' | AC168: ( | AD168: ),
AA169: , | AB169: ' | AC169: ( | AD169: ),
AA170: , | AB170: ' | AC170: ( | AD170: ),
AA171: , | AB171: ' | AC171: ( | AD171: ),
... AA306: , | AB306: ' | AC306: ( | AD306: ),
